{"type":"Feature","geometry":{"type":"Point","coordinates":[3.382688,50.934819]},"properties":{"id":"https://w3id.org/openfooddata/actors/hoevewinkel-obio","name":"Hoevewinkel O'Bio","img":[],"type":["at:pointOfSale","at:farmShop"],"upstream":[{"@type":"ofd:ActorRelationship","ofd:relatedContext":"at:producer","ofd:relatedActor":"https://w3id.org/openfooddata/actors/obio"}]}}