{"type":"Feature","geometry":{"type":"Point","coordinates":[4.695349,51.157387]},"properties":{"foaf:account":[],"foaf:name":"Nijlens Grondwitloof","schema:url":[],"foaf:homepage":[],"foaf:isPrimaryTopicOf":["http://www.rechtvanbijdeboer.be/nijlens-grondwitloof-0","http://www.rechtvanbijdeboer.be/node/3605","https://www.rechtvanbijdeboer.be/nijlens-grondwitloof","https://www.rechtvanbijdeboer.be/node/1958"],"@type":"foaf:Agent","schema:image":[],"@context":"https://openfooddata.github.io/actors/_common/context.jsonld","schema:geo":{"schema:latitude":"51.157387","schema:longitude":"4.695349","@type":"schema:GeoCoordinates","schema:addressCountry":"Belgium","schema:address":{"@type":"schema:PostalAddress","schema:streetAddress":"Boshoek 44 a","schema:postalCode":"2560","schema:addressLocality":"Nijlen"}},"ofd:offersFoodType":["ft:vegetables"],"foaf:depiction":[],"schema:description":"","ofd:upstreamRel":[],"ofd:downstreamRel":[],"@id":"https://w3id.org/openfooddata/actors/nijlens-grondwitloof","extraHeader":"<link rel=\"alternate\" href=\"nijlens-grondwitloof.rdf\" type=\"application/rdf+xml\"/>\n<link rel=\"alternate\" href=\"nijlens-grondwitloof.jsonld\" type=\"application/ld+json\"/>\n<link rel=\"alternate\" href=\"nijlens-grondwitloof.nq\" type=\"application/n-quads\"/>\n<link rel=\"alternate\" href=\"nijlens-grondwitloof.nt\" type=\"application/n-triples\"/>\n<link rel=\"alternate\" href=\"nijlens-grondwitloof.ttl\" type=\"text/turtle\"/>\n<link rel=\"alternate\" href=\"nijlens-grondwitloof.rj\" type=\"application/rdf+json\"/>\n<link rel=\"alternate\" href=\"nijlens-grondwitloof.trig\" type=\"text/trig\"/>\n<link rel=\"alternate\" href=\"nijlens-grondwitloof.trix\" type=\"application/trix\"/>\n","schema:name":"Nijlens Grondwitloof","ofd:actorType":["at:pointOfSale","at:farmShop","at:producer"]}}