{"type":"Feature","geometry":{"type":"Point","coordinates":[4.999574,50.905525]},"properties":{"foaf:account":[],"foaf:name":"Hoevewinkel bij Danny en Carla","schema:url":[],"foaf:homepage":[],"foaf:isPrimaryTopicOf":["http://www.rechtvanbijdeboer.be/hoevewinkel-bij-danny-en-carla-0","http://www.rechtvanbijdeboer.be/node/2969","https://www.rechtvanbijdeboer.be/hoevewinkel-bij-danny-en-carla","https://www.rechtvanbijdeboer.be/node/1480"],"@type":"foaf:Agent","schema:image":[],"@context":"https://openfooddata.github.io/actors/_common/context.jsonld","schema:geo":{"schema:latitude":"50.905525","schema:longitude":"4.999574","@type":"schema:GeoCoordinates","schema:addressCountry":"Belgium","schema:address":{"@type":"schema:PostalAddress","schema:streetAddress":"Oude Tiensestraat 29","schema:postalCode":"3473","schema:addressLocality":"Waanrode"}},"ofd:offersFoodType":["ft:fruits","ft:vegetables","ft:potatoes"],"foaf:depiction":[],"schema:description":"","ofd:upstreamRel":[],"ofd:downstreamRel":[],"@id":"https://w3id.org/openfooddata/actors/hoevewinkel-bij-danny-en-carla","extraHeader":"<link rel=\"alternate\" href=\"hoevewinkel-bij-danny-en-carla.rdf\" type=\"application/rdf+xml\"/>\n<link rel=\"alternate\" href=\"hoevewinkel-bij-danny-en-carla.jsonld\" type=\"application/ld+json\"/>\n<link rel=\"alternate\" href=\"hoevewinkel-bij-danny-en-carla.nq\" type=\"application/n-quads\"/>\n<link rel=\"alternate\" href=\"hoevewinkel-bij-danny-en-carla.nt\" type=\"application/n-triples\"/>\n<link rel=\"alternate\" href=\"hoevewinkel-bij-danny-en-carla.ttl\" type=\"text/turtle\"/>\n<link rel=\"alternate\" href=\"hoevewinkel-bij-danny-en-carla.rj\" type=\"application/rdf+json\"/>\n<link rel=\"alternate\" href=\"hoevewinkel-bij-danny-en-carla.trig\" type=\"text/trig\"/>\n<link rel=\"alternate\" href=\"hoevewinkel-bij-danny-en-carla.trix\" type=\"application/trix\"/>\n","schema:name":"Hoevewinkel bij Danny en Carla","ofd:actorType":["at:pointOfSale","at:farmShop","at:producer"]}}