{"type":"Feature","geometry":{"type":"Point","coordinates":[4.097118,50.859721]},"properties":{"foaf:account":[],"foaf:name":"Terras Smulhoeve","foaf:isPrimaryTopicOf":["http://www.rechtvanbijdeboer.be/terras-smulhoeve","http://www.rechtvanbijdeboer.be/node/2643"],"@type":"foaf:Agent","schema:image":["http://www.rechtvanbijdeboer.be/sites/default/files/styles/producer_teaser/public/img_0805.jpg?itok=ozjnBDir"],"@context":"https://openfooddata.github.io/actors/_common/context.jsonld","schema:geo":{"schema:latitude":"50.859721","schema:longitude":"4.097118","@type":"schema:GeoCoordinates","schema:addressCountry":"Belgium","schema:address":{"@type":"schema:PostalAddress","schema:streetAddress":"Cathemlindeweg 160","schema:postalCode":"1770","schema:addressLocality":"Liedekerke"}},"ofd:offersFoodType":["ft:potatoes","ft:icecream","ft:milk_products"],"foaf:depiction":["http://www.rechtvanbijdeboer.be/sites/default/files/styles/producer_teaser/public/img_0805.jpg?itok=ozjnBDir"],"schema:description":"","ofd:upstreamRel":[{"@type":"ofd:ActorRelationship","ofd:relatedContext":"at:producer","ofd:relatedActor":"https://w3id.org/openfooddata/actors/de-smulhoeve"}],"@id":"https://w3id.org/openfooddata/actors/terras-smulhoeve","schema:name":"Terras Smulhoeve","ofd:actorType":["at:pointOfSale","at:farmShop"]}}