{"type":"Feature","geometry":{"type":"Point","coordinates":[3.56389,51.185272]},"properties":{"foaf:account":[],"foaf:name":"Markt Eeklo","foaf:isPrimaryTopicOf":["http://www.rechtvanbijdeboer.be/markt-eeklo","http://www.rechtvanbijdeboer.be/node/2143"],"@type":"foaf:Agent","schema:image":[],"@context":"https://openfooddata.github.io/actors/_common/context.jsonld","schema:geo":{"schema:latitude":"51.185272","schema:longitude":"3.563890","@type":"schema:GeoCoordinates","schema:addressCountry":"Belgium","schema:address":{"@type":"schema:PostalAddress","schema:streetAddress":"-0","schema:postalCode":"9900","schema:addressLocality":"Eeklo"}},"ofd:offersFoodType":["ft:vegetables","ft:potatoes","ft:fruits"],"foaf:depiction":[],"schema:description":"","ofd:upstreamRel":[{"@type":"ofd:ActorRelationship","ofd:relatedContext":"at:producer","ofd:relatedActor":"https://w3id.org/openfooddata/actors/bio-baarlaars"},{"@type":"ofd:ActorRelationship","ofd:relatedContext":"at:producer","ofd:relatedActor":"https://w3id.org/openfooddata/actors/t-ambrozijn"}],"@id":"https://w3id.org/openfooddata/actors/markt-eeklo","schema:name":"Markt Eeklo","ofd:actorType":["at:pointOfSale","at:market"]}}