{"type":"Feature","geometry":{"type":"Point","coordinates":[4.540234,50.900938]},"properties":{"foaf:account":[],"foaf:name":"Salens","foaf:isPrimaryTopicOf":["http://www.rechtvanbijdeboer.be/salens","http://www.rechtvanbijdeboer.be/node/3497"],"@type":"foaf:Agent","schema:image":[],"@context":"https://openfooddata.github.io/actors/_common/context.jsonld","schema:geo":{"schema:latitude":"50.900938","schema:longitude":"4.540234","@type":"schema:GeoCoordinates","schema:addressCountry":"Belgium","schema:address":{"@type":"schema:PostalAddress","schema:streetAddress":"Vossenputten 10","schema:postalCode":"3071","schema:addressLocality":"Erps-Kwerps"}},"ofd:offersFoodType":["ft:potatoes","ft:vegetables"],"foaf:depiction":[],"schema:description":"","ofd:upstreamRel":[{"@type":"ofd:ActorRelationship","ofd:relatedContext":"at:producer","ofd:relatedActor":"https://w3id.org/openfooddata/actors/salens--van-der-elst-grondwitloof"}],"@id":"https://w3id.org/openfooddata/actors/salens","schema:name":"Salens","ofd:actorType":["at:pointOfSale","at:farmShop"]}}