{"type":"Feature","geometry":{"type":"Point","coordinates":[4.782994,50.881565]},"properties":{"id":"https://w3id.org/openfooddata/actors/oogsttuin-eoster","name":"Oogsttuin Eoster","img":[],"type":["at:pointOfSale","at:csaFarm"],"upstream":[{"@type":"ofd:ActorRelationship","ofd:relatedContext":"at:producer","ofd:relatedActor":"https://w3id.org/openfooddata/actors/het-gulden-gehucht---oogsttuin-eoster"}]}}