{"type":"Feature","geometry":{"type":"Point","coordinates":[3.170146,51.160553]},"properties":{"foaf:account":[],"foaf:name":"Augustijnenhof","schema:url":[],"foaf:homepage":[],"foaf:isPrimaryTopicOf":["http://www.rechtvanbijdeboer.be/augustijnenhof-0","http://www.rechtvanbijdeboer.be/node/2812","https://www.rechtvanbijdeboer.be/augustijnenhof","https://www.rechtvanbijdeboer.be/node/1340"],"@type":"foaf:Agent","schema:image":[],"@context":"https://openfooddata.github.io/actors/_common/context.jsonld","schema:geo":{"schema:latitude":"51.160553","schema:longitude":"3.170146","@type":"schema:GeoCoordinates","schema:addressCountry":"Belgium","schema:address":{"@type":"schema:PostalAddress","schema:streetAddress":"Rolleweg 32","schema:postalCode":"8210","schema:addressLocality":"Loppem"}},"ofd:offersFoodType":["ft:poultry_meat","ft:fruits","ft:vegetables","ft:beef","ft:potatoes"],"foaf:depiction":[],"schema:description":"","ofd:upstreamRel":[],"ofd:downstreamRel":[],"@id":"https://w3id.org/openfooddata/actors/augustijnenhof","schema:name":"Augustijnenhof","ofd:actorType":["at:pointOfSale","at:farmShop","at:producer"]}}