{"type":"Feature","geometry":{"type":"Point","coordinates":[5.127492,51.080647]},"properties":{"id":"https://w3id.org/openfooddata/actors/voedselteam-ham","name":"Voedselteam Ham","img":["http://www.rechtvanbijdeboer.be/sites/default/files/styles/producer_teaser/public/IMG_0311.JPG?itok=qXCIzotY"],"type":["at:pointOfSale","at:foodTeams"],"upstream":[{"@type":"ofd:ActorRelationship","ofd:relatedContext":"at:producer","ofd:relatedActor":"https://w3id.org/openfooddata/actors/de-wroeter-maatwerkbedrijf-vzw"},{"@type":"ofd:ActorRelationship","ofd:relatedContext":"at:producer","ofd:relatedActor":"https://w3id.org/openfooddata/actors/herkenrodeboer"},{"@type":"ofd:ActorRelationship","ofd:relatedContext":"at:producer","ofd:relatedActor":"https://w3id.org/openfooddata/actors/stichting-ommersteyn"},{"@type":"ofd:ActorRelationship","ofd:relatedContext":"at:producer","ofd:relatedActor":"https://w3id.org/openfooddata/actors/natlandhoeve"}]}}