{"type":"Feature","geometry":{"type":"Point","coordinates":[2.864748,51.033313]},"properties":{"foaf:account":[],"foaf:name":"Boerenmarkt Diksmuide","foaf:isPrimaryTopicOf":["http://www.rechtvanbijdeboer.be/boerenmarkt-diksmuide","http://www.rechtvanbijdeboer.be/node/2002"],"@type":"foaf:Agent","schema:image":["http://www.rechtvanbijdeboer.be/sites/default/files/styles/producer_teaser/public/appels.jpg?itok=gZQv_Ega"],"@context":"https://openfooddata.github.io/actors/_common/context.jsonld","schema:geo":{"schema:latitude":"51.033313","schema:longitude":"2.864748","@type":"schema:GeoCoordinates","schema:addressCountry":"Belgium","schema:address":{"@type":"schema:PostalAddress","schema:streetAddress":"Markt","schema:postalCode":"8600","schema:addressLocality":"Diksmuide"}},"ofd:offersFoodType":["ft:potatoes","ft:fruits","ft:eggs","ft:poultry_meat","ft:vegetables"],"foaf:depiction":["http://www.rechtvanbijdeboer.be/sites/default/files/styles/producer_teaser/public/appels.jpg?itok=gZQv_Ega"],"schema:description":"","ofd:upstreamRel":[{"@type":"ofd:ActorRelationship","ofd:relatedContext":"at:producer","ofd:relatedActor":"https://w3id.org/openfooddata/actors/fruit-vervisch"}],"@id":"https://w3id.org/openfooddata/actors/boerenmarkt-diksmuide","schema:name":"Boerenmarkt Diksmuide","ofd:actorType":["at:pointOfSale","at:farmersMarket"]}}