{"type":"Feature","geometry":{"type":"Point","coordinates":[3.439887,51.020534]},"properties":{"foaf:account":[],"foaf:name":"de Artemeersmolen","foaf:isPrimaryTopicOf":["http://www.rechtvanbijdeboer.be/de-artemeersmolen","http://www.rechtvanbijdeboer.be/node/3174"],"@type":"foaf:Agent","schema:image":[],"@context":"https://openfooddata.github.io/actors/_common/context.jsonld","schema:geo":{"schema:latitude":"51.020534","schema:longitude":"3.439887","@type":"schema:GeoCoordinates","schema:addressCountry":"Belgium","schema:address":{"@type":"schema:PostalAddress","schema:streetAddress":"Artemeersstraat 14a","schema:postalCode":"9880","schema:addressLocality":"Poeke (Aalter)"}},"ofd:offersFoodType":["ft:bakery_products"],"foaf:depiction":[],"schema:description":"","ofd:upstreamRel":[{"@type":"ofd:ActorRelationship","ofd:relatedContext":"at:producer","ofd:relatedActor":"https://w3id.org/openfooddata/actors/de-artemeersmolen-(flourpower)"}],"@id":"https://w3id.org/openfooddata/actors/de-artemeersmolen","schema:name":"de Artemeersmolen","ofd:actorType":["at:pointOfSale","at:farmShop"]}}