{"type":"Feature","geometry":{"type":"Point","coordinates":[5.467623,51.074312]},"properties":{"id":"https://w3id.org/openfooddata/actors/blauwbessen-indekeu","name":null,"img":[],"type":["at:pointOfSale","at:farmShop"],"upstream":[],"downstream":[]}}