{"type":"Feature","geometry":{"type":"Point","coordinates":[4.783441,50.869289]},"properties":{"foaf:account":[],"foaf:name":"Pellenberg","foaf:isPrimaryTopicOf":["http://www.rechtvanbijdeboer.be/pellenberg","http://www.rechtvanbijdeboer.be/node/2219"],"@type":"foaf:Agent","schema:image":[],"@context":"https://openfooddata.github.io/actors/_common/context.jsonld","schema:geo":{"schema:latitude":"50.869289","schema:longitude":"4.783441","@type":"schema:GeoCoordinates","schema:addressCountry":"Belgium","schema:address":{"@type":"schema:PostalAddress","schema:streetAddress":"Nederblok","schema:postalCode":"3212","schema:addressLocality":"Pellenberg"}},"ofd:offersFoodType":["ft:potatoes","ft:fruits","ft:bakery_products","ft:eggs","ft:poultry_meat","ft:fruit_juices","ft:icecream","ft:spices","ft:lamb_meat","ft:beef","ft:pork","ft:alcoholic_beverages","ft:vegetables","ft:milk_products"],"foaf:depiction":[],"schema:description":"","ofd:upstreamRel":[],"@id":"https://w3id.org/openfooddata/actors/pellenberg","schema:name":"Pellenberg","ofd:actorType":["at:pointOfSale","at:foodTeams"]}}