{"type":"Feature","geometry":{"type":"Point","coordinates":[4.691942,50.880861]},"properties":{"id":"https://w3id.org/openfooddata/actors/leuven-0","name":"Leuven","img":["http://www.rechtvanbijdeboer.be/sites/default/files/styles/producer_teaser/public/de_levende_aarde_cvba_geitenkaasjes.jpg?itok=LMhPoryB"],"type":["at:pointOfSale","at:market"],"upstream":[{"@type":"ofd:ActorRelationship","ofd:relatedContext":"at:producer","ofd:relatedActor":"https://w3id.org/openfooddata/actors/de-levende-aarde-cvba"},{"@type":"ofd:ActorRelationship","ofd:relatedContext":"at:producer","ofd:relatedActor":"https://w3id.org/openfooddata/actors/den-akker"},{"@type":"ofd:ActorRelationship","ofd:relatedContext":"at:producer","ofd:relatedActor":"https://w3id.org/openfooddata/actors/de-levensbron"},{"@type":"ofd:ActorRelationship","ofd:relatedContext":"at:producer","ofd:relatedActor":"https://w3id.org/openfooddata/actors/polleunis-fruit"},{"@type":"ofd:ActorRelationship","ofd:relatedContext":"at:producer","ofd:relatedActor":"https://w3id.org/openfooddata/actors/de-fruittuin"}]}}