{"type":"Feature","geometry":{"type":"Point","coordinates":[5.484677,51.251791]},"properties":{"foaf:account":[],"foaf:name":"Voedselteam Hamont-Achel","foaf:isPrimaryTopicOf":["http://www.rechtvanbijdeboer.be/voedselteam-hamont-achel","http://www.rechtvanbijdeboer.be/node/2267"],"@type":"foaf:Agent","schema:image":["http://www.rechtvanbijdeboer.be/sites/default/files/styles/producer_teaser/public/IMG_0311.JPG?itok=qXCIzotY"],"@context":"https://openfooddata.github.io/actors/_common/context.jsonld","schema:geo":{"schema:latitude":"51.251791","schema:longitude":"5.484677","@type":"schema:GeoCoordinates","schema:addressCountry":"Belgium","schema:address":{"@type":"schema:PostalAddress","schema:streetAddress":"Catharinadal 5","schema:postalCode":"3930","schema:addressLocality":"Hamont-Achel"}},"ofd:offersFoodType":["ft:fruits","ft:bakery_products","ft:poultry_meat","ft:vegetables","ft:milk_products","ft:potatoes","ft:eggs","ft:fruit_juices","ft:lamb_meat","ft:beef","ft:alcoholic_beverages","ft:pork"],"foaf:depiction":["http://www.rechtvanbijdeboer.be/sites/default/files/styles/producer_teaser/public/IMG_0311.JPG?itok=qXCIzotY"],"schema:description":"","ofd:upstreamRel":[{"@type":"ofd:ActorRelationship","ofd:relatedContext":"at:producer","ofd:relatedActor":"https://w3id.org/openfooddata/actors/de-wroeter-maatwerkbedrijf-vzw"},{"@type":"ofd:ActorRelationship","ofd:relatedContext":"at:producer","ofd:relatedActor":"https://w3id.org/openfooddata/actors/herkenrodeboer"},{"@type":"ofd:ActorRelationship","ofd:relatedContext":"at:producer","ofd:relatedActor":"https://w3id.org/openfooddata/actors/stichting-ommersteyn"},{"@type":"ofd:ActorRelationship","ofd:relatedContext":"at:producer","ofd:relatedActor":"https://w3id.org/openfooddata/actors/natlandhoeve"}],"@id":"https://w3id.org/openfooddata/actors/voedselteam-hamont-achel","schema:name":"Voedselteam Hamont-Achel","ofd:actorType":["at:pointOfSale","at:foodTeams"]}}