{"type":"Feature","geometry":{"type":"Point","coordinates":[4.992668,51.319776]},"properties":{"id":"https://w3id.org/openfooddata/actors/oud-turnhout","name":"Oud-Turnhout","img":[],"type":["at:pointOfSale","at:vegetableSubscription"],"upstream":[{"@type":"ofd:ActorRelationship","ofd:relatedContext":"at:producer","ofd:relatedActor":"https://w3id.org/openfooddata/actors/de-bio-hoeve"}]}}