{"type":"Feature","geometry":{"type":"Point","coordinates":[4.078336,50.808953]},"properties":{"foaf:account":[],"foaf:name":"De Baerdemaeker","schema:url":[],"foaf:homepage":[],"foaf:isPrimaryTopicOf":["http://www.rechtvanbijdeboer.be/de-baerdemaeker-0","http://www.rechtvanbijdeboer.be/node/2927","https://www.rechtvanbijdeboer.be/de-baerdemaeker","https://www.rechtvanbijdeboer.be/node/1438"],"@type":"foaf:Agent","schema:image":[],"@context":"https://openfooddata.github.io/actors/_common/context.jsonld","schema:geo":{"schema:latitude":"50.808953","schema:longitude":"4.078336","@type":"schema:GeoCoordinates","schema:addressCountry":"Belgium","schema:address":{"@type":"schema:PostalAddress","schema:streetAddress":"Bettestraat 12","schema:postalCode":"1755","schema:addressLocality":"Gooik"}},"ofd:offersFoodType":["ft:icecream"],"foaf:depiction":[],"schema:description":"","ofd:upstreamRel":[],"ofd:downstreamRel":[],"@id":"https://w3id.org/openfooddata/actors/de-baerdemaeker","schema:name":"De Baerdemaeker","ofd:actorType":["at:pointOfSale","at:farmShop","at:producer"]}}