{"type":"Feature","geometry":{"type":"Point","coordinates":[4.691611,50.944396]},"properties":{"foaf:account":[],"foaf:name":"Jan & Chris Martens - Vander Sande","schema:url":[],"foaf:homepage":[],"foaf:isPrimaryTopicOf":["http://www.rechtvanbijdeboer.be/jan-chris-martens-vander-sande-0","http://www.rechtvanbijdeboer.be/node/2729","http://www.rechtvanbijdeboer.be/jan-chris-martens-vander-sande","http://www.rechtvanbijdeboer.be/node/1293"],"@type":"foaf:Agent","schema:image":["http://www.rechtvanbijdeboer.be/sites/default/files/styles/producer_teaser/public/img_0262cor.jpg?itok=nnJrF62C"],"@context":"https://openfooddata.github.io/actors/_common/context.jsonld","schema:geo":{"schema:latitude":"50.944396","schema:longitude":"4.691611","@type":"schema:GeoCoordinates","schema:addressCountry":"Belgium","schema:address":{"@type":"schema:PostalAddress","schema:streetAddress":"Walenstraat 13","schema:postalCode":"3110","schema:addressLocality":"Rotselaar"}},"ofd:offersFoodType":["ft:fruit_juices","ft:fruits","ft:vegetables","ft:potatoes"],"foaf:depiction":["http://www.rechtvanbijdeboer.be/sites/default/files/styles/producer_teaser/public/img_0262cor.jpg?itok=nnJrF62C"],"schema:description":"Wij zijn een geïntegreerd fruitteeltbedrijf dat van bij de opstart bewust voor deze werkwijze gekozen heeft. Respect voor de natuur waarbij natuurlijke vijanden kunnen zorgen voor een gezond evenwicht in de plantage en dit gebaseerd op wetenschappelijk onderzoek.","ofd:upstreamRel":[],"schema:contactPoint":{"@type":"schema:ContactPoint","schema:telephone":["016/445223","0476/736037"],"schema:email":["jan.martens@marsan.be"],"foaf:homepage":[],"schema:url":[]},"ofd:downstreamRel":[],"@id":"https://w3id.org/openfooddata/actors/jan-chris-martens-vander-sande","schema:name":"Jan & Chris Martens - Vander Sande","ofd:actorType":["at:pointOfSale","at:farmShop","at:producer"]}}