{"type":"Feature","geometry":{"type":"Point","coordinates":[3.753836,50.866584]},"properties":{"id":"https://w3id.org/openfooddata/actors/cressana","name":"Cressana","img":["http://www.rechtvanbijdeboer.be/sites/default/files/styles/producer_teaser/public/eyecatcher_syrup_nl_a7d6436smaller.jpg?itok=EUTFf7MQ"],"type":["at:pointOfSale","at:farmShop","at:producer"],"upstream":[],"downstream":[]}}