{"type":"Feature","geometry":{"type":"Point","coordinates":[3.802185,50.875615]},"properties":{"foaf:account":[],"foaf:name":"Beiselhoeve","foaf:isPrimaryTopicOf":["http://www.rechtvanbijdeboer.be/beiselhoeve","http://www.rechtvanbijdeboer.be/node/2494"],"@type":"foaf:Agent","schema:image":["http://www.rechtvanbijdeboer.be/sites/default/files/styles/producer_teaser/public/fruitkwekerij_coppens_beiselhove_inrit.jpg?itok=883gBT0p"],"@context":"https://openfooddata.github.io/actors/_common/context.jsonld","schema:geo":{"schema:latitude":"50.875615","schema:longitude":"3.802185","@type":"schema:GeoCoordinates","schema:addressCountry":"Belgium","schema:address":{"@type":"schema:PostalAddress","schema:streetAddress":"Hofstraat 62","schema:postalCode":"9620","schema:addressLocality":"Zottegem"}},"ofd:offersFoodType":["ft:potatoes","ft:fruits","ft:fruit_juices"],"foaf:depiction":["http://www.rechtvanbijdeboer.be/sites/default/files/styles/producer_teaser/public/fruitkwekerij_coppens_beiselhove_inrit.jpg?itok=883gBT0p"],"schema:description":"","ofd:upstreamRel":[{"@type":"ofd:ActorRelationship","ofd:relatedContext":"at:producer","ofd:relatedActor":"https://w3id.org/openfooddata/actors/fruitkwekerij-coppens-beiselhoeve"}],"@id":"https://w3id.org/openfooddata/actors/beiselhoeve","schema:name":"Beiselhoeve","ofd:actorType":["at:pointOfSale","at:farmShop"]}}