{"type":"Feature","geometry":{"type":"Point","coordinates":[2.844536,51.16155]},"properties":{"id":"https://w3id.org/openfooddata/actors/paardenmelekerij-van-t-maneschijnhof","name":"Paardenmelekerij Van 't Maneschijnhof","img":[],"type":["at:pointOfSale","at:farmShop"],"upstream":[{"@type":"ofd:ActorRelationship","ofd:relatedContext":"at:producer","ofd:relatedActor":"https://w3id.org/openfooddata/actors/paardenmelkerij-van-t-maneschijnhof"}]}}