{"type":"Feature","geometry":{"type":"Point","coordinates":[3.694835,50.909395]},"properties":{"id":"https://w3id.org/openfooddata/actors/fruitbedrijf-meire","name":"Fruitbedrijf Meire","img":["http://www.rechtvanbijdeboer.be/sites/default/files/styles/producer_teaser/public/054-meire_pieterjan.jpg?itok=K2IvNDUP"],"type":["at:pointOfSale","at:farmShop","at:producer"],"upstream":[],"downstream":[]}}