{"type":"Feature","geometry":{"type":"Point","coordinates":[4.05961,51.023758]},"properties":{"foaf:account":[],"foaf:name":"Herman Fierlafijn","foaf:isPrimaryTopicOf":["http://www.rechtvanbijdeboer.be/herman-fierlafijn","http://www.rechtvanbijdeboer.be/node/2702"],"@type":"foaf:Agent","schema:image":[],"@context":"https://openfooddata.github.io/actors/_common/context.jsonld","schema:geo":{"schema:latitude":"51.023758","schema:longitude":"4.059610","@type":"schema:GeoCoordinates","schema:addressCountry":"Belgium","schema:address":{"@type":"schema:PostalAddress","schema:streetAddress":"Lindestraat 64","schema:postalCode":"9200","schema:addressLocality":"Dendermonde"}},"ofd:offersFoodType":["ft:potatoes","ft:fruits","ft:vegetables"],"foaf:depiction":[],"schema:description":"","ofd:upstreamRel":[{"@type":"ofd:ActorRelationship","ofd:relatedContext":"at:producer","ofd:relatedActor":"https://w3id.org/openfooddata/actors/fierlafijn"}],"@id":"https://w3id.org/openfooddata/actors/herman-fierlafijn","schema:name":"Herman Fierlafijn","ofd:actorType":["at:pointOfSale","at:farmShop"]}}