{"type":"Feature","geometry":{"type":"Point","coordinates":[4.05961,51.023758]},"properties":{"foaf:account":[],"foaf:name":"Herman Fierlafijn","foaf:isPrimaryTopicOf":["http://www.rechtvanbijdeboer.be/herman-fierlafijn","http://www.rechtvanbijdeboer.be/node/2702"],"@type":"foaf:Agent","schema:image":[],"@context":"https://openfooddata.github.io/actors/_common/context.jsonld","schema:geo":{"schema:latitude":"51.023758","schema:longitude":"4.059610","@type":"schema:GeoCoordinates","schema:addressCountry":"Belgium","schema:address":{"@type":"schema:PostalAddress","schema:streetAddress":"Lindestraat 64","schema:postalCode":"9200","schema:addressLocality":"Dendermonde"}},"ofd:offersFoodType":["ft:potatoes","ft:fruits","ft:vegetables"],"foaf:depiction":[],"schema:description":"","ofd:upstreamRel":[{"@type":"ofd:ActorRelationship","ofd:relatedContext":"at:producer","ofd:relatedActor":"https://w3id.org/openfooddata/actors/fierlafijn"}],"@id":"https://w3id.org/openfooddata/actors/herman-fierlafijn","extraHeader":"<link rel=\"alternate\" href=\"herman-fierlafijn.rdf\" type=\"application/rdf+xml\"/>\n<link rel=\"alternate\" href=\"herman-fierlafijn.jsonld\" type=\"application/ld+json\"/>\n<link rel=\"alternate\" href=\"herman-fierlafijn.nq\" type=\"application/n-quads\"/>\n<link rel=\"alternate\" href=\"herman-fierlafijn.nt\" type=\"application/n-triples\"/>\n<link rel=\"alternate\" href=\"herman-fierlafijn.ttl\" type=\"text/turtle\"/>\n<link rel=\"alternate\" href=\"herman-fierlafijn.rj\" type=\"application/rdf+json\"/>\n<link rel=\"alternate\" href=\"herman-fierlafijn.trig\" type=\"text/trig\"/>\n<link rel=\"alternate\" href=\"herman-fierlafijn.trix\" type=\"application/trix\"/>\n","schema:name":"Herman Fierlafijn","ofd:actorType":["at:pointOfSale","at:farmShop"]}}