{"type":"Feature","geometry":{"type":"Point","coordinates":[4.403361,50.976576]},"properties":{"id":"https://w3id.org/openfooddata/actors/fruithandel-doms","name":"Fruithandel Doms","img":[],"type":["at:pointOfSale","at:farmShop","at:producer"],"upstream":[],"downstream":[]}}