{"type":"Feature","geometry":{"type":"Point","coordinates":[3.00956,51.257125]},"properties":{"id":"https://w3id.org/openfooddata/actors/ijswinkel-t-vossenerf","name":"IJswinkel 't Vossenerf","img":["http://www.rechtvanbijdeboer.be/sites/default/files/styles/producer_teaser/public/1939906_436231369812513_852117107_n.jpg?itok=G5bQOrv_"],"type":["at:pointOfSale","at:farmShop"],"upstream":[{"@type":"ofd:ActorRelationship","ofd:relatedContext":"at:producer","ofd:relatedActor":"https://w3id.org/openfooddata/actors/t-vossenerf"}]}}