{"type":"Feature","geometry":{"type":"Point","coordinates":[5.224428,50.933737]},"properties":{"id":"https://w3id.org/openfooddata/actors/dimitri-meuwis","name":"Dimitri Meuwis","img":[],"type":["at:pointOfSale","at:collectionPoint"],"upstream":[{"@type":"ofd:ActorRelationship","ofd:relatedContext":"at:producer","ofd:relatedActor":"https://w3id.org/openfooddata/actors/vof-pircup"}]}}