{"type":"Feature","geometry":{"type":"Point","coordinates":[3.21403,51.197235]},"properties":{"foaf:account":[],"foaf:name":"Buurderij De Open Poort (Sint-Michiels)","foaf:isPrimaryTopicOf":["http://www.rechtvanbijdeboer.be/buurderij-de-open-poort-sint-michiels","http://www.rechtvanbijdeboer.be/node/2028"],"@type":"foaf:Agent","schema:image":["http://www.rechtvanbijdeboer.be/sites/default/files/styles/producer_teaser/public/herb_box.gif?itok=ZAl8UItf"],"@context":"https://openfooddata.github.io/actors/_common/context.jsonld","schema:geo":{"schema:latitude":"51.197235","schema:longitude":"3.214030","@type":"schema:GeoCoordinates","schema:addressCountry":"Belgium","schema:address":{"@type":"schema:PostalAddress","schema:streetAddress":"Psychiatrisch Ziekenhuis OLV, Koning Albert I-laan 8","schema:postalCode":"8200","schema:addressLocality":"Sint-Michiels (Brugge)"}},"ofd:offersFoodType":["ft:potatoes","ft:fruits","ft:vegetables","ft:poultry_meat","ft:beef","ft:icecream","ft:lamb_meat","ft:milk_products","ft:fruit_juices","ft:pork","ft:eggs","ft:alcoholic_beverages","ft:spices"],"foaf:depiction":["http://www.rechtvanbijdeboer.be/sites/default/files/styles/producer_teaser/public/herb_box.gif?itok=ZAl8UItf"],"schema:description":"","ofd:upstreamRel":[{"@type":"ofd:ActorRelationship","ofd:relatedContext":"at:producer","ofd:relatedActor":"https://w3id.org/openfooddata/actors/hoeve-ijs-z"},{"@type":"ofd:ActorRelationship","ofd:relatedContext":"at:producer","ofd:relatedActor":"https://w3id.org/openfooddata/actors/hof-ter-meulen"},{"@type":"ofd:ActorRelationship","ofd:relatedContext":"at:producer","ofd:relatedActor":"https://w3id.org/openfooddata/actors/milki"},{"@type":"ofd:ActorRelationship","ofd:relatedContext":"at:producer","ofd:relatedActor":"https://w3id.org/openfooddata/actors/t-lof-der-kruiden"},{"@type":"ofd:ActorRelationship","ofd:relatedContext":"at:producer","ofd:relatedActor":"https://w3id.org/openfooddata/actors/augustijnenhof"},{"@type":"ofd:ActorRelationship","ofd:relatedContext":"at:producer","ofd:relatedActor":"https://w3id.org/openfooddata/actors/hoeve-t-lijsternest"}],"@id":"https://w3id.org/openfooddata/actors/buurderij-de-open-poort-sint-michiels","schema:name":"Buurderij De Open Poort (Sint-Michiels)","ofd:actorType":["at:pointOfSale","at:foodAssembly"]}}