{"type":"Feature","geometry":{"type":"Point","coordinates":[4.069884,50.935884]},"properties":{"id":"https://w3id.org/openfooddata/actors/aalst-0","name":"Aalst","img":[],"type":["at:pointOfSale","at:vegetableSubscription"],"upstream":[{"@type":"ofd:ActorRelationship","ofd:relatedContext":"at:producer","ofd:relatedActor":"https://w3id.org/openfooddata/actors/de-kollebloem"}]}}