{"type":"Feature","geometry":{"type":"Point","coordinates":[3.044567,51.093601]},"properties":{"foaf:account":[],"foaf:name":"Open plukdagen","foaf:isPrimaryTopicOf":["http://www.rechtvanbijdeboer.be/open-plukdagen","http://www.rechtvanbijdeboer.be/node/3303"],"@type":"foaf:Agent","schema:image":[],"@context":"https://openfooddata.github.io/actors/_common/context.jsonld","schema:geo":{"schema:latitude":"51.093601","schema:longitude":"3.044567","@type":"schema:GeoCoordinates","schema:addressCountry":"Belgium","schema:address":{"@type":"schema:PostalAddress","schema:streetAddress":"Torhoutbaan","schema:postalCode":"8480","schema:addressLocality":"Ichtegem"}},"ofd:offersFoodType":["ft:fruits","ft:spices","ft:lamb_meat","ft:beef","ft:pork","ft:vegetables","ft:milk_products"],"foaf:depiction":[],"schema:description":"","ofd:upstreamRel":[{"@type":"ofd:ActorRelationship","ofd:relatedContext":"at:producer","ofd:relatedActor":"https://w3id.org/openfooddata/actors/koolmees"}],"@id":"https://w3id.org/openfooddata/actors/open-plukdagen","schema:name":"Open plukdagen","ofd:actorType":["at:pointOfSale"]}}