{"type":"Feature","geometry":{"type":"Point","coordinates":[4.437177,51.316161]},"properties":{"id":"https://w3id.org/openfooddata/actors/voedselteam-kapellen","name":"Voedselteam Kapellen","img":[],"type":["at:pointOfSale","at:foodTeams"],"upstream":[{"@type":"ofd:ActorRelationship","ofd:relatedContext":"at:producer","ofd:relatedActor":"https://w3id.org/openfooddata/actors/antwerpse-honing---de-stadsimker"},{"@type":"ofd:ActorRelationship","ofd:relatedContext":"at:producer","ofd:relatedActor":"https://w3id.org/openfooddata/actors/wijngaardhof"}]}}