{"type":"Feature","geometry":{"type":"Point","coordinates":[3.90271,51.147096]},"properties":{"id":"https://w3id.org/openfooddata/actors/fruitteeltbedrijf-dirk-poelman","name":"Fruitteeltbedrijf Dirk Poelman","img":[],"type":["at:pointOfSale","at:farmShop","at:producer"],"upstream":[],"downstream":[]}}