{"type":"Feature","geometry":{"type":"Point","coordinates":[4.855099,50.859042]},"properties":{"foaf:account":[],"foaf:name":"Aardappelautomaat","foaf:isPrimaryTopicOf":["http://www.rechtvanbijdeboer.be/aardappelautomaat-8","http://www.rechtvanbijdeboer.be/node/3172"],"@type":"foaf:Agent","schema:image":[],"@context":"https://openfooddata.github.io/actors/_common/context.jsonld","schema:geo":{"schema:latitude":"50.859042","schema:longitude":"4.855099","@type":"schema:GeoCoordinates","schema:addressCountry":"Belgium","schema:address":{"@type":"schema:PostalAddress","schema:streetAddress":"Malendriesstraat 137","schema:postalCode":"3370","schema:addressLocality":"Kerkom"}},"ofd:offersFoodType":["ft:potatoes"],"foaf:depiction":[],"schema:description":"","ofd:upstreamRel":[{"@type":"ofd:ActorRelationship","ofd:relatedContext":"at:producer","ofd:relatedActor":"https://w3id.org/openfooddata/actors/pardon-luc"}],"@id":"https://w3id.org/openfooddata/actors/aardappelautomaat-8","extraHeader":"<link rel=\"alternate\" href=\"aardappelautomaat-8.rdf\" type=\"application/rdf+xml\"/>\n<link rel=\"alternate\" href=\"aardappelautomaat-8.jsonld\" type=\"application/ld+json\"/>\n<link rel=\"alternate\" href=\"aardappelautomaat-8.nq\" type=\"application/n-quads\"/>\n<link rel=\"alternate\" href=\"aardappelautomaat-8.nt\" type=\"application/n-triples\"/>\n<link rel=\"alternate\" href=\"aardappelautomaat-8.ttl\" type=\"text/turtle\"/>\n<link rel=\"alternate\" href=\"aardappelautomaat-8.rj\" type=\"application/rdf+json\"/>\n<link rel=\"alternate\" href=\"aardappelautomaat-8.trig\" type=\"text/trig\"/>\n<link rel=\"alternate\" href=\"aardappelautomaat-8.trix\" type=\"application/trix\"/>\n","schema:name":"Aardappelautomaat","ofd:actorType":["at:pointOfSale","at:vendingMachine"]}}