{"type":"Feature","geometry":{"type":"Point","coordinates":[4.855099,50.859042]},"properties":{"foaf:account":[],"foaf:name":"Aardappelautomaat","foaf:isPrimaryTopicOf":["http://www.rechtvanbijdeboer.be/aardappelautomaat-8","http://www.rechtvanbijdeboer.be/node/3172"],"@type":"foaf:Agent","schema:image":[],"@context":"https://openfooddata.github.io/actors/_common/context.jsonld","schema:geo":{"schema:latitude":"50.859042","schema:longitude":"4.855099","@type":"schema:GeoCoordinates","schema:addressCountry":"Belgium","schema:address":{"@type":"schema:PostalAddress","schema:streetAddress":"Malendriesstraat 137","schema:postalCode":"3370","schema:addressLocality":"Kerkom"}},"ofd:offersFoodType":["ft:potatoes"],"foaf:depiction":[],"schema:description":"","ofd:upstreamRel":[{"@type":"ofd:ActorRelationship","ofd:relatedContext":"at:producer","ofd:relatedActor":"https://w3id.org/openfooddata/actors/pardon-luc"}],"@id":"https://w3id.org/openfooddata/actors/aardappelautomaat-8","schema:name":"Aardappelautomaat","ofd:actorType":["at:pointOfSale","at:vendingMachine"]}}