{"type":"Feature","geometry":{"type":"Point","coordinates":[3.233745,51.179248]},"properties":{"foaf:account":[],"foaf:name":"Brugge-St-Michiels (bestellen via biobello.be)","foaf:isPrimaryTopicOf":["http://www.rechtvanbijdeboer.be/brugge-st-michiels-bestellen-biobellobe","http://www.rechtvanbijdeboer.be/node/2435"],"@type":"foaf:Agent","schema:image":["http://www.rechtvanbijdeboer.be/sites/default/files/styles/producer_teaser/public/biobellogroentenenfruitmaxi.jpg?itok=n2EToMw3"],"@context":"https://openfooddata.github.io/actors/_common/context.jsonld","schema:geo":{"schema:latitude":"51.179248","schema:longitude":"3.233745","@type":"schema:GeoCoordinates","schema:addressCountry":"Belgium","schema:address":{"@type":"schema:PostalAddress","schema:streetAddress":"Kortrijkstraat 10","schema:postalCode":"8200","schema:addressLocality":"Sint-Michiels"}},"ofd:offersFoodType":["ft:potatoes","ft:fruits","ft:eggs","ft:vegetables"],"foaf:depiction":["http://www.rechtvanbijdeboer.be/sites/default/files/styles/producer_teaser/public/biobellogroentenenfruitmaxi.jpg?itok=n2EToMw3"],"schema:description":"","ofd:upstreamRel":[{"@type":"ofd:ActorRelationship","ofd:relatedContext":"at:producer","ofd:relatedActor":"https://w3id.org/openfooddata/actors/de-lochting-vzw"}],"@id":"https://w3id.org/openfooddata/actors/brugge-st-michiels-bestellen-biobellobe","extraHeader":"<link rel=\"alternate\" href=\"brugge-st-michiels-bestellen-biobellobe.rdf\" type=\"application/rdf+xml\"/>\n<link rel=\"alternate\" href=\"brugge-st-michiels-bestellen-biobellobe.jsonld\" type=\"application/ld+json\"/>\n<link rel=\"alternate\" href=\"brugge-st-michiels-bestellen-biobellobe.nq\" type=\"application/n-quads\"/>\n<link rel=\"alternate\" href=\"brugge-st-michiels-bestellen-biobellobe.nt\" type=\"application/n-triples\"/>\n<link rel=\"alternate\" href=\"brugge-st-michiels-bestellen-biobellobe.ttl\" type=\"text/turtle\"/>\n<link rel=\"alternate\" href=\"brugge-st-michiels-bestellen-biobellobe.rj\" type=\"application/rdf+json\"/>\n<link rel=\"alternate\" href=\"brugge-st-michiels-bestellen-biobellobe.trig\" type=\"text/trig\"/>\n<link rel=\"alternate\" href=\"brugge-st-michiels-bestellen-biobellobe.trix\" type=\"application/trix\"/>\n","schema:name":"Brugge-St-Michiels (bestellen via biobello.be)","ofd:actorType":["at:pointOfSale","at:collectionPoint"]}}