{"type":"Feature","geometry":{"type":"Point","coordinates":[3.764215,51.204584]},"properties":{"id":"https://w3id.org/openfooddata/actors/hamerlinck-lv","name":"Hamerlinck LV","img":["http://www.rechtvanbijdeboer.be/sites/default/files/styles/producer_teaser/public/05082012223.jpg?itok=CHjZcO9Y"],"type":["at:pointOfSale","at:vendingMachine"],"upstream":[{"@type":"ofd:ActorRelationship","ofd:relatedContext":"at:producer","ofd:relatedActor":"https://w3id.org/openfooddata/actors/aveschoothoeve"}]}}