{"type":"Feature","geometry":{"type":"Point","coordinates":[3.563016,51.21347]},"properties":{"foaf:account":[],"foaf:name":"'t Keizershof","schema:url":[],"foaf:homepage":[],"foaf:isPrimaryTopicOf":["http://www.rechtvanbijdeboer.be/t-keizershof-0","http://www.rechtvanbijdeboer.be/node/3086","https://www.rechtvanbijdeboer.be/t-keizershof","https://www.rechtvanbijdeboer.be/node/1594"],"@type":"foaf:Agent","schema:image":[],"@context":"https://openfooddata.github.io/actors/_common/context.jsonld","schema:geo":{"schema:latitude":"51.213470","schema:longitude":"3.563016","@type":"schema:GeoCoordinates","schema:addressCountry":"Belgium","schema:address":{"@type":"schema:PostalAddress","schema:streetAddress":"Moerstraat 8","schema:postalCode":"9900","schema:addressLocality":"Eeklo"}},"ofd:offersFoodType":["ft:fruits","ft:vegetables","ft:potatoes"],"foaf:depiction":[],"schema:description":"","ofd:upstreamRel":[],"ofd:downstreamRel":[],"@id":"https://w3id.org/openfooddata/actors/t-keizershof","extraHeader":"<link rel=\"alternate\" href=\"t-keizershof.rdf\" type=\"application/rdf+xml\"/>\n<link rel=\"alternate\" href=\"t-keizershof.jsonld\" type=\"application/ld+json\"/>\n<link rel=\"alternate\" href=\"t-keizershof.nq\" type=\"application/n-quads\"/>\n<link rel=\"alternate\" href=\"t-keizershof.nt\" type=\"application/n-triples\"/>\n<link rel=\"alternate\" href=\"t-keizershof.ttl\" type=\"text/turtle\"/>\n<link rel=\"alternate\" href=\"t-keizershof.rj\" type=\"application/rdf+json\"/>\n<link rel=\"alternate\" href=\"t-keizershof.trig\" type=\"text/trig\"/>\n<link rel=\"alternate\" href=\"t-keizershof.trix\" type=\"application/trix\"/>\n","schema:name":"'t Keizershof","ofd:actorType":["at:pointOfSale","at:farmShop","at:producer"]}}