{"type":"Feature","geometry":{"type":"Point","coordinates":[5.57227,50.93196]},"properties":{"id":"https://w3id.org/openfooddata/actors/het-vrije-veld-csa-boerderij-0","name":"Het Vrije Veld - CSA-boerderij","img":[],"type":["at:pointOfSale","at:csaFarm"],"upstream":[{"@type":"ofd:ActorRelationship","ofd:relatedContext":"at:producer","ofd:relatedActor":"https://w3id.org/openfooddata/actors/het-vrije-veld---csa-boerderij"}]}}