{"type":"Feature","geometry":{"type":"Point","coordinates":[4.61917,50.926555]},"properties":{"foaf:account":[],"foaf:name":"wriemeling","schema:url":[],"foaf:homepage":[],"foaf:isPrimaryTopicOf":["http://www.rechtvanbijdeboer.be/wriemeling-0","http://www.rechtvanbijdeboer.be/node/2207","https://www.rechtvanbijdeboer.be/wriemeling","https://www.rechtvanbijdeboer.be/node/1338","http://www.rechtvanbijdeboer.be/wriemeling-1","http://www.rechtvanbijdeboer.be/node/2810"],"@type":"foaf:Agent","schema:image":[],"@context":"https://openfooddata.github.io/actors/_common/context.jsonld","schema:geo":{"schema:latitude":"50.926555","schema:longitude":"4.619170","@type":"schema:GeoCoordinates","schema:addressCountry":"Belgium","schema:address":{"@type":"schema:PostalAddress","schema:streetAddress":"drogenbosstraat 6","schema:postalCode":"3020","schema:addressLocality":"veltem beisem"}},"ofd:offersFoodType":["ft:poultry_meat","ft:milk_products","ft:eggs","ft:fruits","ft:vegetables","ft:potatoes"],"foaf:depiction":[],"schema:description":"","ofd:upstreamRel":[],"ofd:downstreamRel":[],"@id":"https://w3id.org/openfooddata/actors/wriemeling","extraHeader":"<link rel=\"alternate\" href=\"wriemeling.rdf\" type=\"application/rdf+xml\"/>\n<link rel=\"alternate\" href=\"wriemeling.jsonld\" type=\"application/ld+json\"/>\n<link rel=\"alternate\" href=\"wriemeling.nq\" type=\"application/n-quads\"/>\n<link rel=\"alternate\" href=\"wriemeling.nt\" type=\"application/n-triples\"/>\n<link rel=\"alternate\" href=\"wriemeling.ttl\" type=\"text/turtle\"/>\n<link rel=\"alternate\" href=\"wriemeling.rj\" type=\"application/rdf+json\"/>\n<link rel=\"alternate\" href=\"wriemeling.trig\" type=\"text/trig\"/>\n<link rel=\"alternate\" href=\"wriemeling.trix\" type=\"application/trix\"/>\n","schema:name":"wriemeling","ofd:actorType":["at:pointOfSale","at:producer","at:foodTeams","at:farmShop"]}}