{"type":"Feature","geometry":{"type":"Point","coordinates":[3.749019,50.991511]},"properties":{"foaf:account":[],"foaf:name":"Afhaalpunt Merelbeke Centrum","foaf:isPrimaryTopicOf":["http://www.rechtvanbijdeboer.be/afhaalpunt-merelbeke-centrum","http://www.rechtvanbijdeboer.be/node/3545"],"@type":"foaf:Agent","schema:image":[],"@context":"https://openfooddata.github.io/actors/_common/context.jsonld","schema:geo":{"schema:latitude":"50.991511","schema:longitude":"3.749019","@type":"schema:GeoCoordinates","schema:addressCountry":"Belgium","schema:address":{"@type":"schema:PostalAddress","schema:streetAddress":"Dr. O. De Gruyterstraat 10","schema:postalCode":"9820","schema:addressLocality":"Merelbeke"}},"ofd:offersFoodType":["ft:potatoes","ft:fruits","ft:bakery_products","ft:eggs","ft:fruit_juices","ft:spices","ft:beef","ft:alcoholic_beverages","ft:vegetables","ft:milk_products"],"foaf:depiction":[],"schema:description":"","ofd:upstreamRel":[{"@type":"ofd:ActorRelationship","ofd:relatedContext":"at:producer","ofd:relatedActor":"https://w3id.org/openfooddata/actors/de-wassende-maan"}],"@id":"https://w3id.org/openfooddata/actors/afhaalpunt-merelbeke-centrum","schema:name":"Afhaalpunt Merelbeke Centrum","ofd:actorType":["at:pointOfSale","at:vegetableSubscription"]}}