{"type":"Feature","geometry":{"type":"Point","coordinates":[4.521419,51.144698]},"properties":{"id":"https://w3id.org/openfooddata/actors/de-melkautomaat-2","name":"De Melkautomaat","img":[],"type":["at:pointOfSale","at:vendingMachine"],"upstream":[{"@type":"ofd:ActorRelationship","ofd:relatedContext":"at:producer","ofd:relatedActor":"https://w3id.org/openfooddata/actors/melkautomaat"}]}}