{"type":"Feature","geometry":{"type":"Point","coordinates":[3.764015,51.034295]},"properties":{"id":"https://w3id.org/openfooddata/actors/gentbrugge","name":"Gentbrugge","img":[],"type":["at:pointOfSale","at:vegetableSubscription"],"upstream":[{"@type":"ofd:ActorRelationship","ofd:relatedContext":"at:producer","ofd:relatedActor":"https://w3id.org/openfooddata/actors/de-zonnekouter"}]}}