{"type":"Feature","geometry":{"type":"Point","coordinates":[4.394567,51.20771]},"properties":{"id":"https://w3id.org/openfooddata/actors/voedselteam-antwerpen-zuid","name":"Voedselteam Antwerpen-Zuid","img":["http://www.rechtvanbijdeboer.be/sites/default/files/styles/producer_teaser/public/_mg_9535.jpg?itok=xcRRLz6b"],"type":["at:pointOfSale","at:foodTeams"],"upstream":[{"@type":"ofd:ActorRelationship","ofd:relatedContext":"at:producer","ofd:relatedActor":"https://w3id.org/openfooddata/actors/geitenboerderij-t-eikenhof"},{"@type":"ofd:ActorRelationship","ofd:relatedContext":"at:producer","ofd:relatedActor":"https://w3id.org/openfooddata/actors/antwerpse-honing---de-stadsimker"},{"@type":"ofd:ActorRelationship","ofd:relatedContext":"at:producer","ofd:relatedActor":"https://w3id.org/openfooddata/actors/widar"},{"@type":"ofd:ActorRelationship","ofd:relatedContext":"at:producer","ofd:relatedActor":"https://w3id.org/openfooddata/actors/wijngaardhof"}]}}