{"type":"Feature","geometry":{"type":"Point","coordinates":[4.941001,50.918581]},"properties":{"foaf:account":[],"foaf:name":"Het Vershuisje","foaf:isPrimaryTopicOf":["http://www.rechtvanbijdeboer.be/het-vershuisje","http://www.rechtvanbijdeboer.be/node/3358"],"@type":"foaf:Agent","schema:image":[],"@context":"https://openfooddata.github.io/actors/_common/context.jsonld","schema:geo":{"schema:latitude":"50.918581","schema:longitude":"4.941001","@type":"schema:GeoCoordinates","schema:addressCountry":"Belgium","schema:address":{"@type":"schema:PostalAddress","schema:streetAddress":"Halensebaan 68","schema:postalCode":"3461","schema:addressLocality":"Bekkevoort"}},"ofd:offersFoodType":["ft:fruits","ft:poultry_meat","ft:vegetables"],"foaf:depiction":[],"schema:description":"","ofd:upstreamRel":[{"@type":"ofd:ActorRelationship","ofd:relatedContext":"at:producer","ofd:relatedActor":"https://w3id.org/openfooddata/actors/marluk-bvba"}],"@id":"https://w3id.org/openfooddata/actors/het-vershuisje","schema:name":"Het Vershuisje","ofd:actorType":["at:pointOfSale","at:vendingMachine"]}}