{"type":"Feature","geometry":{"type":"Point","coordinates":[4.980098,51.312498]},"properties":{"id":"https://w3id.org/openfooddata/actors/appelen-roes","name":"Appelen Roes","img":[],"type":["at:pointOfSale","at:farmShop"],"upstream":[{"@type":"ofd:ActorRelationship","ofd:relatedContext":"at:producer","ofd:relatedActor":"https://w3id.org/openfooddata/actors/belfru---appelen-roes"}]}}