{"type":"Feature","geometry":{"type":"Point","coordinates":[4.73571,50.88514]},"properties":{"id":"https://w3id.org/openfooddata/actors/markt-kessel-lo","name":"Markt Kessel-Lo","img":["http://www.rechtvanbijdeboer.be/sites/default/files/styles/producer_teaser/public/de_levende_aarde_cvba_geitenkaasjes.jpg?itok=LMhPoryB"],"type":["at:pointOfSale","at:market"],"upstream":[{"@type":"ofd:ActorRelationship","ofd:relatedContext":"at:producer","ofd:relatedActor":"https://w3id.org/openfooddata/actors/de-levende-aarde-cvba"},{"@type":"ofd:ActorRelationship","ofd:relatedContext":"at:producer","ofd:relatedActor":"https://w3id.org/openfooddata/actors/het-gulden-gehucht---oogsttuin-eoster"},{"@type":"ofd:ActorRelationship","ofd:relatedContext":"at:producer","ofd:relatedActor":"https://w3id.org/openfooddata/actors/hoevebrood-van-doren"},{"@type":"ofd:ActorRelationship","ofd:relatedContext":"at:producer","ofd:relatedActor":"https://w3id.org/openfooddata/actors/de-fruittuin"}]}}