{"type":"Feature","geometry":{"type":"Point","coordinates":[4.702979,50.92464]},"properties":{"id":"https://w3id.org/openfooddata/actors/steinerschool-de-zonnewijzer","name":"Steinerschool De Zonnewijzer","img":[],"type":["at:pointOfSale","at:vegetableSubscription"],"upstream":[{"@type":"ofd:ActorRelationship","ofd:relatedContext":"at:producer","ofd:relatedActor":"https://w3id.org/openfooddata/actors/de-levensbron"}]}}