{"type":"Feature","geometry":{"type":"Point","coordinates":[3.625344,51.10999]},"properties":{"foaf:account":[],"foaf:name":"De Zwaluw","schema:url":[],"foaf:homepage":[],"foaf:isPrimaryTopicOf":["http://www.rechtvanbijdeboer.be/de-zwaluw-0","http://www.rechtvanbijdeboer.be/node/2815","https://www.rechtvanbijdeboer.be/de-zwaluw","https://www.rechtvanbijdeboer.be/node/1343"],"@type":"foaf:Agent","schema:image":[],"@context":"https://openfooddata.github.io/actors/_common/context.jsonld","schema:geo":{"schema:latitude":"51.109990","schema:longitude":"3.625344","@type":"schema:GeoCoordinates","schema:addressCountry":"Belgium","schema:address":{"@type":"schema:PostalAddress","schema:streetAddress":"Verbindingsweg 66","schema:postalCode":"9920","schema:addressLocality":"Lovendegem"}},"ofd:offersFoodType":["ft:milk_products","ft:eggs","ft:vegetables","ft:icecream","ft:potatoes"],"foaf:depiction":[],"schema:description":"","ofd:upstreamRel":[],"ofd:downstreamRel":[],"@id":"https://w3id.org/openfooddata/actors/de-zwaluw","schema:name":"De Zwaluw","ofd:actorType":["at:pointOfSale","at:farmShop","at:producer"]}}