{"type":"Feature","geometry":{"type":"Point","coordinates":[4.759874,51.138614]},"properties":{"id":"https://w3id.org/openfooddata/actors/de-kruidenfee","name":"De Kruidenfee","img":[],"type":["at:pointOfSale","at:vegetableSubscription"],"upstream":[{"@type":"ofd:ActorRelationship","ofd:relatedContext":"at:producer","ofd:relatedActor":"https://w3id.org/openfooddata/actors/de-bio-hoeve"}]}}