{"type":"Feature","geometry":{"type":"Point","coordinates":[3.976183,50.984576]},"properties":{"id":"https://w3id.org/openfooddata/actors/van-der-meersch-eeckhaudt","name":"Van Der Meersch - Eeckhaudt","img":[],"type":["at:pointOfSale","at:farmShop"],"upstream":[{"@type":"ofd:ActorRelationship","ofd:relatedContext":"at:producer","ofd:relatedActor":"https://w3id.org/openfooddata/actors/hoeve-van-der-meersch-eeckhaudt"}]}}