{"type":"Feature","geometry":{"type":"Point","coordinates":[3.165536,50.872343]},"properties":{"foaf:account":[],"foaf:name":"Zuivelhoeve Dendauw","foaf:isPrimaryTopicOf":["http://www.rechtvanbijdeboer.be/zuivelhoeve-dendauw-0","http://www.rechtvanbijdeboer.be/node/3359"],"@type":"foaf:Agent","schema:image":[],"@context":"https://openfooddata.github.io/actors/_common/context.jsonld","schema:geo":{"schema:latitude":"50.872343","schema:longitude":"3.165536","@type":"schema:GeoCoordinates","schema:addressCountry":"Belgium","schema:address":{"@type":"schema:PostalAddress","schema:streetAddress":"Rollegemkapelsestr 74","schema:postalCode":"8880","schema:addressLocality":"St. Eloois Winkel"}},"ofd:offersFoodType":["ft:potatoes","ft:eggs","ft:icecream","ft:milk_products"],"foaf:depiction":[],"schema:description":"","ofd:upstreamRel":[{"@type":"ofd:ActorRelationship","ofd:relatedContext":"at:producer","ofd:relatedActor":"https://w3id.org/openfooddata/actors/zuivelhoeve-dendauw"}],"@id":"https://w3id.org/openfooddata/actors/zuivelhoeve-dendauw-0","schema:name":"Zuivelhoeve Dendauw","ofd:actorType":["at:pointOfSale","at:farmShop"]}}