{"type":"Feature","geometry":{"type":"Point","coordinates":[3.165536,50.872343]},"properties":{"foaf:account":[],"foaf:name":"Zuivelhoeve Dendauw","foaf:isPrimaryTopicOf":["http://www.rechtvanbijdeboer.be/zuivelhoeve-dendauw-0","http://www.rechtvanbijdeboer.be/node/3359"],"@type":"foaf:Agent","schema:image":[],"@context":"https://openfooddata.github.io/actors/_common/context.jsonld","schema:geo":{"schema:latitude":"50.872343","schema:longitude":"3.165536","@type":"schema:GeoCoordinates","schema:addressCountry":"Belgium","schema:address":{"@type":"schema:PostalAddress","schema:streetAddress":"Rollegemkapelsestr 74","schema:postalCode":"8880","schema:addressLocality":"St. Eloois Winkel"}},"ofd:offersFoodType":["ft:potatoes","ft:eggs","ft:icecream","ft:milk_products"],"foaf:depiction":[],"schema:description":"","ofd:upstreamRel":[{"@type":"ofd:ActorRelationship","ofd:relatedContext":"at:producer","ofd:relatedActor":"https://w3id.org/openfooddata/actors/zuivelhoeve-dendauw"}],"@id":"https://w3id.org/openfooddata/actors/zuivelhoeve-dendauw-0","extraHeader":"<link rel=\"alternate\" href=\"zuivelhoeve-dendauw-0.rdf\" type=\"application/rdf+xml\"/>\n<link rel=\"alternate\" href=\"zuivelhoeve-dendauw-0.jsonld\" type=\"application/ld+json\"/>\n<link rel=\"alternate\" href=\"zuivelhoeve-dendauw-0.nq\" type=\"application/n-quads\"/>\n<link rel=\"alternate\" href=\"zuivelhoeve-dendauw-0.nt\" type=\"application/n-triples\"/>\n<link rel=\"alternate\" href=\"zuivelhoeve-dendauw-0.ttl\" type=\"text/turtle\"/>\n<link rel=\"alternate\" href=\"zuivelhoeve-dendauw-0.rj\" type=\"application/rdf+json\"/>\n<link rel=\"alternate\" href=\"zuivelhoeve-dendauw-0.trig\" type=\"text/trig\"/>\n<link rel=\"alternate\" href=\"zuivelhoeve-dendauw-0.trix\" type=\"application/trix\"/>\n","schema:name":"Zuivelhoeve Dendauw","ofd:actorType":["at:pointOfSale","at:farmShop"]}}