{"type":"Feature","geometry":{"type":"Point","coordinates":[5.810858,51.136774]},"properties":{"id":"https://w3id.org/openfooddata/actors/het-bommesaarke","name":"Het Bommesaarke","img":["http://www.rechtvanbijdeboer.be/sites/default/files/styles/producer_teaser/public/bommesaarke_asperges_asperge.jpg?itok=lXdocK70"],"type":["at:pointOfSale","at:farmShop"],"upstream":[{"@type":"ofd:ActorRelationship","ofd:relatedContext":"at:producer","ofd:relatedActor":"https://w3id.org/openfooddata/actors/hoeve-t-bommesaarke"}]}}