{"type":"Feature","geometry":{"type":"Point","coordinates":[3.48983,50.899992]},"properties":{"foaf:account":[],"foaf:name":"Boterhoeve","schema:url":[],"foaf:homepage":[],"foaf:isPrimaryTopicOf":["http://www.rechtvanbijdeboer.be/boterhoeve-0","http://www.rechtvanbijdeboer.be/node/3082","https://www.rechtvanbijdeboer.be/boterhoeve","https://www.rechtvanbijdeboer.be/node/1590"],"@type":"foaf:Agent","schema:image":[],"@context":"https://openfooddata.github.io/actors/_common/context.jsonld","schema:geo":{"schema:latitude":"50.899992","schema:longitude":"3.489830","@type":"schema:GeoCoordinates","schema:addressCountry":"Belgium","schema:address":{"@type":"schema:PostalAddress","schema:streetAddress":"Meirestraat 3","schema:postalCode":"9770","schema:addressLocality":"Kruishoutem"}},"ofd:offersFoodType":["ft:milk_products","ft:potatoes"],"foaf:depiction":[],"schema:description":"","ofd:upstreamRel":[],"ofd:downstreamRel":[],"@id":"https://w3id.org/openfooddata/actors/boterhoeve","extraHeader":"<link rel=\"alternate\" href=\"boterhoeve.rdf\" type=\"application/rdf+xml\"/>\n<link rel=\"alternate\" href=\"boterhoeve.jsonld\" type=\"application/ld+json\"/>\n<link rel=\"alternate\" href=\"boterhoeve.nq\" type=\"application/n-quads\"/>\n<link rel=\"alternate\" href=\"boterhoeve.nt\" type=\"application/n-triples\"/>\n<link rel=\"alternate\" href=\"boterhoeve.ttl\" type=\"text/turtle\"/>\n<link rel=\"alternate\" href=\"boterhoeve.rj\" type=\"application/rdf+json\"/>\n<link rel=\"alternate\" href=\"boterhoeve.trig\" type=\"text/trig\"/>\n<link rel=\"alternate\" href=\"boterhoeve.trix\" type=\"application/trix\"/>\n","schema:name":"Boterhoeve","ofd:actorType":["at:pointOfSale","at:farmShop","at:producer"]}}