{"type":"Feature","geometry":{"type":"Point","coordinates":[4.459751,50.941136]},"properties":{"foaf:account":[],"foaf:name":"'t Stalleke","schema:url":[],"foaf:homepage":[],"foaf:isPrimaryTopicOf":["http://www.rechtvanbijdeboer.be/t-stalleke-0","http://www.rechtvanbijdeboer.be/node/2928","https://www.rechtvanbijdeboer.be/t-stalleke","https://www.rechtvanbijdeboer.be/node/1439"],"@type":"foaf:Agent","schema:image":[],"@context":"https://openfooddata.github.io/actors/_common/context.jsonld","schema:geo":{"schema:latitude":"50.941136","schema:longitude":"4.459751","@type":"schema:GeoCoordinates","schema:addressCountry":"Belgium","schema:address":{"@type":"schema:PostalAddress","schema:streetAddress":"Buitingstraat 11","schema:postalCode":"1800","schema:addressLocality":"Vilvoorde"}},"ofd:offersFoodType":["ft:eggs","ft:fruits","ft:vegetables"],"foaf:depiction":[],"schema:description":"","ofd:upstreamRel":[],"ofd:downstreamRel":[],"@id":"https://w3id.org/openfooddata/actors/t-stalleke","schema:name":"'t Stalleke","ofd:actorType":["at:pointOfSale","at:farmShop","at:producer"]}}