{"type":"Feature","geometry":{"type":"Point","coordinates":[3.205145,50.842825]},"properties":{"foaf:account":[],"foaf:name":"Puur","foaf:isPrimaryTopicOf":["http://www.rechtvanbijdeboer.be/puur","http://www.rechtvanbijdeboer.be/node/2451"],"@type":"foaf:Agent","schema:image":["http://www.rechtvanbijdeboer.be/sites/default/files/styles/producer_teaser/public/biobellogroentenenfruitmaxi.jpg?itok=n2EToMw3"],"@context":"https://openfooddata.github.io/actors/_common/context.jsonld","schema:geo":{"schema:latitude":"50.842825","schema:longitude":"3.205145","@type":"schema:GeoCoordinates","schema:addressCountry":"Belgium","schema:address":{"@type":"schema:PostalAddress","schema:streetAddress":"Bissegemsestraat 9","schema:postalCode":"8560","schema:addressLocality":"Gullegem"}},"ofd:offersFoodType":["ft:potatoes","ft:fruits","ft:eggs","ft:vegetables"],"foaf:depiction":["http://www.rechtvanbijdeboer.be/sites/default/files/styles/producer_teaser/public/biobellogroentenenfruitmaxi.jpg?itok=n2EToMw3"],"schema:description":"","ofd:upstreamRel":[{"@type":"ofd:ActorRelationship","ofd:relatedContext":"at:producer","ofd:relatedActor":"https://w3id.org/openfooddata/actors/de-lochting-vzw"}],"@id":"https://w3id.org/openfooddata/actors/puur","schema:name":"Puur","ofd:actorType":["at:pointOfSale","at:vegetableSubscription"]}}