{"type":"Feature","geometry":{"type":"Point","coordinates":[3.334712,50.812885]},"properties":{"foaf:account":[],"foaf:name":"Oxfam Wereldwinkel Zwevegem","foaf:isPrimaryTopicOf":["http://www.rechtvanbijdeboer.be/oxfam-wereldwinkel-zwevegem","http://www.rechtvanbijdeboer.be/node/3185"],"@type":"foaf:Agent","schema:image":[],"@context":"https://openfooddata.github.io/actors/_common/context.jsonld","schema:geo":{"schema:latitude":"50.812885","schema:longitude":"3.334712","@type":"schema:GeoCoordinates","schema:addressCountry":"Belgium","schema:address":{"@type":"schema:PostalAddress","schema:streetAddress":"Otegemstraat 7","schema:postalCode":"8550","schema:addressLocality":"Zwevegem"}},"ofd:offersFoodType":["ft:potatoes","ft:fruits","ft:vegetables","ft:poultry_meat"],"foaf:depiction":[],"schema:description":"","ofd:upstreamRel":[{"@type":"ofd:ActorRelationship","ofd:relatedContext":"at:producer","ofd:relatedActor":"https://w3id.org/openfooddata/actors/de-hakboer"}],"@id":"https://w3id.org/openfooddata/actors/oxfam-wereldwinkel-zwevegem","schema:name":"Oxfam Wereldwinkel Zwevegem","ofd:actorType":["at:pointOfSale","at:collectionPoint"]}}