{"type":"Feature","geometry":{"type":"Point","coordinates":[2.890666,51.100685]},"properties":{"id":"https://w3id.org/openfooddata/actors/josiane-jonckheere-bestellen-biobellobe","name":"Josiane Jonckheere (bestellen via biobello.be)","img":["http://www.rechtvanbijdeboer.be/sites/default/files/styles/producer_teaser/public/biobellogroentenenfruitmaxi.jpg?itok=n2EToMw3"],"type":["at:pointOfSale","at:collectionPoint"],"upstream":[{"@type":"ofd:ActorRelationship","ofd:relatedContext":"at:producer","ofd:relatedActor":"https://w3id.org/openfooddata/actors/de-lochting-vzw"}]}}