{"type":"Feature","geometry":{"type":"Point","coordinates":[2.890666,51.100685]},"properties":{"foaf:account":[],"foaf:name":"Josiane Jonckheere (bestellen via biobello.be)","foaf:isPrimaryTopicOf":["http://www.rechtvanbijdeboer.be/josiane-jonckheere-bestellen-biobellobe","http://www.rechtvanbijdeboer.be/node/2454"],"@type":"foaf:Agent","schema:image":["http://www.rechtvanbijdeboer.be/sites/default/files/styles/producer_teaser/public/biobellogroentenenfruitmaxi.jpg?itok=n2EToMw3"],"@context":"https://openfooddata.github.io/actors/_common/context.jsonld","schema:geo":{"schema:latitude":"51.100685","schema:longitude":"2.890666","@type":"schema:GeoCoordinates","schema:addressCountry":"Belgium","schema:address":{"@type":"schema:PostalAddress","schema:streetAddress":"Lekedorpstraat 70","schema:postalCode":"8600","schema:addressLocality":"Leke"}},"ofd:offersFoodType":["ft:potatoes","ft:fruits","ft:eggs","ft:vegetables"],"foaf:depiction":["http://www.rechtvanbijdeboer.be/sites/default/files/styles/producer_teaser/public/biobellogroentenenfruitmaxi.jpg?itok=n2EToMw3"],"schema:description":"","ofd:upstreamRel":[{"@type":"ofd:ActorRelationship","ofd:relatedContext":"at:producer","ofd:relatedActor":"https://w3id.org/openfooddata/actors/de-lochting-vzw"}],"@id":"https://w3id.org/openfooddata/actors/josiane-jonckheere-bestellen-biobellobe","extraHeader":"<link rel=\"alternate\" href=\"josiane-jonckheere-bestellen-biobellobe.rdf\" type=\"application/rdf+xml\"/>\n<link rel=\"alternate\" href=\"josiane-jonckheere-bestellen-biobellobe.jsonld\" type=\"application/ld+json\"/>\n<link rel=\"alternate\" href=\"josiane-jonckheere-bestellen-biobellobe.nq\" type=\"application/n-quads\"/>\n<link rel=\"alternate\" href=\"josiane-jonckheere-bestellen-biobellobe.nt\" type=\"application/n-triples\"/>\n<link rel=\"alternate\" href=\"josiane-jonckheere-bestellen-biobellobe.ttl\" type=\"text/turtle\"/>\n<link rel=\"alternate\" href=\"josiane-jonckheere-bestellen-biobellobe.rj\" type=\"application/rdf+json\"/>\n<link rel=\"alternate\" href=\"josiane-jonckheere-bestellen-biobellobe.trig\" type=\"text/trig\"/>\n<link rel=\"alternate\" href=\"josiane-jonckheere-bestellen-biobellobe.trix\" type=\"application/trix\"/>\n","schema:name":"Josiane Jonckheere (bestellen via biobello.be)","ofd:actorType":["at:pointOfSale","at:collectionPoint"]}}