{"type":"Feature","geometry":{"type":"Point","coordinates":[3.244739,51.20716]},"properties":{"id":"https://w3id.org/openfooddata/actors/voedselteam-brugge","name":"Voedselteam Brugge","img":["http://www.rechtvanbijdeboer.be/sites/default/files/styles/producer_teaser/public/10449962_1469163179995605_8558182526507174092_n.jpg?itok=_mtcIfby"],"type":["at:pointOfSale","at:foodTeams"],"upstream":[{"@type":"ofd:ActorRelationship","ofd:relatedContext":"at:producer","ofd:relatedActor":"https://w3id.org/openfooddata/actors/hoeve-ijs-z"},{"@type":"ofd:ActorRelationship","ofd:relatedContext":"at:producer","ofd:relatedActor":"https://w3id.org/openfooddata/actors/hoeve-t-lijsternest"},{"@type":"ofd:ActorRelationship","ofd:relatedContext":"at:producer","ofd:relatedActor":"https://w3id.org/openfooddata/actors/koolmees"},{"@type":"ofd:ActorRelationship","ofd:relatedContext":"at:producer","ofd:relatedActor":"https://w3id.org/openfooddata/actors/t-ambrozijn"}]}}