{"type":"Feature","geometry":{"type":"Point","coordinates":[4.234913,50.732485]},"properties":{"foaf:account":[],"foaf:name":"Bioboerderij Vandersmissen","schema:url":[],"foaf:homepage":[],"foaf:isPrimaryTopicOf":["http://www.rechtvanbijdeboer.be/bioboerderij-vandersmissen-0","http://www.rechtvanbijdeboer.be/node/2807","https://www.rechtvanbijdeboer.be/bioboerderij-vandersmissen","https://www.rechtvanbijdeboer.be/node/1335"],"@type":"foaf:Agent","schema:image":[],"@context":"https://openfooddata.github.io/actors/_common/context.jsonld","schema:geo":{"schema:latitude":"50.732485","schema:longitude":"4.234913","@type":"schema:GeoCoordinates","schema:addressCountry":"Belgium","schema:address":{"@type":"schema:PostalAddress","schema:streetAddress":"St-Pietersleeuwsesteenweg 36","schema:postalCode":"1500","schema:addressLocality":"Halle"}},"ofd:offersFoodType":["ft:vegetables","ft:potatoes"],"foaf:depiction":[],"schema:description":"","ofd:upstreamRel":[],"ofd:downstreamRel":[],"@id":"https://w3id.org/openfooddata/actors/bioboerderij-vandersmissen","extraHeader":"<link rel=\"alternate\" href=\"bioboerderij-vandersmissen.rdf\" type=\"application/rdf+xml\"/>\n<link rel=\"alternate\" href=\"bioboerderij-vandersmissen.jsonld\" type=\"application/ld+json\"/>\n<link rel=\"alternate\" href=\"bioboerderij-vandersmissen.nq\" type=\"application/n-quads\"/>\n<link rel=\"alternate\" href=\"bioboerderij-vandersmissen.nt\" type=\"application/n-triples\"/>\n<link rel=\"alternate\" href=\"bioboerderij-vandersmissen.ttl\" type=\"text/turtle\"/>\n<link rel=\"alternate\" href=\"bioboerderij-vandersmissen.rj\" type=\"application/rdf+json\"/>\n<link rel=\"alternate\" href=\"bioboerderij-vandersmissen.trig\" type=\"text/trig\"/>\n<link rel=\"alternate\" href=\"bioboerderij-vandersmissen.trix\" type=\"application/trix\"/>\n","schema:name":"Bioboerderij Vandersmissen","ofd:actorType":["at:pointOfSale","at:vendingMachine","at:producer"]}}