{"type":"Feature","geometry":{"type":"Point","coordinates":[4.234913,50.732485]},"properties":{"id":"https://w3id.org/openfooddata/actors/bioboerderij-vandersmissen","name":"Bioboerderij Vandersmissen","img":[],"type":["at:pointOfSale","at:vendingMachine","at:producer"],"upstream":[],"downstream":[]}}