{"type":"Feature","geometry":{"type":"Point","coordinates":[3.447516,50.78384]},"properties":{"id":"https://w3id.org/openfooddata/actors/het-ganzenhof","name":"Het Ganzenhof","img":[],"type":["at:pointOfSale","at:farmShop","at:producer"],"upstream":[],"downstream":[]}}