{"type":"Feature","geometry":{"type":"Point","coordinates":[2.703599,51.120647]},"properties":{"id":"https://w3id.org/openfooddata/actors/oyaert-noel","name":"Oyaert Noel","img":[],"type":["at:pointOfSale","at:farmShop","at:producer"],"upstream":[],"downstream":[]}}