{"type":"Feature","geometry":{"type":"Point","coordinates":[3.044567,51.093601]},"properties":{"foaf:account":[],"foaf:name":"Koolmees zelfoogsttuin","foaf:isPrimaryTopicOf":["http://www.rechtvanbijdeboer.be/koolmees-zelfoogsttuin","http://www.rechtvanbijdeboer.be/node/3304"],"@type":"foaf:Agent","schema:image":[],"@context":"https://openfooddata.github.io/actors/_common/context.jsonld","schema:geo":{"schema:latitude":"51.093601","schema:longitude":"3.044567","@type":"schema:GeoCoordinates","schema:addressCountry":"Belgium","schema:address":{"@type":"schema:PostalAddress","schema:streetAddress":"Torhoutbaan","schema:postalCode":"8480","schema:addressLocality":"Ichtegem"}},"ofd:offersFoodType":["ft:fruits","ft:spices","ft:lamb_meat","ft:beef","ft:pork","ft:vegetables","ft:milk_products"],"foaf:depiction":[],"schema:description":"","ofd:upstreamRel":[{"@type":"ofd:ActorRelationship","ofd:relatedContext":"at:producer","ofd:relatedActor":"https://w3id.org/openfooddata/actors/koolmees"}],"@id":"https://w3id.org/openfooddata/actors/koolmees-zelfoogsttuin","extraHeader":"<link rel=\"alternate\" href=\"koolmees-zelfoogsttuin.rdf\" type=\"application/rdf+xml\"/>\n<link rel=\"alternate\" href=\"koolmees-zelfoogsttuin.jsonld\" type=\"application/ld+json\"/>\n<link rel=\"alternate\" href=\"koolmees-zelfoogsttuin.nq\" type=\"application/n-quads\"/>\n<link rel=\"alternate\" href=\"koolmees-zelfoogsttuin.nt\" type=\"application/n-triples\"/>\n<link rel=\"alternate\" href=\"koolmees-zelfoogsttuin.ttl\" type=\"text/turtle\"/>\n<link rel=\"alternate\" href=\"koolmees-zelfoogsttuin.rj\" type=\"application/rdf+json\"/>\n<link rel=\"alternate\" href=\"koolmees-zelfoogsttuin.trig\" type=\"text/trig\"/>\n<link rel=\"alternate\" href=\"koolmees-zelfoogsttuin.trix\" type=\"application/trix\"/>\n","schema:name":"Koolmees zelfoogsttuin","ofd:actorType":["at:pointOfSale","at:csaFarm"]}}