{"type":"Feature","geometry":{"type":"Point","coordinates":[5.519941,50.902236]},"properties":{"id":"https://w3id.org/openfooddata/actors/munsterbilzen","name":"Munsterbilzen","img":[],"type":["at:pointOfSale","at:collectionPoint"],"upstream":[{"@type":"ofd:ActorRelationship","ofd:relatedContext":"at:producer","ofd:relatedActor":"https://w3id.org/openfooddata/actors/bio-bij-bernd,-www.biobijbernd.be"}]}}