{"type":"Feature","geometry":{"type":"Point","coordinates":[4.343152,50.821521]},"properties":{"foaf:account":[],"foaf:name":"Gokan","foaf:isPrimaryTopicOf":["http://www.rechtvanbijdeboer.be/gokan","http://www.rechtvanbijdeboer.be/node/3568"],"@type":"foaf:Agent","schema:image":["http://www.rechtvanbijdeboer.be/sites/default/files/styles/producer_teaser/public/fotosessiestreekprodukten%20%2846%29_1.jpg?itok=P8yY02ej"],"@context":"https://openfooddata.github.io/actors/_common/context.jsonld","schema:geo":{"schema:latitude":"50.821521","schema:longitude":"4.343152","@type":"schema:GeoCoordinates","schema:addressCountry":"Belgium","schema:address":{"@type":"schema:PostalAddress","schema:streetAddress":"Albertlaan 8","schema:postalCode":"1190","schema:addressLocality":"Vorst"}},"ofd:offersFoodType":["ft:potatoes","ft:bakery_products","ft:eggs","ft:fruits","ft:fruit_juices","ft:vegetables","ft:icecream","ft:spices","ft:alcoholic_beverages","ft:milk_products"],"foaf:depiction":["http://www.rechtvanbijdeboer.be/sites/default/files/styles/producer_teaser/public/fotosessiestreekprodukten%20%2846%29_1.jpg?itok=P8yY02ej"],"schema:description":"","ofd:upstreamRel":[{"@type":"ofd:ActorRelationship","ofd:relatedContext":"at:producer","ofd:relatedActor":"https://w3id.org/openfooddata/actors/den-diepen-boomgaard"}],"@id":"https://w3id.org/openfooddata/actors/gokan","schema:name":"Gokan","ofd:actorType":["at:pointOfSale","at:vegetableSubscription"]}}