{"type":"Feature","geometry":{"type":"Point","coordinates":[3.004214,51.020511]},"properties":{"foaf:account":[],"foaf:name":"De Strohalm (bestellen via biobello.be)","foaf:isPrimaryTopicOf":["http://www.rechtvanbijdeboer.be/de-strohalm-bestellen-biobellobe","http://www.rechtvanbijdeboer.be/node/2455"],"@type":"foaf:Agent","schema:image":["http://www.rechtvanbijdeboer.be/sites/default/files/styles/producer_teaser/public/biobellogroentenenfruitmaxi.jpg?itok=n2EToMw3"],"@context":"https://openfooddata.github.io/actors/_common/context.jsonld","schema:geo":{"schema:latitude":"51.020511","schema:longitude":"3.004214","@type":"schema:GeoCoordinates","schema:addressCountry":"Belgium","schema:address":{"@type":"schema:PostalAddress","schema:streetAddress":"Kronevoordestraat 64","schema:postalCode":"8610","schema:addressLocality":"Handzame"}},"ofd:offersFoodType":["ft:potatoes","ft:fruits","ft:eggs","ft:vegetables"],"foaf:depiction":["http://www.rechtvanbijdeboer.be/sites/default/files/styles/producer_teaser/public/biobellogroentenenfruitmaxi.jpg?itok=n2EToMw3"],"schema:description":"","ofd:upstreamRel":[{"@type":"ofd:ActorRelationship","ofd:relatedContext":"at:producer","ofd:relatedActor":"https://w3id.org/openfooddata/actors/de-lochting-vzw"}],"@id":"https://w3id.org/openfooddata/actors/de-strohalm-bestellen-biobellobe","schema:name":"De Strohalm (bestellen via biobello.be)","ofd:actorType":["at:pointOfSale","at:collectionPoint"]}}