{"type":"Feature","geometry":{"type":"Point","coordinates":[4.696028,50.928256]},"properties":{"foaf:account":[],"foaf:name":"Voedselteam Wijgmaal Bis","foaf:isPrimaryTopicOf":["http://www.rechtvanbijdeboer.be/voedselteam-wijgmaal-bis","http://www.rechtvanbijdeboer.be/node/2202"],"@type":"foaf:Agent","schema:image":["http://www.rechtvanbijdeboer.be/sites/default/files/styles/producer_teaser/public/ronald.JPG?itok=pGIeS0-1"],"@context":"https://openfooddata.github.io/actors/_common/context.jsonld","schema:geo":{"schema:latitude":"50.928256","schema:longitude":"4.696028","@type":"schema:GeoCoordinates","schema:addressCountry":"Belgium","schema:address":{"@type":"schema:PostalAddress","schema:streetAddress":"Casinolaan 82","schema:postalCode":"3018","schema:addressLocality":"Wijgmaal"}},"ofd:offersFoodType":["ft:potatoes","ft:bakery_products","ft:eggs","ft:poultry_meat","ft:fruit_juices","ft:icecream","ft:spices","ft:lamb_meat","ft:beef","ft:pork","ft:alcoholic_beverages","ft:vegetables","ft:milk_products","ft:fruits"],"foaf:depiction":["http://www.rechtvanbijdeboer.be/sites/default/files/styles/producer_teaser/public/ronald.JPG?itok=pGIeS0-1"],"schema:description":"","ofd:upstreamRel":[{"@type":"ofd:ActorRelationship","ofd:relatedContext":"at:producer","ofd:relatedActor":"https://w3id.org/openfooddata/actors/vzw-de-winning-maatwerk"},{"@type":"ofd:ActorRelationship","ofd:relatedContext":"at:producer","ofd:relatedActor":"https://w3id.org/openfooddata/actors/de-ploeg"},{"@type":"ofd:ActorRelationship","ofd:relatedContext":"at:producer","ofd:relatedActor":"https://w3id.org/openfooddata/actors/druiven-vanderkelen"},{"@type":"ofd:ActorRelationship","ofd:relatedContext":"at:producer","ofd:relatedActor":"https://w3id.org/openfooddata/actors/fv-van-haesendonck"},{"@type":"ofd:ActorRelationship","ofd:relatedContext":"at:producer","ofd:relatedActor":"https://w3id.org/openfooddata/actors/de-levende-aarde-cvba"},{"@type":"ofd:ActorRelationship","ofd:relatedContext":"at:producer","ofd:relatedActor":"https://w3id.org/openfooddata/actors/regalys"},{"@type":"ofd:ActorRelationship","ofd:relatedContext":"at:producer","ofd:relatedActor":"https://w3id.org/openfooddata/actors/de-levensbron"},{"@type":"ofd:ActorRelationship","ofd:relatedContext":"at:producer","ofd:relatedActor":"https://w3id.org/openfooddata/actors/wonen-&-werken-de-wikke"},{"@type":"ofd:ActorRelationship","ofd:relatedContext":"at:producer","ofd:relatedActor":"https://w3id.org/openfooddata/actors/de-fruittuin"},{"@type":"ofd:ActorRelationship","ofd:relatedContext":"at:producer","ofd:relatedActor":"https://w3id.org/openfooddata/actors/gallinero"},{"@type":"ofd:ActorRelationship","ofd:relatedContext":"at:producer","ofd:relatedActor":"https://w3id.org/openfooddata/actors/t-fruitratje"},{"@type":"ofd:ActorRelationship","ofd:relatedContext":"at:producer","ofd:relatedActor":"https://w3id.org/openfooddata/actors/hof-ter-vrijlegem"}],"@id":"https://w3id.org/openfooddata/actors/voedselteam-wijgmaal-bis","extraHeader":"<link rel=\"alternate\" href=\"voedselteam-wijgmaal-bis.rdf\" type=\"application/rdf+xml\"/>\n<link rel=\"alternate\" href=\"voedselteam-wijgmaal-bis.jsonld\" type=\"application/ld+json\"/>\n<link rel=\"alternate\" href=\"voedselteam-wijgmaal-bis.nq\" type=\"application/n-quads\"/>\n<link rel=\"alternate\" href=\"voedselteam-wijgmaal-bis.nt\" type=\"application/n-triples\"/>\n<link rel=\"alternate\" href=\"voedselteam-wijgmaal-bis.ttl\" type=\"text/turtle\"/>\n<link rel=\"alternate\" href=\"voedselteam-wijgmaal-bis.rj\" type=\"application/rdf+json\"/>\n<link rel=\"alternate\" href=\"voedselteam-wijgmaal-bis.trig\" type=\"text/trig\"/>\n<link rel=\"alternate\" href=\"voedselteam-wijgmaal-bis.trix\" type=\"application/trix\"/>\n","schema:name":"Voedselteam Wijgmaal Bis","ofd:actorType":["at:pointOfSale","at:foodTeams"]}}