{"type":"Feature","geometry":{"type":"Point","coordinates":[5.212462,51.017301]},"properties":{"foaf:account":[],"foaf:name":"IJs De Hoef","schema:url":[],"foaf:homepage":[],"foaf:isPrimaryTopicOf":["http://www.rechtvanbijdeboer.be/ijs-de-hoef-0","http://www.rechtvanbijdeboer.be/node/2975","https://www.rechtvanbijdeboer.be/ijs-de-hoef","https://www.rechtvanbijdeboer.be/node/1487"],"@type":"foaf:Agent","schema:image":[],"@context":"https://openfooddata.github.io/actors/_common/context.jsonld","schema:geo":{"schema:latitude":"51.017301","schema:longitude":"5.212462","@type":"schema:GeoCoordinates","schema:addressCountry":"Belgium","schema:address":{"@type":"schema:PostalAddress","schema:streetAddress":"Geneikenstraat 51","schema:postalCode":"3560","schema:addressLocality":"Lummen"}},"ofd:offersFoodType":["ft:icecream"],"foaf:depiction":[],"schema:description":"","ofd:upstreamRel":[],"ofd:downstreamRel":[],"@id":"https://w3id.org/openfooddata/actors/ijs-de-hoef","schema:name":"IJs De Hoef","ofd:actorType":["at:pointOfSale","at:farmShop","at:producer"]}}