{"type":"Feature","geometry":{"type":"Point","coordinates":[3.307739,51.00124]},"properties":{"id":"https://w3id.org/openfooddata/actors/van-koe-op-tafel","name":"Van koe op tafel","img":[],"type":["at:pointOfSale","at:farmShop","at:producer"],"upstream":[],"downstream":[]}}