{"type":"Feature","geometry":{"type":"Point","coordinates":[5.591762,51.183214]},"properties":{"id":"https://w3id.org/openfooddata/actors/danny-clauwers-0","name":"Danny Clauwers","img":[],"type":["at:pointOfSale","at:farmShop"],"upstream":[{"@type":"ofd:ActorRelationship","ofd:relatedContext":"at:producer","ofd:relatedActor":"https://w3id.org/openfooddata/actors/danny-clauwers"}]}}