{"type":"Feature","geometry":{"type":"Point","coordinates":[2.601841,51.082449]},"properties":{"foaf:account":[],"foaf:name":"Hoeve Noordgasthuis","foaf:isPrimaryTopicOf":["http://www.rechtvanbijdeboer.be/hoeve-noordgasthuis","http://www.rechtvanbijdeboer.be/node/2692"],"@type":"foaf:Agent","schema:image":[],"@context":"https://openfooddata.github.io/actors/_common/context.jsonld","schema:geo":{"schema:latitude":"51.082449","schema:longitude":"2.601841","@type":"schema:GeoCoordinates","schema:addressCountry":"Belgium","schema:address":{"@type":"schema:PostalAddress","schema:streetAddress":"De Pannelaan 95","schema:postalCode":"8660","schema:addressLocality":"Adinkerke"}},"ofd:offersFoodType":["ft:potatoes","ft:fruits","ft:icecream","ft:vegetables","ft:milk_products"],"foaf:depiction":[],"schema:description":"","ofd:upstreamRel":[{"@type":"ofd:ActorRelationship","ofd:relatedContext":"at:producer","ofd:relatedActor":"https://w3id.org/openfooddata/actors/hoeve-noord-gasthuis"}],"@id":"https://w3id.org/openfooddata/actors/hoeve-noordgasthuis","extraHeader":"<link rel=\"alternate\" href=\"hoeve-noordgasthuis.rdf\" type=\"application/rdf+xml\"/>\n<link rel=\"alternate\" href=\"hoeve-noordgasthuis.jsonld\" type=\"application/ld+json\"/>\n<link rel=\"alternate\" href=\"hoeve-noordgasthuis.nq\" type=\"application/n-quads\"/>\n<link rel=\"alternate\" href=\"hoeve-noordgasthuis.nt\" type=\"application/n-triples\"/>\n<link rel=\"alternate\" href=\"hoeve-noordgasthuis.ttl\" type=\"text/turtle\"/>\n<link rel=\"alternate\" href=\"hoeve-noordgasthuis.rj\" type=\"application/rdf+json\"/>\n<link rel=\"alternate\" href=\"hoeve-noordgasthuis.trig\" type=\"text/trig\"/>\n<link rel=\"alternate\" href=\"hoeve-noordgasthuis.trix\" type=\"application/trix\"/>\n","schema:name":"Hoeve Noordgasthuis","ofd:actorType":["at:pointOfSale","at:farmShop"]}}