{"type":"Feature","geometry":{"type":"Point","coordinates":[3.34901,51.3405]},"properties":{"id":"https://w3id.org/openfooddata/actors/hoeve-ijs-hazegras","name":"Hoeve-ijs Hazegras","img":[],"type":["at:pointOfSale","at:farmShop","at:producer"],"upstream":[],"downstream":[]}}