{"type":"Feature","geometry":{"type":"Point","coordinates":[4.475534,51.028049]},"properties":{"id":"https://w3id.org/openfooddata/actors/buurderij-mechelen","name":"Buurderij Mechelen","img":["http://www.rechtvanbijdeboer.be/sites/default/files/styles/producer_teaser/public/012-hooilaarthoeve.jpg?itok=PK9kdOh2"],"type":["at:pointOfSale","at:foodAssembly"],"upstream":[{"@type":"ofd:ActorRelationship","ofd:relatedContext":"at:producer","ofd:relatedActor":"https://w3id.org/openfooddata/actors/hammes-hoevevlees"},{"@type":"ofd:ActorRelationship","ofd:relatedContext":"at:producer","ofd:relatedActor":"https://w3id.org/openfooddata/actors/hooilaarthoeve"},{"@type":"ofd:ActorRelationship","ofd:relatedContext":"at:producer","ofd:relatedActor":"https://w3id.org/openfooddata/actors/fruithandel-doms"}]}}