{"type":"Feature","geometry":{"type":"Point","coordinates":[4.204863,50.900288]},"properties":{"id":"https://w3id.org/openfooddata/actors/van-der-meersch","name":"Van Der Meersch","img":[],"type":["at:pointOfSale","at:farmShop"],"upstream":[{"@type":"ofd:ActorRelationship","ofd:relatedContext":"at:producer","ofd:relatedActor":"https://w3id.org/openfooddata/actors/hoeve-van-der-meersch-eeckhaudt"}]}}