{"type":"Feature","geometry":{"type":"Point","coordinates":[3.432345,51.076908]},"properties":{"foaf:account":[],"foaf:name":"Aalter","foaf:isPrimaryTopicOf":["http://www.rechtvanbijdeboer.be/aalter","http://www.rechtvanbijdeboer.be/node/2142"],"@type":"foaf:Agent","schema:image":[],"@context":"https://openfooddata.github.io/actors/_common/context.jsonld","schema:geo":{"schema:latitude":"51.076908","schema:longitude":"3.432345","@type":"schema:GeoCoordinates","schema:addressCountry":"Belgium","schema:address":{"@type":"schema:PostalAddress","schema:postalCode":"9880","schema:addressLocality":"Aalter"}},"ofd:offersFoodType":["ft:eggs","ft:milk_products"],"foaf:depiction":[],"schema:description":"","ofd:upstreamRel":[{"@type":"ofd:ActorRelationship","ofd:relatedContext":"at:producer","ofd:relatedActor":"https://w3id.org/openfooddata/actors/t-hof-rozendale"}],"@id":"https://w3id.org/openfooddata/actors/aalter","schema:name":"Aalter","ofd:actorType":["at:pointOfSale","at:market"]}}