{"type":"Feature","geometry":{"type":"Point","coordinates":[3.811697,50.945617]},"properties":{"foaf:account":[],"foaf:name":"Naturelle","foaf:isPrimaryTopicOf":["http://www.rechtvanbijdeboer.be/naturelle","http://www.rechtvanbijdeboer.be/node/2508"],"@type":"foaf:Agent","schema:image":[],"@context":"https://openfooddata.github.io/actors/_common/context.jsonld","schema:geo":{"schema:latitude":"50.945617","schema:longitude":"3.811697","@type":"schema:GeoCoordinates","schema:addressCountry":"Belgium","schema:address":{"@type":"schema:PostalAddress","schema:streetAddress":"Keiberg","schema:postalCode":"9860","schema:addressLocality":"Oosterzele"}},"ofd:offersFoodType":["ft:potatoes","ft:bakery_products","ft:eggs","ft:fruits","ft:fruit_juices","ft:vegetables","ft:spices","ft:alcoholic_beverages","ft:milk_products"],"foaf:depiction":[],"schema:description":"","ofd:upstreamRel":[{"@type":"ofd:ActorRelationship","ofd:relatedContext":"at:producer","ofd:relatedActor":"https://w3id.org/openfooddata/actors/de-kollebloem"}],"@id":"https://w3id.org/openfooddata/actors/naturelle","extraHeader":"<link rel=\"alternate\" href=\"naturelle.rdf\" type=\"application/rdf+xml\"/>\n<link rel=\"alternate\" href=\"naturelle.jsonld\" type=\"application/ld+json\"/>\n<link rel=\"alternate\" href=\"naturelle.nq\" type=\"application/n-quads\"/>\n<link rel=\"alternate\" href=\"naturelle.nt\" type=\"application/n-triples\"/>\n<link rel=\"alternate\" href=\"naturelle.ttl\" type=\"text/turtle\"/>\n<link rel=\"alternate\" href=\"naturelle.rj\" type=\"application/rdf+json\"/>\n<link rel=\"alternate\" href=\"naturelle.trig\" type=\"text/trig\"/>\n<link rel=\"alternate\" href=\"naturelle.trix\" type=\"application/trix\"/>\n","schema:name":"Naturelle","ofd:actorType":["at:pointOfSale","at:vegetableSubscription"]}}