{"type":"Feature","geometry":{"type":"Point","coordinates":[5.390933,51.135124]},"properties":{"foaf:account":[],"foaf:name":"Slegershof","schema:url":[],"foaf:homepage":[],"foaf:isPrimaryTopicOf":["http://www.rechtvanbijdeboer.be/slegershof-0","http://www.rechtvanbijdeboer.be/node/3478","https://www.rechtvanbijdeboer.be/slegershof","https://www.rechtvanbijdeboer.be/node/1696"],"@type":"foaf:Agent","schema:image":[],"@context":"https://openfooddata.github.io/actors/_common/context.jsonld","schema:geo":{"schema:latitude":"51.135124","schema:longitude":"5.390933","@type":"schema:GeoCoordinates","schema:addressCountry":"Belgium","schema:address":{"@type":"schema:PostalAddress","schema:streetAddress":"Slegerstraat 2","schema:postalCode":"3940","schema:addressLocality":"Hechtel-Eksel"}},"ofd:offersFoodType":["ft:eggs","ft:fruits","ft:vegetables"],"foaf:depiction":[],"schema:description":"","ofd:upstreamRel":[],"ofd:downstreamRel":[],"@id":"https://w3id.org/openfooddata/actors/slegershof","extraHeader":"<link rel=\"alternate\" href=\"slegershof.rdf\" type=\"application/rdf+xml\"/>\n<link rel=\"alternate\" href=\"slegershof.jsonld\" type=\"application/ld+json\"/>\n<link rel=\"alternate\" href=\"slegershof.nq\" type=\"application/n-quads\"/>\n<link rel=\"alternate\" href=\"slegershof.nt\" type=\"application/n-triples\"/>\n<link rel=\"alternate\" href=\"slegershof.ttl\" type=\"text/turtle\"/>\n<link rel=\"alternate\" href=\"slegershof.rj\" type=\"application/rdf+json\"/>\n<link rel=\"alternate\" href=\"slegershof.trig\" type=\"text/trig\"/>\n<link rel=\"alternate\" href=\"slegershof.trix\" type=\"application/trix\"/>\n","schema:name":"Slegershof","ofd:actorType":["at:pointOfSale","at:vendingMachine","at:producer"]}}