{"type":"Feature","geometry":{"type":"Point","coordinates":[3.155577,50.892376]},"properties":{"foaf:account":[],"foaf:name":"'T Hoveke","foaf:isPrimaryTopicOf":["http://www.rechtvanbijdeboer.be/t-hoveke","http://www.rechtvanbijdeboer.be/node/2771"],"@type":"foaf:Agent","schema:image":[],"@context":"https://openfooddata.github.io/actors/_common/context.jsonld","schema:geo":{"schema:latitude":"50.892376","schema:longitude":"3.155577","@type":"schema:GeoCoordinates","schema:addressCountry":"Belgium","schema:address":{"@type":"schema:PostalAddress","schema:streetAddress":"Rennevoordestraat 20","schema:postalCode":"8800","schema:addressLocality":"Roeselare - Oekene"}},"ofd:offersFoodType":["ft:lamb_meat"],"foaf:depiction":[],"schema:description":"","ofd:upstreamRel":[{"@type":"ofd:ActorRelationship","ofd:relatedContext":"at:producer","ofd:relatedActor":"https://w3id.org/openfooddata/actors/schapenfokkerij-t-hoveke"}],"@id":"https://w3id.org/openfooddata/actors/t-hoveke","schema:name":"'T Hoveke","ofd:actorType":["at:pointOfSale","at:farmShop"]}}