{"type":"Feature","geometry":{"type":"Point","coordinates":[3.155577,50.892376]},"properties":{"foaf:account":[],"foaf:name":"'T Hoveke","foaf:isPrimaryTopicOf":["http://www.rechtvanbijdeboer.be/t-hoveke","http://www.rechtvanbijdeboer.be/node/2771"],"@type":"foaf:Agent","schema:image":[],"@context":"https://openfooddata.github.io/actors/_common/context.jsonld","schema:geo":{"schema:latitude":"50.892376","schema:longitude":"3.155577","@type":"schema:GeoCoordinates","schema:addressCountry":"Belgium","schema:address":{"@type":"schema:PostalAddress","schema:streetAddress":"Rennevoordestraat 20","schema:postalCode":"8800","schema:addressLocality":"Roeselare - Oekene"}},"ofd:offersFoodType":["ft:lamb_meat"],"foaf:depiction":[],"schema:description":"","ofd:upstreamRel":[{"@type":"ofd:ActorRelationship","ofd:relatedContext":"at:producer","ofd:relatedActor":"https://w3id.org/openfooddata/actors/schapenfokkerij-t-hoveke"}],"@id":"https://w3id.org/openfooddata/actors/t-hoveke","extraHeader":"<link rel=\"alternate\" href=\"t-hoveke.rdf\" type=\"application/rdf+xml\"/>\n<link rel=\"alternate\" href=\"t-hoveke.jsonld\" type=\"application/ld+json\"/>\n<link rel=\"alternate\" href=\"t-hoveke.nq\" type=\"application/n-quads\"/>\n<link rel=\"alternate\" href=\"t-hoveke.nt\" type=\"application/n-triples\"/>\n<link rel=\"alternate\" href=\"t-hoveke.ttl\" type=\"text/turtle\"/>\n<link rel=\"alternate\" href=\"t-hoveke.rj\" type=\"application/rdf+json\"/>\n<link rel=\"alternate\" href=\"t-hoveke.trig\" type=\"text/trig\"/>\n<link rel=\"alternate\" href=\"t-hoveke.trix\" type=\"application/trix\"/>\n","schema:name":"'T Hoveke","ofd:actorType":["at:pointOfSale","at:farmShop"]}}