{"type":"Feature","geometry":{"type":"Point","coordinates":[4.813346,50.816926]},"properties":{"foaf:account":[],"foaf:name":"Neervelp","foaf:isPrimaryTopicOf":["http://www.rechtvanbijdeboer.be/neervelp","http://www.rechtvanbijdeboer.be/node/2229"],"@type":"foaf:Agent","schema:image":[],"@context":"https://openfooddata.github.io/actors/_common/context.jsonld","schema:geo":{"schema:latitude":"50.816926","schema:longitude":"4.813346","@type":"schema:GeoCoordinates","schema:addressCountry":"Belgium","schema:address":{"@type":"schema:PostalAddress","schema:streetAddress":"Klein-Heidestraat","schema:postalCode":"3370","schema:addressLocality":"Neervelp"}},"ofd:offersFoodType":["ft:potatoes","ft:fruits","ft:bakery_products","ft:eggs","ft:poultry_meat","ft:fruit_juices","ft:icecream","ft:spices","ft:lamb_meat","ft:beef","ft:pork","ft:alcoholic_beverages","ft:vegetables","ft:milk_products"],"foaf:depiction":[],"schema:description":"","ofd:upstreamRel":[],"@id":"https://w3id.org/openfooddata/actors/neervelp","extraHeader":"<link rel=\"alternate\" href=\"neervelp.rdf\" type=\"application/rdf+xml\"/>\n<link rel=\"alternate\" href=\"neervelp.jsonld\" type=\"application/ld+json\"/>\n<link rel=\"alternate\" href=\"neervelp.nq\" type=\"application/n-quads\"/>\n<link rel=\"alternate\" href=\"neervelp.nt\" type=\"application/n-triples\"/>\n<link rel=\"alternate\" href=\"neervelp.ttl\" type=\"text/turtle\"/>\n<link rel=\"alternate\" href=\"neervelp.rj\" type=\"application/rdf+json\"/>\n<link rel=\"alternate\" href=\"neervelp.trig\" type=\"text/trig\"/>\n<link rel=\"alternate\" href=\"neervelp.trix\" type=\"application/trix\"/>\n","schema:name":"Neervelp","ofd:actorType":["at:pointOfSale","at:foodTeams"]}}