{"type":"Feature","geometry":{"type":"Point","coordinates":[4.728836,50.842458]},"properties":{"id":"https://w3id.org/openfooddata/actors/sevenants-benny","name":"Sevenants Benny","img":["http://www.rechtvanbijdeboer.be/sites/default/files/styles/producer_teaser/public/default_images/emptyImg.jpg?itok=6POw8xTv"],"type":["at:pointOfSale","at:vendingMachine","at:producer"],"upstream":[],"downstream":[]}}