{"type":"Feature","geometry":{"type":"Point","coordinates":[4.958623,50.943943]},"properties":{"id":"https://w3id.org/openfooddata/actors/goedhuys-tom","name":"Goedhuys Tom","img":["http://www.rechtvanbijdeboer.be/sites/default/files/styles/producer_teaser/public/img_20150928_165938.jpg?itok=byeR0iMJ"],"type":["at:pointOfSale","at:farmShop"],"upstream":[{"@type":"ofd:ActorRelationship","ofd:relatedContext":"at:producer","ofd:relatedActor":"https://w3id.org/openfooddata/actors/goedhuys"}]}}