{"type":"Feature","geometry":{"type":"Point","coordinates":[3.763955,50.832865]},"properties":{"id":"https://w3id.org/openfooddata/actors/st-micha%C3%ABlshoeve","name":"St-Michaëlshoeve","img":[],"type":["at:pointOfSale","at:farmShop"],"upstream":[{"@type":"ofd:ActorRelationship","ofd:relatedContext":"at:producer","ofd:relatedActor":"https://w3id.org/openfooddata/actors/sint-michaelshoeve"}]}}