{"type":"Feature","geometry":{"type":"Point","coordinates":[3.095872,51.233354]},"properties":{"id":"https://w3id.org/openfooddata/actors/hoeve-t-lijsternest-ambachtelijke-zuivelproducten","name":"Hoeve 't Lijsternest - Ambachtelijke Zuivelproducten","img":[],"type":["at:pointOfSale","at:farmShop"],"upstream":[{"@type":"ofd:ActorRelationship","ofd:relatedContext":"at:producer","ofd:relatedActor":"https://w3id.org/openfooddata/actors/hoeve-t-lijsternest"}]}}