{"type":"Feature","geometry":{"type":"Point","coordinates":[3.233989,51.132134]},"properties":{"id":"https://w3id.org/openfooddata/actors/buythuys","name":"Buythuys","img":[],"type":["at:pointOfSale","at:collectionPoint"],"upstream":[{"@type":"ofd:ActorRelationship","ofd:relatedContext":"at:producer","ofd:relatedActor":"https://w3id.org/openfooddata/actors/vleeshoeve-buythuys"}]}}