{"type":"Feature","geometry":{"type":"Point","coordinates":[3.233989,51.132134]},"properties":{"foaf:account":[],"foaf:name":"Buythuys","foaf:isPrimaryTopicOf":["http://www.rechtvanbijdeboer.be/buythuys","http://www.rechtvanbijdeboer.be/node/3496"],"@type":"foaf:Agent","schema:image":[],"@context":"https://openfooddata.github.io/actors/_common/context.jsonld","schema:geo":{"schema:latitude":"51.132134","schema:longitude":"3.233989","@type":"schema:GeoCoordinates","schema:addressCountry":"Belgium","schema:address":{"@type":"schema:PostalAddress","schema:streetAddress":"Waterstraat 29","schema:postalCode":"8020","schema:addressLocality":"Oostkamp"}},"ofd:offersFoodType":["ft:pork"],"foaf:depiction":[],"schema:description":"","ofd:upstreamRel":[{"@type":"ofd:ActorRelationship","ofd:relatedContext":"at:producer","ofd:relatedActor":"https://w3id.org/openfooddata/actors/vleeshoeve-buythuys"}],"@id":"https://w3id.org/openfooddata/actors/buythuys","schema:name":"Buythuys","ofd:actorType":["at:pointOfSale","at:collectionPoint"]}}