{"type":"Feature","geometry":{"type":"Point","coordinates":[3.189491,50.963049]},"properties":{"foaf:account":[],"foaf:name":"Pattyn Johan","foaf:isPrimaryTopicOf":["http://www.rechtvanbijdeboer.be/pattyn-johan-0","http://www.rechtvanbijdeboer.be/node/3349"],"@type":"foaf:Agent","schema:image":[],"@context":"https://openfooddata.github.io/actors/_common/context.jsonld","schema:geo":{"schema:latitude":"50.963049","schema:longitude":"3.189491","@type":"schema:GeoCoordinates","schema:addressCountry":"Belgium","schema:address":{"@type":"schema:PostalAddress","schema:streetAddress":"Cloetbergstraat","schema:postalCode":"8850","schema:addressLocality":"Ardooie"}},"ofd:offersFoodType":["ft:fruits"],"foaf:depiction":[],"schema:description":"","ofd:upstreamRel":[{"@type":"ofd:ActorRelationship","ofd:relatedContext":"at:producer","ofd:relatedActor":"https://w3id.org/openfooddata/actors/pattyn-johan"}],"@id":"https://w3id.org/openfooddata/actors/pattyn-johan-0","schema:name":"Pattyn Johan","ofd:actorType":["at:pointOfSale","at:vendingMachine"]}}