{"type":"Feature","geometry":{"type":"Point","coordinates":[3.189491,50.963049]},"properties":{"foaf:account":[],"foaf:name":"Pattyn Johan","foaf:isPrimaryTopicOf":["http://www.rechtvanbijdeboer.be/pattyn-johan-0","http://www.rechtvanbijdeboer.be/node/3349"],"@type":"foaf:Agent","schema:image":[],"@context":"https://openfooddata.github.io/actors/_common/context.jsonld","schema:geo":{"schema:latitude":"50.963049","schema:longitude":"3.189491","@type":"schema:GeoCoordinates","schema:addressCountry":"Belgium","schema:address":{"@type":"schema:PostalAddress","schema:streetAddress":"Cloetbergstraat","schema:postalCode":"8850","schema:addressLocality":"Ardooie"}},"ofd:offersFoodType":["ft:fruits"],"foaf:depiction":[],"schema:description":"","ofd:upstreamRel":[{"@type":"ofd:ActorRelationship","ofd:relatedContext":"at:producer","ofd:relatedActor":"https://w3id.org/openfooddata/actors/pattyn-johan"}],"@id":"https://w3id.org/openfooddata/actors/pattyn-johan-0","extraHeader":"<link rel=\"alternate\" href=\"pattyn-johan-0.rdf\" type=\"application/rdf+xml\"/>\n<link rel=\"alternate\" href=\"pattyn-johan-0.jsonld\" type=\"application/ld+json\"/>\n<link rel=\"alternate\" href=\"pattyn-johan-0.nq\" type=\"application/n-quads\"/>\n<link rel=\"alternate\" href=\"pattyn-johan-0.nt\" type=\"application/n-triples\"/>\n<link rel=\"alternate\" href=\"pattyn-johan-0.ttl\" type=\"text/turtle\"/>\n<link rel=\"alternate\" href=\"pattyn-johan-0.rj\" type=\"application/rdf+json\"/>\n<link rel=\"alternate\" href=\"pattyn-johan-0.trig\" type=\"text/trig\"/>\n<link rel=\"alternate\" href=\"pattyn-johan-0.trix\" type=\"application/trix\"/>\n","schema:name":"Pattyn Johan","ofd:actorType":["at:pointOfSale","at:vendingMachine"]}}