{"type":"Feature","geometry":{"type":"Point","coordinates":[3.713626,51.005695]},"properties":{"id":"https://w3id.org/openfooddata/actors/afhaalpunt-zwijnaarde","name":"Afhaalpunt Zwijnaarde","img":[],"type":["at:pointOfSale","at:vegetableSubscription"],"upstream":[{"@type":"ofd:ActorRelationship","ofd:relatedContext":"at:producer","ofd:relatedActor":"https://w3id.org/openfooddata/actors/de-wassende-maan"}]}}