{"type":"Feature","geometry":{"type":"Point","coordinates":[4.372565,50.851311]},"properties":{"id":"https://w3id.org/openfooddata/actors/ten-noey","name":"Ten Noey","img":["http://www.rechtvanbijdeboer.be/sites/default/files/styles/producer_teaser/public/fotosessiestreekprodukten%20%2846%29_1.jpg?itok=P8yY02ej"],"type":["at:pointOfSale","at:vegetableSubscription"],"upstream":[{"@type":"ofd:ActorRelationship","ofd:relatedContext":"at:producer","ofd:relatedActor":"https://w3id.org/openfooddata/actors/den-diepen-boomgaard"}]}}