{"type":"Feature","geometry":{"type":"Point","coordinates":[4.567235,51.134609]},"properties":{"foaf:account":[],"foaf:name":"Buurderij Lier","foaf:isPrimaryTopicOf":["http://www.rechtvanbijdeboer.be/buurderij-lier","http://www.rechtvanbijdeboer.be/node/2020"],"@type":"foaf:Agent","schema:image":["http://www.rechtvanbijdeboer.be/sites/default/files/styles/producer_teaser/public/ipod172.jpg?itok=aOiNwqFK"],"@context":"https://openfooddata.github.io/actors/_common/context.jsonld","schema:geo":{"schema:latitude":"51.134609","schema:longitude":"4.567235","@type":"schema:GeoCoordinates","schema:addressCountry":"Belgium","schema:address":{"@type":"schema:PostalAddress","schema:streetAddress":"VTI Lier, Kruisbogenhofstraat 7","schema:postalCode":"2500","schema:addressLocality":"Lier"}},"ofd:offersFoodType":["ft:potatoes","ft:milk_products","ft:fruits","ft:lamb_meat","ft:beef","ft:pork"],"foaf:depiction":["http://www.rechtvanbijdeboer.be/sites/default/files/styles/producer_teaser/public/ipod172.jpg?itok=aOiNwqFK"],"schema:description":"","ofd:upstreamRel":[{"@type":"ofd:ActorRelationship","ofd:relatedContext":"at:producer","ofd:relatedActor":"https://w3id.org/openfooddata/actors/langveldhoeve"},{"@type":"ofd:ActorRelationship","ofd:relatedContext":"at:producer","ofd:relatedActor":"https://w3id.org/openfooddata/actors/op-het-veld"},{"@type":"ofd:ActorRelationship","ofd:relatedContext":"at:producer","ofd:relatedActor":"https://w3id.org/openfooddata/actors/t-zwarthof"}],"@id":"https://w3id.org/openfooddata/actors/buurderij-lier","extraHeader":"<link rel=\"alternate\" href=\"buurderij-lier.rdf\" type=\"application/rdf+xml\"/>\n<link rel=\"alternate\" href=\"buurderij-lier.jsonld\" type=\"application/ld+json\"/>\n<link rel=\"alternate\" href=\"buurderij-lier.nq\" type=\"application/n-quads\"/>\n<link rel=\"alternate\" href=\"buurderij-lier.nt\" type=\"application/n-triples\"/>\n<link rel=\"alternate\" href=\"buurderij-lier.ttl\" type=\"text/turtle\"/>\n<link rel=\"alternate\" href=\"buurderij-lier.rj\" type=\"application/rdf+json\"/>\n<link rel=\"alternate\" href=\"buurderij-lier.trig\" type=\"text/trig\"/>\n<link rel=\"alternate\" href=\"buurderij-lier.trix\" type=\"application/trix\"/>\n","schema:name":"Buurderij Lier","ofd:actorType":["at:pointOfSale","at:foodAssembly"]}}