{"type":"Feature","geometry":{"type":"Point","coordinates":[2.770429,50.847409]},"properties":{"foaf:account":[],"foaf:name":"Dries Beelprez","foaf:isPrimaryTopicOf":["http://www.rechtvanbijdeboer.be/dries-beelprez","http://www.rechtvanbijdeboer.be/node/3309"],"@type":"foaf:Agent","schema:image":[],"@context":"https://openfooddata.github.io/actors/_common/context.jsonld","schema:geo":{"schema:latitude":"50.847409","schema:longitude":"2.770429","@type":"schema:GeoCoordinates","schema:addressCountry":"Belgium","schema:address":{"@type":"schema:PostalAddress","schema:streetAddress":"Lindegoedstraat 2","schema:postalCode":"8970","schema:addressLocality":"Reningelst"}},"ofd:offersFoodType":["ft:potatoes","ft:fruits","ft:vegetables"],"foaf:depiction":[],"schema:description":"","ofd:upstreamRel":[{"@type":"ofd:ActorRelationship","ofd:relatedContext":"at:producer","ofd:relatedActor":"https://w3id.org/openfooddata/actors/tlindegoed"}],"@id":"https://w3id.org/openfooddata/actors/dries-beelprez","schema:name":"Dries Beelprez","ofd:actorType":["at:pointOfSale","at:farmShop"]}}