{"type":"Feature","geometry":{"type":"Point","coordinates":[5.489098,50.974517]},"properties":{"foaf:account":[],"foaf:name":"Markt Winterslag","foaf:isPrimaryTopicOf":["http://www.rechtvanbijdeboer.be/markt-winterslag","http://www.rechtvanbijdeboer.be/node/2091"],"@type":"foaf:Agent","schema:image":[],"@context":"https://openfooddata.github.io/actors/_common/context.jsonld","schema:geo":{"schema:latitude":"50.974517","schema:longitude":"5.489098","@type":"schema:GeoCoordinates","schema:addressCountry":"Belgium","schema:address":{"@type":"schema:PostalAddress","schema:streetAddress":"Vennestraat","schema:postalCode":"3600","schema:addressLocality":"Winterslag ( Genk)"}},"ofd:offersFoodType":["ft:eggs","ft:fruit_juices"],"foaf:depiction":[],"schema:description":"","ofd:upstreamRel":[{"@type":"ofd:ActorRelationship","ofd:relatedContext":"at:producer","ofd:relatedActor":"https://w3id.org/openfooddata/actors/kippenhof-nijst"}],"@id":"https://w3id.org/openfooddata/actors/markt-winterslag","schema:name":"Markt Winterslag","ofd:actorType":["at:pointOfSale","at:market"]}}