{"type":"Feature","geometry":{"type":"Point","coordinates":[3.736983,51.055626]},"properties":{"id":"https://w3id.org/openfooddata/actors/gent-trappenhuis","name":"Gent Trappenhuis","img":[],"type":["at:pointOfSale","at:vegetableSubscription"],"upstream":[{"@type":"ofd:ActorRelationship","ofd:relatedContext":"at:producer","ofd:relatedActor":"https://w3id.org/openfooddata/actors/de-zonnekouter"}]}}