{"type":"Feature","geometry":{"type":"Point","coordinates":[3.736983,51.055626]},"properties":{"foaf:account":[],"foaf:name":"Gent Trappenhuis","foaf:isPrimaryTopicOf":["http://www.rechtvanbijdeboer.be/gent-trappenhuis","http://www.rechtvanbijdeboer.be/node/2658"],"@type":"foaf:Agent","schema:image":[],"@context":"https://openfooddata.github.io/actors/_common/context.jsonld","schema:geo":{"schema:latitude":"51.055626","schema:longitude":"3.736983","@type":"schema:GeoCoordinates","schema:addressCountry":"Belgium","schema:address":{"@type":"schema:PostalAddress","schema:streetAddress":"L. Munichstraat 29","schema:postalCode":"9000","schema:addressLocality":"Gent"}},"ofd:offersFoodType":["ft:potatoes","ft:fruits","ft:bakery_products","ft:eggs","ft:beef","ft:pork","ft:vegetables","ft:milk_products"],"foaf:depiction":[],"schema:description":"","ofd:upstreamRel":[{"@type":"ofd:ActorRelationship","ofd:relatedContext":"at:producer","ofd:relatedActor":"https://w3id.org/openfooddata/actors/de-zonnekouter"}],"@id":"https://w3id.org/openfooddata/actors/gent-trappenhuis","extraHeader":"<link rel=\"alternate\" href=\"gent-trappenhuis.rdf\" type=\"application/rdf+xml\"/>\n<link rel=\"alternate\" href=\"gent-trappenhuis.jsonld\" type=\"application/ld+json\"/>\n<link rel=\"alternate\" href=\"gent-trappenhuis.nq\" type=\"application/n-quads\"/>\n<link rel=\"alternate\" href=\"gent-trappenhuis.nt\" type=\"application/n-triples\"/>\n<link rel=\"alternate\" href=\"gent-trappenhuis.ttl\" type=\"text/turtle\"/>\n<link rel=\"alternate\" href=\"gent-trappenhuis.rj\" type=\"application/rdf+json\"/>\n<link rel=\"alternate\" href=\"gent-trappenhuis.trig\" type=\"text/trig\"/>\n<link rel=\"alternate\" href=\"gent-trappenhuis.trix\" type=\"application/trix\"/>\n","schema:name":"Gent Trappenhuis","ofd:actorType":["at:pointOfSale","at:vegetableSubscription"]}}