{"type":"Feature","geometry":{"type":"Point","coordinates":[3.588195,50.889249]},"properties":{"id":"https://w3id.org/openfooddata/actors/wwwrooigemvalleibe","name":"www.rooigemvallei.be","img":["http://www.rechtvanbijdeboer.be/sites/default/files/styles/producer_teaser/public/hoeveslagerij_rooigemvallei_producent_met_varkens.jpg?itok=L2fzLLnl"],"type":["at:pointOfSale","at:webshop"],"upstream":[{"@type":"ofd:ActorRelationship","ofd:relatedContext":"at:producer","ofd:relatedActor":"https://w3id.org/openfooddata/actors/hoeveslagerij-rooigemvallei"}]}}