{"type":"Feature","geometry":{"type":"Point","coordinates":[5.298774,50.840559]},"properties":{"foaf:account":[],"foaf:name":"Gallinero","foaf:isPrimaryTopicOf":["http://www.rechtvanbijdeboer.be/gallinero-1","http://www.rechtvanbijdeboer.be/node/2520"],"@type":"foaf:Agent","schema:image":["http://www.rechtvanbijdeboer.be/sites/default/files/styles/producer_teaser/public/p4131116.jpg?itok=4MSAU1Yu"],"@context":"https://openfooddata.github.io/actors/_common/context.jsonld","schema:geo":{"schema:latitude":"50.840559","schema:longitude":"5.298774","@type":"schema:GeoCoordinates","schema:addressCountry":"Belgium","schema:address":{"@type":"schema:PostalAddress","schema:streetAddress":"Kleinaartstraat 37","schema:postalCode":"3832","schema:addressLocality":"Ulbeek (Wellen)"}},"ofd:offersFoodType":["ft:fruit_juices","ft:lamb_meat","ft:beef","ft:pork"],"foaf:depiction":["http://www.rechtvanbijdeboer.be/sites/default/files/styles/producer_teaser/public/p4131116.jpg?itok=4MSAU1Yu"],"schema:description":"","ofd:upstreamRel":[{"@type":"ofd:ActorRelationship","ofd:relatedContext":"at:producer","ofd:relatedActor":"https://w3id.org/openfooddata/actors/hhv"}],"@id":"https://w3id.org/openfooddata/actors/gallinero-1","schema:name":"Gallinero","ofd:actorType":["at:pointOfSale","at:collectionPoint"]}}