{"type":"Feature","geometry":{"type":"Point","coordinates":[5.298774,50.840559]},"properties":{"id":"https://w3id.org/openfooddata/actors/gallinero-1","name":"Gallinero","img":["http://www.rechtvanbijdeboer.be/sites/default/files/styles/producer_teaser/public/p4131116.jpg?itok=4MSAU1Yu"],"type":["at:pointOfSale","at:collectionPoint"],"upstream":[{"@type":"ofd:ActorRelationship","ofd:relatedContext":"at:producer","ofd:relatedActor":"https://w3id.org/openfooddata/actors/hhv"}]}}