{"type":"Feature","geometry":{"type":"Point","coordinates":[3.2326,51.226911]},"properties":{"id":"https://w3id.org/openfooddata/actors/voko-brugge-sint-jozef","name":"Voko Brugge-Sint-Jozef","img":[],"type":["at:pointOfSale","at:vegetableSubscription"],"upstream":[{"@type":"ofd:ActorRelationship","ofd:relatedContext":"at:producer","ofd:relatedActor":"https://w3id.org/openfooddata/actors/t-ambrozijn"}]}}