{"type":"Feature","geometry":{"type":"Point","coordinates":[5.20664,50.853137]},"properties":{"foaf:account":[],"foaf:name":"Samenland","foaf:isPrimaryTopicOf":["http://www.rechtvanbijdeboer.be/samenland","http://www.rechtvanbijdeboer.be/node/2853"],"@type":"foaf:Agent","schema:image":[],"@context":"https://openfooddata.github.io/actors/_common/context.jsonld","schema:geo":{"schema:latitude":"50.853137","schema:longitude":"5.206640","@type":"schema:GeoCoordinates","schema:addressCountry":"Belgium","schema:address":{"@type":"schema:PostalAddress","schema:streetAddress":"Engelbamp 57","schema:postalCode":"3800","schema:addressLocality":"Sint-Truiden"}},"ofd:offersFoodType":["ft:potatoes","ft:fruits","ft:vegetables","ft:spices"],"foaf:depiction":[],"schema:description":"","ofd:upstreamRel":[{"@type":"ofd:ActorRelationship","ofd:relatedContext":"at:producer","ofd:relatedActor":"https://w3id.org/openfooddata/actors/samenland---csa-boerderij"}],"@id":"https://w3id.org/openfooddata/actors/samenland","schema:name":"Samenland","ofd:actorType":["at:pointOfSale","at:csaFarm"]}}