{"type":"Feature","geometry":{"type":"Point","coordinates":[3.099136,51.139167]},"properties":{"foaf:account":[],"foaf:name":"De Vrolijke Aardbei","foaf:isPrimaryTopicOf":["http://www.rechtvanbijdeboer.be/de-vrolijke-aardbei-0","http://www.rechtvanbijdeboer.be/node/2997"],"@type":"foaf:Agent","schema:image":[],"@context":"https://openfooddata.github.io/actors/_common/context.jsonld","schema:geo":{"schema:latitude":"51.139167","schema:longitude":"3.099136","@type":"schema:GeoCoordinates","schema:addressCountry":"Belgium","schema:address":{"@type":"schema:PostalAddress","schema:streetAddress":"Zabekestraat 21B","schema:postalCode":"8211","schema:addressLocality":"Aartrijke"}},"ofd:offersFoodType":["ft:fruits"],"foaf:depiction":[],"schema:description":"","ofd:upstreamRel":[{"@type":"ofd:ActorRelationship","ofd:relatedContext":"at:producer","ofd:relatedActor":"https://w3id.org/openfooddata/actors/de-vrolijke-aardbei"}],"@id":"https://w3id.org/openfooddata/actors/de-vrolijke-aardbei-0","schema:name":"De Vrolijke Aardbei","ofd:actorType":["at:pointOfSale","at:farmShop"]}}