{"type":"Feature","geometry":{"type":"Point","coordinates":[3.781816,50.804045]},"properties":{"foaf:account":[],"foaf:name":"De Schapenmelkerij","schema:url":[],"foaf:homepage":[],"foaf:isPrimaryTopicOf":["http://www.rechtvanbijdeboer.be/de-schapenmelkerij-0","http://www.rechtvanbijdeboer.be/node/2885","https://www.rechtvanbijdeboer.be/de-schapenmelkerij","https://www.rechtvanbijdeboer.be/node/1408"],"@type":"foaf:Agent","schema:image":[],"@context":"https://openfooddata.github.io/actors/_common/context.jsonld","schema:geo":{"schema:latitude":"50.804045","schema:longitude":"3.781816","@type":"schema:GeoCoordinates","schema:addressCountry":"Belgium","schema:address":{"@type":"schema:PostalAddress","schema:streetAddress":"Halsembergweg 14","schema:postalCode":"9660","schema:addressLocality":"Brakel"}},"ofd:offersFoodType":["ft:milk_products","ft:lamb_meat","ft:icecream"],"foaf:depiction":[],"schema:description":"","ofd:upstreamRel":[],"ofd:downstreamRel":[],"@id":"https://w3id.org/openfooddata/actors/de-schapenmelkerij","schema:name":"De Schapenmelkerij","ofd:actorType":["at:pointOfSale","at:farmShop","at:producer"]}}