{"type":"Feature","geometry":{"type":"Point","coordinates":[3.026973,50.88499]},"properties":{"foaf:account":[],"foaf:name":"Hoeveproducten Sioen","schema:url":[],"foaf:homepage":[],"foaf:isPrimaryTopicOf":["http://www.rechtvanbijdeboer.be/hoeveproducten-sioen-0","http://www.rechtvanbijdeboer.be/node/3045","https://www.rechtvanbijdeboer.be/hoeveproducten-sioen","https://www.rechtvanbijdeboer.be/node/1555"],"@type":"foaf:Agent","schema:image":[],"@context":"https://openfooddata.github.io/actors/_common/context.jsonld","schema:geo":{"schema:latitude":"50.884990","schema:longitude":"3.026973","@type":"schema:GeoCoordinates","schema:addressCountry":"Belgium","schema:address":{"@type":"schema:PostalAddress","schema:streetAddress":"Zuidstraat 30","schema:postalCode":"8980","schema:addressLocality":"Passendale"}},"ofd:offersFoodType":["ft:milk_products","ft:vegetables","ft:potatoes"],"foaf:depiction":[],"schema:description":"","ofd:upstreamRel":[],"ofd:downstreamRel":[],"@id":"https://w3id.org/openfooddata/actors/hoeveproducten-sioen","extraHeader":"<link rel=\"alternate\" href=\"hoeveproducten-sioen.rdf\" type=\"application/rdf+xml\"/>\n<link rel=\"alternate\" href=\"hoeveproducten-sioen.jsonld\" type=\"application/ld+json\"/>\n<link rel=\"alternate\" href=\"hoeveproducten-sioen.nq\" type=\"application/n-quads\"/>\n<link rel=\"alternate\" href=\"hoeveproducten-sioen.nt\" type=\"application/n-triples\"/>\n<link rel=\"alternate\" href=\"hoeveproducten-sioen.ttl\" type=\"text/turtle\"/>\n<link rel=\"alternate\" href=\"hoeveproducten-sioen.rj\" type=\"application/rdf+json\"/>\n<link rel=\"alternate\" href=\"hoeveproducten-sioen.trig\" type=\"text/trig\"/>\n<link rel=\"alternate\" href=\"hoeveproducten-sioen.trix\" type=\"application/trix\"/>\n","schema:name":"Hoeveproducten Sioen","ofd:actorType":["at:pointOfSale","at:farmShop","at:producer"]}}