{"type":"Feature","geometry":{"type":"Point","coordinates":[4.183932,50.942559]},"properties":{"id":"https://w3id.org/openfooddata/actors/peter-de-coninck","name":"Peter De Coninck","img":["http://www.rechtvanbijdeboer.be/sites/default/files/styles/producer_teaser/public/004_1.jpg?itok=gi6bvptl"],"type":["at:pointOfSale","at:farmShop"],"upstream":[{"@type":"ofd:ActorRelationship","ofd:relatedContext":"at:producer","ofd:relatedActor":"https://w3id.org/openfooddata/actors/fruitbedrijf-peter-de-coninck"}]}}