{"type":"Feature","geometry":{"type":"Point","coordinates":[3.708227,51.03446]},"properties":{"foaf:account":[],"foaf:name":"Max Mobiel","foaf:isPrimaryTopicOf":["http://www.rechtvanbijdeboer.be/max-mobiel","http://www.rechtvanbijdeboer.be/node/3518"],"@type":"foaf:Agent","schema:image":[],"@context":"https://openfooddata.github.io/actors/_common/context.jsonld","schema:geo":{"schema:latitude":"51.034460","schema:longitude":"3.708227","@type":"schema:GeoCoordinates","schema:addressCountry":"Belgium","schema:address":{"@type":"schema:PostalAddress","schema:streetAddress":"Voskenslaan 27","schema:postalCode":"9000","schema:addressLocality":"Gent"}},"ofd:offersFoodType":["ft:potatoes","ft:fruits","ft:bakery_products","ft:eggs","ft:fruit_juices","ft:spices","ft:beef","ft:alcoholic_beverages","ft:vegetables","ft:milk_products"],"foaf:depiction":[],"schema:description":"","ofd:upstreamRel":[{"@type":"ofd:ActorRelationship","ofd:relatedContext":"at:producer","ofd:relatedActor":"https://w3id.org/openfooddata/actors/de-wassende-maan"}],"@id":"https://w3id.org/openfooddata/actors/max-mobiel","extraHeader":"<link rel=\"alternate\" href=\"max-mobiel.rdf\" type=\"application/rdf+xml\"/>\n<link rel=\"alternate\" href=\"max-mobiel.jsonld\" type=\"application/ld+json\"/>\n<link rel=\"alternate\" href=\"max-mobiel.nq\" type=\"application/n-quads\"/>\n<link rel=\"alternate\" href=\"max-mobiel.nt\" type=\"application/n-triples\"/>\n<link rel=\"alternate\" href=\"max-mobiel.ttl\" type=\"text/turtle\"/>\n<link rel=\"alternate\" href=\"max-mobiel.rj\" type=\"application/rdf+json\"/>\n<link rel=\"alternate\" href=\"max-mobiel.trig\" type=\"text/trig\"/>\n<link rel=\"alternate\" href=\"max-mobiel.trix\" type=\"application/trix\"/>\n","schema:name":"Max Mobiel","ofd:actorType":["at:pointOfSale","at:vegetableSubscription"]}}