{"type":"Feature","geometry":{"type":"Point","coordinates":[3.458781,51.216135]},"properties":{"foaf:account":[],"foaf:name":"Maldegem","foaf:isPrimaryTopicOf":["http://www.rechtvanbijdeboer.be/maldegem","http://www.rechtvanbijdeboer.be/node/2347"],"@type":"foaf:Agent","schema:image":[],"@context":"https://openfooddata.github.io/actors/_common/context.jsonld","schema:geo":{"schema:latitude":"51.216135","schema:longitude":"3.458781","@type":"schema:GeoCoordinates","schema:addressCountry":"Belgium","schema:address":{"@type":"schema:PostalAddress","schema:streetAddress":"Kleine Warmestraat","schema:postalCode":"9990","schema:addressLocality":"Maldegem"}},"ofd:offersFoodType":["ft:potatoes","ft:eggs","ft:icecream","ft:vegetables","ft:milk_products"],"foaf:depiction":[],"schema:description":"","ofd:upstreamRel":[{"@type":"ofd:ActorRelationship","ofd:relatedContext":"at:producer","ofd:relatedActor":"https://w3id.org/openfooddata/actors/de-zwaluw"}],"@id":"https://w3id.org/openfooddata/actors/maldegem","schema:name":"Maldegem","ofd:actorType":["at:pointOfSale","at:foodTeams"]}}