{"type":"Feature","geometry":{"type":"Point","coordinates":[3.764015,51.034295]},"properties":{"id":"https://w3id.org/openfooddata/actors/oogstgoed","name":"Oogstgoed","img":["http://www.rechtvanbijdeboer.be/sites/default/files/styles/producer_teaser/public/rony-benny.jpg?itok=DbQBVkw5"],"type":["at:pointOfSale","at:csaFarm"],"upstream":[{"@type":"ofd:ActorRelationship","ofd:relatedContext":"at:producer","ofd:relatedActor":"https://w3id.org/openfooddata/actors/oogstgoed-csa-boerderij"}]}}