{"type":"Feature","geometry":{"type":"Point","coordinates":[4.99084,51.16257]},"properties":{"foaf:account":[],"foaf:name":"Zaterdagmarkt Geel","foaf:isPrimaryTopicOf":["http://www.rechtvanbijdeboer.be/zaterdagmarkt-geel","http://www.rechtvanbijdeboer.be/node/2073"],"@type":"foaf:Agent","schema:image":["http://www.rechtvanbijdeboer.be/sites/default/files/styles/producer_teaser/public/image_3.jpg?itok=9qrCM5fR"],"@context":"https://openfooddata.github.io/actors/_common/context.jsonld","schema:geo":{"schema:latitude":"51.162570","schema:longitude":"4.990840","@type":"schema:GeoCoordinates","schema:addressCountry":"Belgium","schema:address":{"@type":"schema:PostalAddress","schema:streetAddress":"-0","schema:postalCode":"2440","schema:addressLocality":"Geel"}},"ofd:offersFoodType":["ft:fruits","ft:poultry_meat","ft:potatoes","ft:vegetables"],"foaf:depiction":["http://www.rechtvanbijdeboer.be/sites/default/files/styles/producer_teaser/public/image_3.jpg?itok=9qrCM5fR"],"schema:description":"","ofd:upstreamRel":[{"@type":"ofd:ActorRelationship","ofd:relatedContext":"at:producer","ofd:relatedActor":"https://w3id.org/openfooddata/actors/tuinbouwbedrijf-vercammen"},{"@type":"ofd:ActorRelationship","ofd:relatedContext":"at:producer","ofd:relatedActor":"https://w3id.org/openfooddata/actors/fruitbedrijf-jos-helsen"}],"@id":"https://w3id.org/openfooddata/actors/zaterdagmarkt-geel","extraHeader":"<link rel=\"alternate\" href=\"zaterdagmarkt-geel.rdf\" type=\"application/rdf+xml\"/>\n<link rel=\"alternate\" href=\"zaterdagmarkt-geel.jsonld\" type=\"application/ld+json\"/>\n<link rel=\"alternate\" href=\"zaterdagmarkt-geel.nq\" type=\"application/n-quads\"/>\n<link rel=\"alternate\" href=\"zaterdagmarkt-geel.nt\" type=\"application/n-triples\"/>\n<link rel=\"alternate\" href=\"zaterdagmarkt-geel.ttl\" type=\"text/turtle\"/>\n<link rel=\"alternate\" href=\"zaterdagmarkt-geel.rj\" type=\"application/rdf+json\"/>\n<link rel=\"alternate\" href=\"zaterdagmarkt-geel.trig\" type=\"text/trig\"/>\n<link rel=\"alternate\" href=\"zaterdagmarkt-geel.trix\" type=\"application/trix\"/>\n","schema:name":"Zaterdagmarkt Geel","ofd:actorType":["at:pointOfSale","at:market"]}}