{"type":"Feature","geometry":{"type":"Point","coordinates":[5.200811,51.18121]},"properties":{"id":"https://w3id.org/openfooddata/actors/lemmens-gerd","name":"lemmens gerd","img":[],"type":["at:pointOfSale","at:vendingMachine"],"upstream":[{"@type":"ofd:ActorRelationship","ofd:relatedContext":"at:producer","ofd:relatedActor":"https://w3id.org/openfooddata/actors/lemmens"}]}}