{"type":"Feature","geometry":{"type":"Point","coordinates":[5.113838,50.976979]},"properties":{"foaf:account":[],"foaf:name":"Den Boogerd VOF","schema:url":[],"foaf:homepage":[],"foaf:isPrimaryTopicOf":["http://www.rechtvanbijdeboer.be/den-boogerd-vof-0","http://www.rechtvanbijdeboer.be/node/3555","https://www.rechtvanbijdeboer.be/den-boogerd-vof","https://www.rechtvanbijdeboer.be/node/1823"],"@type":"foaf:Agent","schema:image":[],"@context":"https://openfooddata.github.io/actors/_common/context.jsonld","schema:geo":{"schema:latitude":"50.976979","schema:longitude":"5.113838","@type":"schema:GeoCoordinates","schema:addressCountry":"Belgium","schema:address":{"@type":"schema:PostalAddress","schema:streetAddress":"Karestraat 35","schema:postalCode":"3545","schema:addressLocality":"Zelem"}},"ofd:offersFoodType":["ft:poultry_meat","ft:lamb_meat","ft:fruits"],"foaf:depiction":[],"schema:description":"","ofd:upstreamRel":[],"ofd:downstreamRel":[],"@id":"https://w3id.org/openfooddata/actors/den-boogerd-vof","schema:name":"Den Boogerd VOF","ofd:actorType":["at:pointOfSale","at:collectionPoint","at:producer"]}}