{"type":"Feature","geometry":{"type":"Point","coordinates":[5.272102,50.987219]},"properties":{"id":"https://w3id.org/openfooddata/actors/geitenhoeve-hoeveberg","name":"Geitenhoeve \"Hoeveberg\"","img":[],"type":["at:pointOfSale","at:farmShop","at:producer"],"upstream":[],"downstream":[]}}