{"type":"Feature","geometry":{"type":"Point","coordinates":[4.097554,50.785433]},"properties":{"id":"https://w3id.org/openfooddata/actors/bioboerderij-dubbeldoel-0","name":"Bioboerderij Dubbeldoel","img":["http://www.rechtvanbijdeboer.be/sites/default/files/styles/producer_teaser/public/bioboerderij_dubbeldoel_gezin_producent_stal_hr.jpg?itok=0dyuTU8V"],"type":["at:pointOfSale","at:farmShop"],"upstream":[{"@type":"ofd:ActorRelationship","ofd:relatedContext":"at:producer","ofd:relatedActor":"https://w3id.org/openfooddata/actors/bioboerderij-dubbeldoel"}]}}