{"type":"Feature","geometry":{"type":"Point","coordinates":[4.963564,50.921321]},"properties":{"id":"https://w3id.org/openfooddata/actors/van-der-velpen-kris","name":"Van Der Velpen Kris","img":[],"type":["at:pointOfSale","at:farmShop","at:producer"],"upstream":[{"@type":"ofd:ActorRelationship","ofd:relatedContext":"at:producer","ofd:relatedActor":"https://w3id.org/openfooddata/actors/kris-van-der-velpen-fruit"},{"@type":"ofd:ActorRelationship","ofd:relatedContext":"at:producer","ofd:relatedActor":"https://w3id.org/openfooddata/actors/kris-van-der-velpen-fruit"}],"downstream":[]}}