{"type":"Feature","geometry":{"type":"Point","coordinates":[4.45246,51.196854]},"properties":{"foaf:account":[],"foaf:name":"Deurne zuid","foaf:isPrimaryTopicOf":["http://www.rechtvanbijdeboer.be/deurne-zuid","http://www.rechtvanbijdeboer.be/node/2163"],"@type":"foaf:Agent","schema:image":[],"@context":"https://openfooddata.github.io/actors/_common/context.jsonld","schema:geo":{"schema:latitude":"51.196854","schema:longitude":"4.452460","@type":"schema:GeoCoordinates","schema:addressCountry":"Belgium","schema:address":{"@type":"schema:PostalAddress","schema:streetAddress":"Vosstraat","schema:postalCode":"2140","schema:addressLocality":"Borgerhout"}},"ofd:offersFoodType":["ft:potatoes","ft:fruits","ft:bakery_products","ft:eggs","ft:poultry_meat","ft:fruit_juices","ft:icecream","ft:spices","ft:lamb_meat","ft:beef","ft:pork","ft:alcoholic_beverages","ft:vegetables","ft:milk_products"],"foaf:depiction":[],"schema:description":"","ofd:upstreamRel":[],"@id":"https://w3id.org/openfooddata/actors/deurne-zuid","schema:name":"Deurne zuid","ofd:actorType":["at:pointOfSale","at:foodTeams"]}}