{"type":"Feature","geometry":{"type":"Point","coordinates":[4.841948,51.177608]},"properties":{"foaf:account":[],"foaf:name":"Boerenmarkt Herentals","foaf:isPrimaryTopicOf":["http://www.rechtvanbijdeboer.be/boerenmarkt-herentals","http://www.rechtvanbijdeboer.be/node/1998"],"@type":"foaf:Agent","schema:image":["http://www.rechtvanbijdeboer.be/sites/default/files/styles/producer_teaser/public/naamloos-6684.jpg?itok=TTld9ZIi"],"@context":"https://openfooddata.github.io/actors/_common/context.jsonld","schema:geo":{"schema:latitude":"51.177608","schema:longitude":"4.841948","@type":"schema:GeoCoordinates","schema:addressCountry":"Belgium","schema:address":{"@type":"schema:PostalAddress","schema:streetAddress":"Augustijnenlaan","schema:postalCode":"2200","schema:addressLocality":"Herentals"}},"ofd:offersFoodType":["ft:icecream","ft:milk_products"],"foaf:depiction":["http://www.rechtvanbijdeboer.be/sites/default/files/styles/producer_teaser/public/naamloos-6684.jpg?itok=TTld9ZIi"],"schema:description":"","ofd:upstreamRel":[{"@type":"ofd:ActorRelationship","ofd:relatedContext":"at:producer","ofd:relatedActor":"https://w3id.org/openfooddata/actors/kempense-geitenkaas-polle"}],"@id":"https://w3id.org/openfooddata/actors/boerenmarkt-herentals","extraHeader":"<link rel=\"alternate\" href=\"boerenmarkt-herentals.rdf\" type=\"application/rdf+xml\"/>\n<link rel=\"alternate\" href=\"boerenmarkt-herentals.jsonld\" type=\"application/ld+json\"/>\n<link rel=\"alternate\" href=\"boerenmarkt-herentals.nq\" type=\"application/n-quads\"/>\n<link rel=\"alternate\" href=\"boerenmarkt-herentals.nt\" type=\"application/n-triples\"/>\n<link rel=\"alternate\" href=\"boerenmarkt-herentals.ttl\" type=\"text/turtle\"/>\n<link rel=\"alternate\" href=\"boerenmarkt-herentals.rj\" type=\"application/rdf+json\"/>\n<link rel=\"alternate\" href=\"boerenmarkt-herentals.trig\" type=\"text/trig\"/>\n<link rel=\"alternate\" href=\"boerenmarkt-herentals.trix\" type=\"application/trix\"/>\n","schema:name":"Boerenmarkt Herentals","ofd:actorType":["at:pointOfSale","at:farmersMarket"]}}