{"type":"Feature","geometry":{"type":"Point","coordinates":[4.841948,51.177608]},"properties":{"id":"https://w3id.org/openfooddata/actors/boerenmarkt-herentals","name":"Boerenmarkt Herentals","img":["http://www.rechtvanbijdeboer.be/sites/default/files/styles/producer_teaser/public/naamloos-6684.jpg?itok=TTld9ZIi"],"type":["at:pointOfSale","at:farmersMarket"],"upstream":[{"@type":"ofd:ActorRelationship","ofd:relatedContext":"at:producer","ofd:relatedActor":"https://w3id.org/openfooddata/actors/kempense-geitenkaas-polle"}]}}