{"type":"Feature","geometry":{"type":"Point","coordinates":[3.35086,51.159825]},"properties":{"id":"https://w3id.org/openfooddata/actors/de-hogen-akker","name":"De Hogen Akker","img":[],"type":["at:pointOfSale","at:farmShop","at:producer"],"upstream":[],"downstream":[]}}