{"type":"Feature","geometry":{"type":"Point","coordinates":[3.372351,51.251922]},"properties":{"id":"https://w3id.org/openfooddata/actors/het-hoorns-geitenkaasje-0","name":"Het Hoorns Geitenkaasje","img":[],"type":["at:pointOfSale","at:farmShop"],"upstream":[{"@type":"ofd:ActorRelationship","ofd:relatedContext":"at:producer","ofd:relatedActor":"https://w3id.org/openfooddata/actors/het-hoorns-geitenkaasje"}]}}