{"type":"Feature","geometry":{"type":"Point","coordinates":[3.683965,50.946539]},"properties":{"id":"https://w3id.org/openfooddata/actors/hoeve-oc-borgwal","name":"Hoeve OC BORGWAL","img":["http://www.rechtvanbijdeboer.be/sites/default/files/styles/producer_teaser/public/dsc_2941.jpg?itok=AXt1vbWE"],"type":["at:pointOfSale","at:vegetableSubscription"],"upstream":[{"@type":"ofd:ActorRelationship","ofd:relatedContext":"at:producer","ofd:relatedActor":"https://w3id.org/openfooddata/actors/blauw-kasteel-bvba"}]}}