{"type":"Feature","geometry":{"type":"Point","coordinates":[4.659719,51.139128]},"properties":{"id":"https://w3id.org/openfooddata/actors/iona-vzw","name":"Iona vzw","img":[],"type":["at:pointOfSale","at:collectionPoint"],"upstream":[{"@type":"ofd:ActorRelationship","ofd:relatedContext":"at:producer","ofd:relatedActor":"https://w3id.org/openfooddata/actors/herdershof"}]}}