{"type":"Feature","geometry":{"type":"Point","coordinates":[3.910591,51.071934]},"properties":{"foaf:account":[],"foaf:name":"Aardbeien (vollegronds): Fam.Wim en Kristien","foaf:isPrimaryTopicOf":["http://www.rechtvanbijdeboer.be/aardbeien-vollegronds-famwim-en-kristien","http://www.rechtvanbijdeboer.be/node/3414"],"@type":"foaf:Agent","schema:image":["http://www.rechtvanbijdeboer.be/sites/default/files/styles/producer_teaser/public/030.jpg?itok=a3nEENdt"],"@context":"https://openfooddata.github.io/actors/_common/context.jsonld","schema:geo":{"schema:latitude":"51.071934","schema:longitude":"3.910591","@type":"schema:GeoCoordinates","schema:addressCountry":"Belgium","schema:address":{"@type":"schema:PostalAddress","schema:streetAddress":"Cootveld 22","schema:postalCode":"9080","schema:addressLocality":"Beervelde"}},"ofd:offersFoodType":["ft:fruits"],"foaf:depiction":["http://www.rechtvanbijdeboer.be/sites/default/files/styles/producer_teaser/public/030.jpg?itok=a3nEENdt"],"schema:description":"","ofd:upstreamRel":[{"@type":"ofd:ActorRelationship","ofd:relatedContext":"at:producer","ofd:relatedActor":"https://w3id.org/openfooddata/actors/vollegrondsaardbeien-rooms-van-puyvelde"}],"@id":"https://w3id.org/openfooddata/actors/aardbeien-vollegronds-famwim-en-kristien","schema:name":"Aardbeien (vollegronds): Fam.Wim en Kristien","ofd:actorType":["at:pointOfSale","at:farmShop"]}}