{"type":"Feature","geometry":{"type":"Point","coordinates":[4.333888,50.748655]},"properties":{"foaf:account":[],"foaf:name":"Voedselteam Beersel","foaf:isPrimaryTopicOf":["http://www.rechtvanbijdeboer.be/voedselteam-beersel","http://www.rechtvanbijdeboer.be/node/2149"],"@type":"foaf:Agent","schema:image":["http://www.rechtvanbijdeboer.be/sites/default/files/styles/producer_teaser/public/bioboerderij_dubbeldoel_gezin_producent_stal_hr.jpg?itok=0dyuTU8V"],"@context":"https://openfooddata.github.io/actors/_common/context.jsonld","schema:geo":{"schema:latitude":"50.748655","schema:longitude":"4.333888","@type":"schema:GeoCoordinates","schema:addressCountry":"Belgium","schema:address":{"@type":"schema:PostalAddress","schema:streetAddress":"Brusselsesteenweg 45","schema:postalCode":"1650","schema:addressLocality":"Alsemberg"}},"ofd:offersFoodType":["ft:beef","ft:pork","ft:icecream","ft:lamb_meat","ft:milk_products","ft:fruit_juices","ft:bakery_products","ft:potatoes","ft:vegetables"],"foaf:depiction":["http://www.rechtvanbijdeboer.be/sites/default/files/styles/producer_teaser/public/bioboerderij_dubbeldoel_gezin_producent_stal_hr.jpg?itok=0dyuTU8V"],"schema:description":"","ofd:upstreamRel":[{"@type":"ofd:ActorRelationship","ofd:relatedContext":"at:producer","ofd:relatedActor":"https://w3id.org/openfooddata/actors/bioboerderij-dubbeldoel"},{"@type":"ofd:ActorRelationship","ofd:relatedContext":"at:producer","ofd:relatedActor":"https://w3id.org/openfooddata/actors/hoevebakkerij-de-haseleer"},{"@type":"ofd:ActorRelationship","ofd:relatedContext":"at:producer","ofd:relatedActor":"https://w3id.org/openfooddata/actors/cleyn-hof-ten-bautebrugge"},{"@type":"ofd:ActorRelationship","ofd:relatedContext":"at:producer","ofd:relatedActor":"https://w3id.org/openfooddata/actors/de-schapenmelkerij"},{"@type":"ofd:ActorRelationship","ofd:relatedContext":"at:producer","ofd:relatedActor":"https://w3id.org/openfooddata/actors/hof-seghers"},{"@type":"ofd:ActorRelationship","ofd:relatedContext":"at:producer","ofd:relatedActor":"https://w3id.org/openfooddata/actors/vanysacker"}],"@id":"https://w3id.org/openfooddata/actors/voedselteam-beersel","extraHeader":"<link rel=\"alternate\" href=\"voedselteam-beersel.rdf\" type=\"application/rdf+xml\"/>\n<link rel=\"alternate\" href=\"voedselteam-beersel.jsonld\" type=\"application/ld+json\"/>\n<link rel=\"alternate\" href=\"voedselteam-beersel.nq\" type=\"application/n-quads\"/>\n<link rel=\"alternate\" href=\"voedselteam-beersel.nt\" type=\"application/n-triples\"/>\n<link rel=\"alternate\" href=\"voedselteam-beersel.ttl\" type=\"text/turtle\"/>\n<link rel=\"alternate\" href=\"voedselteam-beersel.rj\" type=\"application/rdf+json\"/>\n<link rel=\"alternate\" href=\"voedselteam-beersel.trig\" type=\"text/trig\"/>\n<link rel=\"alternate\" href=\"voedselteam-beersel.trix\" type=\"application/trix\"/>\n","schema:name":"Voedselteam Beersel","ofd:actorType":["at:pointOfSale","at:foodTeams"]}}