{"type":"Feature","geometry":{"type":"Point","coordinates":[3.509064,50.893082]},"properties":{"id":"https://w3id.org/openfooddata/actors/kruiden-claus","name":"Kruiden Claus","img":["http://www.rechtvanbijdeboer.be/sites/default/files/styles/producer_teaser/public/KRUIDEN%20CLAUS%2006.jpg?itok=lrNKsx0f","http://www.rechtvanbijdeboer.be/sites/default/files/styles/producer_teaser/public/kruidenclausfoto1.jpg?itok=mozBEJDX"],"type":["at:pointOfSale","at:farmShop","at:producer"],"upstream":[],"downstream":[]}}