{"type":"Feature","geometry":{"type":"Point","coordinates":[4.27884,51.252531]},"properties":{"foaf:account":[],"foaf:name":"Vleeshoeve 't Kasteeltje","schema:url":[],"foaf:homepage":[],"foaf:isPrimaryTopicOf":["http://www.rechtvanbijdeboer.be/vleeshoeve-t-kasteeltje-0","http://www.rechtvanbijdeboer.be/node/2535","http://www.rechtvanbijdeboer.be/vleeshoeve-t-kasteeltje","http://www.rechtvanbijdeboer.be/node/1145"],"@type":"foaf:Agent","schema:image":["http://www.rechtvanbijdeboer.be/sites/default/files/styles/producer_teaser/public/lenaerts002.jpg?itok=SV8o3FgQ","http://www.rechtvanbijdeboer.be/sites/default/files/styles/producer_teaser/public/dsc02572.jpg?itok=zmH80R5i"],"@context":"https://openfooddata.github.io/actors/_common/context.jsonld","schema:geo":{"schema:latitude":"51.252531","schema:longitude":"4.278840","@type":"schema:GeoCoordinates","schema:addressCountry":"Belgium","schema:address":{"@type":"schema:PostalAddress","schema:streetAddress":"Gemeenteplein 7","schema:postalCode":"9120","schema:addressLocality":"Kallo"}},"ofd:offersFoodType":["ft:beef"],"foaf:depiction":["http://www.rechtvanbijdeboer.be/sites/default/files/styles/producer_teaser/public/lenaerts002.jpg?itok=SV8o3FgQ","http://www.rechtvanbijdeboer.be/sites/default/files/styles/producer_teaser/public/dsc02572.jpg?itok=zmH80R5i"],"schema:description":"Wij zijn een familiaal landbouwbedrijf en sedert drie generaties gespecialiseerd in het produceren van vlees van topkwaliteit. Onze dieren zijn van het Belgisch Wit-Blauw ras: mager, sappig en mals vlees. We verkopen het vlees rechtstreeks aan particulieren, in pakketten van 5 of 15 kg. De rund- en kalfspakketten zijn hygiënisch verpakt en klaar om in te vriezen.","ofd:upstreamRel":[],"schema:contactPoint":{"@type":"schema:ContactPoint","schema:telephone":["03/5750327","0476/863598"],"schema:email":["lenaerts.raf@skynet.be"],"foaf:homepage":[],"schema:url":[]},"ofd:downstreamRel":[],"@id":"https://w3id.org/openfooddata/actors/vleeshoeve-t-kasteeltje","extraHeader":"<link rel=\"alternate\" href=\"vleeshoeve-t-kasteeltje.rdf\" type=\"application/rdf+xml\"/>\n<link rel=\"alternate\" href=\"vleeshoeve-t-kasteeltje.jsonld\" type=\"application/ld+json\"/>\n<link rel=\"alternate\" href=\"vleeshoeve-t-kasteeltje.nq\" type=\"application/n-quads\"/>\n<link rel=\"alternate\" href=\"vleeshoeve-t-kasteeltje.nt\" type=\"application/n-triples\"/>\n<link rel=\"alternate\" href=\"vleeshoeve-t-kasteeltje.ttl\" type=\"text/turtle\"/>\n<link rel=\"alternate\" href=\"vleeshoeve-t-kasteeltje.rj\" type=\"application/rdf+json\"/>\n<link rel=\"alternate\" href=\"vleeshoeve-t-kasteeltje.trig\" type=\"text/trig\"/>\n<link rel=\"alternate\" href=\"vleeshoeve-t-kasteeltje.trix\" type=\"application/trix\"/>\n","schema:name":"Vleeshoeve 't Kasteeltje","ofd:actorType":["at:pointOfSale","at:farmShop","at:producer"]}}