{"type":"Feature","geometry":{"type":"Point","coordinates":[4.194824,50.800838]},"properties":{"id":"https://w3id.org/openfooddata/actors/lekkers-uit-het-pajottenland","name":"Lekkers uit het Pajottenland","img":[],"type":["at:pointOfSale","at:cooperative"],"upstream":[{"@type":"ofd:ActorRelationship","ofd:relatedContext":"at:producer","ofd:relatedActor":"https://w3id.org/openfooddata/actors/kruidenkwekerij-duizendblad"}]}}