{"type":"Feature","geometry":{"type":"Point","coordinates":[4.194824,50.800838]},"properties":{"foaf:account":[],"foaf:name":"Lekkers uit het Pajottenland","foaf:isPrimaryTopicOf":["http://www.rechtvanbijdeboer.be/lekkers-uit-het-pajottenland","http://www.rechtvanbijdeboer.be/node/2820"],"@type":"foaf:Agent","schema:image":[],"@context":"https://openfooddata.github.io/actors/_common/context.jsonld","schema:geo":{"schema:latitude":"50.800838","schema:longitude":"4.194824","@type":"schema:GeoCoordinates","schema:addressCountry":"Belgium","schema:address":{"@type":"schema:PostalAddress","schema:streetAddress":"Donkerstraat 8","schema:postalCode":"1750","schema:addressLocality":"Lennik"}},"ofd:offersFoodType":["ft:spices"],"foaf:depiction":[],"schema:description":"","ofd:upstreamRel":[{"@type":"ofd:ActorRelationship","ofd:relatedContext":"at:producer","ofd:relatedActor":"https://w3id.org/openfooddata/actors/kruidenkwekerij-duizendblad"}],"@id":"https://w3id.org/openfooddata/actors/lekkers-uit-het-pajottenland","extraHeader":"<link rel=\"alternate\" href=\"lekkers-uit-het-pajottenland.rdf\" type=\"application/rdf+xml\"/>\n<link rel=\"alternate\" href=\"lekkers-uit-het-pajottenland.jsonld\" type=\"application/ld+json\"/>\n<link rel=\"alternate\" href=\"lekkers-uit-het-pajottenland.nq\" type=\"application/n-quads\"/>\n<link rel=\"alternate\" href=\"lekkers-uit-het-pajottenland.nt\" type=\"application/n-triples\"/>\n<link rel=\"alternate\" href=\"lekkers-uit-het-pajottenland.ttl\" type=\"text/turtle\"/>\n<link rel=\"alternate\" href=\"lekkers-uit-het-pajottenland.rj\" type=\"application/rdf+json\"/>\n<link rel=\"alternate\" href=\"lekkers-uit-het-pajottenland.trig\" type=\"text/trig\"/>\n<link rel=\"alternate\" href=\"lekkers-uit-het-pajottenland.trix\" type=\"application/trix\"/>\n","schema:name":"Lekkers uit het Pajottenland","ofd:actorType":["at:pointOfSale","at:cooperative"]}}