{"type":"Feature","geometry":{"type":"Point","coordinates":[4.942744,51.322383]},"properties":{"foaf:account":[],"foaf:name":"Herboristerie Betonnie","foaf:isPrimaryTopicOf":["http://www.rechtvanbijdeboer.be/herboristerie-betonnie","http://www.rechtvanbijdeboer.be/node/2796"],"@type":"foaf:Agent","schema:image":[],"@context":"https://openfooddata.github.io/actors/_common/context.jsonld","schema:geo":{"schema:latitude":"51.322383","schema:longitude":"4.942744","@type":"schema:GeoCoordinates","schema:addressCountry":"Belgium","schema:address":{"@type":"schema:PostalAddress","schema:streetAddress":"De Merodelei 14","schema:postalCode":"2300","schema:addressLocality":"Turnhout"}},"ofd:offersFoodType":["ft:potatoes","ft:vegetables"],"foaf:depiction":[],"schema:description":"","ofd:upstreamRel":[{"@type":"ofd:ActorRelationship","ofd:relatedContext":"at:producer","ofd:relatedActor":"https://w3id.org/openfooddata/actors/de-bio-hoeve"}],"@id":"https://w3id.org/openfooddata/actors/herboristerie-betonnie","extraHeader":"<link rel=\"alternate\" href=\"herboristerie-betonnie.rdf\" type=\"application/rdf+xml\"/>\n<link rel=\"alternate\" href=\"herboristerie-betonnie.jsonld\" type=\"application/ld+json\"/>\n<link rel=\"alternate\" href=\"herboristerie-betonnie.nq\" type=\"application/n-quads\"/>\n<link rel=\"alternate\" href=\"herboristerie-betonnie.nt\" type=\"application/n-triples\"/>\n<link rel=\"alternate\" href=\"herboristerie-betonnie.ttl\" type=\"text/turtle\"/>\n<link rel=\"alternate\" href=\"herboristerie-betonnie.rj\" type=\"application/rdf+json\"/>\n<link rel=\"alternate\" href=\"herboristerie-betonnie.trig\" type=\"text/trig\"/>\n<link rel=\"alternate\" href=\"herboristerie-betonnie.trix\" type=\"application/trix\"/>\n","schema:name":"Herboristerie Betonnie","ofd:actorType":["at:pointOfSale","at:vegetableSubscription"]}}