{"type":"Feature","geometry":{"type":"Point","coordinates":[4.390532,51.172369]},"properties":{"foaf:account":[],"foaf:name":"Voedselteam Wilrijk","foaf:isPrimaryTopicOf":["http://www.rechtvanbijdeboer.be/voedselteam-wilrijk","http://www.rechtvanbijdeboer.be/node/2176"],"@type":"foaf:Agent","schema:image":["http://www.rechtvanbijdeboer.be/sites/default/files/styles/producer_teaser/public/_mg_9535.jpg?itok=xcRRLz6b"],"@context":"https://openfooddata.github.io/actors/_common/context.jsonld","schema:geo":{"schema:latitude":"51.172369","schema:longitude":"4.390532","@type":"schema:GeoCoordinates","schema:addressCountry":"Belgium","schema:address":{"@type":"schema:PostalAddress","schema:streetAddress":"Jules Moretuslei 468","schema:postalCode":"2610","schema:addressLocality":"Wilrijk"}},"ofd:offersFoodType":["ft:icecream","ft:milk_products","ft:fruits","ft:bakery_products","ft:pork","ft:vegetables","ft:potatoes","ft:spices"],"foaf:depiction":["http://www.rechtvanbijdeboer.be/sites/default/files/styles/producer_teaser/public/_mg_9535.jpg?itok=xcRRLz6b"],"schema:description":"","ofd:upstreamRel":[{"@type":"ofd:ActorRelationship","ofd:relatedContext":"at:producer","ofd:relatedActor":"https://w3id.org/openfooddata/actors/geitenboerderij-t-eikenhof"},{"@type":"ofd:ActorRelationship","ofd:relatedContext":"at:producer","ofd:relatedActor":"https://w3id.org/openfooddata/actors/antwerpse-honing---de-stadsimker"},{"@type":"ofd:ActorRelationship","ofd:relatedContext":"at:producer","ofd:relatedActor":"https://w3id.org/openfooddata/actors/widar"},{"@type":"ofd:ActorRelationship","ofd:relatedContext":"at:producer","ofd:relatedActor":"https://w3id.org/openfooddata/actors/wijngaardhof"}],"@id":"https://w3id.org/openfooddata/actors/voedselteam-wilrijk","extraHeader":"<link rel=\"alternate\" href=\"voedselteam-wilrijk.rdf\" type=\"application/rdf+xml\"/>\n<link rel=\"alternate\" href=\"voedselteam-wilrijk.jsonld\" type=\"application/ld+json\"/>\n<link rel=\"alternate\" href=\"voedselteam-wilrijk.nq\" type=\"application/n-quads\"/>\n<link rel=\"alternate\" href=\"voedselteam-wilrijk.nt\" type=\"application/n-triples\"/>\n<link rel=\"alternate\" href=\"voedselteam-wilrijk.ttl\" type=\"text/turtle\"/>\n<link rel=\"alternate\" href=\"voedselteam-wilrijk.rj\" type=\"application/rdf+json\"/>\n<link rel=\"alternate\" href=\"voedselteam-wilrijk.trig\" type=\"text/trig\"/>\n<link rel=\"alternate\" href=\"voedselteam-wilrijk.trix\" type=\"application/trix\"/>\n","schema:name":"Voedselteam Wilrijk","ofd:actorType":["at:pointOfSale","at:foodTeams"]}}