{"type":"Feature","geometry":{"type":"Point","coordinates":[4.236756,51.132824]},"properties":{"foaf:account":[],"foaf:name":"De Vleeshoeve","foaf:isPrimaryTopicOf":["http://www.rechtvanbijdeboer.be/de-vleeshoeve","http://www.rechtvanbijdeboer.be/node/2614"],"@type":"foaf:Agent","schema:image":["http://www.rechtvanbijdeboer.be/sites/default/files/styles/producer_teaser/public/4_0.jpg?itok=5557rO-O"],"@context":"https://openfooddata.github.io/actors/_common/context.jsonld","schema:geo":{"schema:latitude":"51.132824","schema:longitude":"4.236756","@type":"schema:GeoCoordinates","schema:addressCountry":"Belgium","schema:address":{"@type":"schema:PostalAddress","schema:streetAddress":"Hollebeek 61","schema:postalCode":"9140","schema:addressLocality":"Temse"}},"ofd:offersFoodType":["ft:fruit_juices","ft:lamb_meat","ft:beef","ft:pork"],"foaf:depiction":["http://www.rechtvanbijdeboer.be/sites/default/files/styles/producer_teaser/public/4_0.jpg?itok=5557rO-O"],"schema:description":"","ofd:upstreamRel":[{"@type":"ofd:ActorRelationship","ofd:relatedContext":"at:producer","ofd:relatedActor":"https://w3id.org/openfooddata/actors/de-vleeshoeve-bij-rudy-gerda"}],"@id":"https://w3id.org/openfooddata/actors/de-vleeshoeve","extraHeader":"<link rel=\"alternate\" href=\"de-vleeshoeve.rdf\" type=\"application/rdf+xml\"/>\n<link rel=\"alternate\" href=\"de-vleeshoeve.jsonld\" type=\"application/ld+json\"/>\n<link rel=\"alternate\" href=\"de-vleeshoeve.nq\" type=\"application/n-quads\"/>\n<link rel=\"alternate\" href=\"de-vleeshoeve.nt\" type=\"application/n-triples\"/>\n<link rel=\"alternate\" href=\"de-vleeshoeve.ttl\" type=\"text/turtle\"/>\n<link rel=\"alternate\" href=\"de-vleeshoeve.rj\" type=\"application/rdf+json\"/>\n<link rel=\"alternate\" href=\"de-vleeshoeve.trig\" type=\"text/trig\"/>\n<link rel=\"alternate\" href=\"de-vleeshoeve.trix\" type=\"application/trix\"/>\n","schema:name":"De Vleeshoeve","ofd:actorType":["at:pointOfSale","at:farmShop"]}}