{"type":"Feature","geometry":{"type":"Point","coordinates":[4.404566,50.880034]},"properties":{"id":"https://w3id.org/openfooddata/actors/gc-everna","name":"GC Everna","img":["http://www.rechtvanbijdeboer.be/sites/default/files/styles/producer_teaser/public/fotosessiestreekprodukten%20%2846%29_1.jpg?itok=P8yY02ej"],"type":["at:pointOfSale","at:vegetableSubscription"],"upstream":[{"@type":"ofd:ActorRelationship","ofd:relatedContext":"at:producer","ofd:relatedActor":"https://w3id.org/openfooddata/actors/den-diepen-boomgaard"}]}}