{"type":"Feature","geometry":{"type":"Point","coordinates":[2.842278,50.918783]},"properties":{"foaf:account":[],"foaf:name":"Wijnkelder","foaf:isPrimaryTopicOf":["http://www.rechtvanbijdeboer.be/wijnkelder","http://www.rechtvanbijdeboer.be/node/2581"],"@type":"foaf:Agent","schema:image":[],"@context":"https://openfooddata.github.io/actors/_common/context.jsonld","schema:geo":{"schema:latitude":"50.918783","schema:longitude":"2.842278","@type":"schema:GeoCoordinates","schema:addressCountry":"Belgium","schema:address":{"@type":"schema:PostalAddress","schema:streetAddress":"Diksmuidseweg 530","schema:postalCode":"8904","schema:addressLocality":"Boezinge - Ieper"}},"ofd:offersFoodType":["ft:alcoholic_beverages"],"foaf:depiction":[],"schema:description":"","ofd:upstreamRel":[{"@type":"ofd:ActorRelationship","ofd:relatedContext":"at:producer","ofd:relatedActor":"https://w3id.org/openfooddata/actors/wijngoed-zilver-cruys"}],"@id":"https://w3id.org/openfooddata/actors/wijnkelder","extraHeader":"<link rel=\"alternate\" href=\"wijnkelder.rdf\" type=\"application/rdf+xml\"/>\n<link rel=\"alternate\" href=\"wijnkelder.jsonld\" type=\"application/ld+json\"/>\n<link rel=\"alternate\" href=\"wijnkelder.nq\" type=\"application/n-quads\"/>\n<link rel=\"alternate\" href=\"wijnkelder.nt\" type=\"application/n-triples\"/>\n<link rel=\"alternate\" href=\"wijnkelder.ttl\" type=\"text/turtle\"/>\n<link rel=\"alternate\" href=\"wijnkelder.rj\" type=\"application/rdf+json\"/>\n<link rel=\"alternate\" href=\"wijnkelder.trig\" type=\"text/trig\"/>\n<link rel=\"alternate\" href=\"wijnkelder.trix\" type=\"application/trix\"/>\n","schema:name":"Wijnkelder","ofd:actorType":["at:pointOfSale","at:farmShop"]}}