{"type":"Feature","geometry":{"type":"Point","coordinates":[3.716589,51.039843]},"properties":{"id":"https://w3id.org/openfooddata/actors/origino","name":"Origin'O","img":[],"type":["at:pointOfSale","at:vegetableSubscription"],"upstream":[{"@type":"ofd:ActorRelationship","ofd:relatedContext":"at:producer","ofd:relatedActor":"https://w3id.org/openfooddata/actors/de-wassende-maan"}]}}