{"type":"Feature","geometry":{"type":"Point","coordinates":[3.928375,51.036654]},"properties":{"foaf:account":[],"foaf:name":"Afhaalpunt Kalken","foaf:isPrimaryTopicOf":["http://www.rechtvanbijdeboer.be/afhaalpunt-kalken","http://www.rechtvanbijdeboer.be/node/3540"],"@type":"foaf:Agent","schema:image":[],"@context":"https://openfooddata.github.io/actors/_common/context.jsonld","schema:geo":{"schema:latitude":"51.036654","schema:longitude":"3.928375","@type":"schema:GeoCoordinates","schema:addressCountry":"Belgium","schema:address":{"@type":"schema:PostalAddress","schema:streetAddress":"Uitbergsestraat 51","schema:postalCode":"9270","schema:addressLocality":"Kalken"}},"ofd:offersFoodType":["ft:potatoes","ft:fruits","ft:bakery_products","ft:eggs","ft:fruit_juices","ft:spices","ft:beef","ft:alcoholic_beverages","ft:vegetables","ft:milk_products"],"foaf:depiction":[],"schema:description":"","ofd:upstreamRel":[{"@type":"ofd:ActorRelationship","ofd:relatedContext":"at:producer","ofd:relatedActor":"https://w3id.org/openfooddata/actors/de-wassende-maan"}],"@id":"https://w3id.org/openfooddata/actors/afhaalpunt-kalken","extraHeader":"<link rel=\"alternate\" href=\"afhaalpunt-kalken.rdf\" type=\"application/rdf+xml\"/>\n<link rel=\"alternate\" href=\"afhaalpunt-kalken.jsonld\" type=\"application/ld+json\"/>\n<link rel=\"alternate\" href=\"afhaalpunt-kalken.nq\" type=\"application/n-quads\"/>\n<link rel=\"alternate\" href=\"afhaalpunt-kalken.nt\" type=\"application/n-triples\"/>\n<link rel=\"alternate\" href=\"afhaalpunt-kalken.ttl\" type=\"text/turtle\"/>\n<link rel=\"alternate\" href=\"afhaalpunt-kalken.rj\" type=\"application/rdf+json\"/>\n<link rel=\"alternate\" href=\"afhaalpunt-kalken.trig\" type=\"text/trig\"/>\n<link rel=\"alternate\" href=\"afhaalpunt-kalken.trix\" type=\"application/trix\"/>\n","schema:name":"Afhaalpunt Kalken","ofd:actorType":["at:pointOfSale","at:vegetableSubscription"]}}