{"type":"Feature","geometry":{"type":"Point","coordinates":[3.928375,51.036654]},"properties":{"foaf:account":[],"foaf:name":"Afhaalpunt Kalken","foaf:isPrimaryTopicOf":["http://www.rechtvanbijdeboer.be/afhaalpunt-kalken","http://www.rechtvanbijdeboer.be/node/3540"],"@type":"foaf:Agent","schema:image":[],"@context":"https://openfooddata.github.io/actors/_common/context.jsonld","schema:geo":{"schema:latitude":"51.036654","schema:longitude":"3.928375","@type":"schema:GeoCoordinates","schema:addressCountry":"Belgium","schema:address":{"@type":"schema:PostalAddress","schema:streetAddress":"Uitbergsestraat 51","schema:postalCode":"9270","schema:addressLocality":"Kalken"}},"ofd:offersFoodType":["ft:potatoes","ft:fruits","ft:bakery_products","ft:eggs","ft:fruit_juices","ft:spices","ft:beef","ft:alcoholic_beverages","ft:vegetables","ft:milk_products"],"foaf:depiction":[],"schema:description":"","ofd:upstreamRel":[{"@type":"ofd:ActorRelationship","ofd:relatedContext":"at:producer","ofd:relatedActor":"https://w3id.org/openfooddata/actors/de-wassende-maan"}],"@id":"https://w3id.org/openfooddata/actors/afhaalpunt-kalken","schema:name":"Afhaalpunt Kalken","ofd:actorType":["at:pointOfSale","at:vegetableSubscription"]}}