{"type":"Feature","geometry":{"type":"Point","coordinates":[5.260795,51.169118]},"properties":{"id":"https://w3id.org/openfooddata/actors/hoevermaay-0","name":"Hoevermaay","img":[],"type":["at:pointOfSale","at:farmShop"],"upstream":[{"@type":"ofd:ActorRelationship","ofd:relatedContext":"at:producer","ofd:relatedActor":"https://w3id.org/openfooddata/actors/hoevermaay"}]}}