{"type":"Feature","geometry":{"type":"Point","coordinates":[3.34787,51.055657]},"properties":{"foaf:account":[],"foaf:name":"De Klimop","schema:url":[],"foaf:homepage":[],"foaf:isPrimaryTopicOf":["http://www.rechtvanbijdeboer.be/de-klimop-0","http://www.rechtvanbijdeboer.be/node/3292","https://www.rechtvanbijdeboer.be/de-klimop","https://www.rechtvanbijdeboer.be/node/1746"],"@type":"foaf:Agent","schema:image":[],"@context":"https://openfooddata.github.io/actors/_common/context.jsonld","schema:geo":{"schema:latitude":"51.055657","schema:longitude":"3.347870","@type":"schema:GeoCoordinates","schema:addressCountry":"Belgium","schema:address":{"@type":"schema:PostalAddress","schema:streetAddress":"Schoutskruisestraat 11","schema:postalCode":"8755","schema:addressLocality":"Ruiselede"}},"ofd:offersFoodType":["ft:milk_products","ft:icecream"],"foaf:depiction":[],"schema:description":"","ofd:upstreamRel":[],"ofd:downstreamRel":[],"@id":"https://w3id.org/openfooddata/actors/de-klimop","schema:name":"De Klimop","ofd:actorType":["at:pointOfSale","at:farmShop","at:producer"]}}