{"type":"Feature","geometry":{"type":"Point","coordinates":[4.66564,50.931351]},"properties":{"id":"https://w3id.org/openfooddata/actors/gille-lv","name":"Gille LV","img":[],"type":["at:pointOfSale","at:producer","at:farmShop","at:vendingMachine"],"upstream":[],"downstream":[]}}