{"type":"Feature","geometry":{"type":"Point","coordinates":[3.125411,51.208788]},"properties":{"foaf:account":[],"foaf:name":"Martens -Kerckhove Dirk en Hilde","foaf:isPrimaryTopicOf":["http://www.rechtvanbijdeboer.be/martens-kerckhove-dirk-en-hilde","http://www.rechtvanbijdeboer.be/node/3499"],"@type":"foaf:Agent","schema:image":[],"@context":"https://openfooddata.github.io/actors/_common/context.jsonld","schema:geo":{"schema:latitude":"51.208788","schema:longitude":"3.125411","@type":"schema:GeoCoordinates","schema:addressCountry":"Belgium","schema:address":{"@type":"schema:PostalAddress","schema:streetAddress":"Westernieuwweg 96","schema:postalCode":"8490","schema:addressLocality":"Jabbeke-Varsenare"}},"ofd:offersFoodType":["ft:potatoes","ft:eggs","ft:milk_products"],"foaf:depiction":[],"schema:description":"","ofd:upstreamRel":[{"@type":"ofd:ActorRelationship","ofd:relatedContext":"at:producer","ofd:relatedActor":"https://w3id.org/openfooddata/actors/dirk-en-hilde-martens-kerckhove"}],"@id":"https://w3id.org/openfooddata/actors/martens-kerckhove-dirk-en-hilde","schema:name":"Martens -Kerckhove Dirk en Hilde","ofd:actorType":["at:pointOfSale","at:farmShop"]}}