{"type":"Feature","geometry":{"type":"Point","coordinates":[4.498827,51.250809]},"properties":{"id":"https://w3id.org/openfooddata/actors/buurderij-schoten","name":"Buurderij Schoten","img":[],"type":["at:pointOfSale","at:foodAssembly"],"upstream":[]}}