{"type":"Feature","geometry":{"type":"Point","coordinates":[4.023326,50.831189]},"properties":{"foaf:account":[],"foaf:name":"De Gezondheidswinkel","foaf:isPrimaryTopicOf":["http://www.rechtvanbijdeboer.be/de-gezondheidswinkel","http://www.rechtvanbijdeboer.be/node/2507"],"@type":"foaf:Agent","schema:image":[],"@context":"https://openfooddata.github.io/actors/_common/context.jsonld","schema:geo":{"schema:latitude":"50.831189","schema:longitude":"4.023326","@type":"schema:GeoCoordinates","schema:addressCountry":"Belgium","schema:address":{"@type":"schema:PostalAddress","schema:streetAddress":"Burchtdam","schema:postalCode":"9400","schema:addressLocality":"Ninove"}},"ofd:offersFoodType":["ft:potatoes","ft:bakery_products","ft:eggs","ft:fruits","ft:fruit_juices","ft:vegetables","ft:spices","ft:alcoholic_beverages","ft:milk_products"],"foaf:depiction":[],"schema:description":"","ofd:upstreamRel":[{"@type":"ofd:ActorRelationship","ofd:relatedContext":"at:producer","ofd:relatedActor":"https://w3id.org/openfooddata/actors/de-kollebloem"}],"@id":"https://w3id.org/openfooddata/actors/de-gezondheidswinkel","extraHeader":"<link rel=\"alternate\" href=\"de-gezondheidswinkel.rdf\" type=\"application/rdf+xml\"/>\n<link rel=\"alternate\" href=\"de-gezondheidswinkel.jsonld\" type=\"application/ld+json\"/>\n<link rel=\"alternate\" href=\"de-gezondheidswinkel.nq\" type=\"application/n-quads\"/>\n<link rel=\"alternate\" href=\"de-gezondheidswinkel.nt\" type=\"application/n-triples\"/>\n<link rel=\"alternate\" href=\"de-gezondheidswinkel.ttl\" type=\"text/turtle\"/>\n<link rel=\"alternate\" href=\"de-gezondheidswinkel.rj\" type=\"application/rdf+json\"/>\n<link rel=\"alternate\" href=\"de-gezondheidswinkel.trig\" type=\"text/trig\"/>\n<link rel=\"alternate\" href=\"de-gezondheidswinkel.trix\" type=\"application/trix\"/>\n","schema:name":"De Gezondheidswinkel","ofd:actorType":["at:pointOfSale","at:vegetableSubscription"]}}