{"type":"Feature","geometry":{"type":"Point","coordinates":[4.342201,50.86354]},"properties":{"foaf:account":[],"foaf:name":"Buurderij Molenbeek","foaf:isPrimaryTopicOf":["http://www.rechtvanbijdeboer.be/buurderij-molenbeek","http://www.rechtvanbijdeboer.be/node/2053"],"@type":"foaf:Agent","schema:image":[],"@context":"https://openfooddata.github.io/actors/_common/context.jsonld","schema:geo":{"schema:latitude":"50.863540","schema:longitude":"4.342201","@type":"schema:GeoCoordinates","schema:addressCountry":"Belgium","schema:address":{"@type":"schema:PostalAddress","schema:streetAddress":"Le Centre Communautaire Maritime, Rue Vandenboogaerde 93","schema:postalCode":"1080","schema:addressLocality":"Molenbeek"}},"ofd:offersFoodType":[],"foaf:depiction":[],"schema:description":"","ofd:upstreamRel":[],"@id":"https://w3id.org/openfooddata/actors/buurderij-molenbeek","schema:name":"Buurderij Molenbeek","ofd:actorType":["at:pointOfSale","at:foodAssembly"]}}