{"type":"Feature","geometry":{"type":"Point","coordinates":[4.70366,50.945851]},"properties":{"foaf:account":[],"foaf:name":"De Molentuin","foaf:isPrimaryTopicOf":["http://www.rechtvanbijdeboer.be/de-molentuin-0","http://www.rechtvanbijdeboer.be/node/2752"],"@type":"foaf:Agent","schema:image":[],"@context":"https://openfooddata.github.io/actors/_common/context.jsonld","schema:geo":{"schema:latitude":"50.945851","schema:longitude":"4.703660","@type":"schema:GeoCoordinates","schema:addressCountry":"Belgium","schema:address":{"@type":"schema:PostalAddress","schema:streetAddress":"Molenstraat 2 bus 3","schema:postalCode":"3110","schema:addressLocality":"Rotselaar"}},"ofd:offersFoodType":["ft:potatoes","ft:fruits","ft:vegetables"],"foaf:depiction":[],"schema:description":"","ofd:upstreamRel":[{"@type":"ofd:ActorRelationship","ofd:relatedContext":"at:producer","ofd:relatedActor":"https://w3id.org/openfooddata/actors/de-molentuin"}],"@id":"https://w3id.org/openfooddata/actors/de-molentuin-0","schema:name":"De Molentuin","ofd:actorType":["at:pointOfSale","at:farmShop"]}}