{"type":"Feature","geometry":{"type":"Point","coordinates":[3.810705,50.865001]},"properties":{"id":"https://w3id.org/openfooddata/actors/konkinklijk-atheneum-zottegem","name":"Konkinklijk Atheneum Zottegem","img":[],"type":["at:pointOfSale","at:vegetableSubscription"],"upstream":[{"@type":"ofd:ActorRelationship","ofd:relatedContext":"at:producer","ofd:relatedActor":"https://w3id.org/openfooddata/actors/de-kollebloem"}]}}