{"type":"Feature","geometry":{"type":"Point","coordinates":[3.445407,51.2088]},"properties":{"foaf:account":[],"foaf:name":"Markt Maldegem","foaf:isPrimaryTopicOf":["http://www.rechtvanbijdeboer.be/markt-maldegem","http://www.rechtvanbijdeboer.be/node/2146"],"@type":"foaf:Agent","schema:image":[],"@context":"https://openfooddata.github.io/actors/_common/context.jsonld","schema:geo":{"schema:latitude":"51.208800","schema:longitude":"3.445407","@type":"schema:GeoCoordinates","schema:addressCountry":"Belgium","schema:address":{"@type":"schema:PostalAddress","schema:streetAddress":"markt","schema:postalCode":"9990","schema:addressLocality":"Maldegem"}},"ofd:offersFoodType":["ft:potatoes","ft:fruits","ft:vegetables","ft:eggs","ft:milk_products"],"foaf:depiction":[],"schema:description":"","ofd:upstreamRel":[{"@type":"ofd:ActorRelationship","ofd:relatedContext":"at:producer","ofd:relatedActor":"https://w3id.org/openfooddata/actors/t-hof-rozendale"},{"@type":"ofd:ActorRelationship","ofd:relatedContext":"at:producer","ofd:relatedActor":"https://w3id.org/openfooddata/actors/t-ambrozijn"}],"@id":"https://w3id.org/openfooddata/actors/markt-maldegem","schema:name":"Markt Maldegem","ofd:actorType":["at:pointOfSale","at:market"]}}