{"type":"Feature","geometry":{"type":"Point","coordinates":[4.022691,50.872177]},"properties":{"id":"https://w3id.org/openfooddata/actors/tuin-dier-en-hobbycenter-wim-de-middeleer","name":"Tuin- dier- en hobbycenter Wim De Middeleer","img":[],"type":["at:pointOfSale","at:farmShop"],"upstream":[{"@type":"ofd:ActorRelationship","ofd:relatedContext":"at:producer","ofd:relatedActor":"https://w3id.org/openfooddata/actors/schapenmelkerij-bosschelle"}]}}