{"type":"Feature","geometry":{"type":"Point","coordinates":[4.422582,51.288332]},"properties":{"id":"https://w3id.org/openfooddata/actors/ter-schriek","name":"Ter Schriek","img":[],"type":["at:pointOfSale","at:farmShop","at:producer"],"upstream":[],"downstream":[]}}