{"type":"Feature","geometry":{"type":"Point","coordinates":[3.557511,51.27362]},"properties":{"id":"https://w3id.org/openfooddata/actors/de-zuivelhoeve-0","name":"De Zuivelhoeve","img":[],"type":["at:pointOfSale","at:farmShop"],"upstream":[{"@type":"ofd:ActorRelationship","ofd:relatedContext":"at:producer","ofd:relatedActor":"https://w3id.org/openfooddata/actors/de-zuivelhoeve"}]}}