{"type":"Feature","geometry":{"type":"Point","coordinates":[4.928441,50.834902]},"properties":{"id":"https://w3id.org/openfooddata/actors/yggdrasil","name":"Yggdrasil","img":[],"type":["at:pointOfSale","at:producer","at:farmShop"],"upstream":[],"downstream":[]}}