{"type":"Feature","geometry":{"type":"Point","coordinates":[4.032862,50.938888]},"properties":{"foaf:account":[],"foaf:name":"Aalst","foaf:isPrimaryTopicOf":["http://www.rechtvanbijdeboer.be/aalst","http://www.rechtvanbijdeboer.be/node/2137"],"@type":"foaf:Agent","schema:image":["http://www.rechtvanbijdeboer.be/sites/default/files/styles/producer_teaser/public/img_4698.jpg?itok=zS9m9TpB"],"@context":"https://openfooddata.github.io/actors/_common/context.jsonld","schema:geo":{"schema:latitude":"50.938888","schema:longitude":"4.032862","@type":"schema:GeoCoordinates","schema:addressCountry":"Belgium","schema:address":{"@type":"schema:PostalAddress","schema:streetAddress":"Vredesplein","schema:postalCode":"9300","schema:addressLocality":"Aalst"}},"ofd:offersFoodType":["ft:potatoes","ft:fruits","ft:vegetables","ft:bakery_products","ft:fruit_juices","ft:spices","ft:alcoholic_beverages","ft:milk_products"],"foaf:depiction":["http://www.rechtvanbijdeboer.be/sites/default/files/styles/producer_teaser/public/img_4698.jpg?itok=zS9m9TpB"],"schema:description":"","ofd:upstreamRel":[{"@type":"ofd:ActorRelationship","ofd:relatedContext":"at:producer","ofd:relatedActor":"https://w3id.org/openfooddata/actors/boerderij-de-loods"},{"@type":"ofd:ActorRelationship","ofd:relatedContext":"at:producer","ofd:relatedActor":"https://w3id.org/openfooddata/actors/fierlafijn"}],"@id":"https://w3id.org/openfooddata/actors/aalst","schema:name":"Aalst","ofd:actorType":["at:pointOfSale","at:market"]}}