{"type":"Feature","geometry":{"type":"Point","coordinates":[3.051964,50.929155]},"properties":{"id":"https://w3id.org/openfooddata/actors/demaegdt-demeulenaere-filip-en-leen","name":"Demaegdt-Demeulenaere Filip en Leen","img":[],"type":["at:pointOfSale","at:producer","at:farmShop","at:vendingMachine"],"upstream":[],"downstream":[]}}