{"type":"Feature","geometry":{"type":"Point","coordinates":[3.051964,50.929155]},"properties":{"foaf:account":[],"foaf:name":"Demaegdt-Demeulenaere Filip en Leen","schema:url":[],"foaf:homepage":[],"foaf:isPrimaryTopicOf":["http://www.rechtvanbijdeboer.be/demaegdt-demeulenaere-filip-en-leen-0","http://www.rechtvanbijdeboer.be/node/3404","https://www.rechtvanbijdeboer.be/demaegdt-demeulenaere-filip-en-leen","https://www.rechtvanbijdeboer.be/node/1837","http://www.rechtvanbijdeboer.be/demaegdt-demeulenaere-filip-en-leen-1","http://www.rechtvanbijdeboer.be/node/3405"],"@type":"foaf:Agent","schema:image":[],"@context":"https://openfooddata.github.io/actors/_common/context.jsonld","schema:geo":{"schema:latitude":"50.929155","schema:longitude":"3.051964","@type":"schema:GeoCoordinates","schema:addressCountry":"Belgium","schema:address":{"@type":"schema:PostalAddress","schema:streetAddress":"Spanjestraat 72","schema:postalCode":"8840","schema:addressLocality":"Oostnieuwkerke"}},"ofd:offersFoodType":["ft:fruits","ft:potatoes"],"foaf:depiction":[],"schema:description":"","ofd:upstreamRel":[],"ofd:downstreamRel":[],"@id":"https://w3id.org/openfooddata/actors/demaegdt-demeulenaere-filip-en-leen","extraHeader":"<link rel=\"alternate\" href=\"demaegdt-demeulenaere-filip-en-leen.rdf\" type=\"application/rdf+xml\"/>\n<link rel=\"alternate\" href=\"demaegdt-demeulenaere-filip-en-leen.jsonld\" type=\"application/ld+json\"/>\n<link rel=\"alternate\" href=\"demaegdt-demeulenaere-filip-en-leen.nq\" type=\"application/n-quads\"/>\n<link rel=\"alternate\" href=\"demaegdt-demeulenaere-filip-en-leen.nt\" type=\"application/n-triples\"/>\n<link rel=\"alternate\" href=\"demaegdt-demeulenaere-filip-en-leen.ttl\" type=\"text/turtle\"/>\n<link rel=\"alternate\" href=\"demaegdt-demeulenaere-filip-en-leen.rj\" type=\"application/rdf+json\"/>\n<link rel=\"alternate\" href=\"demaegdt-demeulenaere-filip-en-leen.trig\" type=\"text/trig\"/>\n<link rel=\"alternate\" href=\"demaegdt-demeulenaere-filip-en-leen.trix\" type=\"application/trix\"/>\n","schema:name":"Demaegdt-Demeulenaere Filip en Leen","ofd:actorType":["at:pointOfSale","at:producer","at:farmShop","at:vendingMachine"]}}