{"type":"Feature","geometry":{"type":"Point","coordinates":[4.935917,51.333896]},"properties":{"id":"https://w3id.org/openfooddata/actors/zelfoogsttuin-de-troef","name":"Zelfoogsttuin De Troef","img":[],"type":["at:pointOfSale","at:csaFarm","at:producer"],"upstream":[],"downstream":[]}}