{"type":"Feature","geometry":{"type":"Point","coordinates":[3.109458,50.917987]},"properties":{"foaf:account":[],"foaf:name":"Vanysacker","schema:url":[],"foaf:homepage":[],"foaf:isPrimaryTopicOf":["http://www.rechtvanbijdeboer.be/vanysacker-0","http://www.rechtvanbijdeboer.be/node/2863","https://www.rechtvanbijdeboer.be/vanysacker","https://www.rechtvanbijdeboer.be/node/1390"],"@type":"foaf:Agent","schema:image":[],"@context":"https://openfooddata.github.io/actors/_common/context.jsonld","schema:geo":{"schema:latitude":"50.917987","schema:longitude":"3.109458","@type":"schema:GeoCoordinates","schema:addressCountry":"Belgium","schema:address":{"@type":"schema:PostalAddress","schema:streetAddress":"Knokuilstraat 18","schema:postalCode":"8800","schema:addressLocality":"Rumbeke"}},"ofd:offersFoodType":["ft:vegetables"],"foaf:depiction":[],"schema:description":"","ofd:upstreamRel":[],"ofd:downstreamRel":[],"@id":"https://w3id.org/openfooddata/actors/vanysacker","extraHeader":"<link rel=\"alternate\" href=\"vanysacker.rdf\" type=\"application/rdf+xml\"/>\n<link rel=\"alternate\" href=\"vanysacker.jsonld\" type=\"application/ld+json\"/>\n<link rel=\"alternate\" href=\"vanysacker.nq\" type=\"application/n-quads\"/>\n<link rel=\"alternate\" href=\"vanysacker.nt\" type=\"application/n-triples\"/>\n<link rel=\"alternate\" href=\"vanysacker.ttl\" type=\"text/turtle\"/>\n<link rel=\"alternate\" href=\"vanysacker.rj\" type=\"application/rdf+json\"/>\n<link rel=\"alternate\" href=\"vanysacker.trig\" type=\"text/trig\"/>\n<link rel=\"alternate\" href=\"vanysacker.trix\" type=\"application/trix\"/>\n","schema:name":"Vanysacker","ofd:actorType":["at:pointOfSale","at:farmShop","at:producer"]}}