{"type":"Feature","geometry":{"type":"Point","coordinates":[3.109458,50.917987]},"properties":{"id":"https://w3id.org/openfooddata/actors/vanysacker","name":"Vanysacker","img":[],"type":["at:pointOfSale","at:farmShop","at:producer"],"upstream":[],"downstream":[]}}