{"type":"Feature","geometry":{"type":"Point","coordinates":[2.953867,51.197361]},"properties":{"foaf:account":[],"foaf:name":"De Kaashoeve","foaf:isPrimaryTopicOf":["http://www.rechtvanbijdeboer.be/de-kaashoeve-1","http://www.rechtvanbijdeboer.be/node/3004"],"@type":"foaf:Agent","schema:image":[],"@context":"https://openfooddata.github.io/actors/_common/context.jsonld","schema:geo":{"schema:latitude":"51.197361","schema:longitude":"2.953867","@type":"schema:GeoCoordinates","schema:addressCountry":"Belgium","schema:address":{"@type":"schema:PostalAddress","schema:streetAddress":"Gistelsesteenweg 612","schema:postalCode":"8400","schema:addressLocality":"Oostende"}},"ofd:offersFoodType":["ft:milk_products"],"foaf:depiction":[],"schema:description":"","ofd:upstreamRel":[{"@type":"ofd:ActorRelationship","ofd:relatedContext":"at:producer","ofd:relatedActor":"https://w3id.org/openfooddata/actors/de-kaashoeve-oostende"}],"@id":"https://w3id.org/openfooddata/actors/de-kaashoeve-1","schema:name":"De Kaashoeve","ofd:actorType":["at:pointOfSale","at:farmShop"]}}