{"type":"Feature","geometry":{"type":"Point","coordinates":[5.031894,50.947707]},"properties":{"id":"https://w3id.org/openfooddata/actors/vandebroeck-lv","name":"Vandebroeck LV","img":[],"type":["at:pointOfSale","at:collectionPoint"],"upstream":[{"@type":"ofd:ActorRelationship","ofd:relatedContext":"at:producer","ofd:relatedActor":"https://w3id.org/openfooddata/actors/vandebroeck"}]}}