{"type":"Feature","geometry":{"type":"Point","coordinates":[3.687762,50.987427]},"properties":{"foaf:account":[],"foaf:name":"Lerouge Frederic","foaf:isPrimaryTopicOf":["http://www.rechtvanbijdeboer.be/lerouge-frederic","http://www.rechtvanbijdeboer.be/node/3459"],"@type":"foaf:Agent","schema:image":[],"@context":"https://openfooddata.github.io/actors/_common/context.jsonld","schema:geo":{"schema:latitude":"50.987427","schema:longitude":"3.687762","@type":"schema:GeoCoordinates","schema:addressCountry":"Belgium","schema:address":{"@type":"schema:PostalAddress","schema:streetAddress":"Boeregemstraat 4a","schema:postalCode":"9840","schema:addressLocality":"Zevergem"}},"ofd:offersFoodType":["ft:fruits","ft:fruit_juices"],"foaf:depiction":[],"schema:description":"","ofd:upstreamRel":[{"@type":"ofd:ActorRelationship","ofd:relatedContext":"at:producer","ofd:relatedActor":"https://w3id.org/openfooddata/actors/mobiele-fruitpers-lerouge-zevergem"}],"@id":"https://w3id.org/openfooddata/actors/lerouge-frederic","schema:name":"Lerouge Frederic","ofd:actorType":["at:pointOfSale","at:vendingMachine"]}}