{"type":"Feature","geometry":{"type":"Point","coordinates":[4.231806,50.946156]},"properties":{"foaf:account":[],"foaf:name":"Koeweidehof","schema:url":[],"foaf:homepage":[],"foaf:isPrimaryTopicOf":["http://www.rechtvanbijdeboer.be/koeweidehof-0","http://www.rechtvanbijdeboer.be/node/3252","https://www.rechtvanbijdeboer.be/koeweidehof","https://www.rechtvanbijdeboer.be/node/1715"],"@type":"foaf:Agent","schema:image":[],"@context":"https://openfooddata.github.io/actors/_common/context.jsonld","schema:geo":{"schema:latitude":"50.946156","schema:longitude":"4.231806","@type":"schema:GeoCoordinates","schema:addressCountry":"Belgium","schema:address":{"@type":"schema:PostalAddress","schema:streetAddress":"Koeweidestraat 25","schema:postalCode":"1785","schema:addressLocality":"Merchtem"}},"ofd:offersFoodType":["ft:eggs","ft:vegetables","ft:potatoes"],"foaf:depiction":[],"schema:description":"","ofd:upstreamRel":[],"ofd:downstreamRel":[],"@id":"https://w3id.org/openfooddata/actors/koeweidehof","schema:name":"Koeweidehof","ofd:actorType":["at:pointOfSale","at:vendingMachine","at:producer"]}}