{"type":"Feature","geometry":{"type":"Point","coordinates":[2.923393,50.960305]},"properties":{"id":"https://w3id.org/openfooddata/actors/glorius","name":"GLORIUS","img":["http://www.rechtvanbijdeboer.be/sites/default/files/styles/producer_teaser/public/glorius_vlees_worsten_lr.jpg?itok=R20PZxs2","http://www.rechtvanbijdeboer.be/sites/default/files/styles/producer_teaser/public/glorius_vlees_versnijden_lr.jpg?itok=3SgEheUR","http://www.rechtvanbijdeboer.be/sites/default/files/styles/producer_teaser/public/glorius_bedrijf_luchtfoto_lr.jpg?itok=rPzpEz-W"],"type":["at:pointOfSale","at:farmShop","at:producer"],"upstream":[],"downstream":[{"@type":"ofd:ActorRelationship","ofd:relatedContext":"at:pointOfSale","ofd:relatedActor":"https://w3id.org/openfooddata/actors/wwwgloriusbe"}]}}