{"type":"Feature","geometry":{"type":"Point","coordinates":[2.923393,50.960305]},"properties":{"foaf:account":[],"foaf:name":"GLORIUS","schema:url":[],"foaf:homepage":[],"foaf:isPrimaryTopicOf":["http://www.rechtvanbijdeboer.be/glorius-0","http://www.rechtvanbijdeboer.be/node/3221","http://www.rechtvanbijdeboer.be/glorius","http://www.rechtvanbijdeboer.be/node/1698"],"@type":"foaf:Agent","schema:image":["http://www.rechtvanbijdeboer.be/sites/default/files/styles/producer_teaser/public/glorius_vlees_worsten_lr.jpg?itok=R20PZxs2","http://www.rechtvanbijdeboer.be/sites/default/files/styles/producer_teaser/public/glorius_vlees_versnijden_lr.jpg?itok=3SgEheUR","http://www.rechtvanbijdeboer.be/sites/default/files/styles/producer_teaser/public/glorius_bedrijf_luchtfoto_lr.jpg?itok=rPzpEz-W"],"@context":"https://openfooddata.github.io/actors/_common/context.jsonld","schema:geo":{"schema:latitude":"50.960305","schema:longitude":"2.923393","@type":"schema:GeoCoordinates","schema:addressCountry":"Belgium","schema:address":{"@type":"schema:PostalAddress","schema:streetAddress":"Melanedreef 24","schema:postalCode":"8650","schema:addressLocality":"Merkem"}},"ofd:offersFoodType":["ft:pork"],"foaf:depiction":["http://www.rechtvanbijdeboer.be/sites/default/files/styles/producer_teaser/public/glorius_vlees_worsten_lr.jpg?itok=R20PZxs2","http://www.rechtvanbijdeboer.be/sites/default/files/styles/producer_teaser/public/glorius_vlees_versnijden_lr.jpg?itok=3SgEheUR","http://www.rechtvanbijdeboer.be/sites/default/files/styles/producer_teaser/public/glorius_bedrijf_luchtfoto_lr.jpg?itok=rPzpEz-W"],"schema:description":"","ofd:upstreamRel":[],"schema:contactPoint":{"@type":"schema:ContactPoint","schema:telephone":["0478428404"],"schema:email":["info@glorius.be"],"foaf:homepage":[],"schema:url":[]},"ofd:downstreamRel":[{"@type":"ofd:ActorRelationship","ofd:relatedContext":"at:pointOfSale","ofd:relatedActor":"https://w3id.org/openfooddata/actors/wwwgloriusbe"}],"@id":"https://w3id.org/openfooddata/actors/glorius","schema:name":"GLORIUS","ofd:actorType":["at:pointOfSale","at:farmShop","at:producer"]}}