{"type":"Feature","geometry":{"type":"Point","coordinates":[4.463233,51.215016]},"properties":{"foaf:account":[],"foaf:name":"Buurderij Deurne","foaf:isPrimaryTopicOf":["http://www.rechtvanbijdeboer.be/buurderij-deurne","http://www.rechtvanbijdeboer.be/node/2039"],"@type":"foaf:Agent","schema:image":[],"@context":"https://openfooddata.github.io/actors/_common/context.jsonld","schema:geo":{"schema:latitude":"51.215016","schema:longitude":"4.463233","@type":"schema:GeoCoordinates","schema:addressCountry":"Belgium","schema:address":{"@type":"schema:PostalAddress","schema:streetAddress":"Hooftvunderlei 160","schema:postalCode":"2100","schema:addressLocality":"Deurne"}},"ofd:offersFoodType":[],"foaf:depiction":[],"schema:description":"","ofd:upstreamRel":[],"@id":"https://w3id.org/openfooddata/actors/buurderij-deurne","extraHeader":"<link rel=\"alternate\" href=\"buurderij-deurne.rdf\" type=\"application/rdf+xml\"/>\n<link rel=\"alternate\" href=\"buurderij-deurne.jsonld\" type=\"application/ld+json\"/>\n<link rel=\"alternate\" href=\"buurderij-deurne.nq\" type=\"application/n-quads\"/>\n<link rel=\"alternate\" href=\"buurderij-deurne.nt\" type=\"application/n-triples\"/>\n<link rel=\"alternate\" href=\"buurderij-deurne.ttl\" type=\"text/turtle\"/>\n<link rel=\"alternate\" href=\"buurderij-deurne.rj\" type=\"application/rdf+json\"/>\n<link rel=\"alternate\" href=\"buurderij-deurne.trig\" type=\"text/trig\"/>\n<link rel=\"alternate\" href=\"buurderij-deurne.trix\" type=\"application/trix\"/>\n","schema:name":"Buurderij Deurne","ofd:actorType":["at:pointOfSale","at:foodAssembly"]}}