{"type":"Feature","geometry":{"type":"Point","coordinates":[3.553842,50.876894]},"properties":{"foaf:account":[],"foaf:name":"Aardbeienautomaat","foaf:isPrimaryTopicOf":["http://www.rechtvanbijdeboer.be/aardbeienautomaat-0","http://www.rechtvanbijdeboer.be/node/2718"],"@type":"foaf:Agent","schema:image":["http://www.rechtvanbijdeboer.be/sites/default/files/styles/producer_teaser/public/10363332_776877332331409_4323796495604880457_n.jpg?itok=bPjtaTuA"],"@context":"https://openfooddata.github.io/actors/_common/context.jsonld","schema:geo":{"schema:latitude":"50.876894","schema:longitude":"3.553842","@type":"schema:GeoCoordinates","schema:addressCountry":"Belgium","schema:address":{"@type":"schema:PostalAddress","schema:streetAddress":"Deinzestraat 78","schema:postalCode":"9790","schema:addressLocality":"Wortegem-Petegem"}},"ofd:offersFoodType":["ft:potatoes","ft:fruits","ft:vegetables"],"foaf:depiction":["http://www.rechtvanbijdeboer.be/sites/default/files/styles/producer_teaser/public/10363332_776877332331409_4323796495604880457_n.jpg?itok=bPjtaTuA"],"schema:description":"","ofd:upstreamRel":[{"@type":"ofd:ActorRelationship","ofd:relatedContext":"at:producer","ofd:relatedActor":"https://w3id.org/openfooddata/actors/aardbeien-aardappelen-de-cock"}],"@id":"https://w3id.org/openfooddata/actors/aardbeienautomaat-0","extraHeader":"<link rel=\"alternate\" href=\"aardbeienautomaat-0.rdf\" type=\"application/rdf+xml\"/>\n<link rel=\"alternate\" href=\"aardbeienautomaat-0.jsonld\" type=\"application/ld+json\"/>\n<link rel=\"alternate\" href=\"aardbeienautomaat-0.nq\" type=\"application/n-quads\"/>\n<link rel=\"alternate\" href=\"aardbeienautomaat-0.nt\" type=\"application/n-triples\"/>\n<link rel=\"alternate\" href=\"aardbeienautomaat-0.ttl\" type=\"text/turtle\"/>\n<link rel=\"alternate\" href=\"aardbeienautomaat-0.rj\" type=\"application/rdf+json\"/>\n<link rel=\"alternate\" href=\"aardbeienautomaat-0.trig\" type=\"text/trig\"/>\n<link rel=\"alternate\" href=\"aardbeienautomaat-0.trix\" type=\"application/trix\"/>\n","schema:name":"Aardbeienautomaat","ofd:actorType":["at:pointOfSale","at:vendingMachine"]}}