{"type":"Feature","geometry":{"type":"Point","coordinates":[3.714866,51.056256]},"properties":{"id":"https://w3id.org/openfooddata/actors/tavontuur","name":"Tavontuur","img":["http://www.rechtvanbijdeboer.be/sites/default/files/styles/producer_teaser/public/dsc_2941.jpg?itok=AXt1vbWE"],"type":["at:pointOfSale","at:farmShop"],"upstream":[{"@type":"ofd:ActorRelationship","ofd:relatedContext":"at:producer","ofd:relatedActor":"https://w3id.org/openfooddata/actors/blauw-kasteel-bvba"}]}}