{"type":"Feature","geometry":{"type":"Point","coordinates":[4.429148,51.209394]},"properties":{"id":"https://w3id.org/openfooddata/actors/kievitsei","name":"Kievitsei","img":[],"type":["at:pointOfSale","at:foodTeams"],"upstream":[]}}