{"type":"Feature","geometry":{"type":"Point","coordinates":[4.472868,51.032269]},"properties":{"id":"https://w3id.org/openfooddata/actors/boeren-en-buren-het-anker","name":"Boeren en Buren/ Het Anker","img":[],"type":["at:pointOfSale","at:collectionPoint"],"upstream":[]}}