{"type":"Feature","geometry":{"type":"Point","coordinates":[5.74185,51.1449]},"properties":{"id":"https://w3id.org/openfooddata/actors/kinrooi","name":"Kinrooi","img":[],"type":["at:pointOfSale","at:market"],"upstream":[{"@type":"ofd:ActorRelationship","ofd:relatedContext":"at:producer","ofd:relatedActor":"https://w3id.org/openfooddata/actors/hoevewinkel-baens"}]}}