{"type":"Feature","geometry":{"type":"Point","coordinates":[4.135245,50.96235]},"properties":{"id":"https://w3id.org/openfooddata/actors/de-koker-lv-0","name":"De Koker LV","img":[],"type":["at:pointOfSale","at:vendingMachine"],"upstream":[{"@type":"ofd:ActorRelationship","ofd:relatedContext":"at:producer","ofd:relatedActor":"https://w3id.org/openfooddata/actors/de-koker-lv"}]}}