{"type":"Feature","geometry":{"type":"Point","coordinates":[4.64349,51.064273]},"properties":{"id":"https://w3id.org/openfooddata/actors/wwwdeeleenhelekoebe","name":"www.deeleenhelekoe.be","img":[],"type":["at:pointOfSale","at:webshop"],"upstream":[{"@type":"ofd:ActorRelationship","ofd:relatedContext":"at:producer","ofd:relatedActor":"https://w3id.org/openfooddata/actors/de-guldenhoeve"}]}}