{"type":"Feature","geometry":{"type":"Point","coordinates":[5.276057,50.828172]},"properties":{"foaf:account":[],"foaf:name":"Aardbeienautomaat Vanleeuw-Schoubben Fruit LV","foaf:isPrimaryTopicOf":["http://www.rechtvanbijdeboer.be/aardbeienautomaat-vanleeuw-schoubben-fruit-lv","http://www.rechtvanbijdeboer.be/node/3328"],"@type":"foaf:Agent","schema:image":[],"@context":"https://openfooddata.github.io/actors/_common/context.jsonld","schema:geo":{"schema:latitude":"50.828172","schema:longitude":"5.276057","@type":"schema:GeoCoordinates","schema:addressCountry":"Belgium","schema:address":{"@type":"schema:PostalAddress","schema:streetAddress":"Tereykenstraat 9","schema:postalCode":"3800","schema:addressLocality":"Zepperen"}},"ofd:offersFoodType":["ft:fruits"],"foaf:depiction":[],"schema:description":"","ofd:upstreamRel":[{"@type":"ofd:ActorRelationship","ofd:relatedContext":"at:producer","ofd:relatedActor":"https://w3id.org/openfooddata/actors/vanleeuw-schoubben-fruit-lv"}],"@id":"https://w3id.org/openfooddata/actors/aardbeienautomaat-vanleeuw-schoubben-fruit-lv","extraHeader":"<link rel=\"alternate\" href=\"aardbeienautomaat-vanleeuw-schoubben-fruit-lv.rdf\" type=\"application/rdf+xml\"/>\n<link rel=\"alternate\" href=\"aardbeienautomaat-vanleeuw-schoubben-fruit-lv.jsonld\" type=\"application/ld+json\"/>\n<link rel=\"alternate\" href=\"aardbeienautomaat-vanleeuw-schoubben-fruit-lv.nq\" type=\"application/n-quads\"/>\n<link rel=\"alternate\" href=\"aardbeienautomaat-vanleeuw-schoubben-fruit-lv.nt\" type=\"application/n-triples\"/>\n<link rel=\"alternate\" href=\"aardbeienautomaat-vanleeuw-schoubben-fruit-lv.ttl\" type=\"text/turtle\"/>\n<link rel=\"alternate\" href=\"aardbeienautomaat-vanleeuw-schoubben-fruit-lv.rj\" type=\"application/rdf+json\"/>\n<link rel=\"alternate\" href=\"aardbeienautomaat-vanleeuw-schoubben-fruit-lv.trig\" type=\"text/trig\"/>\n<link rel=\"alternate\" href=\"aardbeienautomaat-vanleeuw-schoubben-fruit-lv.trix\" type=\"application/trix\"/>\n","schema:name":"Aardbeienautomaat Vanleeuw-Schoubben Fruit LV","ofd:actorType":["at:pointOfSale","at:vendingMachine"]}}