{"type":"Feature","geometry":{"type":"Point","coordinates":[5.276057,50.828172]},"properties":{"foaf:account":[],"foaf:name":"Aardbeienautomaat Vanleeuw-Schoubben Fruit LV","foaf:isPrimaryTopicOf":["http://www.rechtvanbijdeboer.be/aardbeienautomaat-vanleeuw-schoubben-fruit-lv","http://www.rechtvanbijdeboer.be/node/3328"],"@type":"foaf:Agent","schema:image":[],"@context":"https://openfooddata.github.io/actors/_common/context.jsonld","schema:geo":{"schema:latitude":"50.828172","schema:longitude":"5.276057","@type":"schema:GeoCoordinates","schema:addressCountry":"Belgium","schema:address":{"@type":"schema:PostalAddress","schema:streetAddress":"Tereykenstraat 9","schema:postalCode":"3800","schema:addressLocality":"Zepperen"}},"ofd:offersFoodType":["ft:fruits"],"foaf:depiction":[],"schema:description":"","ofd:upstreamRel":[{"@type":"ofd:ActorRelationship","ofd:relatedContext":"at:producer","ofd:relatedActor":"https://w3id.org/openfooddata/actors/vanleeuw-schoubben-fruit-lv"}],"@id":"https://w3id.org/openfooddata/actors/aardbeienautomaat-vanleeuw-schoubben-fruit-lv","schema:name":"Aardbeienautomaat Vanleeuw-Schoubben Fruit LV","ofd:actorType":["at:pointOfSale","at:vendingMachine"]}}