{"type":"Feature","geometry":{"type":"Point","coordinates":[4.208427,50.836513]},"properties":{"foaf:account":[],"foaf:name":"Lemaire","foaf:isPrimaryTopicOf":["http://www.rechtvanbijdeboer.be/lemaire","http://www.rechtvanbijdeboer.be/node/2630"],"@type":"foaf:Agent","schema:image":["http://www.rechtvanbijdeboer.be/sites/default/files/styles/producer_teaser/public/p1000110.jpg?itok=NPZdWKCB"],"@context":"https://openfooddata.github.io/actors/_common/context.jsonld","schema:geo":{"schema:latitude":"50.836513","schema:longitude":"4.208427","@type":"schema:GeoCoordinates","schema:addressCountry":"Belgium","schema:address":{"@type":"schema:PostalAddress","schema:streetAddress":"Geraardsbergsestraat 29","schema:postalCode":"1703","schema:addressLocality":"Schepdaal (Dilbeek)"}},"ofd:offersFoodType":["ft:potatoes"],"foaf:depiction":["http://www.rechtvanbijdeboer.be/sites/default/files/styles/producer_teaser/public/p1000110.jpg?itok=NPZdWKCB"],"schema:description":"","ofd:upstreamRel":[{"@type":"ofd:ActorRelationship","ofd:relatedContext":"at:producer","ofd:relatedActor":"https://w3id.org/openfooddata/actors/jan-lemaire"}],"@id":"https://w3id.org/openfooddata/actors/lemaire","extraHeader":"<link rel=\"alternate\" href=\"lemaire.rdf\" type=\"application/rdf+xml\"/>\n<link rel=\"alternate\" href=\"lemaire.jsonld\" type=\"application/ld+json\"/>\n<link rel=\"alternate\" href=\"lemaire.nq\" type=\"application/n-quads\"/>\n<link rel=\"alternate\" href=\"lemaire.nt\" type=\"application/n-triples\"/>\n<link rel=\"alternate\" href=\"lemaire.ttl\" type=\"text/turtle\"/>\n<link rel=\"alternate\" href=\"lemaire.rj\" type=\"application/rdf+json\"/>\n<link rel=\"alternate\" href=\"lemaire.trig\" type=\"text/trig\"/>\n<link rel=\"alternate\" href=\"lemaire.trix\" type=\"application/trix\"/>\n","schema:name":"Lemaire","ofd:actorType":["at:pointOfSale","at:farmShop"]}}