{"type":"Feature","geometry":{"type":"Point","coordinates":[3.797688,51.060809]},"properties":{"foaf:account":[],"foaf:name":"Bakkerij Bolleken","foaf:isPrimaryTopicOf":["http://www.rechtvanbijdeboer.be/bakkerij-bolleken","http://www.rechtvanbijdeboer.be/node/3534"],"@type":"foaf:Agent","schema:image":[],"@context":"https://openfooddata.github.io/actors/_common/context.jsonld","schema:geo":{"schema:latitude":"51.060809","schema:longitude":"3.797688","@type":"schema:GeoCoordinates","schema:addressCountry":"Belgium","schema:address":{"@type":"schema:PostalAddress","schema:streetAddress":"Stationsstraat 1","schema:postalCode":"9070","schema:addressLocality":"Destelbergen"}},"ofd:offersFoodType":["ft:potatoes","ft:fruits","ft:bakery_products","ft:eggs","ft:fruit_juices","ft:spices","ft:beef","ft:alcoholic_beverages","ft:vegetables","ft:milk_products"],"foaf:depiction":[],"schema:description":"","ofd:upstreamRel":[{"@type":"ofd:ActorRelationship","ofd:relatedContext":"at:producer","ofd:relatedActor":"https://w3id.org/openfooddata/actors/de-wassende-maan"}],"@id":"https://w3id.org/openfooddata/actors/bakkerij-bolleken","schema:name":"Bakkerij Bolleken","ofd:actorType":["at:pointOfSale","at:vegetableSubscription"]}}