{"type":"Feature","geometry":{"type":"Point","coordinates":[3.535834,51.073894]},"properties":{"foaf:account":[],"foaf:name":"Afhaalpunt Hansbeke","foaf:isPrimaryTopicOf":["http://www.rechtvanbijdeboer.be/afhaalpunt-hansbeke","http://www.rechtvanbijdeboer.be/node/3548"],"@type":"foaf:Agent","schema:image":[],"@context":"https://openfooddata.github.io/actors/_common/context.jsonld","schema:geo":{"schema:latitude":"51.073894","schema:longitude":"3.535834","@type":"schema:GeoCoordinates","schema:addressCountry":"Belgium","schema:address":{"@type":"schema:PostalAddress","schema:streetAddress":"Hansbekedorp 23","schema:postalCode":"9850","schema:addressLocality":"Hansbeke"}},"ofd:offersFoodType":["ft:potatoes","ft:fruits","ft:bakery_products","ft:eggs","ft:fruit_juices","ft:spices","ft:beef","ft:alcoholic_beverages","ft:vegetables","ft:milk_products"],"foaf:depiction":[],"schema:description":"","ofd:upstreamRel":[{"@type":"ofd:ActorRelationship","ofd:relatedContext":"at:producer","ofd:relatedActor":"https://w3id.org/openfooddata/actors/de-wassende-maan"}],"@id":"https://w3id.org/openfooddata/actors/afhaalpunt-hansbeke","extraHeader":"<link rel=\"alternate\" href=\"afhaalpunt-hansbeke.rdf\" type=\"application/rdf+xml\"/>\n<link rel=\"alternate\" href=\"afhaalpunt-hansbeke.jsonld\" type=\"application/ld+json\"/>\n<link rel=\"alternate\" href=\"afhaalpunt-hansbeke.nq\" type=\"application/n-quads\"/>\n<link rel=\"alternate\" href=\"afhaalpunt-hansbeke.nt\" type=\"application/n-triples\"/>\n<link rel=\"alternate\" href=\"afhaalpunt-hansbeke.ttl\" type=\"text/turtle\"/>\n<link rel=\"alternate\" href=\"afhaalpunt-hansbeke.rj\" type=\"application/rdf+json\"/>\n<link rel=\"alternate\" href=\"afhaalpunt-hansbeke.trig\" type=\"text/trig\"/>\n<link rel=\"alternate\" href=\"afhaalpunt-hansbeke.trix\" type=\"application/trix\"/>\n","schema:name":"Afhaalpunt Hansbeke","ofd:actorType":["at:pointOfSale","at:vegetableSubscription"]}}