{"type":"Feature","geometry":{"type":"Point","coordinates":[3.10157,51.06498]},"properties":{"id":"https://w3id.org/openfooddata/actors/torhout","name":"Torhout","img":[],"type":["at:pointOfSale","at:market"],"upstream":[{"@type":"ofd:ActorRelationship","ofd:relatedContext":"at:producer","ofd:relatedActor":"https://w3id.org/openfooddata/actors/de-zaaier"}]}}