{"type":"Feature","geometry":{"type":"Point","coordinates":[4.673166,51.382382]},"properties":{"id":"https://w3id.org/openfooddata/actors/het-boerenijsje","name":"Het Boerenijsje","img":[],"type":["at:pointOfSale","at:farmShop","at:producer"],"upstream":[],"downstream":[]}}