{"type":"Feature","geometry":{"type":"Point","coordinates":[4.840822,51.228057]},"properties":{"id":"https://w3id.org/openfooddata/actors/poederlee","name":"Poederlee","img":[],"type":["at:pointOfSale","at:vegetableSubscription"],"upstream":[{"@type":"ofd:ActorRelationship","ofd:relatedContext":"at:producer","ofd:relatedActor":"https://w3id.org/openfooddata/actors/de-bio-hoeve"}]}}