{"type":"Feature","geometry":{"type":"Point","coordinates":[3.564923,51.18835]},"properties":{"foaf:account":[],"foaf:name":"'t Hobbitje","foaf:isPrimaryTopicOf":["http://www.rechtvanbijdeboer.be/t-hobbitje","http://www.rechtvanbijdeboer.be/node/2488"],"@type":"foaf:Agent","schema:image":["http://www.rechtvanbijdeboer.be/sites/default/files/styles/producer_teaser/public/biobellogroentenenfruitmaxi.jpg?itok=n2EToMw3"],"@context":"https://openfooddata.github.io/actors/_common/context.jsonld","schema:geo":{"schema:latitude":"51.188350","schema:longitude":"3.564923","@type":"schema:GeoCoordinates","schema:addressCountry":"Belgium","schema:address":{"@type":"schema:PostalAddress","schema:streetAddress":"J.F. Willemsplein 10","schema:postalCode":"9900","schema:addressLocality":"Eeklo"}},"ofd:offersFoodType":["ft:potatoes","ft:fruits","ft:eggs","ft:vegetables"],"foaf:depiction":["http://www.rechtvanbijdeboer.be/sites/default/files/styles/producer_teaser/public/biobellogroentenenfruitmaxi.jpg?itok=n2EToMw3"],"schema:description":"","ofd:upstreamRel":[{"@type":"ofd:ActorRelationship","ofd:relatedContext":"at:producer","ofd:relatedActor":"https://w3id.org/openfooddata/actors/de-lochting-vzw"}],"@id":"https://w3id.org/openfooddata/actors/t-hobbitje","schema:name":"'t Hobbitje","ofd:actorType":["at:pointOfSale","at:vegetableSubscription"]}}