{"type":"Feature","geometry":{"type":"Point","coordinates":[3.211167,50.873789]},"properties":{"id":"https://w3id.org/openfooddata/actors/de-groene-boomgaard","name":"De Groene Boomgaard","img":[],"type":["at:pointOfSale","at:farmShop","at:producer"],"upstream":[],"downstream":[]}}