{"type":"Feature","geometry":{"type":"Point","coordinates":[3.680825,51.071526]},"properties":{"id":"https://w3id.org/openfooddata/actors/wereldwinkel-0","name":"Wereldwinkel","img":[],"type":["at:pointOfSale","at:vegetableSubscription"],"upstream":[{"@type":"ofd:ActorRelationship","ofd:relatedContext":"at:producer","ofd:relatedActor":"https://w3id.org/openfooddata/actors/de-wassende-maan"}]}}