{"type":"Feature","geometry":{"type":"Point","coordinates":[5.187539,50.729885]},"properties":{"id":"https://w3id.org/openfooddata/actors/hoeveslagerij-stefan-thijsen","name":"Hoeveslagerij Stefan Thijsen","img":[],"type":["at:pointOfSale","at:farmShop","at:producer"],"upstream":[],"downstream":[]}}