{"type":"Feature","geometry":{"type":"Point","coordinates":[4.140269,51.090201]},"properties":{"id":"https://w3id.org/openfooddata/actors/regio-hamme","name":"Regio Hamme","img":[],"type":["at:pointOfSale","at:foodTeams"],"upstream":[{"@type":"ofd:ActorRelationship","ofd:relatedContext":"at:producer","ofd:relatedActor":"https://w3id.org/openfooddata/actors/hammes-hoevevlees"}]}}