{"type":"Feature","geometry":{"type":"Point","coordinates":[3.680841,51.071532]},"properties":{"foaf:account":[],"foaf:name":"Wereldwinkel Mariakerke","foaf:isPrimaryTopicOf":["http://www.rechtvanbijdeboer.be/wereldwinkel-mariakerke","http://www.rechtvanbijdeboer.be/node/2479"],"@type":"foaf:Agent","schema:image":["http://www.rechtvanbijdeboer.be/sites/default/files/styles/producer_teaser/public/biobellogroentenenfruitmaxi.jpg?itok=n2EToMw3"],"@context":"https://openfooddata.github.io/actors/_common/context.jsonld","schema:geo":{"schema:latitude":"51.071532","schema:longitude":"3.680841","@type":"schema:GeoCoordinates","schema:addressCountry":"Belgium","schema:address":{"@type":"schema:PostalAddress","schema:streetAddress":"Brugsesteenweg 526","schema:postalCode":"9030","schema:addressLocality":"Mariakerke"}},"ofd:offersFoodType":["ft:potatoes","ft:fruits","ft:eggs","ft:vegetables"],"foaf:depiction":["http://www.rechtvanbijdeboer.be/sites/default/files/styles/producer_teaser/public/biobellogroentenenfruitmaxi.jpg?itok=n2EToMw3"],"schema:description":"","ofd:upstreamRel":[{"@type":"ofd:ActorRelationship","ofd:relatedContext":"at:producer","ofd:relatedActor":"https://w3id.org/openfooddata/actors/de-lochting-vzw"}],"@id":"https://w3id.org/openfooddata/actors/wereldwinkel-mariakerke","schema:name":"Wereldwinkel Mariakerke","ofd:actorType":["at:pointOfSale","at:vegetableSubscription"]}}