{"type":"Feature","geometry":{"type":"Point","coordinates":[3.400219,50.989806]},"properties":{"foaf:account":[],"foaf:name":"'t Meikensvlasvarken","foaf:isPrimaryTopicOf":["http://www.rechtvanbijdeboer.be/t-meikensvlasvarken","http://www.rechtvanbijdeboer.be/node/3395"],"@type":"foaf:Agent","schema:image":["http://www.rechtvanbijdeboer.be/sites/default/files/styles/producer_teaser/public/meikensvlasvarken_varkens_lr.jpg?itok=zjwaVkcu"],"@context":"https://openfooddata.github.io/actors/_common/context.jsonld","schema:geo":{"schema:latitude":"50.989806","schema:longitude":"3.400219","@type":"schema:GeoCoordinates","schema:addressCountry":"Belgium","schema:address":{"@type":"schema:PostalAddress","schema:streetAddress":"Karmstraat 64","schema:postalCode":"8700","schema:addressLocality":"Tielt"}},"ofd:offersFoodType":["ft:pork"],"foaf:depiction":["http://www.rechtvanbijdeboer.be/sites/default/files/styles/producer_teaser/public/meikensvlasvarken_varkens_lr.jpg?itok=zjwaVkcu"],"schema:description":"","ofd:upstreamRel":[{"@type":"ofd:ActorRelationship","ofd:relatedContext":"at:producer","ofd:relatedActor":"https://w3id.org/openfooddata/actors/t-meikensvlasvarken-gcv"}],"@id":"https://w3id.org/openfooddata/actors/t-meikensvlasvarken","schema:name":"'t Meikensvlasvarken","ofd:actorType":["at:pointOfSale","at:farmShop"]}}