{"type":"Feature","geometry":{"type":"Point","coordinates":[3.294608,51.234]},"properties":{"id":"https://w3id.org/openfooddata/actors/de-ijshoeve-0","name":"De Ijshoeve","img":["http://www.rechtvanbijdeboer.be/sites/default/files/styles/producer_teaser/public/8340dammedeijshoeve998-www.ralph.be-0076r.jpg?itok=ENHd9EUW"],"type":["at:pointOfSale","at:farmShop"],"upstream":[{"@type":"ofd:ActorRelationship","ofd:relatedContext":"at:producer","ofd:relatedActor":"https://w3id.org/openfooddata/actors/de-ijshoeve"}]}}