{"type":"Feature","geometry":{"type":"Point","coordinates":[3.987398,51.127741]},"properties":{"id":"https://w3id.org/openfooddata/actors/de-teerling-emiliani-0","name":"De Teerling / Emiliani","img":[],"type":["at:pointOfSale","at:farmShop"],"upstream":[{"@type":"ofd:ActorRelationship","ofd:relatedContext":"at:producer","ofd:relatedActor":"https://w3id.org/openfooddata/actors/de-teerling-/-emiliani"}]}}