{"type":"Feature","geometry":{"type":"Point","coordinates":[4.438785,51.219974]},"properties":{"id":"https://w3id.org/openfooddata/actors/de-melkauto-melkronde-vrij-930","name":"De Melkauto (melkronde) - Vrij 9:30","img":[],"type":["at:pointOfSale","at:collectionPoint"],"upstream":[{"@type":"ofd:ActorRelationship","ofd:relatedContext":"at:producer","ofd:relatedActor":"https://w3id.org/openfooddata/actors/keysershoeve"}]}}