{"type":"Feature","geometry":{"type":"Point","coordinates":[4.438785,51.219974]},"properties":{"foaf:account":[],"foaf:name":"De Melkauto (melkronde) - Vrij 9:30","foaf:isPrimaryTopicOf":["http://www.rechtvanbijdeboer.be/de-melkauto-melkronde-vrij-930","http://www.rechtvanbijdeboer.be/node/3317"],"@type":"foaf:Agent","schema:image":[],"@context":"https://openfooddata.github.io/actors/_common/context.jsonld","schema:geo":{"schema:latitude":"51.219974","schema:longitude":"4.438785","@type":"schema:GeoCoordinates","schema:addressCountry":"Belgium","schema:address":{"@type":"schema:PostalAddress","schema:streetAddress":"Groeningerplein,","schema:postalCode":"2140","schema:addressLocality":"Borgerhout"}},"ofd:offersFoodType":["ft:milk_products"],"foaf:depiction":[],"schema:description":"","ofd:upstreamRel":[{"@type":"ofd:ActorRelationship","ofd:relatedContext":"at:producer","ofd:relatedActor":"https://w3id.org/openfooddata/actors/keysershoeve"}],"@id":"https://w3id.org/openfooddata/actors/de-melkauto-melkronde-vrij-930","schema:name":"De Melkauto (melkronde) - Vrij 9:30","ofd:actorType":["at:pointOfSale","at:collectionPoint"]}}