{"type":"Feature","geometry":{"type":"Point","coordinates":[4.438785,51.219974]},"properties":{"foaf:account":[],"foaf:name":"De Melkauto (melkronde) - Vrij 9:30","foaf:isPrimaryTopicOf":["http://www.rechtvanbijdeboer.be/de-melkauto-melkronde-vrij-930","http://www.rechtvanbijdeboer.be/node/3317"],"@type":"foaf:Agent","schema:image":[],"@context":"https://openfooddata.github.io/actors/_common/context.jsonld","schema:geo":{"schema:latitude":"51.219974","schema:longitude":"4.438785","@type":"schema:GeoCoordinates","schema:addressCountry":"Belgium","schema:address":{"@type":"schema:PostalAddress","schema:streetAddress":"Groeningerplein,","schema:postalCode":"2140","schema:addressLocality":"Borgerhout"}},"ofd:offersFoodType":["ft:milk_products"],"foaf:depiction":[],"schema:description":"","ofd:upstreamRel":[{"@type":"ofd:ActorRelationship","ofd:relatedContext":"at:producer","ofd:relatedActor":"https://w3id.org/openfooddata/actors/keysershoeve"}],"@id":"https://w3id.org/openfooddata/actors/de-melkauto-melkronde-vrij-930","extraHeader":"<link rel=\"alternate\" href=\"de-melkauto-melkronde-vrij-930.rdf\" type=\"application/rdf+xml\"/>\n<link rel=\"alternate\" href=\"de-melkauto-melkronde-vrij-930.jsonld\" type=\"application/ld+json\"/>\n<link rel=\"alternate\" href=\"de-melkauto-melkronde-vrij-930.nq\" type=\"application/n-quads\"/>\n<link rel=\"alternate\" href=\"de-melkauto-melkronde-vrij-930.nt\" type=\"application/n-triples\"/>\n<link rel=\"alternate\" href=\"de-melkauto-melkronde-vrij-930.ttl\" type=\"text/turtle\"/>\n<link rel=\"alternate\" href=\"de-melkauto-melkronde-vrij-930.rj\" type=\"application/rdf+json\"/>\n<link rel=\"alternate\" href=\"de-melkauto-melkronde-vrij-930.trig\" type=\"text/trig\"/>\n<link rel=\"alternate\" href=\"de-melkauto-melkronde-vrij-930.trix\" type=\"application/trix\"/>\n","schema:name":"De Melkauto (melkronde) - Vrij 9:30","ofd:actorType":["at:pointOfSale","at:collectionPoint"]}}