{"type":"Feature","geometry":{"type":"Point","coordinates":[3.674982,51.019794]},"properties":{"foaf:account":[],"foaf:name":"Afhaalpunt Sint-Denijs-Westrem","foaf:isPrimaryTopicOf":["http://www.rechtvanbijdeboer.be/afhaalpunt-sint-denijs-westrem","http://www.rechtvanbijdeboer.be/node/3531"],"@type":"foaf:Agent","schema:image":[],"@context":"https://openfooddata.github.io/actors/_common/context.jsonld","schema:geo":{"schema:latitude":"51.019794","schema:longitude":"3.674982","@type":"schema:GeoCoordinates","schema:addressCountry":"Belgium","schema:address":{"@type":"schema:PostalAddress","schema:streetAddress":"Nieuwstraat 14","schema:postalCode":"9051","schema:addressLocality":"Sint-Denijs-Westrem"}},"ofd:offersFoodType":["ft:potatoes","ft:fruits","ft:bakery_products","ft:eggs","ft:fruit_juices","ft:spices","ft:beef","ft:alcoholic_beverages","ft:vegetables","ft:milk_products"],"foaf:depiction":[],"schema:description":"","ofd:upstreamRel":[{"@type":"ofd:ActorRelationship","ofd:relatedContext":"at:producer","ofd:relatedActor":"https://w3id.org/openfooddata/actors/de-wassende-maan"}],"@id":"https://w3id.org/openfooddata/actors/afhaalpunt-sint-denijs-westrem","extraHeader":"<link rel=\"alternate\" href=\"afhaalpunt-sint-denijs-westrem.rdf\" type=\"application/rdf+xml\"/>\n<link rel=\"alternate\" href=\"afhaalpunt-sint-denijs-westrem.jsonld\" type=\"application/ld+json\"/>\n<link rel=\"alternate\" href=\"afhaalpunt-sint-denijs-westrem.nq\" type=\"application/n-quads\"/>\n<link rel=\"alternate\" href=\"afhaalpunt-sint-denijs-westrem.nt\" type=\"application/n-triples\"/>\n<link rel=\"alternate\" href=\"afhaalpunt-sint-denijs-westrem.ttl\" type=\"text/turtle\"/>\n<link rel=\"alternate\" href=\"afhaalpunt-sint-denijs-westrem.rj\" type=\"application/rdf+json\"/>\n<link rel=\"alternate\" href=\"afhaalpunt-sint-denijs-westrem.trig\" type=\"text/trig\"/>\n<link rel=\"alternate\" href=\"afhaalpunt-sint-denijs-westrem.trix\" type=\"application/trix\"/>\n","schema:name":"Afhaalpunt Sint-Denijs-Westrem","ofd:actorType":["at:pointOfSale","at:vegetableSubscription"]}}