{"type":"Feature","geometry":{"type":"Point","coordinates":[4.107718,50.786945]},"properties":{"foaf:account":[],"foaf:name":"De Groentelaar","schema:url":[],"foaf:homepage":[],"foaf:isPrimaryTopicOf":["http://www.rechtvanbijdeboer.be/de-groentelaar-0","http://www.rechtvanbijdeboer.be/node/2823","https://www.rechtvanbijdeboer.be/de-groentelaar","https://www.rechtvanbijdeboer.be/node/1350","http://www.rechtvanbijdeboer.be/de-groentelaar-1","http://www.rechtvanbijdeboer.be/node/2824"],"@type":"foaf:Agent","schema:image":[],"@context":"https://openfooddata.github.io/actors/_common/context.jsonld","schema:geo":{"schema:latitude":"50.786945","schema:longitude":"4.107718","@type":"schema:GeoCoordinates","schema:addressCountry":"Belgium","schema:address":{"@type":"schema:PostalAddress","schema:streetAddress":"Paddenbroekstraat z/n","schema:postalCode":"1755","schema:addressLocality":"Gooik"}},"ofd:offersFoodType":["ft:vegetables","ft:spices"],"foaf:depiction":[],"schema:description":"","ofd:upstreamRel":[],"ofd:downstreamRel":[],"@id":"https://w3id.org/openfooddata/actors/de-groentelaar","extraHeader":"<link rel=\"alternate\" href=\"de-groentelaar.rdf\" type=\"application/rdf+xml\"/>\n<link rel=\"alternate\" href=\"de-groentelaar.jsonld\" type=\"application/ld+json\"/>\n<link rel=\"alternate\" href=\"de-groentelaar.nq\" type=\"application/n-quads\"/>\n<link rel=\"alternate\" href=\"de-groentelaar.nt\" type=\"application/n-triples\"/>\n<link rel=\"alternate\" href=\"de-groentelaar.ttl\" type=\"text/turtle\"/>\n<link rel=\"alternate\" href=\"de-groentelaar.rj\" type=\"application/rdf+json\"/>\n<link rel=\"alternate\" href=\"de-groentelaar.trig\" type=\"text/trig\"/>\n<link rel=\"alternate\" href=\"de-groentelaar.trix\" type=\"application/trix\"/>\n","schema:name":"De Groentelaar","ofd:actorType":["at:pointOfSale","at:producer","at:farmShop"]}}