{"type":"Feature","geometry":{"type":"Point","coordinates":[4.607268,51.228868]},"properties":{"foaf:account":[],"foaf:name":"De Dobbelhoeve","schema:url":["http://www.dobbelhoeve.be"],"foaf:homepage":["http://www.dobbelhoeve.be"],"foaf:isPrimaryTopicOf":["http://www.rechtvanbijdeboer.be/de-dobbelhoeve-0","http://www.rechtvanbijdeboer.be/node/2393","http://www.rechtvanbijdeboer.be/de-dobbelhoeve","http://www.rechtvanbijdeboer.be/node/1113","http://www.rechtvanbijdeboer.be/de-dobbelhoeve-1","http://www.rechtvanbijdeboer.be/node/3181"],"@type":"foaf:Agent","schema:image":["http://www.rechtvanbijdeboer.be/sites/default/files/styles/producer_teaser/public/de_dobbelhoeve_winkel.jpg?itok=LnSnsXEj"],"@context":"https://openfooddata.github.io/actors/_common/context.jsonld","schema:geo":{"schema:latitude":"51.228868","schema:longitude":"4.607268","@type":"schema:GeoCoordinates","schema:addressCountry":"Belgium","schema:address":{"@type":"schema:PostalAddress","schema:streetAddress":"Goorstraat 43","schema:postalCode":"2970","schema:addressLocality":"Schilde"}},"ofd:offersFoodType":["ft:fruits","ft:bakery_products","ft:poultry_meat","ft:fruit_juices","ft:milk_products","ft:eggs","ft:pork","ft:alcoholic_beverages","ft:lamb_meat","ft:beef","ft:vegetables","ft:potatoes","ft:spices"],"foaf:depiction":["http://www.rechtvanbijdeboer.be/sites/default/files/styles/producer_teaser/public/de_dobbelhoeve_winkel.jpg?itok=LnSnsXEj"],"schema:description":["Bovenaan het dakraam van onze hoeve staat het jaartal 1341 te lezen. (Historici en bouwkundigen achten het gebouw eigenlijk twee eeuwen jonger). In een ver verleden zou de hoeve gefungeerd hebben als turfopslagplaats. De boerderij vormde later samen met een andere hoeve de “Bredeveldse Hoeven”. Tijdens de Franse revolutie werd het goed verkocht aan baron van de Werve de Schilde, die van de hoeve aan de Goorstraat op haar beurt een “Dobbelhoeve” maakte. Deze herbergde dan twee boerenfamilies. Bij de openbare verkoop in 1952 verwierf de familie De Winter het oudste, westelijke deel, en het “nieuwere” oostelijke deel werd verkocht aan de familie De Meutter. Karel De Meutter bouwde dit uit tot een modern landbouwbedrijf vanaf 1955. Bij diens kinderen groeide dertig jaar later de idee om biologisch te gaan werken en op 1 april 1987 werd die grote stap gezet. De Dobbelhoeve werd sindsdien een der eerste gemengde biologische bedrijven in Vlaanderen en ook een der bekendste. In 2001 kregen we dan de kans om ook het westelijke deel van de “Dubbelhoeve” te kopen. Zo lijkt de cirkel weer rond en kan het oude historische gebouw weer één geheel vormen …",""],"ofd:upstreamRel":[{"@type":"ofd:ActorRelationship","ofd:relatedContext":"at:producer","ofd:relatedActor":"https://w3id.org/openfooddata/actors/de-groene-boerderij"}],"schema:contactPoint":{"@type":"schema:ContactPoint","schema:telephone":["03/3830782"],"schema:email":["info@dobbelhoeve.be"],"foaf:homepage":["http://www.dobbelhoeve.be"],"schema:url":["http://www.dobbelhoeve.be"]},"ofd:downstreamRel":[],"@id":"https://w3id.org/openfooddata/actors/de-dobbelhoeve","extraHeader":"<link rel=\"alternate\" href=\"de-dobbelhoeve.rdf\" type=\"application/rdf+xml\"/>\n<link rel=\"alternate\" href=\"de-dobbelhoeve.jsonld\" type=\"application/ld+json\"/>\n<link rel=\"alternate\" href=\"de-dobbelhoeve.nq\" type=\"application/n-quads\"/>\n<link rel=\"alternate\" href=\"de-dobbelhoeve.nt\" type=\"application/n-triples\"/>\n<link rel=\"alternate\" href=\"de-dobbelhoeve.ttl\" type=\"text/turtle\"/>\n<link rel=\"alternate\" href=\"de-dobbelhoeve.rj\" type=\"application/rdf+json\"/>\n<link rel=\"alternate\" href=\"de-dobbelhoeve.trig\" type=\"text/trig\"/>\n<link rel=\"alternate\" href=\"de-dobbelhoeve.trix\" type=\"application/trix\"/>\n","schema:name":"De Dobbelhoeve","ofd:actorType":["at:pointOfSale","at:collectionPoint","at:producer","at:farmShop"]}}