{"type":"Feature","geometry":{"type":"Point","coordinates":[3.426693,50.874441]},"properties":{"id":"https://w3id.org/openfooddata/actors/hemelhof","name":"Hemelhof","img":["http://www.rechtvanbijdeboer.be/sites/default/files/styles/producer_teaser/public/biobellogroentenenfruitmaxi.jpg?itok=n2EToMw3"],"type":["at:pointOfSale","at:vegetableSubscription"],"upstream":[{"@type":"ofd:ActorRelationship","ofd:relatedContext":"at:producer","ofd:relatedActor":"https://w3id.org/openfooddata/actors/de-lochting-vzw"}]}}