{"type":"Feature","geometry":{"type":"Point","coordinates":[3.730593,51.033115]},"properties":{"foaf:account":[],"foaf:name":"Onthaalmoeder Caro (bestellen via Biobello.be)","foaf:isPrimaryTopicOf":["http://www.rechtvanbijdeboer.be/onthaalmoeder-caro-bestellen-biobellobe","http://www.rechtvanbijdeboer.be/node/2476"],"@type":"foaf:Agent","schema:image":["http://www.rechtvanbijdeboer.be/sites/default/files/styles/producer_teaser/public/biobellogroentenenfruitmaxi.jpg?itok=n2EToMw3"],"@context":"https://openfooddata.github.io/actors/_common/context.jsonld","schema:geo":{"schema:latitude":"51.033115","schema:longitude":"3.730593","@type":"schema:GeoCoordinates","schema:addressCountry":"Belgium","schema:address":{"@type":"schema:PostalAddress","schema:streetAddress":"Stropstraat 150","schema:postalCode":"9000","schema:addressLocality":"Gent"}},"ofd:offersFoodType":["ft:potatoes","ft:fruits","ft:eggs","ft:vegetables"],"foaf:depiction":["http://www.rechtvanbijdeboer.be/sites/default/files/styles/producer_teaser/public/biobellogroentenenfruitmaxi.jpg?itok=n2EToMw3"],"schema:description":"","ofd:upstreamRel":[{"@type":"ofd:ActorRelationship","ofd:relatedContext":"at:producer","ofd:relatedActor":"https://w3id.org/openfooddata/actors/de-lochting-vzw"}],"@id":"https://w3id.org/openfooddata/actors/onthaalmoeder-caro-bestellen-biobellobe","extraHeader":"<link rel=\"alternate\" href=\"onthaalmoeder-caro-bestellen-biobellobe.rdf\" type=\"application/rdf+xml\"/>\n<link rel=\"alternate\" href=\"onthaalmoeder-caro-bestellen-biobellobe.jsonld\" type=\"application/ld+json\"/>\n<link rel=\"alternate\" href=\"onthaalmoeder-caro-bestellen-biobellobe.nq\" type=\"application/n-quads\"/>\n<link rel=\"alternate\" href=\"onthaalmoeder-caro-bestellen-biobellobe.nt\" type=\"application/n-triples\"/>\n<link rel=\"alternate\" href=\"onthaalmoeder-caro-bestellen-biobellobe.ttl\" type=\"text/turtle\"/>\n<link rel=\"alternate\" href=\"onthaalmoeder-caro-bestellen-biobellobe.rj\" type=\"application/rdf+json\"/>\n<link rel=\"alternate\" href=\"onthaalmoeder-caro-bestellen-biobellobe.trig\" type=\"text/trig\"/>\n<link rel=\"alternate\" href=\"onthaalmoeder-caro-bestellen-biobellobe.trix\" type=\"application/trix\"/>\n","schema:name":"Onthaalmoeder Caro (bestellen via Biobello.be)","ofd:actorType":["at:pointOfSale","at:collectionPoint"]}}