{"type":"Feature","geometry":{"type":"Point","coordinates":[4.23238,50.764611]},"properties":{"foaf:account":[],"foaf:name":"Johan Steens","schema:url":[],"foaf:homepage":[],"foaf:isPrimaryTopicOf":["http://www.rechtvanbijdeboer.be/johan-steens-0","http://www.rechtvanbijdeboer.be/node/2895","https://www.rechtvanbijdeboer.be/johan-steens","https://www.rechtvanbijdeboer.be/node/1416"],"@type":"foaf:Agent","schema:image":[],"@context":"https://openfooddata.github.io/actors/_common/context.jsonld","schema:geo":{"schema:latitude":"50.764611","schema:longitude":"4.232380","@type":"schema:GeoCoordinates","schema:addressCountry":"Belgium","schema:address":{"@type":"schema:PostalAddress","schema:streetAddress":"Pijnbroekstraat 186","schema:postalCode":"1600","schema:addressLocality":"Sint-Pieters-Leeuw"}},"ofd:offersFoodType":["ft:potatoes"],"foaf:depiction":[],"schema:description":"","ofd:upstreamRel":[],"ofd:downstreamRel":[],"@id":"https://w3id.org/openfooddata/actors/johan-steens","extraHeader":"<link rel=\"alternate\" href=\"johan-steens.rdf\" type=\"application/rdf+xml\"/>\n<link rel=\"alternate\" href=\"johan-steens.jsonld\" type=\"application/ld+json\"/>\n<link rel=\"alternate\" href=\"johan-steens.nq\" type=\"application/n-quads\"/>\n<link rel=\"alternate\" href=\"johan-steens.nt\" type=\"application/n-triples\"/>\n<link rel=\"alternate\" href=\"johan-steens.ttl\" type=\"text/turtle\"/>\n<link rel=\"alternate\" href=\"johan-steens.rj\" type=\"application/rdf+json\"/>\n<link rel=\"alternate\" href=\"johan-steens.trig\" type=\"text/trig\"/>\n<link rel=\"alternate\" href=\"johan-steens.trix\" type=\"application/trix\"/>\n","schema:name":"Johan Steens","ofd:actorType":["at:pointOfSale","at:farmShop","at:producer"]}}