{"type":"Feature","geometry":{"type":"Point","coordinates":[3.941757,51.178765]},"properties":{"foaf:account":[],"foaf:name":"Drongengoed","schema:url":[],"foaf:homepage":[],"foaf:isPrimaryTopicOf":["http://www.rechtvanbijdeboer.be/drongengoed-0","http://www.rechtvanbijdeboer.be/node/3049","http://www.rechtvanbijdeboer.be/drongengoed","http://www.rechtvanbijdeboer.be/node/1560"],"@type":"foaf:Agent","schema:image":["http://www.rechtvanbijdeboer.be/sites/default/files/styles/producer_teaser/public/default_images/emptyImg.jpg?itok=6POw8xTv"],"@context":"https://openfooddata.github.io/actors/_common/context.jsonld","schema:geo":{"schema:latitude":"51.178765","schema:longitude":"3.941757","@type":"schema:GeoCoordinates","schema:addressCountry":"Belgium","schema:address":{"@type":"schema:PostalAddress","schema:streetAddress":"Drongendreef 92","schema:postalCode":"9180","schema:addressLocality":"Moerbeke-Waas"}},"ofd:offersFoodType":["ft:potatoes"],"foaf:depiction":["http://www.rechtvanbijdeboer.be/sites/default/files/styles/producer_teaser/public/default_images/emptyImg.jpg?itok=6POw8xTv"],"schema:description":"","ofd:upstreamRel":[],"schema:contactPoint":{"@type":"schema:ContactPoint","schema:telephone":["09/3467921"],"schema:email":[],"foaf:homepage":[],"schema:url":[]},"ofd:downstreamRel":[],"@id":"https://w3id.org/openfooddata/actors/drongengoed","extraHeader":"<link rel=\"alternate\" href=\"drongengoed.rdf\" type=\"application/rdf+xml\"/>\n<link rel=\"alternate\" href=\"drongengoed.jsonld\" type=\"application/ld+json\"/>\n<link rel=\"alternate\" href=\"drongengoed.nq\" type=\"application/n-quads\"/>\n<link rel=\"alternate\" href=\"drongengoed.nt\" type=\"application/n-triples\"/>\n<link rel=\"alternate\" href=\"drongengoed.ttl\" type=\"text/turtle\"/>\n<link rel=\"alternate\" href=\"drongengoed.rj\" type=\"application/rdf+json\"/>\n<link rel=\"alternate\" href=\"drongengoed.trig\" type=\"text/trig\"/>\n<link rel=\"alternate\" href=\"drongengoed.trix\" type=\"application/trix\"/>\n","schema:name":"Drongengoed","ofd:actorType":["at:pointOfSale","at:farmShop","at:producer"]}}