{"type":"Feature","geometry":{"type":"Point","coordinates":[4.733779,51.195929]},"properties":{"id":"https://w3id.org/openfooddata/actors/afhaalpunt-bio-abonnement-2","name":"Afhaalpunt bio-abonnement","img":[],"type":["at:pointOfSale","at:collectionPoint"],"upstream":[{"@type":"ofd:ActorRelationship","ofd:relatedContext":"at:producer","ofd:relatedActor":"https://w3id.org/openfooddata/actors/t-meulenhuys"}]}}