{"type":"Feature","geometry":{"type":"Point","coordinates":[3.600935,51.244855]},"properties":{"id":"https://w3id.org/openfooddata/actors/de-vlotakker","name":"De Vlotakker","img":["http://www.rechtvanbijdeboer.be/sites/default/files/styles/producer_teaser/public/default_images/emptyImg.jpg?itok=6POw8xTv"],"type":["at:pointOfSale","at:farmShop","at:producer"],"upstream":[],"downstream":[]}}