{"type":"Feature","geometry":{"type":"Point","coordinates":[4.867562,51.266748]},"properties":{"id":"https://w3id.org/openfooddata/actors/de-acht-zaligheden","name":"De Acht Zaligheden","img":[],"type":["at:pointOfSale","at:vegetableSubscription"],"upstream":[{"@type":"ofd:ActorRelationship","ofd:relatedContext":"at:producer","ofd:relatedActor":"https://w3id.org/openfooddata/actors/de-bio-hoeve"}]}}