{"type":"Feature","geometry":{"type":"Point","coordinates":[4.427294,50.929504]},"properties":{"foaf:account":[],"foaf:name":"Oxfam Vilvoorde","foaf:isPrimaryTopicOf":["http://www.rechtvanbijdeboer.be/oxfam-vilvoorde","http://www.rechtvanbijdeboer.be/node/3575"],"@type":"foaf:Agent","schema:image":["http://www.rechtvanbijdeboer.be/sites/default/files/styles/producer_teaser/public/fotosessiestreekprodukten%20%2846%29_1.jpg?itok=P8yY02ej"],"@context":"https://openfooddata.github.io/actors/_common/context.jsonld","schema:geo":{"schema:latitude":"50.929504","schema:longitude":"4.427294","@type":"schema:GeoCoordinates","schema:addressCountry":"Belgium","schema:address":{"@type":"schema:PostalAddress","schema:streetAddress":"Toekomststraat 53","schema:postalCode":"1800","schema:addressLocality":"Vilvoorde"}},"ofd:offersFoodType":["ft:potatoes","ft:bakery_products","ft:eggs","ft:fruits","ft:fruit_juices","ft:vegetables","ft:icecream","ft:spices","ft:alcoholic_beverages","ft:milk_products"],"foaf:depiction":["http://www.rechtvanbijdeboer.be/sites/default/files/styles/producer_teaser/public/fotosessiestreekprodukten%20%2846%29_1.jpg?itok=P8yY02ej"],"schema:description":"","ofd:upstreamRel":[{"@type":"ofd:ActorRelationship","ofd:relatedContext":"at:producer","ofd:relatedActor":"https://w3id.org/openfooddata/actors/den-diepen-boomgaard"}],"@id":"https://w3id.org/openfooddata/actors/oxfam-vilvoorde","extraHeader":"<link rel=\"alternate\" href=\"oxfam-vilvoorde.rdf\" type=\"application/rdf+xml\"/>\n<link rel=\"alternate\" href=\"oxfam-vilvoorde.jsonld\" type=\"application/ld+json\"/>\n<link rel=\"alternate\" href=\"oxfam-vilvoorde.nq\" type=\"application/n-quads\"/>\n<link rel=\"alternate\" href=\"oxfam-vilvoorde.nt\" type=\"application/n-triples\"/>\n<link rel=\"alternate\" href=\"oxfam-vilvoorde.ttl\" type=\"text/turtle\"/>\n<link rel=\"alternate\" href=\"oxfam-vilvoorde.rj\" type=\"application/rdf+json\"/>\n<link rel=\"alternate\" href=\"oxfam-vilvoorde.trig\" type=\"text/trig\"/>\n<link rel=\"alternate\" href=\"oxfam-vilvoorde.trix\" type=\"application/trix\"/>\n","schema:name":"Oxfam Vilvoorde","ofd:actorType":["at:pointOfSale","at:vegetableSubscription"]}}