{"type":"Feature","geometry":{"type":"Point","coordinates":[4.704101,51.138453]},"properties":{"foaf:account":[],"foaf:name":"Emiliushoeve","foaf:isPrimaryTopicOf":["http://www.rechtvanbijdeboer.be/emiliushoeve","http://www.rechtvanbijdeboer.be/node/3367"],"@type":"foaf:Agent","schema:image":[],"@context":"https://openfooddata.github.io/actors/_common/context.jsonld","schema:geo":{"schema:latitude":"51.138453","schema:longitude":"4.704101","@type":"schema:GeoCoordinates","schema:addressCountry":"Belgium","schema:address":{"@type":"schema:PostalAddress","schema:streetAddress":"Herdersstraat 31","schema:postalCode":"2560","schema:addressLocality":"Bevel"}},"ofd:offersFoodType":["ft:fruits","ft:vegetables"],"foaf:depiction":[],"schema:description":"","ofd:upstreamRel":[{"@type":"ofd:ActorRelationship","ofd:relatedContext":"at:producer","ofd:relatedActor":"https://w3id.org/openfooddata/actors/herdershof"}],"@id":"https://w3id.org/openfooddata/actors/emiliushoeve","schema:name":"Emiliushoeve","ofd:actorType":["at:pointOfSale","at:collectionPoint"]}}