{"type":"Feature","geometry":{"type":"Point","coordinates":[3.273815,51.17912]},"properties":{"foaf:account":[],"foaf:name":"Moo","schema:url":[],"foaf:homepage":[],"foaf:isPrimaryTopicOf":["http://www.rechtvanbijdeboer.be/moo-0","http://www.rechtvanbijdeboer.be/node/2695","http://www.rechtvanbijdeboer.be/moo","http://www.rechtvanbijdeboer.be/node/1270"],"@type":"foaf:Agent","schema:image":["http://www.rechtvanbijdeboer.be/sites/default/files/styles/producer_teaser/public/default_images/emptyImg.jpg?itok=6POw8xTv"],"@context":"https://openfooddata.github.io/actors/_common/context.jsonld","schema:geo":{"schema:latitude":"51.179120","schema:longitude":"3.273815","@type":"schema:GeoCoordinates","schema:addressCountry":"Belgium","schema:address":{"@type":"schema:PostalAddress","schema:streetAddress":"Beverhoutstraat 37","schema:postalCode":"8020","schema:addressLocality":"Moerbrugge (Oostkamp)"}},"ofd:offersFoodType":["ft:milk_products","ft:icecream"],"foaf:depiction":["http://www.rechtvanbijdeboer.be/sites/default/files/styles/producer_teaser/public/default_images/emptyImg.jpg?itok=6POw8xTv"],"schema:description":"","ofd:upstreamRel":[],"schema:contactPoint":{"@type":"schema:ContactPoint","schema:telephone":[],"schema:email":["carolinegur@hotmail.com"],"foaf:homepage":[],"schema:url":[]},"ofd:downstreamRel":[],"@id":"https://w3id.org/openfooddata/actors/moo","extraHeader":"<link rel=\"alternate\" href=\"moo.rdf\" type=\"application/rdf+xml\"/>\n<link rel=\"alternate\" href=\"moo.jsonld\" type=\"application/ld+json\"/>\n<link rel=\"alternate\" href=\"moo.nq\" type=\"application/n-quads\"/>\n<link rel=\"alternate\" href=\"moo.nt\" type=\"application/n-triples\"/>\n<link rel=\"alternate\" href=\"moo.ttl\" type=\"text/turtle\"/>\n<link rel=\"alternate\" href=\"moo.rj\" type=\"application/rdf+json\"/>\n<link rel=\"alternate\" href=\"moo.trig\" type=\"text/trig\"/>\n<link rel=\"alternate\" href=\"moo.trix\" type=\"application/trix\"/>\n","schema:name":"Moo","ofd:actorType":["at:pointOfSale","at:farmShop","at:producer"]}}