{"type":"Feature","geometry":{"type":"Point","coordinates":[3.234037,51.106728]},"properties":{"foaf:account":[],"foaf:name":"De Zaaier","schema:url":[],"foaf:homepage":[],"foaf:isPrimaryTopicOf":["http://www.rechtvanbijdeboer.be/de-zaaier-0","http://www.rechtvanbijdeboer.be/node/2753","https://www.rechtvanbijdeboer.be/de-zaaier","https://www.rechtvanbijdeboer.be/node/1310"],"@type":"foaf:Agent","schema:image":[],"@context":"https://openfooddata.github.io/actors/_common/context.jsonld","schema:geo":{"schema:latitude":"51.106728","schema:longitude":"3.234037","@type":"schema:GeoCoordinates","schema:addressCountry":"Belgium","schema:address":{"@type":"schema:PostalAddress","schema:streetAddress":"Korte Akkerstraat 2","schema:postalCode":"8020","schema:addressLocality":"Ruddervoorde"}},"ofd:offersFoodType":["ft:lamb_meat","ft:fruits","ft:vegetables","ft:potatoes"],"foaf:depiction":[],"schema:description":"","ofd:upstreamRel":[],"ofd:downstreamRel":[],"@id":"https://w3id.org/openfooddata/actors/de-zaaier","extraHeader":"<link rel=\"alternate\" href=\"de-zaaier.rdf\" type=\"application/rdf+xml\"/>\n<link rel=\"alternate\" href=\"de-zaaier.jsonld\" type=\"application/ld+json\"/>\n<link rel=\"alternate\" href=\"de-zaaier.nq\" type=\"application/n-quads\"/>\n<link rel=\"alternate\" href=\"de-zaaier.nt\" type=\"application/n-triples\"/>\n<link rel=\"alternate\" href=\"de-zaaier.ttl\" type=\"text/turtle\"/>\n<link rel=\"alternate\" href=\"de-zaaier.rj\" type=\"application/rdf+json\"/>\n<link rel=\"alternate\" href=\"de-zaaier.trig\" type=\"text/trig\"/>\n<link rel=\"alternate\" href=\"de-zaaier.trix\" type=\"application/trix\"/>\n","schema:name":"De Zaaier","ofd:actorType":["at:pointOfSale","at:farmShop","at:producer"]}}