{"type":"Feature","geometry":{"type":"Point","coordinates":[4.243325,50.778716]},"properties":{"id":"https://w3id.org/openfooddata/actors/markt-sint-pieters-leeuw","name":"Markt Sint-Pieters-Leeuw","img":[],"type":["at:pointOfSale","at:market"],"upstream":[{"@type":"ofd:ActorRelationship","ofd:relatedContext":"at:producer","ofd:relatedActor":"https://w3id.org/openfooddata/actors/hoevebakkerij-de-haseleer"}]}}