{"type":"Feature","geometry":{"type":"Point","coordinates":[3.713653,51.03925]},"properties":{"id":"https://w3id.org/openfooddata/actors/gent-sint-pieters","name":"Gent-Sint-Pieters","img":[],"type":["at:pointOfSale","at:vegetableSubscription"],"upstream":[{"@type":"ofd:ActorRelationship","ofd:relatedContext":"at:producer","ofd:relatedActor":"https://w3id.org/openfooddata/actors/de-zwaluw"}]}}