{"type":"Feature","geometry":{"type":"Point","coordinates":[3.58721,51.121081]},"properties":{"foaf:account":[],"foaf:name":"Fruitbedrijf Van Hecke","foaf:isPrimaryTopicOf":["http://www.rechtvanbijdeboer.be/fruitbedrijf-van-hecke","http://www.rechtvanbijdeboer.be/node/3090"],"@type":"foaf:Agent","schema:image":[],"@context":"https://openfooddata.github.io/actors/_common/context.jsonld","schema:geo":{"schema:latitude":"51.121081","schema:longitude":"3.587210","@type":"schema:GeoCoordinates","schema:addressCountry":"Belgium","schema:address":{"@type":"schema:PostalAddress","schema:streetAddress":"Korteboeken 78","schema:postalCode":"9930","schema:addressLocality":"Zomergem"}},"ofd:offersFoodType":["ft:potatoes","ft:eggs","ft:fruits","ft:fruit_juices","ft:vegetables","ft:alcoholic_beverages","ft:milk_products"],"foaf:depiction":[],"schema:description":"","ofd:upstreamRel":[{"@type":"ofd:ActorRelationship","ofd:relatedContext":"at:producer","ofd:relatedActor":"https://w3id.org/openfooddata/actors/hoevewinkel-fruit-land"}],"@id":"https://w3id.org/openfooddata/actors/fruitbedrijf-van-hecke","extraHeader":"<link rel=\"alternate\" href=\"fruitbedrijf-van-hecke.rdf\" type=\"application/rdf+xml\"/>\n<link rel=\"alternate\" href=\"fruitbedrijf-van-hecke.jsonld\" type=\"application/ld+json\"/>\n<link rel=\"alternate\" href=\"fruitbedrijf-van-hecke.nq\" type=\"application/n-quads\"/>\n<link rel=\"alternate\" href=\"fruitbedrijf-van-hecke.nt\" type=\"application/n-triples\"/>\n<link rel=\"alternate\" href=\"fruitbedrijf-van-hecke.ttl\" type=\"text/turtle\"/>\n<link rel=\"alternate\" href=\"fruitbedrijf-van-hecke.rj\" type=\"application/rdf+json\"/>\n<link rel=\"alternate\" href=\"fruitbedrijf-van-hecke.trig\" type=\"text/trig\"/>\n<link rel=\"alternate\" href=\"fruitbedrijf-van-hecke.trix\" type=\"application/trix\"/>\n","schema:name":"Fruitbedrijf Van Hecke","ofd:actorType":["at:pointOfSale","at:farmShop"]}}