{"type":"Feature","geometry":{"type":"Point","coordinates":[3.73815,51.052904]},"properties":{"id":"https://w3id.org/openfooddata/actors/eetcaf%C3%A9-het-gouden-hoofd","name":"Eetcafé Het Gouden Hoofd","img":[],"type":["at:pointOfSale","at:vegetableSubscription"],"upstream":[{"@type":"ofd:ActorRelationship","ofd:relatedContext":"at:producer","ofd:relatedActor":"https://w3id.org/openfooddata/actors/de-wassende-maan"}]}}