{"type":"Feature","geometry":{"type":"Point","coordinates":[4.795835,51.363829]},"properties":{"id":"https://w3id.org/openfooddata/actors/fruitbedrijf-bruneel-cox","name":"Fruitbedrijf Bruneel - Cox","img":["http://www.rechtvanbijdeboer.be/sites/default/files/styles/producer_teaser/public/046-fruitbedrijfbruneel-cox.jpg?itok=n0S_hZSu"],"type":["at:pointOfSale","at:farmShop","at:producer"],"upstream":[],"downstream":[{"@type":"ofd:ActorRelationship","ofd:relatedContext":"at:pointOfSale","ofd:relatedActor":"https://w3id.org/openfooddata/actors/fruitbedrijf-kestergat"}]}}