{"type":"Feature","geometry":{"type":"Point","coordinates":[3.979859,50.935723]},"properties":{"id":"https://w3id.org/openfooddata/actors/aardappelautomaat-t-schuurke","name":"Aardappelautomaat 't Schuurke","img":["http://www.rechtvanbijdeboer.be/sites/default/files/styles/producer_teaser/public/100_4185.jpg?itok=r-E1F89v"],"type":["at:pointOfSale","at:vendingMachine"],"upstream":[{"@type":"ofd:ActorRelationship","ofd:relatedContext":"at:producer","ofd:relatedActor":"https://w3id.org/openfooddata/actors/t-schuurke"}]}}