{"type":"Feature","geometry":{"type":"Point","coordinates":[4.905067,50.837518]},"properties":{"foaf:account":[],"foaf:name":"Familiale Hoevebeenhouwerij Thijs","schema:url":[],"foaf:homepage":[],"foaf:isPrimaryTopicOf":["http://www.rechtvanbijdeboer.be/familiale-hoevebeenhouwerij-thijs-0","http://www.rechtvanbijdeboer.be/node/2959","http://www.rechtvanbijdeboer.be/familiale-hoevebeenhouwerij-thijs","http://www.rechtvanbijdeboer.be/node/1470"],"@type":"foaf:Agent","schema:image":["http://www.rechtvanbijdeboer.be/sites/default/files/styles/producer_teaser/public/default_images/emptyImg.jpg?itok=6POw8xTv"],"@context":"https://openfooddata.github.io/actors/_common/context.jsonld","schema:geo":{"schema:latitude":"50.837518","schema:longitude":"4.905067","@type":"schema:GeoCoordinates","schema:addressCountry":"Belgium","schema:address":{"@type":"schema:PostalAddress","schema:streetAddress":"Sint-Pietersstraat 169","schema:postalCode":"3300","schema:addressLocality":"Vissenaken"}},"ofd:offersFoodType":["ft:pork","ft:lamb_meat"],"foaf:depiction":["http://www.rechtvanbijdeboer.be/sites/default/files/styles/producer_teaser/public/default_images/emptyImg.jpg?itok=6POw8xTv"],"schema:description":"","ofd:upstreamRel":[],"schema:contactPoint":{"@type":"schema:ContactPoint","schema:telephone":["016/760566","0496/703283"],"schema:email":["Stijn-thijs@hotmail.com"],"foaf:homepage":[],"schema:url":[]},"ofd:downstreamRel":[],"@id":"https://w3id.org/openfooddata/actors/familiale-hoevebeenhouwerij-thijs","extraHeader":"<link rel=\"alternate\" href=\"familiale-hoevebeenhouwerij-thijs.rdf\" type=\"application/rdf+xml\"/>\n<link rel=\"alternate\" href=\"familiale-hoevebeenhouwerij-thijs.jsonld\" type=\"application/ld+json\"/>\n<link rel=\"alternate\" href=\"familiale-hoevebeenhouwerij-thijs.nq\" type=\"application/n-quads\"/>\n<link rel=\"alternate\" href=\"familiale-hoevebeenhouwerij-thijs.nt\" type=\"application/n-triples\"/>\n<link rel=\"alternate\" href=\"familiale-hoevebeenhouwerij-thijs.ttl\" type=\"text/turtle\"/>\n<link rel=\"alternate\" href=\"familiale-hoevebeenhouwerij-thijs.rj\" type=\"application/rdf+json\"/>\n<link rel=\"alternate\" href=\"familiale-hoevebeenhouwerij-thijs.trig\" type=\"text/trig\"/>\n<link rel=\"alternate\" href=\"familiale-hoevebeenhouwerij-thijs.trix\" type=\"application/trix\"/>\n","schema:name":"Familiale Hoevebeenhouwerij Thijs","ofd:actorType":["at:pointOfSale","at:farmShop","at:producer"]}}