{"type":"Feature","geometry":{"type":"Point","coordinates":[4.372887,50.783376]},"properties":{"id":"https://w3id.org/openfooddata/actors/buurderij-ukkel","name":"Buurderij Ukkel","img":["http://www.rechtvanbijdeboer.be/sites/default/files/styles/producer_teaser/public/aardbeien2.jpg?itok=496FTkkI"],"type":["at:pointOfSale","at:foodAssembly"],"upstream":[{"@type":"ofd:ActorRelationship","ofd:relatedContext":"at:producer","ofd:relatedActor":"https://w3id.org/openfooddata/actors/de-seizoenschuur"},{"@type":"ofd:ActorRelationship","ofd:relatedContext":"at:producer","ofd:relatedActor":"https://w3id.org/openfooddata/actors/hammes-hoevevlees"},{"@type":"ofd:ActorRelationship","ofd:relatedContext":"at:producer","ofd:relatedActor":"https://w3id.org/openfooddata/actors/hof-van-piemont"},{"@type":"ofd:ActorRelationship","ofd:relatedContext":"at:producer","ofd:relatedActor":"https://w3id.org/openfooddata/actors/zuivelhoeve-keymeulen"}]}}