{"type":"Feature","geometry":{"type":"Point","coordinates":[4.201099,51.013674]},"properties":{"id":"https://w3id.org/openfooddata/actors/voedselteam-buggenhout","name":"Voedselteam Buggenhout","img":["http://www.rechtvanbijdeboer.be/sites/default/files/styles/producer_teaser/public/img_4698.jpg?itok=zS9m9TpB"],"type":["at:pointOfSale","at:foodTeams"],"upstream":[{"@type":"ofd:ActorRelationship","ofd:relatedContext":"at:producer","ofd:relatedActor":"https://w3id.org/openfooddata/actors/boerderij-de-loods"},{"@type":"ofd:ActorRelationship","ofd:relatedContext":"at:producer","ofd:relatedActor":"https://w3id.org/openfooddata/actors/de-seepscherf"},{"@type":"ofd:ActorRelationship","ofd:relatedContext":"at:producer","ofd:relatedActor":"https://w3id.org/openfooddata/actors/zuivelhoeve-keymeulen"},{"@type":"ofd:ActorRelationship","ofd:relatedContext":"at:producer","ofd:relatedActor":"https://w3id.org/openfooddata/actors/geitenboerderij-t-eikenhof"},{"@type":"ofd:ActorRelationship","ofd:relatedContext":"at:producer","ofd:relatedActor":"https://w3id.org/openfooddata/actors/huis-van-de-tomaat"},{"@type":"ofd:ActorRelationship","ofd:relatedContext":"at:producer","ofd:relatedActor":"https://w3id.org/openfooddata/actors/t-uilenbos"},{"@type":"ofd:ActorRelationship","ofd:relatedContext":"at:producer","ofd:relatedActor":"https://w3id.org/openfooddata/actors/de-wollebol"}]}}