{"type":"Feature","geometry":{"type":"Point","coordinates":[3.162594,51.003213]},"properties":{"id":"https://w3id.org/openfooddata/actors/de-bossneppe","name":"De Bossneppe","img":["http://www.rechtvanbijdeboer.be/sites/default/files/styles/producer_teaser/public/snv32812.jpg?itok=JdjUUcZV","http://www.rechtvanbijdeboer.be/sites/default/files/styles/producer_teaser/public/imag0148.jpg?itok=YA6XLMVG","http://www.rechtvanbijdeboer.be/sites/default/files/styles/producer_teaser/public/prut4455.jpg?itok=-5dhwZNa"],"type":["at:pointOfSale","at:farmShop","at:producer"],"upstream":[],"downstream":[]}}