{"type":"Feature","geometry":{"type":"Point","coordinates":[4.746572,51.081741]},"properties":{"foaf:account":[],"foaf:name":"Jos Van Oosterwyck","foaf:isPrimaryTopicOf":["http://www.rechtvanbijdeboer.be/node/2363","http://www.rechtvanbijdeboer.be/node/2363"],"@type":"foaf:Agent","schema:image":["http://www.rechtvanbijdeboer.be/sites/default/files/styles/producer_teaser/public/dscf0064.jpg?itok=rFmfnHpm"],"@context":"https://openfooddata.github.io/actors/_common/context.jsonld","schema:geo":{"schema:latitude":"51.081741","schema:longitude":"4.746572","@type":"schema:GeoCoordinates","schema:addressCountry":"Belgium","schema:address":{"@type":"schema:PostalAddress","schema:streetAddress":"Broekstraat 88","schema:postalCode":"2220","schema:addressLocality":"Heist-Op-Den-Berg"}},"ofd:offersFoodType":["ft:potatoes","ft:fruits","ft:vegetables"],"foaf:depiction":["http://www.rechtvanbijdeboer.be/sites/default/files/styles/producer_teaser/public/dscf0064.jpg?itok=rFmfnHpm"],"schema:description":"","ofd:upstreamRel":[{"@type":"ofd:ActorRelationship","ofd:relatedContext":"at:producer","ofd:relatedActor":"https://w3id.org/openfooddata/actors/jos-van-oosterwyck"}],"@id":"https://w3id.org/openfooddata/actors/2363","extraHeader":"<link rel=\"alternate\" href=\"2363.rdf\" type=\"application/rdf+xml\"/>\n<link rel=\"alternate\" href=\"2363.jsonld\" type=\"application/ld+json\"/>\n<link rel=\"alternate\" href=\"2363.nq\" type=\"application/n-quads\"/>\n<link rel=\"alternate\" href=\"2363.nt\" type=\"application/n-triples\"/>\n<link rel=\"alternate\" href=\"2363.ttl\" type=\"text/turtle\"/>\n<link rel=\"alternate\" href=\"2363.rj\" type=\"application/rdf+json\"/>\n<link rel=\"alternate\" href=\"2363.trig\" type=\"text/trig\"/>\n<link rel=\"alternate\" href=\"2363.trix\" type=\"application/trix\"/>\n","schema:name":"Jos Van Oosterwyck","ofd:actorType":["at:pointOfSale","at:farmShop"]}}