{"type":"Feature","geometry":{"type":"Point","coordinates":[3.216172,50.845749]},"properties":{"foaf:account":[],"foaf:name":"Aardappelautomaat","foaf:isPrimaryTopicOf":["http://www.rechtvanbijdeboer.be/aardappelautomaat-6","http://www.rechtvanbijdeboer.be/node/3126"],"@type":"foaf:Agent","schema:image":[],"@context":"https://openfooddata.github.io/actors/_common/context.jsonld","schema:geo":{"schema:latitude":"50.845749","schema:longitude":"3.216172","@type":"schema:GeoCoordinates","schema:addressCountry":"Belgium","schema:address":{"@type":"schema:PostalAddress","schema:streetAddress":"Pijplap","schema:postalCode":"8560","schema:addressLocality":"Gullegem"}},"ofd:offersFoodType":["ft:potatoes"],"foaf:depiction":[],"schema:description":"","ofd:upstreamRel":[{"@type":"ofd:ActorRelationship","ofd:relatedContext":"at:producer","ofd:relatedActor":"https://w3id.org/openfooddata/actors/pottie-decock"}],"@id":"https://w3id.org/openfooddata/actors/aardappelautomaat-6","schema:name":"Aardappelautomaat","ofd:actorType":["at:pointOfSale","at:vendingMachine"]}}