{"type":"Feature","geometry":{"type":"Point","coordinates":[2.674808,50.874459]},"properties":{"foaf:account":[],"foaf:name":"Couthof Hoeve","schema:url":[],"foaf:homepage":[],"foaf:isPrimaryTopicOf":["http://www.rechtvanbijdeboer.be/couthof-hoeve-0","http://www.rechtvanbijdeboer.be/node/3044","https://www.rechtvanbijdeboer.be/couthof-hoeve","https://www.rechtvanbijdeboer.be/node/1554"],"@type":"foaf:Agent","schema:image":[],"@context":"https://openfooddata.github.io/actors/_common/context.jsonld","schema:geo":{"schema:latitude":"50.874459","schema:longitude":"2.674808","@type":"schema:GeoCoordinates","schema:addressCountry":"Belgium","schema:address":{"@type":"schema:PostalAddress","schema:streetAddress":"Gravendreef 21","schema:postalCode":"8972","schema:addressLocality":"Proven"}},"ofd:offersFoodType":["ft:milk_products"],"foaf:depiction":[],"schema:description":"","ofd:upstreamRel":[],"ofd:downstreamRel":[],"@id":"https://w3id.org/openfooddata/actors/couthof-hoeve","schema:name":"Couthof Hoeve","ofd:actorType":["at:pointOfSale","at:farmShop","at:producer"]}}