{"type":"Feature","geometry":{"type":"Point","coordinates":[4.971979,51.119795]},"properties":{"foaf:account":[],"foaf:name":"Fruitbedrijf Jos Helsen","schema:url":[],"foaf:homepage":[],"foaf:isPrimaryTopicOf":["http://www.rechtvanbijdeboer.be/fruitbedrijf-jos-helsen-0","http://www.rechtvanbijdeboer.be/node/2942","https://www.rechtvanbijdeboer.be/fruitbedrijf-jos-helsen","https://www.rechtvanbijdeboer.be/node/1453"],"@type":"foaf:Agent","schema:image":[],"@context":"https://openfooddata.github.io/actors/_common/context.jsonld","schema:geo":{"schema:latitude":"51.119795","schema:longitude":"4.971979","@type":"schema:GeoCoordinates","schema:addressCountry":"Belgium","schema:address":{"@type":"schema:PostalAddress","schema:streetAddress":"Janssen-Pharmaceuticalaan 1","schema:postalCode":"2440","schema:addressLocality":"Geel"}},"ofd:offersFoodType":["ft:poultry_meat","ft:fruits"],"foaf:depiction":[],"schema:description":"","ofd:upstreamRel":[],"ofd:downstreamRel":[],"@id":"https://w3id.org/openfooddata/actors/fruitbedrijf-jos-helsen","schema:name":"Fruitbedrijf Jos Helsen","ofd:actorType":["at:pointOfSale","at:farmShop","at:producer"]}}