{"type":"Feature","geometry":{"type":"Point","coordinates":[4.971979,51.119795]},"properties":{"foaf:account":[],"foaf:name":"Fruitbedrijf Jos Helsen","schema:url":[],"foaf:homepage":[],"foaf:isPrimaryTopicOf":["http://www.rechtvanbijdeboer.be/fruitbedrijf-jos-helsen-0","http://www.rechtvanbijdeboer.be/node/2942","https://www.rechtvanbijdeboer.be/fruitbedrijf-jos-helsen","https://www.rechtvanbijdeboer.be/node/1453"],"@type":"foaf:Agent","schema:image":[],"@context":"https://openfooddata.github.io/actors/_common/context.jsonld","schema:geo":{"schema:latitude":"51.119795","schema:longitude":"4.971979","@type":"schema:GeoCoordinates","schema:addressCountry":"Belgium","schema:address":{"@type":"schema:PostalAddress","schema:streetAddress":"Janssen-Pharmaceuticalaan 1","schema:postalCode":"2440","schema:addressLocality":"Geel"}},"ofd:offersFoodType":["ft:poultry_meat","ft:fruits"],"foaf:depiction":[],"schema:description":"","ofd:upstreamRel":[],"ofd:downstreamRel":[],"@id":"https://w3id.org/openfooddata/actors/fruitbedrijf-jos-helsen","extraHeader":"<link rel=\"alternate\" href=\"fruitbedrijf-jos-helsen.rdf\" type=\"application/rdf+xml\"/>\n<link rel=\"alternate\" href=\"fruitbedrijf-jos-helsen.jsonld\" type=\"application/ld+json\"/>\n<link rel=\"alternate\" href=\"fruitbedrijf-jos-helsen.nq\" type=\"application/n-quads\"/>\n<link rel=\"alternate\" href=\"fruitbedrijf-jos-helsen.nt\" type=\"application/n-triples\"/>\n<link rel=\"alternate\" href=\"fruitbedrijf-jos-helsen.ttl\" type=\"text/turtle\"/>\n<link rel=\"alternate\" href=\"fruitbedrijf-jos-helsen.rj\" type=\"application/rdf+json\"/>\n<link rel=\"alternate\" href=\"fruitbedrijf-jos-helsen.trig\" type=\"text/trig\"/>\n<link rel=\"alternate\" href=\"fruitbedrijf-jos-helsen.trix\" type=\"application/trix\"/>\n","schema:name":"Fruitbedrijf Jos Helsen","ofd:actorType":["at:pointOfSale","at:farmShop","at:producer"]}}