{"type":"Feature","geometry":{"type":"Point","coordinates":[3.716322,51.049081]},"properties":{"id":"https://w3id.org/openfooddata/actors/afhaalpunt-stoppelstraat","name":"Afhaalpunt Stoppelstraat","img":[],"type":["at:pointOfSale","at:vegetableSubscription"],"upstream":[{"@type":"ofd:ActorRelationship","ofd:relatedContext":"at:producer","ofd:relatedActor":"https://w3id.org/openfooddata/actors/de-wassende-maan"}]}}