{"type":"Feature","geometry":{"type":"Point","coordinates":[3.134633,51.106931]},"properties":{"id":"https://w3id.org/openfooddata/actors/frambozenkwekerij-devlieghere","name":"Frambozenkwekerij Devlieghere","img":["http://www.rechtvanbijdeboer.be/sites/default/files/styles/producer_teaser/public/20160708_145140.jpg?itok=LHWj_oYI","http://www.rechtvanbijdeboer.be/sites/default/files/styles/producer_teaser/public/118.JPG?itok=MwN4ltMl","http://www.rechtvanbijdeboer.be/sites/default/files/styles/producer_teaser/public/foto%27s%20producten%20045.jpg?itok=J2rblzF2"],"type":["at:pointOfSale","at:farmShop","at:producer"],"upstream":[],"downstream":[]}}