{"type":"Feature","geometry":{"type":"Point","coordinates":[3.36978,51.098045]},"properties":{"id":"https://w3id.org/openfooddata/actors/lambert-vanlaere-0","name":"Lambert-Vanlaere","img":[],"type":["at:pointOfSale","at:farmShop"],"upstream":[{"@type":"ofd:ActorRelationship","ofd:relatedContext":"at:producer","ofd:relatedActor":"https://w3id.org/openfooddata/actors/lambert-vanlaere"}]}}