{"type":"Feature","geometry":{"type":"Point","coordinates":[3.26284,50.92325]},"properties":{"id":"https://w3id.org/openfooddata/actors/ingelmunster","name":"Ingelmunster","img":[],"type":["at:pointOfSale","at:market"],"upstream":[{"@type":"ofd:ActorRelationship","ofd:relatedContext":"at:producer","ofd:relatedActor":"https://w3id.org/openfooddata/actors/t-hof-rozendale"}]}}