{"type":"Feature","geometry":{"type":"Point","coordinates":[3.809096,51.057442]},"properties":{"id":"https://w3id.org/openfooddata/actors/afhaalpunt-destelbergen","name":"Afhaalpunt Destelbergen","img":[],"type":["at:pointOfSale","at:vegetableSubscription"],"upstream":[{"@type":"ofd:ActorRelationship","ofd:relatedContext":"at:producer","ofd:relatedActor":"https://w3id.org/openfooddata/actors/de-wassende-maan"}]}}