{"type":"Feature","geometry":{"type":"Point","coordinates":[4.275793,51.169869]},"properties":{"foaf:account":[],"foaf:name":"Platteput Hoeve","schema:url":[],"foaf:homepage":[],"foaf:isPrimaryTopicOf":["http://www.rechtvanbijdeboer.be/platteput-hoeve-0","http://www.rechtvanbijdeboer.be/node/3067","https://www.rechtvanbijdeboer.be/platteput-hoeve","https://www.rechtvanbijdeboer.be/node/1577"],"@type":"foaf:Agent","schema:image":[],"@context":"https://openfooddata.github.io/actors/_common/context.jsonld","schema:geo":{"schema:latitude":"51.169869","schema:longitude":"4.275793","@type":"schema:GeoCoordinates","schema:addressCountry":"Belgium","schema:address":{"@type":"schema:PostalAddress","schema:streetAddress":"Pismolenstraat 1","schema:postalCode":"9150","schema:addressLocality":"Kruibeke"}},"ofd:offersFoodType":["ft:milk_products","ft:eggs","ft:potatoes"],"foaf:depiction":[],"schema:description":"","ofd:upstreamRel":[],"ofd:downstreamRel":[],"@id":"https://w3id.org/openfooddata/actors/platteput-hoeve","extraHeader":"<link rel=\"alternate\" href=\"platteput-hoeve.rdf\" type=\"application/rdf+xml\"/>\n<link rel=\"alternate\" href=\"platteput-hoeve.jsonld\" type=\"application/ld+json\"/>\n<link rel=\"alternate\" href=\"platteput-hoeve.nq\" type=\"application/n-quads\"/>\n<link rel=\"alternate\" href=\"platteput-hoeve.nt\" type=\"application/n-triples\"/>\n<link rel=\"alternate\" href=\"platteput-hoeve.ttl\" type=\"text/turtle\"/>\n<link rel=\"alternate\" href=\"platteput-hoeve.rj\" type=\"application/rdf+json\"/>\n<link rel=\"alternate\" href=\"platteput-hoeve.trig\" type=\"text/trig\"/>\n<link rel=\"alternate\" href=\"platteput-hoeve.trix\" type=\"application/trix\"/>\n","schema:name":"Platteput Hoeve","ofd:actorType":["at:pointOfSale","at:farmShop","at:producer"]}}