{"type":"Feature","geometry":{"type":"Point","coordinates":[3.922767,50.907869]},"properties":{"id":"https://w3id.org/openfooddata/actors/aardappelautomaat-7","name":"Aardappelautomaat","img":["http://www.rechtvanbijdeboer.be/sites/default/files/styles/producer_teaser/public/100_4185.jpg?itok=r-E1F89v"],"type":["at:pointOfSale","at:vendingMachine"],"upstream":[{"@type":"ofd:ActorRelationship","ofd:relatedContext":"at:producer","ofd:relatedActor":"https://w3id.org/openfooddata/actors/t-schuurke"}]}}