{"type":"Feature","geometry":{"type":"Point","coordinates":[4.757728,50.817255]},"properties":{"foaf:account":[],"foaf:name":"Voedselteam Bierbeek","foaf:isPrimaryTopicOf":["http://www.rechtvanbijdeboer.be/voedselteam-bierbeek","http://www.rechtvanbijdeboer.be/node/2226"],"@type":"foaf:Agent","schema:image":["http://www.rechtvanbijdeboer.be/sites/default/files/styles/producer_teaser/public/fotohnb.jpg?itok=m5oamG6W"],"@context":"https://openfooddata.github.io/actors/_common/context.jsonld","schema:geo":{"schema:latitude":"50.817255","schema:longitude":"4.757728","@type":"schema:GeoCoordinates","schema:addressCountry":"Belgium","schema:address":{"@type":"schema:PostalAddress","schema:streetAddress":"Oude Geldenaaksebaan 31","schema:postalCode":"3360","schema:addressLocality":"Bierbeek"}},"ofd:offersFoodType":["ft:potatoes","ft:bakery_products","ft:eggs","ft:poultry_meat","ft:fruit_juices","ft:icecream","ft:spices","ft:lamb_meat","ft:beef","ft:pork","ft:alcoholic_beverages","ft:vegetables","ft:milk_products","ft:fruits"],"foaf:depiction":["http://www.rechtvanbijdeboer.be/sites/default/files/styles/producer_teaser/public/fotohnb.jpg?itok=m5oamG6W"],"schema:description":"","ofd:upstreamRel":[{"@type":"ofd:ActorRelationship","ofd:relatedContext":"at:producer","ofd:relatedActor":"https://w3id.org/openfooddata/actors/vzw-de-winning-maatwerk"},{"@type":"ofd:ActorRelationship","ofd:relatedContext":"at:producer","ofd:relatedActor":"https://w3id.org/openfooddata/actors/de-ploeg"},{"@type":"ofd:ActorRelationship","ofd:relatedContext":"at:producer","ofd:relatedActor":"https://w3id.org/openfooddata/actors/fv-van-haesendonck"},{"@type":"ofd:ActorRelationship","ofd:relatedContext":"at:producer","ofd:relatedActor":"https://w3id.org/openfooddata/actors/de-levende-aarde-cvba"},{"@type":"ofd:ActorRelationship","ofd:relatedContext":"at:producer","ofd:relatedActor":"https://w3id.org/openfooddata/actors/regalys"},{"@type":"ofd:ActorRelationship","ofd:relatedContext":"at:producer","ofd:relatedActor":"https://w3id.org/openfooddata/actors/wonen-&-werken-de-wikke"},{"@type":"ofd:ActorRelationship","ofd:relatedContext":"at:producer","ofd:relatedActor":"https://w3id.org/openfooddata/actors/de-fruittuin"},{"@type":"ofd:ActorRelationship","ofd:relatedContext":"at:producer","ofd:relatedActor":"https://w3id.org/openfooddata/actors/t-fruitratje"}],"@id":"https://w3id.org/openfooddata/actors/voedselteam-bierbeek","extraHeader":"<link rel=\"alternate\" href=\"voedselteam-bierbeek.rdf\" type=\"application/rdf+xml\"/>\n<link rel=\"alternate\" href=\"voedselteam-bierbeek.jsonld\" type=\"application/ld+json\"/>\n<link rel=\"alternate\" href=\"voedselteam-bierbeek.nq\" type=\"application/n-quads\"/>\n<link rel=\"alternate\" href=\"voedselteam-bierbeek.nt\" type=\"application/n-triples\"/>\n<link rel=\"alternate\" href=\"voedselteam-bierbeek.ttl\" type=\"text/turtle\"/>\n<link rel=\"alternate\" href=\"voedselteam-bierbeek.rj\" type=\"application/rdf+json\"/>\n<link rel=\"alternate\" href=\"voedselteam-bierbeek.trig\" type=\"text/trig\"/>\n<link rel=\"alternate\" href=\"voedselteam-bierbeek.trix\" type=\"application/trix\"/>\n","schema:name":"Voedselteam Bierbeek","ofd:actorType":["at:pointOfSale","at:foodTeams"]}}