{"type":"Feature","geometry":{"type":"Point","coordinates":[3.205786,50.983638]},"properties":{"foaf:account":[],"foaf:name":"Voeders Callewaert (bestellen via biobello.be)","foaf:isPrimaryTopicOf":["http://www.rechtvanbijdeboer.be/voeders-callewaert-bestellen-biobellobe","http://www.rechtvanbijdeboer.be/node/2470"],"@type":"foaf:Agent","schema:image":["http://www.rechtvanbijdeboer.be/sites/default/files/styles/producer_teaser/public/biobellogroentenenfruitmaxi.jpg?itok=n2EToMw3"],"@context":"https://openfooddata.github.io/actors/_common/context.jsonld","schema:geo":{"schema:latitude":"50.983638","schema:longitude":"3.205786","@type":"schema:GeoCoordinates","schema:addressCountry":"Belgium","schema:address":{"@type":"schema:PostalAddress","schema:streetAddress":"Berlingmolenstraat 64","schema:postalCode":"8850","schema:addressLocality":"Ardooie"}},"ofd:offersFoodType":["ft:potatoes","ft:fruits","ft:eggs","ft:vegetables"],"foaf:depiction":["http://www.rechtvanbijdeboer.be/sites/default/files/styles/producer_teaser/public/biobellogroentenenfruitmaxi.jpg?itok=n2EToMw3"],"schema:description":"","ofd:upstreamRel":[{"@type":"ofd:ActorRelationship","ofd:relatedContext":"at:producer","ofd:relatedActor":"https://w3id.org/openfooddata/actors/de-lochting-vzw"}],"@id":"https://w3id.org/openfooddata/actors/voeders-callewaert-bestellen-biobellobe","schema:name":"Voeders Callewaert (bestellen via biobello.be)","ofd:actorType":["at:pointOfSale","at:collectionPoint"]}}