{"type":"Feature","geometry":{"type":"Point","coordinates":[3.19891,50.83667]},"properties":{"id":"https://w3id.org/openfooddata/actors/aardappelautomaat-5","name":"Aardappelautomaat","img":[],"type":["at:pointOfSale","at:vendingMachine"],"upstream":[{"@type":"ofd:ActorRelationship","ofd:relatedContext":"at:producer","ofd:relatedActor":"https://w3id.org/openfooddata/actors/pottie-decock"}]}}