{"type":"Feature","geometry":{"type":"Point","coordinates":[3.269159,50.981174]},"properties":{"foaf:account":[],"foaf:name":"Goed ter Deurhout","schema:url":[],"foaf:homepage":[],"foaf:isPrimaryTopicOf":["http://www.rechtvanbijdeboer.be/goed-ter-deurhout-0","http://www.rechtvanbijdeboer.be/node/2735","https://www.rechtvanbijdeboer.be/goed-ter-deurhout","https://www.rechtvanbijdeboer.be/node/1299"],"@type":"foaf:Agent","schema:image":[],"@context":"https://openfooddata.github.io/actors/_common/context.jsonld","schema:geo":{"schema:latitude":"50.981174","schema:longitude":"3.269159","@type":"schema:GeoCoordinates","schema:addressCountry":"Belgium","schema:address":{"@type":"schema:PostalAddress","schema:streetAddress":"Meulebekestraat 97","schema:postalCode":"8740","schema:addressLocality":"Pittem"}},"ofd:offersFoodType":["ft:pork","ft:beef","ft:vegetables","ft:potatoes","ft:spices"],"foaf:depiction":[],"schema:description":"","ofd:upstreamRel":[],"ofd:downstreamRel":[],"@id":"https://w3id.org/openfooddata/actors/goed-ter-deurhout","schema:name":"Goed ter Deurhout","ofd:actorType":["at:pointOfSale","at:farmShop","at:producer"]}}