{"type":"Feature","geometry":{"type":"Point","coordinates":[4.616663,51.254352]},"properties":{"foaf:account":[],"foaf:name":"Appelen Roes","foaf:isPrimaryTopicOf":["http://www.rechtvanbijdeboer.be/appelen-roes-1","http://www.rechtvanbijdeboer.be/node/3439"],"@type":"foaf:Agent","schema:image":[],"@context":"https://openfooddata.github.io/actors/_common/context.jsonld","schema:geo":{"schema:latitude":"51.254352","schema:longitude":"4.616663","@type":"schema:GeoCoordinates","schema:addressCountry":"Belgium","schema:address":{"@type":"schema:PostalAddress","schema:streetAddress":"Kapellei 213","schema:postalCode":"2980","schema:addressLocality":"Zoersel"}},"ofd:offersFoodType":["ft:fruits","ft:fruit_juices"],"foaf:depiction":[],"schema:description":"","ofd:upstreamRel":[{"@type":"ofd:ActorRelationship","ofd:relatedContext":"at:producer","ofd:relatedActor":"https://w3id.org/openfooddata/actors/belfru---appelen-roes"}],"@id":"https://w3id.org/openfooddata/actors/appelen-roes-1","extraHeader":"<link rel=\"alternate\" href=\"appelen-roes-1.rdf\" type=\"application/rdf+xml\"/>\n<link rel=\"alternate\" href=\"appelen-roes-1.jsonld\" type=\"application/ld+json\"/>\n<link rel=\"alternate\" href=\"appelen-roes-1.nq\" type=\"application/n-quads\"/>\n<link rel=\"alternate\" href=\"appelen-roes-1.nt\" type=\"application/n-triples\"/>\n<link rel=\"alternate\" href=\"appelen-roes-1.ttl\" type=\"text/turtle\"/>\n<link rel=\"alternate\" href=\"appelen-roes-1.rj\" type=\"application/rdf+json\"/>\n<link rel=\"alternate\" href=\"appelen-roes-1.trig\" type=\"text/trig\"/>\n<link rel=\"alternate\" href=\"appelen-roes-1.trix\" type=\"application/trix\"/>\n","schema:name":"Appelen Roes","ofd:actorType":["at:pointOfSale","at:farmShop"]}}