{"type":"Feature","geometry":{"type":"Point","coordinates":[5.171511,50.704634]},"properties":{"foaf:account":[],"foaf:name":"Hoeve Jadoul","schema:url":[],"foaf:homepage":[],"foaf:isPrimaryTopicOf":["http://www.rechtvanbijdeboer.be/hoeve-jadoul-0","http://www.rechtvanbijdeboer.be/node/2986","https://www.rechtvanbijdeboer.be/hoeve-jadoul","https://www.rechtvanbijdeboer.be/node/1498"],"@type":"foaf:Agent","schema:image":[],"@context":"https://openfooddata.github.io/actors/_common/context.jsonld","schema:geo":{"schema:latitude":"50.704634","schema:longitude":"5.171511","@type":"schema:GeoCoordinates","schema:addressCountry":"Belgium","schema:address":{"@type":"schema:PostalAddress","schema:streetAddress":"Hoogstraat 34","schema:postalCode":"3890","schema:addressLocality":"Gingelom"}},"ofd:offersFoodType":["ft:fruit_juices","ft:fruits"],"foaf:depiction":[],"schema:description":"","ofd:upstreamRel":[],"ofd:downstreamRel":[],"@id":"https://w3id.org/openfooddata/actors/hoeve-jadoul","extraHeader":"<link rel=\"alternate\" href=\"hoeve-jadoul.rdf\" type=\"application/rdf+xml\"/>\n<link rel=\"alternate\" href=\"hoeve-jadoul.jsonld\" type=\"application/ld+json\"/>\n<link rel=\"alternate\" href=\"hoeve-jadoul.nq\" type=\"application/n-quads\"/>\n<link rel=\"alternate\" href=\"hoeve-jadoul.nt\" type=\"application/n-triples\"/>\n<link rel=\"alternate\" href=\"hoeve-jadoul.ttl\" type=\"text/turtle\"/>\n<link rel=\"alternate\" href=\"hoeve-jadoul.rj\" type=\"application/rdf+json\"/>\n<link rel=\"alternate\" href=\"hoeve-jadoul.trig\" type=\"text/trig\"/>\n<link rel=\"alternate\" href=\"hoeve-jadoul.trix\" type=\"application/trix\"/>\n","schema:name":"Hoeve Jadoul","ofd:actorType":["at:pointOfSale","at:farmShop","at:producer"]}}