{"type":"Feature","geometry":{"type":"Point","coordinates":[5.171511,50.704634]},"properties":{"id":"https://w3id.org/openfooddata/actors/hoeve-jadoul","name":"Hoeve Jadoul","img":[],"type":["at:pointOfSale","at:farmShop","at:producer"],"upstream":[],"downstream":[]}}