{"type":"Feature","geometry":{"type":"Point","coordinates":[3.654986,51.070222]},"properties":{"id":"https://w3id.org/openfooddata/actors/de-bekwame-boon","name":"De Bekwame Boon","img":[],"type":["at:pointOfSale","at:farmShop","at:producer"],"upstream":[],"downstream":[]}}