{"type":"Feature","geometry":{"type":"Point","coordinates":[3.349737,50.851191]},"properties":{"id":"https://w3id.org/openfooddata/actors/lokaal","name":"Lokaal","img":["http://www.rechtvanbijdeboer.be/sites/default/files/styles/producer_teaser/public/dsc09250.jpg?itok=1yuUaDuy"],"type":["at:pointOfSale","at:farmersMarket"],"upstream":[{"@type":"ofd:ActorRelationship","ofd:relatedContext":"at:producer","ofd:relatedActor":"https://w3id.org/openfooddata/actors/t-meikensvlasvarken-gcv"},{"@type":"ofd:ActorRelationship","ofd:relatedContext":"at:producer","ofd:relatedActor":"https://w3id.org/openfooddata/actors/fruit-lambrecht-baart"},{"@type":"ofd:ActorRelationship","ofd:relatedContext":"at:producer","ofd:relatedActor":"https://w3id.org/openfooddata/actors/fruithandel-doms"}]}}