{"type":"Feature","geometry":{"type":"Point","coordinates":[4.936822,51.146917]},"properties":{"id":"https://w3id.org/openfooddata/actors/steinerschool-novalis","name":"Steinerschool Novalis","img":[],"type":["at:pointOfSale","at:vegetableSubscription"],"upstream":[{"@type":"ofd:ActorRelationship","ofd:relatedContext":"at:producer","ofd:relatedActor":"https://w3id.org/openfooddata/actors/de-bio-hoeve"}]}}