{"type":"Feature","geometry":{"type":"Point","coordinates":[2.854793,50.896746]},"properties":{"id":"https://w3id.org/openfooddata/actors/plukdag-bij-fruit-vervisch","name":"Plukdag bij Fruit Vervisch","img":["http://www.rechtvanbijdeboer.be/sites/default/files/styles/producer_teaser/public/appels.jpg?itok=gZQv_Ega"],"type":["at:pointOfSale"],"upstream":[{"@type":"ofd:ActorRelationship","ofd:relatedContext":"at:producer","ofd:relatedActor":"https://w3id.org/openfooddata/actors/fruit-vervisch"}]}}