{"type":"Feature","geometry":{"type":"Point","coordinates":[4.12402,50.950228]},"properties":{"foaf:account":[],"foaf:name":"Ons Dagelijks Groen","schema:url":["http://www.odgroen.be"],"foaf:homepage":["http://www.odgroen.be"],"foaf:isPrimaryTopicOf":["http://www.rechtvanbijdeboer.be/ons-dagelijks-groen-0","http://www.rechtvanbijdeboer.be/node/3248","http://www.rechtvanbijdeboer.be/ons-dagelijks-groen","http://www.rechtvanbijdeboer.be/node/1712"],"@type":"foaf:Agent","schema:image":["http://www.rechtvanbijdeboer.be/sites/default/files/styles/producer_teaser/public/preipralinemetgedroogdpreigroen.jpg?itok=HQxQg957","http://www.rechtvanbijdeboer.be/sites/default/files/styles/producer_teaser/public/rondleidingagragroepinwinkelinfo.jpg?itok=xuimL1FH","http://www.rechtvanbijdeboer.be/sites/default/files/styles/producer_teaser/public/ons_dagelijks_groen_producent_hr.jpg?itok=Klrx64d-","http://www.rechtvanbijdeboer.be/sites/default/files/styles/producer_teaser/public/preikaasmetgedroogdpreigroen.jpg?itok=Xu-EgFc7"],"@context":"https://openfooddata.github.io/actors/_common/context.jsonld","schema:geo":{"schema:latitude":"50.950228","schema:longitude":"4.124020","@type":"schema:GeoCoordinates","schema:addressCountry":"Belgium","schema:address":{"@type":"schema:PostalAddress","schema:streetAddress":"Kammenkouterstraat 80","schema:postalCode":"9310","schema:addressLocality":"Meldert"}},"ofd:offersFoodType":["ft:bakery_products","ft:poultry_meat","ft:milk_products","ft:alcoholic_beverages","ft:fruits","ft:vegetables","ft:potatoes","ft:spices"],"foaf:depiction":["http://www.rechtvanbijdeboer.be/sites/default/files/styles/producer_teaser/public/preipralinemetgedroogdpreigroen.jpg?itok=HQxQg957","http://www.rechtvanbijdeboer.be/sites/default/files/styles/producer_teaser/public/rondleidingagragroepinwinkelinfo.jpg?itok=xuimL1FH","http://www.rechtvanbijdeboer.be/sites/default/files/styles/producer_teaser/public/ons_dagelijks_groen_producent_hr.jpg?itok=Klrx64d-","http://www.rechtvanbijdeboer.be/sites/default/files/styles/producer_teaser/public/preikaasmetgedroogdpreigroen.jpg?itok=Xu-EgFc7"],"schema:description":"'Ons Dagelijks Groen', is een preibedrijf met zorgboerderij, heeft een hoeve-automatenwinkel en doet aan landbouweducatie, ontvangt klassen, verzorgt (verjaardag)workshops, bedrijfsbezoeken, seminaries, teambuilding…in een land- en tuinbouwgebeuren. Ons dagelijks groen is ontstaan vanuit een preibedrijf . De naam ‘Ons Dagelijks Groen' wijst erop dat groenten, fruit, de akker en de tuin essentieel zijn in ons dagelijks leven om een gezonde en duurzame levensstijl te behouden. Op basis van het gedroogde preigroen, dat volgens recente studies rijk is aan antioxidanten en kankerwerend is, brengt dit bedrijf preikaas, preilikeur, preipralines, preibrood… op de markt. In de automatenwinkel worden eigen producten en producten van collega’s verkocht. Tijdens een rondleiding krijg je uitleg over de productie van prei, de zorgboerderij, de automatenwinkel, het landbouweducatief project... Op aanvraag kan een rondleiding ook gecombineerd worden met een tweekamp, volksspelen of een quiz. Plezier gegarandeerd! Een hapje en een drankje of zelfs een volledige maaltijd “van de grond in de mond” is mogelijk in de polyvalente zaal .","ofd:upstreamRel":[],"schema:contactPoint":{"@type":"schema:ContactPoint","schema:telephone":["053 70 64 73","0499 18 99 25"],"schema:email":["info@odgroen.be"],"foaf:homepage":["http://www.odgroen.be"],"schema:url":["http://www.odgroen.be"]},"ofd:downstreamRel":[],"@id":"https://w3id.org/openfooddata/actors/ons-dagelijks-groen","extraHeader":"<link rel=\"alternate\" href=\"ons-dagelijks-groen.rdf\" type=\"application/rdf+xml\"/>\n<link rel=\"alternate\" href=\"ons-dagelijks-groen.jsonld\" type=\"application/ld+json\"/>\n<link rel=\"alternate\" href=\"ons-dagelijks-groen.nq\" type=\"application/n-quads\"/>\n<link rel=\"alternate\" href=\"ons-dagelijks-groen.nt\" type=\"application/n-triples\"/>\n<link rel=\"alternate\" href=\"ons-dagelijks-groen.ttl\" type=\"text/turtle\"/>\n<link rel=\"alternate\" href=\"ons-dagelijks-groen.rj\" type=\"application/rdf+json\"/>\n<link rel=\"alternate\" href=\"ons-dagelijks-groen.trig\" type=\"text/trig\"/>\n<link rel=\"alternate\" href=\"ons-dagelijks-groen.trix\" type=\"application/trix\"/>\n","schema:name":"Ons Dagelijks Groen","ofd:actorType":["at:pointOfSale","at:farmShop","at:producer"]}}