{"type":"Feature","geometry":{"type":"Point","coordinates":[4.12402,50.950228]},"properties":{"id":"https://w3id.org/openfooddata/actors/ons-dagelijks-groen","name":"Ons Dagelijks Groen","img":["http://www.rechtvanbijdeboer.be/sites/default/files/styles/producer_teaser/public/preipralinemetgedroogdpreigroen.jpg?itok=HQxQg957","http://www.rechtvanbijdeboer.be/sites/default/files/styles/producer_teaser/public/rondleidingagragroepinwinkelinfo.jpg?itok=xuimL1FH","http://www.rechtvanbijdeboer.be/sites/default/files/styles/producer_teaser/public/ons_dagelijks_groen_producent_hr.jpg?itok=Klrx64d-","http://www.rechtvanbijdeboer.be/sites/default/files/styles/producer_teaser/public/preikaasmetgedroogdpreigroen.jpg?itok=Xu-EgFc7"],"type":["at:pointOfSale","at:farmShop","at:producer"],"upstream":[],"downstream":[]}}