{"type":"Feature","geometry":{"type":"Point","coordinates":[4.766009,51.01963]},"properties":{"id":"https://w3id.org/openfooddata/actors/wijngaard-ten-gaerde-0","name":"Wijngaard ten Gaerde","img":[],"type":["at:pointOfSale","at:collectionPoint"],"upstream":[{"@type":"ofd:ActorRelationship","ofd:relatedContext":"at:producer","ofd:relatedActor":"https://w3id.org/openfooddata/actors/wijngaard-ten-gaerde"}]}}