{"type":"Feature","geometry":{"type":"Point","coordinates":[4.643229,51.399006]},"properties":{"id":"https://w3id.org/openfooddata/actors/romberama-amaryllis","name":"Romberama Amaryllis","img":[],"type":["at:pointOfSale","at:farmShop"],"upstream":[{"@type":"ofd:ActorRelationship","ofd:relatedContext":"at:producer","ofd:relatedActor":"https://w3id.org/openfooddata/actors/romberama-bvba"}]}}