{"type":"Feature","geometry":{"type":"Point","coordinates":[3.900864,51.003319]},"properties":{"foaf:account":[],"foaf:name":"Afhaalpunt Wetteren","foaf:isPrimaryTopicOf":["http://www.rechtvanbijdeboer.be/afhaalpunt-wetteren","http://www.rechtvanbijdeboer.be/node/3538"],"@type":"foaf:Agent","schema:image":[],"@context":"https://openfooddata.github.io/actors/_common/context.jsonld","schema:geo":{"schema:latitude":"51.003319","schema:longitude":"3.900864","@type":"schema:GeoCoordinates","schema:addressCountry":"Belgium","schema:address":{"@type":"schema:PostalAddress","schema:streetAddress":"Victor Van Sandelaan 164","schema:postalCode":"9230","schema:addressLocality":"Wetteren"}},"ofd:offersFoodType":["ft:potatoes","ft:fruits","ft:bakery_products","ft:eggs","ft:fruit_juices","ft:spices","ft:beef","ft:alcoholic_beverages","ft:vegetables","ft:milk_products"],"foaf:depiction":[],"schema:description":"","ofd:upstreamRel":[{"@type":"ofd:ActorRelationship","ofd:relatedContext":"at:producer","ofd:relatedActor":"https://w3id.org/openfooddata/actors/de-wassende-maan"}],"@id":"https://w3id.org/openfooddata/actors/afhaalpunt-wetteren","extraHeader":"<link rel=\"alternate\" href=\"afhaalpunt-wetteren.rdf\" type=\"application/rdf+xml\"/>\n<link rel=\"alternate\" href=\"afhaalpunt-wetteren.jsonld\" type=\"application/ld+json\"/>\n<link rel=\"alternate\" href=\"afhaalpunt-wetteren.nq\" type=\"application/n-quads\"/>\n<link rel=\"alternate\" href=\"afhaalpunt-wetteren.nt\" type=\"application/n-triples\"/>\n<link rel=\"alternate\" href=\"afhaalpunt-wetteren.ttl\" type=\"text/turtle\"/>\n<link rel=\"alternate\" href=\"afhaalpunt-wetteren.rj\" type=\"application/rdf+json\"/>\n<link rel=\"alternate\" href=\"afhaalpunt-wetteren.trig\" type=\"text/trig\"/>\n<link rel=\"alternate\" href=\"afhaalpunt-wetteren.trix\" type=\"application/trix\"/>\n","schema:name":"Afhaalpunt Wetteren","ofd:actorType":["at:pointOfSale","at:vegetableSubscription"]}}