{"type":"Feature","geometry":{"type":"Point","coordinates":[3.77901,51.005137]},"properties":{"id":"https://w3id.org/openfooddata/actors/het-landhuis","name":"Het Landhuis","img":[],"type":["at:pointOfSale","at:farmShop","at:producer"],"upstream":[],"downstream":[]}}