{"type":"Feature","geometry":{"type":"Point","coordinates":[4.321554,50.878529]},"properties":{"id":"https://w3id.org/openfooddata/actors/buurderij-jette","name":"Buurderij Jette","img":["http://www.rechtvanbijdeboer.be/sites/default/files/styles/producer_teaser/public/flyeraardbeien.png?itok=xdbUh_oV"],"type":["at:pointOfSale","at:foodAssembly"],"upstream":[{"@type":"ofd:ActorRelationship","ofd:relatedContext":"at:producer","ofd:relatedActor":"https://w3id.org/openfooddata/actors/donderij"},{"@type":"ofd:ActorRelationship","ofd:relatedContext":"at:producer","ofd:relatedActor":"https://w3id.org/openfooddata/actors/seizoensmaak"},{"@type":"ofd:ActorRelationship","ofd:relatedContext":"at:producer","ofd:relatedActor":"https://w3id.org/openfooddata/actors/hof-te-berchemveld"},{"@type":"ofd:ActorRelationship","ofd:relatedContext":"at:producer","ofd:relatedActor":"https://w3id.org/openfooddata/actors/hof-ter-vrijlegem"},{"@type":"ofd:ActorRelationship","ofd:relatedContext":"at:producer","ofd:relatedActor":"https://w3id.org/openfooddata/actors/permafungi"},{"@type":"ofd:ActorRelationship","ofd:relatedContext":"at:producer","ofd:relatedActor":"https://w3id.org/openfooddata/actors/fruitkwekerij-van-biervliet"}]}}