{"type":"Feature","geometry":{"type":"Point","coordinates":[4.321554,50.878529]},"properties":{"foaf:account":[],"foaf:name":"Buurderij Jette","foaf:isPrimaryTopicOf":["http://www.rechtvanbijdeboer.be/buurderij-jette","http://www.rechtvanbijdeboer.be/node/2049"],"@type":"foaf:Agent","schema:image":["http://www.rechtvanbijdeboer.be/sites/default/files/styles/producer_teaser/public/flyeraardbeien.png?itok=xdbUh_oV"],"@context":"https://openfooddata.github.io/actors/_common/context.jsonld","schema:geo":{"schema:latitude":"50.878529","schema:longitude":"4.321554","@type":"schema:GeoCoordinates","schema:addressCountry":"Belgium","schema:address":{"@type":"schema:PostalAddress","schema:streetAddress":"Rue Eugène Toussaint","schema:addressLocality":"Jette"}},"ofd:offersFoodType":["ft:beef","ft:pork","ft:vegetables","ft:potatoes","ft:fruits","ft:eggs","ft:poultry_meat"],"foaf:depiction":["http://www.rechtvanbijdeboer.be/sites/default/files/styles/producer_teaser/public/flyeraardbeien.png?itok=xdbUh_oV"],"schema:description":"","ofd:upstreamRel":[{"@type":"ofd:ActorRelationship","ofd:relatedContext":"at:producer","ofd:relatedActor":"https://w3id.org/openfooddata/actors/donderij"},{"@type":"ofd:ActorRelationship","ofd:relatedContext":"at:producer","ofd:relatedActor":"https://w3id.org/openfooddata/actors/seizoensmaak"},{"@type":"ofd:ActorRelationship","ofd:relatedContext":"at:producer","ofd:relatedActor":"https://w3id.org/openfooddata/actors/hof-te-berchemveld"},{"@type":"ofd:ActorRelationship","ofd:relatedContext":"at:producer","ofd:relatedActor":"https://w3id.org/openfooddata/actors/hof-ter-vrijlegem"},{"@type":"ofd:ActorRelationship","ofd:relatedContext":"at:producer","ofd:relatedActor":"https://w3id.org/openfooddata/actors/permafungi"},{"@type":"ofd:ActorRelationship","ofd:relatedContext":"at:producer","ofd:relatedActor":"https://w3id.org/openfooddata/actors/fruitkwekerij-van-biervliet"}],"@id":"https://w3id.org/openfooddata/actors/buurderij-jette","schema:name":"Buurderij Jette","ofd:actorType":["at:pointOfSale","at:foodAssembly"]}}