{"type":"Feature","geometry":{"type":"Point","coordinates":[3.709986,51.029286]},"properties":{"id":"https://w3id.org/openfooddata/actors/gent-maaltebruggestraat","name":"Gent Maaltebruggestraat","img":[],"type":["at:pointOfSale","at:vegetableSubscription"],"upstream":[{"@type":"ofd:ActorRelationship","ofd:relatedContext":"at:producer","ofd:relatedActor":"https://w3id.org/openfooddata/actors/de-zonnekouter"}]}}