{"type":"Feature","geometry":{"type":"Point","coordinates":[3.732504,51.074168]},"properties":{"foaf:account":[],"foaf:name":"Stedelijk Buurtcentrum Muide–Meulestede","foaf:isPrimaryTopicOf":["http://www.rechtvanbijdeboer.be/stedelijk-buurtcentrum-muide%E2%80%93meulestede","http://www.rechtvanbijdeboer.be/node/2661"],"@type":"foaf:Agent","schema:image":[],"@context":"https://openfooddata.github.io/actors/_common/context.jsonld","schema:geo":{"schema:latitude":"51.074168","schema:longitude":"3.732504","@type":"schema:GeoCoordinates","schema:addressCountry":"Belgium","schema:address":{"@type":"schema:PostalAddress","schema:streetAddress":"Patrijsstraat 10","schema:postalCode":"9000","schema:addressLocality":"Gent"}},"ofd:offersFoodType":["ft:potatoes","ft:fruits","ft:bakery_products","ft:eggs","ft:beef","ft:pork","ft:vegetables","ft:milk_products"],"foaf:depiction":[],"schema:description":"","ofd:upstreamRel":[{"@type":"ofd:ActorRelationship","ofd:relatedContext":"at:producer","ofd:relatedActor":"https://w3id.org/openfooddata/actors/de-zonnekouter"}],"@id":"https://w3id.org/openfooddata/actors/stedelijk-buurtcentrum-muide%E2%80%93meulestede","extraHeader":"<link rel=\"alternate\" href=\"stedelijk-buurtcentrum-muide%E2%80%93meulestede.rdf\" type=\"application/rdf+xml\"/>\n<link rel=\"alternate\" href=\"stedelijk-buurtcentrum-muide%E2%80%93meulestede.jsonld\" type=\"application/ld+json\"/>\n<link rel=\"alternate\" href=\"stedelijk-buurtcentrum-muide%E2%80%93meulestede.nq\" type=\"application/n-quads\"/>\n<link rel=\"alternate\" href=\"stedelijk-buurtcentrum-muide%E2%80%93meulestede.nt\" type=\"application/n-triples\"/>\n<link rel=\"alternate\" href=\"stedelijk-buurtcentrum-muide%E2%80%93meulestede.ttl\" type=\"text/turtle\"/>\n<link rel=\"alternate\" href=\"stedelijk-buurtcentrum-muide%E2%80%93meulestede.rj\" type=\"application/rdf+json\"/>\n<link rel=\"alternate\" href=\"stedelijk-buurtcentrum-muide%E2%80%93meulestede.trig\" type=\"text/trig\"/>\n<link rel=\"alternate\" href=\"stedelijk-buurtcentrum-muide%E2%80%93meulestede.trix\" type=\"application/trix\"/>\n","schema:name":"Stedelijk Buurtcentrum Muide–Meulestede","ofd:actorType":["at:pointOfSale","at:vegetableSubscription"]}}