{"type":"Feature","geometry":{"type":"Point","coordinates":[4.158618,51.072907]},"properties":{"id":"https://w3id.org/openfooddata/actors/aardappelen-en-ruwvoeders-van-geyte","name":"Aardappelen en ruwvoeders Van Geyte","img":[],"type":["at:pointOfSale","at:vendingMachine","at:producer"],"upstream":[],"downstream":[]}}