{"type":"Feature","geometry":{"type":"Point","coordinates":[3.210592,50.847721]},"properties":{"id":"https://w3id.org/openfooddata/actors/zuivelboerderij-de-natuurhoeve","name":"Zuivelboerderij De Natuurhoeve","img":[],"type":["at:pointOfSale","at:farmShop","at:producer"],"upstream":[],"downstream":[]}}