{"type":"Feature","geometry":{"type":"Point","coordinates":[3.054003,51.102047]},"properties":{"foaf:account":[],"foaf:name":"Buurderij Ichtegem","foaf:isPrimaryTopicOf":["http://www.rechtvanbijdeboer.be/buurderij-ichtegem","http://www.rechtvanbijdeboer.be/node/2024"],"@type":"foaf:Agent","schema:image":[],"@context":"https://openfooddata.github.io/actors/_common/context.jsonld","schema:geo":{"schema:latitude":"51.102047","schema:longitude":"3.054003","@type":"schema:GeoCoordinates","schema:addressCountry":"Belgium","schema:address":{"@type":"schema:PostalAddress","schema:streetAddress":"Korenstraat 35","schema:postalCode":"8480","schema:addressLocality":"Ichtegem"}},"ofd:offersFoodType":["ft:eggs","ft:beef","ft:pork","ft:icecream","ft:milk_products","ft:fruits","ft:poultry_meat"],"foaf:depiction":[],"schema:description":"","ofd:upstreamRel":[{"@type":"ofd:ActorRelationship","ofd:relatedContext":"at:producer","ofd:relatedActor":"https://w3id.org/openfooddata/actors/steffi-fruit"},{"@type":"ofd:ActorRelationship","ofd:relatedContext":"at:producer","ofd:relatedActor":"https://w3id.org/openfooddata/actors/hoeve-pascal-en-sandra"},{"@type":"ofd:ActorRelationship","ofd:relatedContext":"at:producer","ofd:relatedActor":"https://w3id.org/openfooddata/actors/hoeve-t-lijsternest"}],"@id":"https://w3id.org/openfooddata/actors/buurderij-ichtegem","schema:name":"Buurderij Ichtegem","ofd:actorType":["at:pointOfSale","at:foodAssembly"]}}