{"type":"Feature","geometry":{"type":"Point","coordinates":[3.054003,51.102047]},"properties":{"foaf:account":[],"foaf:name":"Buurderij Ichtegem","foaf:isPrimaryTopicOf":["http://www.rechtvanbijdeboer.be/buurderij-ichtegem","http://www.rechtvanbijdeboer.be/node/2024"],"@type":"foaf:Agent","schema:image":[],"@context":"https://openfooddata.github.io/actors/_common/context.jsonld","schema:geo":{"schema:latitude":"51.102047","schema:longitude":"3.054003","@type":"schema:GeoCoordinates","schema:addressCountry":"Belgium","schema:address":{"@type":"schema:PostalAddress","schema:streetAddress":"Korenstraat 35","schema:postalCode":"8480","schema:addressLocality":"Ichtegem"}},"ofd:offersFoodType":["ft:eggs","ft:beef","ft:pork","ft:icecream","ft:milk_products","ft:fruits","ft:poultry_meat"],"foaf:depiction":[],"schema:description":"","ofd:upstreamRel":[{"@type":"ofd:ActorRelationship","ofd:relatedContext":"at:producer","ofd:relatedActor":"https://w3id.org/openfooddata/actors/steffi-fruit"},{"@type":"ofd:ActorRelationship","ofd:relatedContext":"at:producer","ofd:relatedActor":"https://w3id.org/openfooddata/actors/hoeve-pascal-en-sandra"},{"@type":"ofd:ActorRelationship","ofd:relatedContext":"at:producer","ofd:relatedActor":"https://w3id.org/openfooddata/actors/hoeve-t-lijsternest"}],"@id":"https://w3id.org/openfooddata/actors/buurderij-ichtegem","extraHeader":"<link rel=\"alternate\" href=\"buurderij-ichtegem.rdf\" type=\"application/rdf+xml\"/>\n<link rel=\"alternate\" href=\"buurderij-ichtegem.jsonld\" type=\"application/ld+json\"/>\n<link rel=\"alternate\" href=\"buurderij-ichtegem.nq\" type=\"application/n-quads\"/>\n<link rel=\"alternate\" href=\"buurderij-ichtegem.nt\" type=\"application/n-triples\"/>\n<link rel=\"alternate\" href=\"buurderij-ichtegem.ttl\" type=\"text/turtle\"/>\n<link rel=\"alternate\" href=\"buurderij-ichtegem.rj\" type=\"application/rdf+json\"/>\n<link rel=\"alternate\" href=\"buurderij-ichtegem.trig\" type=\"text/trig\"/>\n<link rel=\"alternate\" href=\"buurderij-ichtegem.trix\" type=\"application/trix\"/>\n","schema:name":"Buurderij Ichtegem","ofd:actorType":["at:pointOfSale","at:foodAssembly"]}}