{"type":"Feature","geometry":{"type":"Point","coordinates":[4.198494,50.780579]},"properties":{"foaf:account":[],"foaf:name":"Hoevebakkerij Basteleus - De Haseleer","foaf:isPrimaryTopicOf":["http://www.rechtvanbijdeboer.be/hoevebakkerij-basteleus-de-haseleer","http://www.rechtvanbijdeboer.be/node/2538"],"@type":"foaf:Agent","schema:image":[],"@context":"https://openfooddata.github.io/actors/_common/context.jsonld","schema:geo":{"schema:latitude":"50.780579","schema:longitude":"4.198494","@type":"schema:GeoCoordinates","schema:addressCountry":"Belgium","schema:address":{"@type":"schema:PostalAddress","schema:streetAddress":"Baasbergstraat 65","schema:postalCode":"1600","schema:addressLocality":"Oudenaken"}},"ofd:offersFoodType":["ft:bakery_products"],"foaf:depiction":[],"schema:description":"","ofd:upstreamRel":[{"@type":"ofd:ActorRelationship","ofd:relatedContext":"at:producer","ofd:relatedActor":"https://w3id.org/openfooddata/actors/hoevebakkerij-de-haseleer"}],"@id":"https://w3id.org/openfooddata/actors/hoevebakkerij-basteleus-de-haseleer","schema:name":"Hoevebakkerij Basteleus - De Haseleer","ofd:actorType":["at:pointOfSale","at:farmShop"]}}