{"type":"Feature","geometry":{"type":"Point","coordinates":[3.507938,50.827796]},"properties":{"foaf:account":[],"foaf:name":"Depot Elsegem","foaf:isPrimaryTopicOf":["http://www.rechtvanbijdeboer.be/depot-elsegem","http://www.rechtvanbijdeboer.be/node/3150"],"@type":"foaf:Agent","schema:image":["http://www.rechtvanbijdeboer.be/sites/default/files/styles/producer_teaser/public/dsc_2941.jpg?itok=AXt1vbWE"],"@context":"https://openfooddata.github.io/actors/_common/context.jsonld","schema:geo":{"schema:latitude":"50.827796","schema:longitude":"3.507938","@type":"schema:GeoCoordinates","schema:addressCountry":"Belgium","schema:address":{"@type":"schema:PostalAddress","schema:streetAddress":"Kwadenbulk 42","schema:postalCode":"9790","schema:addressLocality":"Elsegem"}},"ofd:offersFoodType":["ft:potatoes","ft:bakery_products","ft:eggs","ft:fruits","ft:fruit_juices","ft:vegetables","ft:icecream","ft:spices","ft:lamb_meat","ft:poultry_meat","ft:alcoholic_beverages","ft:milk_products"],"foaf:depiction":["http://www.rechtvanbijdeboer.be/sites/default/files/styles/producer_teaser/public/dsc_2941.jpg?itok=AXt1vbWE"],"schema:description":"","ofd:upstreamRel":[{"@type":"ofd:ActorRelationship","ofd:relatedContext":"at:producer","ofd:relatedActor":"https://w3id.org/openfooddata/actors/blauw-kasteel-bvba"}],"@id":"https://w3id.org/openfooddata/actors/depot-elsegem","schema:name":"Depot Elsegem","ofd:actorType":["at:pointOfSale","at:vegetableSubscription"]}}