{"type":"Feature","geometry":{"type":"Point","coordinates":[4.469936,50.503887]},"properties":{"foaf:account":[],"foaf:name":"www.wijnkasteel.com","foaf:isPrimaryTopicOf":["http://www.rechtvanbijdeboer.be/wwwwijnkasteelcom","http://www.rechtvanbijdeboer.be/node/3203"],"@type":"foaf:Agent","schema:image":[],"@context":"https://openfooddata.github.io/actors/_common/context.jsonld","schema:geo":{"schema:latitude":"50.503887","schema:longitude":"4.469936","@type":"schema:GeoCoordinates","schema:addressCountry":"Belgium","schema:address":{"@type":"schema:PostalAddress"}},"ofd:offersFoodType":["ft:alcoholic_beverages"],"foaf:depiction":[],"schema:description":"","ofd:upstreamRel":[{"@type":"ofd:ActorRelationship","ofd:relatedContext":"at:producer","ofd:relatedActor":"https://w3id.org/openfooddata/actors/wijnkasteel-genoelselderen"}],"@id":"https://w3id.org/openfooddata/actors/wwwwijnkasteelcom","schema:name":"www.wijnkasteel.com","ofd:actorType":["at:pointOfSale","at:webshop"]}}