{"type":"Feature","geometry":{"type":"Point","coordinates":[5.79323,51.155891]},"properties":{"foaf:account":[],"foaf:name":"Hoeve-ijs Engelenveld","foaf:isPrimaryTopicOf":["http://www.rechtvanbijdeboer.be/hoeve-ijs-engelenveld","http://www.rechtvanbijdeboer.be/node/2364"],"@type":"foaf:Agent","schema:image":["http://www.rechtvanbijdeboer.be/sites/default/files/styles/producer_teaser/public/hoeve-ijs_engelenveld_buitenkant_inkom.jpg?itok=r2ZOWphY"],"@context":"https://openfooddata.github.io/actors/_common/context.jsonld","schema:geo":{"schema:latitude":"51.155891","schema:longitude":"5.793230","@type":"schema:GeoCoordinates","schema:addressCountry":"Belgium","schema:address":{"@type":"schema:PostalAddress","schema:streetAddress":"Lakerweg 6","schema:postalCode":"3640","schema:addressLocality":"Kessenich (Kinrooi)"}},"ofd:offersFoodType":["ft:icecream"],"foaf:depiction":["http://www.rechtvanbijdeboer.be/sites/default/files/styles/producer_teaser/public/hoeve-ijs_engelenveld_buitenkant_inkom.jpg?itok=r2ZOWphY"],"schema:description":"","ofd:upstreamRel":[{"@type":"ofd:ActorRelationship","ofd:relatedContext":"at:producer","ofd:relatedActor":"https://w3id.org/openfooddata/actors/hoeveijs-engelenveld"}],"@id":"https://w3id.org/openfooddata/actors/hoeve-ijs-engelenveld","schema:name":"Hoeve-ijs Engelenveld","ofd:actorType":["at:pointOfSale","at:farmShop"]}}