{"type":"Feature","geometry":{"type":"Point","coordinates":[2.88466,50.952393]},"properties":{"id":"https://w3id.org/openfooddata/actors/hoevevlees-casier","name":"Hoevevlees Casier","img":[],"type":["at:pointOfSale","at:collectionPoint","at:producer"],"upstream":[],"downstream":[]}}