{"type":"Feature","geometry":{"type":"Point","coordinates":[4.435124,51.185003]},"properties":{"id":"https://w3id.org/openfooddata/actors/markt-berchem","name":"Markt Berchem","img":[],"type":["at:pointOfSale","at:market"],"upstream":[{"@type":"ofd:ActorRelationship","ofd:relatedContext":"at:producer","ofd:relatedActor":"https://w3id.org/openfooddata/actors/biohofke"}]}}