{"type":"Feature","geometry":{"type":"Point","coordinates":[4.386995,50.837767]},"properties":{"foaf:account":[],"foaf:name":"Buurderij Etterbeek","foaf:isPrimaryTopicOf":["http://www.rechtvanbijdeboer.be/buurderij-etterbeek","http://www.rechtvanbijdeboer.be/node/2046"],"@type":"foaf:Agent","schema:image":[],"@context":"https://openfooddata.github.io/actors/_common/context.jsonld","schema:geo":{"schema:latitude":"50.837767","schema:longitude":"4.386995","@type":"schema:GeoCoordinates","schema:addressCountry":"Belgium","schema:address":{"@type":"schema:PostalAddress","schema:streetAddress":"Rue du Cornet 97","schema:postalCode":"1040","schema:addressLocality":"Etterbeek"}},"ofd:offersFoodType":["ft:fruits"],"foaf:depiction":[],"schema:description":"","ofd:upstreamRel":[{"@type":"ofd:ActorRelationship","ofd:relatedContext":"at:producer","ofd:relatedActor":"https://w3id.org/openfooddata/actors/t-fruitratje"},{"@type":"ofd:ActorRelationship","ofd:relatedContext":"at:producer","ofd:relatedActor":"https://w3id.org/openfooddata/actors/bo&co"}],"@id":"https://w3id.org/openfooddata/actors/buurderij-etterbeek","extraHeader":"<link rel=\"alternate\" href=\"buurderij-etterbeek.rdf\" type=\"application/rdf+xml\"/>\n<link rel=\"alternate\" href=\"buurderij-etterbeek.jsonld\" type=\"application/ld+json\"/>\n<link rel=\"alternate\" href=\"buurderij-etterbeek.nq\" type=\"application/n-quads\"/>\n<link rel=\"alternate\" href=\"buurderij-etterbeek.nt\" type=\"application/n-triples\"/>\n<link rel=\"alternate\" href=\"buurderij-etterbeek.ttl\" type=\"text/turtle\"/>\n<link rel=\"alternate\" href=\"buurderij-etterbeek.rj\" type=\"application/rdf+json\"/>\n<link rel=\"alternate\" href=\"buurderij-etterbeek.trig\" type=\"text/trig\"/>\n<link rel=\"alternate\" href=\"buurderij-etterbeek.trix\" type=\"application/trix\"/>\n","schema:name":"Buurderij Etterbeek","ofd:actorType":["at:pointOfSale","at:foodAssembly"]}}