{"type":"Feature","geometry":{"type":"Point","coordinates":[5.420108,50.745403]},"properties":{"id":"https://w3id.org/openfooddata/actors/baillien","name":"Baillien","img":["http://www.rechtvanbijdeboer.be/sites/default/files/16105634_1389955867721585_6965783432440328089_n_0.jpg"],"type":["at:pointOfSale","at:vendingMachine","at:producer"],"upstream":[],"downstream":[]}}