{"type":"Feature","geometry":{"type":"Point","coordinates":[3.233989,51.132134]},"properties":{"id":"https://w3id.org/openfooddata/actors/wwwbuythuysbe","name":"www.buythuys.be","img":[],"type":["at:pointOfSale","at:webshop"],"upstream":[{"@type":"ofd:ActorRelationship","ofd:relatedContext":"at:producer","ofd:relatedActor":"https://w3id.org/openfooddata/actors/vleeshoeve-buythuys"}]}}