{"type":"Feature","geometry":{"type":"Point","coordinates":[3.282411,50.966894]},"properties":{"id":"https://w3id.org/openfooddata/actors/hoevewinkel-bij-delmotjes-0","name":"Hoevewinkel bij Delmotjes","img":["http://www.rechtvanbijdeboer.be/sites/default/files/styles/producer_teaser/public/bij_delmotjes_uithangbord_lr.jpg?itok=wo3cucDV"],"type":["at:pointOfSale","at:farmShop"],"upstream":[{"@type":"ofd:ActorRelationship","ofd:relatedContext":"at:producer","ofd:relatedActor":"https://w3id.org/openfooddata/actors/hoevewinkel-bij-delmotjes"}]}}