{"type":"Feature","geometry":{"type":"Point","coordinates":[3.715296,51.085621]},"properties":{"foaf:account":[],"foaf:name":"Slagerij Raemdonck - Van Hulle","foaf:isPrimaryTopicOf":["http://www.rechtvanbijdeboer.be/slagerij-raemdonck-van-hulle","http://www.rechtvanbijdeboer.be/node/2647"],"@type":"foaf:Agent","schema:image":["http://www.rechtvanbijdeboer.be/sites/default/files/styles/producer_teaser/public/foto0033.jpg?itok=lYisXwTC"],"@context":"https://openfooddata.github.io/actors/_common/context.jsonld","schema:geo":{"schema:latitude":"51.085621","schema:longitude":"3.715296","@type":"schema:GeoCoordinates","schema:addressCountry":"Belgium","schema:address":{"@type":"schema:PostalAddress","schema:streetAddress":"Molenstraat 123","schema:postalCode":"9032","schema:addressLocality":"Wondelgem"}},"ofd:offersFoodType":["ft:beef","ft:pork"],"foaf:depiction":["http://www.rechtvanbijdeboer.be/sites/default/files/styles/producer_teaser/public/foto0033.jpg?itok=lYisXwTC"],"schema:description":"","ofd:upstreamRel":[{"@type":"ofd:ActorRelationship","ofd:relatedContext":"at:producer","ofd:relatedActor":"https://w3id.org/openfooddata/actors/slagerij-raemdonck"}],"@id":"https://w3id.org/openfooddata/actors/slagerij-raemdonck-van-hulle","extraHeader":"<link rel=\"alternate\" href=\"slagerij-raemdonck-van-hulle.rdf\" type=\"application/rdf+xml\"/>\n<link rel=\"alternate\" href=\"slagerij-raemdonck-van-hulle.jsonld\" type=\"application/ld+json\"/>\n<link rel=\"alternate\" href=\"slagerij-raemdonck-van-hulle.nq\" type=\"application/n-quads\"/>\n<link rel=\"alternate\" href=\"slagerij-raemdonck-van-hulle.nt\" type=\"application/n-triples\"/>\n<link rel=\"alternate\" href=\"slagerij-raemdonck-van-hulle.ttl\" type=\"text/turtle\"/>\n<link rel=\"alternate\" href=\"slagerij-raemdonck-van-hulle.rj\" type=\"application/rdf+json\"/>\n<link rel=\"alternate\" href=\"slagerij-raemdonck-van-hulle.trig\" type=\"text/trig\"/>\n<link rel=\"alternate\" href=\"slagerij-raemdonck-van-hulle.trix\" type=\"application/trix\"/>\n","schema:name":"Slagerij Raemdonck - Van Hulle","ofd:actorType":["at:pointOfSale","at:farmShop"]}}