{"type":"Feature","geometry":{"type":"Point","coordinates":[4.284193,51.160758]},"properties":{"foaf:account":[],"foaf:name":"Hollebeekhoeve","foaf:isPrimaryTopicOf":["http://www.rechtvanbijdeboer.be/hollebeekhoeve","http://www.rechtvanbijdeboer.be/node/2386"],"@type":"foaf:Agent","schema:image":["http://www.rechtvanbijdeboer.be/sites/default/files/styles/producer_teaser/public/043-hollebeekhoeve_aanwijzingsbord.jpg?itok=Gs8U47Le"],"@context":"https://openfooddata.github.io/actors/_common/context.jsonld","schema:geo":{"schema:latitude":"51.160758","schema:longitude":"4.284193","@type":"schema:GeoCoordinates","schema:addressCountry":"Belgium","schema:address":{"@type":"schema:PostalAddress","schema:streetAddress":"Hondenstraat 24","schema:postalCode":"9150","schema:addressLocality":"Kruibeke"}},"ofd:offersFoodType":["ft:eggs","ft:poultry_meat","ft:fruit_juices","ft:icecream","ft:milk_products"],"foaf:depiction":["http://www.rechtvanbijdeboer.be/sites/default/files/styles/producer_teaser/public/043-hollebeekhoeve_aanwijzingsbord.jpg?itok=Gs8U47Le"],"schema:description":"","ofd:upstreamRel":[{"@type":"ofd:ActorRelationship","ofd:relatedContext":"at:producer","ofd:relatedActor":"https://w3id.org/openfooddata/actors/hollebeekhoeve-nv"}],"@id":"https://w3id.org/openfooddata/actors/hollebeekhoeve","extraHeader":"<link rel=\"alternate\" href=\"hollebeekhoeve.rdf\" type=\"application/rdf+xml\"/>\n<link rel=\"alternate\" href=\"hollebeekhoeve.jsonld\" type=\"application/ld+json\"/>\n<link rel=\"alternate\" href=\"hollebeekhoeve.nq\" type=\"application/n-quads\"/>\n<link rel=\"alternate\" href=\"hollebeekhoeve.nt\" type=\"application/n-triples\"/>\n<link rel=\"alternate\" href=\"hollebeekhoeve.ttl\" type=\"text/turtle\"/>\n<link rel=\"alternate\" href=\"hollebeekhoeve.rj\" type=\"application/rdf+json\"/>\n<link rel=\"alternate\" href=\"hollebeekhoeve.trig\" type=\"text/trig\"/>\n<link rel=\"alternate\" href=\"hollebeekhoeve.trix\" type=\"application/trix\"/>\n","schema:name":"Hollebeekhoeve","ofd:actorType":["at:pointOfSale","at:farmShop"]}}