{"type":"Feature","geometry":{"type":"Point","coordinates":[4.072642,50.844428]},"properties":{"id":"https://w3id.org/openfooddata/actors/boerenmarkt-roosdaal-pamel","name":"Boerenmarkt Roosdaal - Pamel","img":[],"type":["at:pointOfSale","at:farmersMarket"],"upstream":[{"@type":"ofd:ActorRelationship","ofd:relatedContext":"at:producer","ofd:relatedActor":"https://w3id.org/openfooddata/actors/hoevebakkerij-de-haseleer"}]}}