{"type":"Feature","geometry":{"type":"Point","coordinates":[3.747202,51.036282]},"properties":{"foaf:account":[],"foaf:name":"Afhaalpunt Ledeberg","foaf:isPrimaryTopicOf":["http://www.rechtvanbijdeboer.be/afhaalpunt-ledeberg","http://www.rechtvanbijdeboer.be/node/3530"],"@type":"foaf:Agent","schema:image":[],"@context":"https://openfooddata.github.io/actors/_common/context.jsonld","schema:geo":{"schema:latitude":"51.036282","schema:longitude":"3.747202","@type":"schema:GeoCoordinates","schema:addressCountry":"Belgium","schema:address":{"@type":"schema:PostalAddress","schema:streetAddress":"E. Van Hoorebekestraat 90","schema:postalCode":"9050","schema:addressLocality":"Ledeberg"}},"ofd:offersFoodType":["ft:potatoes","ft:fruits","ft:bakery_products","ft:eggs","ft:fruit_juices","ft:spices","ft:beef","ft:alcoholic_beverages","ft:vegetables","ft:milk_products"],"foaf:depiction":[],"schema:description":"","ofd:upstreamRel":[{"@type":"ofd:ActorRelationship","ofd:relatedContext":"at:producer","ofd:relatedActor":"https://w3id.org/openfooddata/actors/de-wassende-maan"}],"@id":"https://w3id.org/openfooddata/actors/afhaalpunt-ledeberg","schema:name":"Afhaalpunt Ledeberg","ofd:actorType":["at:pointOfSale","at:vegetableSubscription"]}}