{"type":"Feature","geometry":{"type":"Point","coordinates":[4.156198,50.916926]},"properties":{"id":"https://w3id.org/openfooddata/actors/noten-de-ridder-1","name":"Noten De Ridder","img":[],"type":["at:pointOfSale","at:collectionPoint"],"upstream":[{"@type":"ofd:ActorRelationship","ofd:relatedContext":"at:producer","ofd:relatedActor":"https://w3id.org/openfooddata/actors/noten-de-ridder"}]}}