{"type":"Feature","geometry":{"type":"Point","coordinates":[3.05735,51.148995]},"properties":{"foaf:account":[],"foaf:name":"Bekegemse foie gras","schema:url":["http://www.foiegras-vanackere.com/"],"foaf:homepage":["http://www.foiegras-vanackere.com/"],"foaf:isPrimaryTopicOf":["http://www.rechtvanbijdeboer.be/bekegemse-foie-gras-0","http://www.rechtvanbijdeboer.be/node/2602","http://www.rechtvanbijdeboer.be/bekegemse-foie-gras","http://www.rechtvanbijdeboer.be/node/1199"],"@type":"foaf:Agent","schema:image":["http://www.rechtvanbijdeboer.be/sites/default/files/styles/producer_teaser/public/default_images/emptyImg.jpg?itok=6POw8xTv"],"@context":"https://openfooddata.github.io/actors/_common/context.jsonld","schema:geo":{"schema:latitude":"51.148995","schema:longitude":"3.057350","@type":"schema:GeoCoordinates","schema:addressCountry":"Belgium","schema:address":{"@type":"schema:PostalAddress","schema:streetAddress":"Doornhoekstraat 59","schema:postalCode":"8480","schema:addressLocality":"Bekegem"}},"ofd:offersFoodType":["ft:fruit_juices"],"foaf:depiction":["http://www.rechtvanbijdeboer.be/sites/default/files/styles/producer_teaser/public/default_images/emptyImg.jpg?itok=6POw8xTv"],"schema:description":"","ofd:upstreamRel":[],"schema:contactPoint":{"@type":"schema:ContactPoint","schema:telephone":["050813156"],"schema:email":["filip.callemeyn@gmail.com"],"foaf:homepage":["http://www.foiegras-vanackere.com/"],"schema:url":["http://www.foiegras-vanackere.com/"]},"ofd:downstreamRel":[{"@type":"ofd:ActorRelationship","ofd:relatedContext":"at:pointOfSale","ofd:relatedActor":"https://w3id.org/openfooddata/actors/foie-gras-canard-vanackere"}],"@id":"https://w3id.org/openfooddata/actors/bekegemse-foie-gras","schema:name":"Bekegemse foie gras","ofd:actorType":["at:pointOfSale","at:farmShop","at:producer"]}}