{"type":"Feature","geometry":{"type":"Point","coordinates":[3.496067,51.105976]},"properties":{"id":"https://w3id.org/openfooddata/actors/bachten-t-kloosterhof","name":"Bachten 't Kloosterhof","img":["http://www.rechtvanbijdeboer.be/sites/default/files/styles/producer_teaser/public/bachten-t_kloosterhof_binnenkant_winkel_lr.jpg?itok=BQX0TxO5"],"type":["at:pointOfSale","at:farmShop"],"upstream":[{"@type":"ofd:ActorRelationship","ofd:relatedContext":"at:producer","ofd:relatedActor":"https://w3id.org/openfooddata/actors/bachtent-kloosterhof"}]}}