{"type":"Feature","geometry":{"type":"Point","coordinates":[4.512954,50.820195]},"properties":{"foaf:account":[],"foaf:name":"Tervuren","foaf:isPrimaryTopicOf":["http://www.rechtvanbijdeboer.be/tervuren","http://www.rechtvanbijdeboer.be/node/2211"],"@type":"foaf:Agent","schema:image":[],"@context":"https://openfooddata.github.io/actors/_common/context.jsonld","schema:geo":{"schema:latitude":"50.820195","schema:longitude":"4.512954","@type":"schema:GeoCoordinates","schema:addressCountry":"Belgium","schema:address":{"@type":"schema:PostalAddress","schema:streetAddress":"Bergestraat","schema:postalCode":"3080","schema:addressLocality":"Tervuren"}},"ofd:offersFoodType":["ft:potatoes","ft:fruits","ft:bakery_products","ft:eggs","ft:poultry_meat","ft:fruit_juices","ft:icecream","ft:spices","ft:lamb_meat","ft:beef","ft:pork","ft:alcoholic_beverages","ft:vegetables","ft:milk_products"],"foaf:depiction":[],"schema:description":"","ofd:upstreamRel":[],"@id":"https://w3id.org/openfooddata/actors/tervuren","extraHeader":"<link rel=\"alternate\" href=\"tervuren.rdf\" type=\"application/rdf+xml\"/>\n<link rel=\"alternate\" href=\"tervuren.jsonld\" type=\"application/ld+json\"/>\n<link rel=\"alternate\" href=\"tervuren.nq\" type=\"application/n-quads\"/>\n<link rel=\"alternate\" href=\"tervuren.nt\" type=\"application/n-triples\"/>\n<link rel=\"alternate\" href=\"tervuren.ttl\" type=\"text/turtle\"/>\n<link rel=\"alternate\" href=\"tervuren.rj\" type=\"application/rdf+json\"/>\n<link rel=\"alternate\" href=\"tervuren.trig\" type=\"text/trig\"/>\n<link rel=\"alternate\" href=\"tervuren.trix\" type=\"application/trix\"/>\n","schema:name":"Tervuren","ofd:actorType":["at:pointOfSale","at:foodTeams"]}}