{"type":"Feature","geometry":{"type":"Point","coordinates":[4.64159,51.149509]},"properties":{"id":"https://w3id.org/openfooddata/actors/opnieuw-co","name":"Opnieuw & Co","img":[],"type":["at:pointOfSale","at:collectionPoint"],"upstream":[{"@type":"ofd:ActorRelationship","ofd:relatedContext":"at:producer","ofd:relatedActor":"https://w3id.org/openfooddata/actors/t-meulenhuys"}]}}