{"type":"Feature","geometry":{"type":"Point","coordinates":[2.828522,50.90952]},"properties":{"id":"https://w3id.org/openfooddata/actors/fruit-vervisch","name":"Fruit vervisch","img":["http://www.rechtvanbijdeboer.be/sites/default/files/styles/producer_teaser/public/marktkraam.jpg?itok=G0fIUFhH","http://www.rechtvanbijdeboer.be/sites/default/files/styles/producer_teaser/public/appels.jpg?itok=gZQv_Ega","http://www.rechtvanbijdeboer.be/sites/default/files/styles/producer_teaser/public/peren.jpg?itok=9Y9GPU4U","http://www.rechtvanbijdeboer.be/sites/default/files/styles/producer_teaser/public/winkel_0.jpg?itok=NhhWiOJ7"],"type":["at:pointOfSale","at:farmShop","at:producer"],"upstream":[],"downstream":[{"@type":"ofd:ActorRelationship","ofd:relatedContext":"at:pointOfSale","ofd:relatedActor":"https://w3id.org/openfooddata/actors/plukdag-bij-fruit-vervisch"},{"@type":"ofd:ActorRelationship","ofd:relatedContext":"at:pointOfSale","ofd:relatedActor":"https://w3id.org/openfooddata/actors/boerenmarkt-diksmuide"}]}}