{"type":"Feature","geometry":{"type":"Point","coordinates":[3.973508,51.186366]},"properties":{"foaf:account":[],"foaf:name":"Oxfam Moerbeke","foaf:isPrimaryTopicOf":["http://www.rechtvanbijdeboer.be/oxfam-moerbeke","http://www.rechtvanbijdeboer.be/node/2375"],"@type":"foaf:Agent","schema:image":["http://www.rechtvanbijdeboer.be/sites/default/files/styles/producer_teaser/public/de_vierklaver_hoeveslagerij_buitenkant_winkel.jpg?itok=WLfllS0H"],"@context":"https://openfooddata.github.io/actors/_common/context.jsonld","schema:geo":{"schema:latitude":"51.186366","schema:longitude":"3.973508","@type":"schema:GeoCoordinates","schema:addressCountry":"Belgium","schema:address":{"@type":"schema:PostalAddress","schema:streetAddress":"Oostvaart 63","schema:postalCode":"9180","schema:addressLocality":"Moerbeke"}},"ofd:offersFoodType":["ft:potatoes","ft:eggs","ft:poultry_meat","ft:fruit_juices","ft:icecream","ft:lamb_meat","ft:beef","ft:pork","ft:alcoholic_beverages","ft:vegetables","ft:milk_products"],"foaf:depiction":["http://www.rechtvanbijdeboer.be/sites/default/files/styles/producer_teaser/public/de_vierklaver_hoeveslagerij_buitenkant_winkel.jpg?itok=WLfllS0H"],"schema:description":"","ofd:upstreamRel":[{"@type":"ofd:ActorRelationship","ofd:relatedContext":"at:producer","ofd:relatedActor":"https://w3id.org/openfooddata/actors/hoeveslagerij-de-vierklaver"}],"@id":"https://w3id.org/openfooddata/actors/oxfam-moerbeke","schema:name":"Oxfam Moerbeke","ofd:actorType":["at:pointOfSale","at:collectionPoint"]}}