{"type":"Feature","geometry":{"type":"Point","coordinates":[4.087534,50.956948]},"properties":{"id":"https://w3id.org/openfooddata/actors/zorgboerderij-boer-dirk-3","name":"Zorgboerderij Boer Dirk","img":["http://www.rechtvanbijdeboer.be/sites/default/files/styles/producer_teaser/public/17295_940792232611432_8246600415968225218_n.jpg?itok=skuauEpt"],"type":["at:pointOfSale","at:farmShop"],"upstream":[{"@type":"ofd:ActorRelationship","ofd:relatedContext":"at:producer","ofd:relatedActor":"https://w3id.org/openfooddata/actors/zorgboerderij-boer-dirk"}]}}