{"type":"Feature","geometry":{"type":"Point","coordinates":[4.373661,50.93795]},"properties":{"id":"https://w3id.org/openfooddata/actors/wwwdiepenboomgaardbewebshop","name":"www.diepenboomgaard.be/webshop","img":["http://www.rechtvanbijdeboer.be/sites/default/files/styles/producer_teaser/public/fotosessiestreekprodukten%20%2846%29_1.jpg?itok=P8yY02ej"],"type":["at:pointOfSale","at:webshop"],"upstream":[{"@type":"ofd:ActorRelationship","ofd:relatedContext":"at:producer","ofd:relatedActor":"https://w3id.org/openfooddata/actors/den-diepen-boomgaard"}]}}