{"type":"Feature","geometry":{"type":"Point","coordinates":[2.74399,50.980192]},"properties":{"foaf:account":[],"foaf:name":"Aurelia","foaf:isPrimaryTopicOf":["http://www.rechtvanbijdeboer.be/aurelia","http://www.rechtvanbijdeboer.be/node/3338"],"@type":"foaf:Agent","schema:image":[],"@context":"https://openfooddata.github.io/actors/_common/context.jsonld","schema:geo":{"schema:latitude":"50.980192","schema:longitude":"2.743990","@type":"schema:GeoCoordinates","schema:addressCountry":"Belgium","schema:address":{"@type":"schema:PostalAddress","schema:streetAddress":"Weststraat 17-19","schema:postalCode":"8647","schema:addressLocality":"Lo"}},"ofd:offersFoodType":["ft:potatoes","ft:vegetables"],"foaf:depiction":[],"schema:description":"","ofd:upstreamRel":[{"@type":"ofd:ActorRelationship","ofd:relatedContext":"at:producer","ofd:relatedActor":"https://w3id.org/openfooddata/actors/de-lovie"}],"@id":"https://w3id.org/openfooddata/actors/aurelia","extraHeader":"<link rel=\"alternate\" href=\"aurelia.rdf\" type=\"application/rdf+xml\"/>\n<link rel=\"alternate\" href=\"aurelia.jsonld\" type=\"application/ld+json\"/>\n<link rel=\"alternate\" href=\"aurelia.nq\" type=\"application/n-quads\"/>\n<link rel=\"alternate\" href=\"aurelia.nt\" type=\"application/n-triples\"/>\n<link rel=\"alternate\" href=\"aurelia.ttl\" type=\"text/turtle\"/>\n<link rel=\"alternate\" href=\"aurelia.rj\" type=\"application/rdf+json\"/>\n<link rel=\"alternate\" href=\"aurelia.trig\" type=\"text/trig\"/>\n<link rel=\"alternate\" href=\"aurelia.trix\" type=\"application/trix\"/>\n","schema:name":"Aurelia","ofd:actorType":["at:pointOfSale","at:collectionPoint"]}}