{"type":"Feature","geometry":{"type":"Point","coordinates":[3.124672,51.041676]},"properties":{"foaf:account":[{"@type":"foaf:OnlineAccount","@id":"https://www.facebook.com/pages/Het-Merelhof/273252196046672?fref=ts","skos:prefLabel":"Facebook","foaf:accountServiceHomepage":"https://www.facebook.com","foaf:accountName":"Het-Merelhof","dct:identifier":"273252196046672?fref=ts"}],"foaf:name":"Het Merelhof","schema:url":["http://www.hetmerelhof.be"],"foaf:homepage":["http://www.hetmerelhof.be"],"foaf:isPrimaryTopicOf":["http://www.rechtvanbijdeboer.be/het-merelhof-0","http://www.rechtvanbijdeboer.be/node/2706","http://www.rechtvanbijdeboer.be/het-merelhof","http://www.rechtvanbijdeboer.be/node/1278"],"@type":"foaf:Agent","schema:image":["http://www.rechtvanbijdeboer.be/sites/default/files/styles/producer_teaser/public/default_images/emptyImg.jpg?itok=6POw8xTv"],"@context":"https://openfooddata.github.io/actors/_common/context.jsonld","schema:geo":{"schema:latitude":"51.041676","schema:longitude":"3.124672","@type":"schema:GeoCoordinates","schema:addressCountry":"Belgium","schema:address":{"@type":"schema:PostalAddress","schema:streetAddress":"Merelstraat 5","schema:postalCode":"8810","schema:addressLocality":"Lichtervelde"}},"ofd:offersFoodType":["ft:fruit_juices","ft:eggs","ft:pork","ft:beef"],"foaf:depiction":["http://www.rechtvanbijdeboer.be/sites/default/files/styles/producer_teaser/public/default_images/emptyImg.jpg?itok=6POw8xTv"],"schema:description":"Hoeveslagerij 'Het Merelhof' is gelegen in het mooie landelijke Lichtervelde in de provincie West-Vlaanderen. in onze hoeveslagerij worden er varkens en hoevekippen versneden van eigen kweek , de runderen worden bij lokale veekweker gekocht. Je kan ons vinden op markten.","ofd:upstreamRel":[],"schema:contactPoint":{"@type":"schema:ContactPoint","schema:telephone":["051/722409","0474/978254"],"schema:email":["eric.lavens@telenet.be"],"foaf:homepage":["http://www.hetmerelhof.be"],"schema:url":["http://www.hetmerelhof.be"]},"ofd:downstreamRel":[],"@id":"https://w3id.org/openfooddata/actors/het-merelhof","extraHeader":"<link rel=\"alternate\" href=\"het-merelhof.rdf\" type=\"application/rdf+xml\"/>\n<link rel=\"alternate\" href=\"het-merelhof.jsonld\" type=\"application/ld+json\"/>\n<link rel=\"alternate\" href=\"het-merelhof.nq\" type=\"application/n-quads\"/>\n<link rel=\"alternate\" href=\"het-merelhof.nt\" type=\"application/n-triples\"/>\n<link rel=\"alternate\" href=\"het-merelhof.ttl\" type=\"text/turtle\"/>\n<link rel=\"alternate\" href=\"het-merelhof.rj\" type=\"application/rdf+json\"/>\n<link rel=\"alternate\" href=\"het-merelhof.trig\" type=\"text/trig\"/>\n<link rel=\"alternate\" href=\"het-merelhof.trix\" type=\"application/trix\"/>\n","schema:name":"Het Merelhof","ofd:actorType":["at:pointOfSale","at:farmShop","at:producer"]}}