{"type":"Feature","geometry":{"type":"Point","coordinates":[3.230066,50.92265]},"properties":{"id":"https://w3id.org/openfooddata/actors/buurderij-izegem","name":"Buurderij Izegem","img":["http://www.rechtvanbijdeboer.be/sites/default/files/styles/producer_teaser/public/11991329_901870156573777_318383248_o.jpg?itok=P-KLTTMa"],"type":["at:pointOfSale","at:foodAssembly"],"upstream":[{"@type":"ofd:ActorRelationship","ofd:relatedContext":"at:producer","ofd:relatedActor":"https://w3id.org/openfooddata/actors/heidi-popelier"},{"@type":"ofd:ActorRelationship","ofd:relatedContext":"at:producer","ofd:relatedActor":"https://w3id.org/openfooddata/actors/varkenshoeve-klein-gistelgoed"},{"@type":"ofd:ActorRelationship","ofd:relatedContext":"at:producer","ofd:relatedActor":"https://w3id.org/openfooddata/actors/zuivelboerderij-ter-vluggebusch"}]}}