{"type":"Feature","geometry":{"type":"Point","coordinates":[3.911756,50.749943]},"properties":{"id":"https://w3id.org/openfooddata/actors/lf-meat-0","name":"L&F Meat","img":[],"type":["at:pointOfSale","at:farmShop"],"upstream":[{"@type":"ofd:ActorRelationship","ofd:relatedContext":"at:producer","ofd:relatedActor":"https://w3id.org/openfooddata/actors/l&f-meat"}]}}