{"type":"Feature","geometry":{"type":"Point","coordinates":[4.407787,50.823411]},"properties":{"foaf:account":[],"foaf:name":"Superboni","foaf:isPrimaryTopicOf":["http://www.rechtvanbijdeboer.be/superboni","http://www.rechtvanbijdeboer.be/node/2413"],"@type":"foaf:Agent","schema:image":["http://www.rechtvanbijdeboer.be/sites/default/files/styles/producer_teaser/public/biobellogroentenenfruitmaxi.jpg?itok=n2EToMw3"],"@context":"https://openfooddata.github.io/actors/_common/context.jsonld","schema:geo":{"schema:latitude":"50.823411","schema:longitude":"4.407787","@type":"schema:GeoCoordinates","schema:addressCountry":"Belgium","schema:address":{"@type":"schema:PostalAddress","schema:streetAddress":"Edouard Henrardstraat 7","schema:postalCode":"1160","schema:addressLocality":"Oudergem"}},"ofd:offersFoodType":["ft:potatoes","ft:fruits","ft:eggs","ft:vegetables"],"foaf:depiction":["http://www.rechtvanbijdeboer.be/sites/default/files/styles/producer_teaser/public/biobellogroentenenfruitmaxi.jpg?itok=n2EToMw3"],"schema:description":"","ofd:upstreamRel":[{"@type":"ofd:ActorRelationship","ofd:relatedContext":"at:producer","ofd:relatedActor":"https://w3id.org/openfooddata/actors/de-lochting-vzw"}],"@id":"https://w3id.org/openfooddata/actors/superboni","schema:name":"Superboni","ofd:actorType":["at:pointOfSale","at:vegetableSubscription"]}}