{"type":"Feature","geometry":{"type":"Point","coordinates":[5.113631,51.183233]},"properties":{"foaf:account":[],"foaf:name":"Herba","foaf:isPrimaryTopicOf":["http://www.rechtvanbijdeboer.be/herba-0","http://www.rechtvanbijdeboer.be/node/2789"],"@type":"foaf:Agent","schema:image":[],"@context":"https://openfooddata.github.io/actors/_common/context.jsonld","schema:geo":{"schema:latitude":"51.183233","schema:longitude":"5.113631","@type":"schema:GeoCoordinates","schema:addressCountry":"Belgium","schema:address":{"@type":"schema:PostalAddress","schema:streetAddress":"Markt 48","schema:postalCode":"2400","schema:addressLocality":"Mol"}},"ofd:offersFoodType":["ft:potatoes","ft:vegetables"],"foaf:depiction":[],"schema:description":"","ofd:upstreamRel":[{"@type":"ofd:ActorRelationship","ofd:relatedContext":"at:producer","ofd:relatedActor":"https://w3id.org/openfooddata/actors/de-bio-hoeve"}],"@id":"https://w3id.org/openfooddata/actors/herba-0","schema:name":"Herba","ofd:actorType":["at:pointOfSale","at:vegetableSubscription"]}}