{"type":"Feature","geometry":{"type":"Point","coordinates":[3.576851,51.273701]},"properties":{"foaf:account":[],"foaf:name":"Van Hyfte","schema:url":[],"foaf:homepage":[],"foaf:isPrimaryTopicOf":["http://www.rechtvanbijdeboer.be/van-hyfte-0","http://www.rechtvanbijdeboer.be/node/3096","https://www.rechtvanbijdeboer.be/van-hyfte","https://www.rechtvanbijdeboer.be/node/1603"],"@type":"foaf:Agent","schema:image":[],"@context":"https://openfooddata.github.io/actors/_common/context.jsonld","schema:geo":{"schema:latitude":"51.273701","schema:longitude":"3.576851","@type":"schema:GeoCoordinates","schema:addressCountry":"Belgium","schema:address":{"@type":"schema:PostalAddress","schema:streetAddress":"Moerstraat 28","schema:postalCode":"9982","schema:addressLocality":"Sint-Jan-In-Eremo"}},"ofd:offersFoodType":["ft:vegetables","ft:potatoes"],"foaf:depiction":[],"schema:description":"","ofd:upstreamRel":[],"ofd:downstreamRel":[],"@id":"https://w3id.org/openfooddata/actors/van-hyfte","schema:name":"Van Hyfte","ofd:actorType":["at:pointOfSale","at:farmShop","at:producer"]}}