{"type":"Feature","geometry":{"type":"Point","coordinates":[3.576851,51.273701]},"properties":{"foaf:account":[],"foaf:name":"Van Hyfte","schema:url":[],"foaf:homepage":[],"foaf:isPrimaryTopicOf":["http://www.rechtvanbijdeboer.be/van-hyfte-0","http://www.rechtvanbijdeboer.be/node/3096","https://www.rechtvanbijdeboer.be/van-hyfte","https://www.rechtvanbijdeboer.be/node/1603"],"@type":"foaf:Agent","schema:image":[],"@context":"https://openfooddata.github.io/actors/_common/context.jsonld","schema:geo":{"schema:latitude":"51.273701","schema:longitude":"3.576851","@type":"schema:GeoCoordinates","schema:addressCountry":"Belgium","schema:address":{"@type":"schema:PostalAddress","schema:streetAddress":"Moerstraat 28","schema:postalCode":"9982","schema:addressLocality":"Sint-Jan-In-Eremo"}},"ofd:offersFoodType":["ft:vegetables","ft:potatoes"],"foaf:depiction":[],"schema:description":"","ofd:upstreamRel":[],"ofd:downstreamRel":[],"@id":"https://w3id.org/openfooddata/actors/van-hyfte","extraHeader":"<link rel=\"alternate\" href=\"van-hyfte.rdf\" type=\"application/rdf+xml\"/>\n<link rel=\"alternate\" href=\"van-hyfte.jsonld\" type=\"application/ld+json\"/>\n<link rel=\"alternate\" href=\"van-hyfte.nq\" type=\"application/n-quads\"/>\n<link rel=\"alternate\" href=\"van-hyfte.nt\" type=\"application/n-triples\"/>\n<link rel=\"alternate\" href=\"van-hyfte.ttl\" type=\"text/turtle\"/>\n<link rel=\"alternate\" href=\"van-hyfte.rj\" type=\"application/rdf+json\"/>\n<link rel=\"alternate\" href=\"van-hyfte.trig\" type=\"text/trig\"/>\n<link rel=\"alternate\" href=\"van-hyfte.trix\" type=\"application/trix\"/>\n","schema:name":"Van Hyfte","ofd:actorType":["at:pointOfSale","at:farmShop","at:producer"]}}