{"type":"Feature","geometry":{"type":"Point","coordinates":[4.167706,51.201339]},"properties":{"id":"https://w3id.org/openfooddata/actors/bij-griet","name":"Bij Griet","img":["http://www.rechtvanbijdeboer.be/sites/default/files/styles/producer_teaser/public/tine-s_groentemandjes_pakket_groenten_lr.jpg?itok=44D5Ogap"],"type":["at:pointOfSale","at:collectionPoint"],"upstream":[{"@type":"ofd:ActorRelationship","ofd:relatedContext":"at:producer","ofd:relatedActor":"https://w3id.org/openfooddata/actors/tines-groentemandjes"}]}}