{"type":"Feature","geometry":{"type":"Point","coordinates":[5.150214,50.98078]},"properties":{"id":"https://w3id.org/openfooddata/actors/goerenhof","name":"Goerenhof","img":["http://www.rechtvanbijdeboer.be/sites/default/files/styles/producer_teaser/public/IMG_0311.JPG?itok=qXCIzotY"],"type":["at:pointOfSale","at:farmShop"],"upstream":[{"@type":"ofd:ActorRelationship","ofd:relatedContext":"at:producer","ofd:relatedActor":"https://w3id.org/openfooddata/actors/herkenrodeboer"}]}}