{"type":"Feature","geometry":{"type":"Point","coordinates":[3.588937,50.89384]},"properties":{"id":"https://w3id.org/openfooddata/actors/kapellehof","name":"Kapellehof","img":[],"type":["at:pointOfSale","at:farmShop","at:producer"],"upstream":[],"downstream":[]}}