{"type":"Feature","geometry":{"type":"Point","coordinates":[4.829106,51.176893]},"properties":{"id":"https://w3id.org/openfooddata/actors/van-eccelpoel","name":"Van Eccelpoel","img":[],"type":["at:pointOfSale","at:vegetableSubscription"],"upstream":[{"@type":"ofd:ActorRelationship","ofd:relatedContext":"at:producer","ofd:relatedActor":"https://w3id.org/openfooddata/actors/de-bio-hoeve"}]}}