{"type":"Feature","geometry":{"type":"Point","coordinates":[5.520022,51.256943]},"properties":{"id":"https://w3id.org/openfooddata/actors/hoevewinkel-beli%C3%ABn-sevens","name":"Hoevewinkel Beliën-Sevens","img":["http://www.rechtvanbijdeboer.be/sites/default/files/styles/producer_teaser/public/Beli%C3%ABn_Sevens_aardappelen_oogsten_producent_kindjes.jpg?itok=vLnYRTfK"],"type":["at:pointOfSale","at:farmShop"],"upstream":[{"@type":"ofd:ActorRelationship","ofd:relatedContext":"at:producer","ofd:relatedActor":"https://w3id.org/openfooddata/actors/beli%C3%ABn-sevens"}]}}