{"type":"Feature","geometry":{"type":"Point","coordinates":[4.656883,50.922369]},"properties":{"id":"https://w3id.org/openfooddata/actors/voedselteam-herent-doren","name":"Voedselteam Herent Doren","img":["http://www.rechtvanbijdeboer.be/sites/default/files/styles/producer_teaser/public/40c25724f17bcae1a710c550fb091562.jpg?itok=DZZ83o0e"],"type":["at:pointOfSale","at:foodTeams"],"upstream":[{"@type":"ofd:ActorRelationship","ofd:relatedContext":"at:producer","ofd:relatedActor":"https://w3id.org/openfooddata/actors/vzw-de-winning-maatwerk"},{"@type":"ofd:ActorRelationship","ofd:relatedContext":"at:producer","ofd:relatedActor":"https://w3id.org/openfooddata/actors/de-ploeg"},{"@type":"ofd:ActorRelationship","ofd:relatedContext":"at:producer","ofd:relatedActor":"https://w3id.org/openfooddata/actors/fv-van-haesendonck"},{"@type":"ofd:ActorRelationship","ofd:relatedContext":"at:producer","ofd:relatedActor":"https://w3id.org/openfooddata/actors/de-levende-aarde-cvba"},{"@type":"ofd:ActorRelationship","ofd:relatedContext":"at:producer","ofd:relatedActor":"https://w3id.org/openfooddata/actors/regalys"},{"@type":"ofd:ActorRelationship","ofd:relatedContext":"at:producer","ofd:relatedActor":"https://w3id.org/openfooddata/actors/de-appelfabriek"},{"@type":"ofd:ActorRelationship","ofd:relatedContext":"at:producer","ofd:relatedActor":"https://w3id.org/openfooddata/actors/wonen-&-werken-de-wikke"}]}}