{"type":"Feature","geometry":{"type":"Point","coordinates":[2.729766,50.859402]},"properties":{"foaf:account":[],"foaf:name":"Voedselteam Poperinge","foaf:isPrimaryTopicOf":["http://www.rechtvanbijdeboer.be/voedselteam-poperinge","http://www.rechtvanbijdeboer.be/node/2281"],"@type":"foaf:Agent","schema:image":["http://www.rechtvanbijdeboer.be/sites/default/files/styles/producer_teaser/public/1_0.JPG?itok=BNjJf1vK"],"@context":"https://openfooddata.github.io/actors/_common/context.jsonld","schema:geo":{"schema:latitude":"50.859402","schema:longitude":"2.729766","@type":"schema:GeoCoordinates","schema:addressCountry":"Belgium","schema:address":{"@type":"schema:PostalAddress","schema:streetAddress":"Veurnestraat","schema:postalCode":"8970","schema:addressLocality":"Poperinge"}},"ofd:offersFoodType":["ft:lamb_meat","ft:icecream","ft:milk_products","ft:vegetables","ft:poultry_meat","ft:fruits","ft:bakery_products","ft:fruit_juices","ft:beef","ft:pork"],"foaf:depiction":["http://www.rechtvanbijdeboer.be/sites/default/files/styles/producer_teaser/public/1_0.JPG?itok=BNjJf1vK"],"schema:description":"","ofd:upstreamRel":[{"@type":"ofd:ActorRelationship","ofd:relatedContext":"at:producer","ofd:relatedActor":"https://w3id.org/openfooddata/actors/vleeshoeve-sint-pieterke"},{"@type":"ofd:ActorRelationship","ofd:relatedContext":"at:producer","ofd:relatedActor":"https://w3id.org/openfooddata/actors/den-overdraght,-lamsvlees-op-bestelling"},{"@type":"ofd:ActorRelationship","ofd:relatedContext":"at:producer","ofd:relatedActor":"https://w3id.org/openfooddata/actors/t-foncierhof"},{"@type":"ofd:ActorRelationship","ofd:relatedContext":"at:producer","ofd:relatedActor":"https://w3id.org/openfooddata/actors/bio-bedijf-hebben-van-driessche"},{"@type":"ofd:ActorRelationship","ofd:relatedContext":"at:producer","ofd:relatedActor":"https://w3id.org/openfooddata/actors/tuinsappen-lombarts-calville"},{"@type":"ofd:ActorRelationship","ofd:relatedContext":"at:producer","ofd:relatedActor":"https://w3id.org/openfooddata/actors/het-warandehof"},{"@type":"ofd:ActorRelationship","ofd:relatedContext":"at:producer","ofd:relatedActor":"https://w3id.org/openfooddata/actors/hoeveslagerij-t-lindebos"},{"@type":"ofd:ActorRelationship","ofd:relatedContext":"at:producer","ofd:relatedActor":"https://w3id.org/openfooddata/actors/tuinsappen-lombarts-calville"},{"@type":"ofd:ActorRelationship","ofd:relatedContext":"at:producer","ofd:relatedActor":"https://w3id.org/openfooddata/actors/vanysacker"},{"@type":"ofd:ActorRelationship","ofd:relatedContext":"at:producer","ofd:relatedActor":"https://w3id.org/openfooddata/actors/baljuwhoeve---hoeve-verdonck"}],"@id":"https://w3id.org/openfooddata/actors/voedselteam-poperinge","schema:name":"Voedselteam Poperinge","ofd:actorType":["at:pointOfSale","at:foodTeams"]}}