{"type":"Feature","geometry":{"type":"Point","coordinates":[3.2748,51.05865]},"properties":{"id":"https://w3id.org/openfooddata/actors/wingene","name":"Wingene","img":[],"type":["at:pointOfSale","at:market"],"upstream":[{"@type":"ofd:ActorRelationship","ofd:relatedContext":"at:producer","ofd:relatedActor":"https://w3id.org/openfooddata/actors/t-hof-rozendale"}]}}