{"type":"Feature","geometry":{"type":"Point","coordinates":[3.552214,51.0318]},"properties":{"foaf:account":[],"foaf:name":"Afhaalpunt Nevele Vosselare","foaf:isPrimaryTopicOf":["http://www.rechtvanbijdeboer.be/afhaalpunt-nevele-vosselare","http://www.rechtvanbijdeboer.be/node/3550"],"@type":"foaf:Agent","schema:image":[],"@context":"https://openfooddata.github.io/actors/_common/context.jsonld","schema:geo":{"schema:latitude":"51.031800","schema:longitude":"3.552214","@type":"schema:GeoCoordinates","schema:addressCountry":"Belgium","schema:address":{"@type":"schema:PostalAddress","schema:streetAddress":"Langemunt 18","schema:postalCode":"9850","schema:addressLocality":"Nevele"}},"ofd:offersFoodType":["ft:potatoes","ft:fruits","ft:bakery_products","ft:eggs","ft:fruit_juices","ft:spices","ft:beef","ft:alcoholic_beverages","ft:vegetables","ft:milk_products"],"foaf:depiction":[],"schema:description":"","ofd:upstreamRel":[{"@type":"ofd:ActorRelationship","ofd:relatedContext":"at:producer","ofd:relatedActor":"https://w3id.org/openfooddata/actors/de-wassende-maan"}],"@id":"https://w3id.org/openfooddata/actors/afhaalpunt-nevele-vosselare","extraHeader":"<link rel=\"alternate\" href=\"afhaalpunt-nevele-vosselare.rdf\" type=\"application/rdf+xml\"/>\n<link rel=\"alternate\" href=\"afhaalpunt-nevele-vosselare.jsonld\" type=\"application/ld+json\"/>\n<link rel=\"alternate\" href=\"afhaalpunt-nevele-vosselare.nq\" type=\"application/n-quads\"/>\n<link rel=\"alternate\" href=\"afhaalpunt-nevele-vosselare.nt\" type=\"application/n-triples\"/>\n<link rel=\"alternate\" href=\"afhaalpunt-nevele-vosselare.ttl\" type=\"text/turtle\"/>\n<link rel=\"alternate\" href=\"afhaalpunt-nevele-vosselare.rj\" type=\"application/rdf+json\"/>\n<link rel=\"alternate\" href=\"afhaalpunt-nevele-vosselare.trig\" type=\"text/trig\"/>\n<link rel=\"alternate\" href=\"afhaalpunt-nevele-vosselare.trix\" type=\"application/trix\"/>\n","schema:name":"Afhaalpunt Nevele Vosselare","ofd:actorType":["at:pointOfSale","at:vegetableSubscription"]}}