{"type":"Feature","geometry":{"type":"Point","coordinates":[4.158817,51.123824]},"properties":{"id":"https://w3id.org/openfooddata/actors/de-wollebol","name":"De Wollebol","img":[],"type":["at:pointOfSale","at:farmShop","at:producer"],"upstream":[],"downstream":[]}}