{"type":"Feature","geometry":{"type":"Point","coordinates":[4.774289,51.100126]},"properties":{"foaf:account":[{"@type":"foaf:OnlineAccount","@id":"https://www.facebook.com/boerderijdewittelelie","skos:prefLabel":"Facebook","foaf:accountServiceHomepage":"https://www.facebook.com","foaf:accountName":"https:","dct:identifier":""}],"foaf:name":"De Witte Lelie","schema:url":[],"foaf:homepage":[],"foaf:isPrimaryTopicOf":["http://www.rechtvanbijdeboer.be/de-witte-lelie-0","http://www.rechtvanbijdeboer.be/node/2908","http://www.rechtvanbijdeboer.be/de-witte-lelie","http://www.rechtvanbijdeboer.be/node/1426"],"@type":"foaf:Agent","schema:image":["http://www.rechtvanbijdeboer.be/sites/default/files/styles/producer_teaser/public/pia2.jpg?itok=YfYMHthE","http://www.rechtvanbijdeboer.be/sites/default/files/styles/producer_teaser/public/10805846_814260991964598_3711691333705069181_n.jpg?itok=-rK8E0Mb","http://www.rechtvanbijdeboer.be/sites/default/files/styles/producer_teaser/public/koe.jpg?itok=Bv_QD_6B"],"@context":"https://openfooddata.github.io/actors/_common/context.jsonld","schema:geo":{"schema:latitude":"51.100126","schema:longitude":"4.774289","@type":"schema:GeoCoordinates","schema:addressCountry":"Belgium","schema:address":{"@type":"schema:PostalAddress","schema:streetAddress":"Itegemseweg 98","schema:postalCode":"2222","schema:addressLocality":"Wiekevorst"}},"ofd:offersFoodType":["ft:milk_products","ft:eggs","ft:icecream"],"foaf:depiction":["http://www.rechtvanbijdeboer.be/sites/default/files/styles/producer_teaser/public/pia2.jpg?itok=YfYMHthE","http://www.rechtvanbijdeboer.be/sites/default/files/styles/producer_teaser/public/10805846_814260991964598_3711691333705069181_n.jpg?itok=-rK8E0Mb","http://www.rechtvanbijdeboer.be/sites/default/files/styles/producer_teaser/public/koe.jpg?itok=Bv_QD_6B"],"schema:description":"Reeds meer dan 20 jaar verwerken wij op ons melkveebedrijf onze melk tot allerlei lekkers. Gaande van boter en boerenchoco voor tussen de boterham, zachte plattekaas en yoghurt als tussendoortje tot lekkere dessertjes en hoeveijs.","ofd:upstreamRel":[],"schema:contactPoint":{"@type":"schema:ContactPoint","schema:telephone":["014265908"],"schema:email":["marc-en-ingrid@hotmail.com"],"foaf:homepage":[],"schema:url":[]},"ofd:downstreamRel":[{"@type":"ofd:ActorRelationship","ofd:relatedContext":"at:pointOfSale","ofd:relatedActor":"https://w3id.org/openfooddata/actors/buurderij-permeke-antwerpen"},{"@type":"ofd:ActorRelationship","ofd:relatedContext":"at:pointOfSale","ofd:relatedActor":"https://w3id.org/openfooddata/actors/buurderij-wommelgem"},{"@type":"ofd:ActorRelationship","ofd:relatedContext":"at:pointOfSale","ofd:relatedActor":"https://w3id.org/openfooddata/actors/buurderij-cultuurcentrum-berchem"}],"@id":"https://w3id.org/openfooddata/actors/de-witte-lelie","schema:name":"De Witte Lelie","ofd:actorType":["at:pointOfSale","at:farmShop","at:producer"]}}