{"type":"Feature","geometry":{"type":"Point","coordinates":[5.222345,50.86613]},"properties":{"id":"https://w3id.org/openfooddata/actors/jacobsfruit","name":"Jacobsfruit","img":[],"type":["at:pointOfSale","at:producer","at:vendingMachine"],"upstream":[],"downstream":[]}}