{"type":"Feature","geometry":{"type":"Point","coordinates":[4.705327,50.886809]},"properties":{"foaf:account":[],"foaf:name":"Leuven OPEC","foaf:isPrimaryTopicOf":["http://www.rechtvanbijdeboer.be/leuven-opec","http://www.rechtvanbijdeboer.be/node/2182"],"@type":"foaf:Agent","schema:image":[],"@context":"https://openfooddata.github.io/actors/_common/context.jsonld","schema:geo":{"schema:latitude":"50.886809","schema:longitude":"4.705327","@type":"schema:GeoCoordinates","schema:addressCountry":"Belgium","schema:address":{"@type":"schema:PostalAddress","schema:streetAddress":"Stapelhuisstraat","schema:postalCode":"3000","schema:addressLocality":"Leuven"}},"ofd:offersFoodType":["ft:potatoes","ft:fruits","ft:bakery_products","ft:eggs","ft:poultry_meat","ft:fruit_juices","ft:icecream","ft:spices","ft:lamb_meat","ft:beef","ft:pork","ft:alcoholic_beverages","ft:vegetables","ft:milk_products"],"foaf:depiction":[],"schema:description":"","ofd:upstreamRel":[],"@id":"https://w3id.org/openfooddata/actors/leuven-opec","extraHeader":"<link rel=\"alternate\" href=\"leuven-opec.rdf\" type=\"application/rdf+xml\"/>\n<link rel=\"alternate\" href=\"leuven-opec.jsonld\" type=\"application/ld+json\"/>\n<link rel=\"alternate\" href=\"leuven-opec.nq\" type=\"application/n-quads\"/>\n<link rel=\"alternate\" href=\"leuven-opec.nt\" type=\"application/n-triples\"/>\n<link rel=\"alternate\" href=\"leuven-opec.ttl\" type=\"text/turtle\"/>\n<link rel=\"alternate\" href=\"leuven-opec.rj\" type=\"application/rdf+json\"/>\n<link rel=\"alternate\" href=\"leuven-opec.trig\" type=\"text/trig\"/>\n<link rel=\"alternate\" href=\"leuven-opec.trix\" type=\"application/trix\"/>\n","schema:name":"Leuven OPEC","ofd:actorType":["at:pointOfSale","at:foodTeams"]}}