{"type":"Feature","geometry":{"type":"Point","coordinates":[4.705327,50.886809]},"properties":{"foaf:account":[],"foaf:name":"Leuven OPEC","foaf:isPrimaryTopicOf":["http://www.rechtvanbijdeboer.be/leuven-opec","http://www.rechtvanbijdeboer.be/node/2182"],"@type":"foaf:Agent","schema:image":[],"@context":"https://openfooddata.github.io/actors/_common/context.jsonld","schema:geo":{"schema:latitude":"50.886809","schema:longitude":"4.705327","@type":"schema:GeoCoordinates","schema:addressCountry":"Belgium","schema:address":{"@type":"schema:PostalAddress","schema:streetAddress":"Stapelhuisstraat","schema:postalCode":"3000","schema:addressLocality":"Leuven"}},"ofd:offersFoodType":["ft:potatoes","ft:fruits","ft:bakery_products","ft:eggs","ft:poultry_meat","ft:fruit_juices","ft:icecream","ft:spices","ft:lamb_meat","ft:beef","ft:pork","ft:alcoholic_beverages","ft:vegetables","ft:milk_products"],"foaf:depiction":[],"schema:description":"","ofd:upstreamRel":[],"@id":"https://w3id.org/openfooddata/actors/leuven-opec","schema:name":"Leuven OPEC","ofd:actorType":["at:pointOfSale","at:foodTeams"]}}