{"type":"Feature","geometry":{"type":"Point","coordinates":[2.908928,51.224551]},"properties":{"id":"https://w3id.org/openfooddata/actors/dieet-petit-paris","name":"Dieet Petit Paris","img":["http://www.rechtvanbijdeboer.be/sites/default/files/styles/producer_teaser/public/biobellogroentenenfruitmaxi.jpg?itok=n2EToMw3"],"type":["at:pointOfSale","at:vegetableSubscription"],"upstream":[{"@type":"ofd:ActorRelationship","ofd:relatedContext":"at:producer","ofd:relatedActor":"https://w3id.org/openfooddata/actors/de-lochting-vzw"}]}}