{"type":"Feature","geometry":{"type":"Point","coordinates":[4.638845,50.764333]},"properties":{"foaf:account":[],"foaf:name":"De Ferme Framboos","schema:url":[],"foaf:homepage":[],"foaf:isPrimaryTopicOf":["http://www.rechtvanbijdeboer.be/de-ferme-framboos-0","http://www.rechtvanbijdeboer.be/node/3157","https://www.rechtvanbijdeboer.be/de-ferme-framboos","https://www.rechtvanbijdeboer.be/node/1649","http://www.rechtvanbijdeboer.be/de-ferme-framboos-1","http://www.rechtvanbijdeboer.be/node/3158"],"@type":"foaf:Agent","schema:image":[],"@context":"https://openfooddata.github.io/actors/_common/context.jsonld","schema:geo":{"schema:latitude":"50.764333","schema:longitude":"4.638845","@type":"schema:GeoCoordinates","schema:addressCountry":"Belgium","schema:address":{"@type":"schema:PostalAddress","schema:streetAddress":"Veeweidestraat 50","schema:postalCode":"3040","schema:addressLocality":"Sint-Agatha-Rode"}},"ofd:offersFoodType":["ft:poultry_meat","ft:lamb_meat","ft:fruits","ft:beef"],"foaf:depiction":[],"schema:description":"","ofd:upstreamRel":[],"ofd:downstreamRel":[],"@id":"https://w3id.org/openfooddata/actors/de-ferme-framboos","extraHeader":"<link rel=\"alternate\" href=\"de-ferme-framboos.rdf\" type=\"application/rdf+xml\"/>\n<link rel=\"alternate\" href=\"de-ferme-framboos.jsonld\" type=\"application/ld+json\"/>\n<link rel=\"alternate\" href=\"de-ferme-framboos.nq\" type=\"application/n-quads\"/>\n<link rel=\"alternate\" href=\"de-ferme-framboos.nt\" type=\"application/n-triples\"/>\n<link rel=\"alternate\" href=\"de-ferme-framboos.ttl\" type=\"text/turtle\"/>\n<link rel=\"alternate\" href=\"de-ferme-framboos.rj\" type=\"application/rdf+json\"/>\n<link rel=\"alternate\" href=\"de-ferme-framboos.trig\" type=\"text/trig\"/>\n<link rel=\"alternate\" href=\"de-ferme-framboos.trix\" type=\"application/trix\"/>\n","schema:name":"De Ferme Framboos","ofd:actorType":["at:pointOfSale","at:producer","at:farmShop"]}}