{"type":"Feature","geometry":{"type":"Point","coordinates":[4.479416,51.40635]},"properties":{"id":"https://w3id.org/openfooddata/actors/hoeve-de-sneppe","name":"Hoeve \"De Sneppe\"","img":[],"type":["at:pointOfSale","at:farmShop"],"upstream":[{"@type":"ofd:ActorRelationship","ofd:relatedContext":"at:producer","ofd:relatedActor":"https://w3id.org/openfooddata/actors/frans-vanden-bergh"}]}}