{"type":"Feature","geometry":{"type":"Point","coordinates":[4.033303,51.032457]},"properties":{"foaf:account":[],"foaf:name":"Hoeveslagerij De Nil","foaf:isPrimaryTopicOf":["http://www.rechtvanbijdeboer.be/hoeveslagerij-de-nil-0","http://www.rechtvanbijdeboer.be/node/2902"],"@type":"foaf:Agent","schema:image":[],"@context":"https://openfooddata.github.io/actors/_common/context.jsonld","schema:geo":{"schema:latitude":"51.032457","schema:longitude":"4.033303","@type":"schema:GeoCoordinates","schema:addressCountry":"Belgium","schema:address":{"@type":"schema:PostalAddress","schema:streetAddress":"Waterhoek 11a","schema:postalCode":"9290","schema:addressLocality":"Berlare"}},"ofd:offersFoodType":["ft:beef","ft:pork"],"foaf:depiction":[],"schema:description":"","ofd:upstreamRel":[{"@type":"ofd:ActorRelationship","ofd:relatedContext":"at:producer","ofd:relatedActor":"https://w3id.org/openfooddata/actors/hoeveslagerij-de-nil"}],"@id":"https://w3id.org/openfooddata/actors/hoeveslagerij-de-nil-0","schema:name":"Hoeveslagerij De Nil","ofd:actorType":["at:pointOfSale","at:farmShop"]}}