{"type":"Feature","geometry":{"type":"Point","coordinates":[2.911174,51.227342]},"properties":{"foaf:account":[],"foaf:name":"Leefschool De Vlieger (bestellen via biobello.be)","foaf:isPrimaryTopicOf":["http://www.rechtvanbijdeboer.be/leefschool-de-vlieger-bestellen-biobellobe","http://www.rechtvanbijdeboer.be/node/2440"],"@type":"foaf:Agent","schema:image":["http://www.rechtvanbijdeboer.be/sites/default/files/styles/producer_teaser/public/biobellogroentenenfruitmaxi.jpg?itok=n2EToMw3"],"@context":"https://openfooddata.github.io/actors/_common/context.jsonld","schema:geo":{"schema:latitude":"51.227342","schema:longitude":"2.911174","@type":"schema:GeoCoordinates","schema:addressCountry":"Belgium","schema:address":{"@type":"schema:PostalAddress","schema:streetAddress":"Rogierlaan 12","schema:postalCode":"8400","schema:addressLocality":"Oostende"}},"ofd:offersFoodType":["ft:potatoes","ft:fruits","ft:eggs","ft:vegetables"],"foaf:depiction":["http://www.rechtvanbijdeboer.be/sites/default/files/styles/producer_teaser/public/biobellogroentenenfruitmaxi.jpg?itok=n2EToMw3"],"schema:description":"","ofd:upstreamRel":[{"@type":"ofd:ActorRelationship","ofd:relatedContext":"at:producer","ofd:relatedActor":"https://w3id.org/openfooddata/actors/de-lochting-vzw"}],"@id":"https://w3id.org/openfooddata/actors/leefschool-de-vlieger-bestellen-biobellobe","schema:name":"Leefschool De Vlieger (bestellen via biobello.be)","ofd:actorType":["at:pointOfSale","at:collectionPoint"]}}