{"type":"Feature","geometry":{"type":"Point","coordinates":[3.614431,51.135804]},"properties":{"id":"https://w3id.org/openfooddata/actors/hoeveslagerij-effenaf","name":"Hoeveslagerij Effenaf","img":[],"type":["at:pointOfSale","at:farmShop","at:producer"],"upstream":[],"downstream":[]}}