{"type":"Feature","geometry":{"type":"Point","coordinates":[5.137951,50.948606]},"properties":{"id":"https://w3id.org/openfooddata/actors/de-waterkant-0","name":"De Waterkant","img":[],"type":["at:pointOfSale","at:farmShop"],"upstream":[{"@type":"ofd:ActorRelationship","ofd:relatedContext":"at:producer","ofd:relatedActor":"https://w3id.org/openfooddata/actors/de-waterkant"}]}}