{"type":"Feature","geometry":{"type":"Point","coordinates":[4.82476,51.140007]},"properties":{"id":"https://w3id.org/openfooddata/actors/de-kijfelaar","name":"De Kijfelaar","img":[],"type":["at:pointOfSale","at:farmShop","at:producer"],"upstream":[],"downstream":[]}}