{"type":"Feature","geometry":{"type":"Point","coordinates":[4.63886,50.76434]},"properties":{"id":"https://w3id.org/openfooddata/actors/ferme-framboos","name":"Ferme Framboos","img":[],"type":["at:pointOfSale","at:collectionPoint"],"upstream":[{"@type":"ofd:ActorRelationship","ofd:relatedContext":"at:producer","ofd:relatedActor":"https://w3id.org/openfooddata/actors/bo&co"}]}}