{"type":"Feature","geometry":{"type":"Point","coordinates":[4.538018,50.785946]},"properties":{"id":"https://w3id.org/openfooddata/actors/druiven-ronald-vanderkelen","name":"Druiven Ronald Vanderkelen","img":["http://www.rechtvanbijdeboer.be/sites/default/files/styles/producer_teaser/public/ronald.JPG?itok=pGIeS0-1"],"type":["at:pointOfSale","at:farmShop"],"upstream":[{"@type":"ofd:ActorRelationship","ofd:relatedContext":"at:producer","ofd:relatedActor":"https://w3id.org/openfooddata/actors/druiven-vanderkelen"}]}}