{"type":"Feature","geometry":{"type":"Point","coordinates":[3.54061,50.823477]},"properties":{"id":"https://w3id.org/openfooddata/actors/aardbeienautomaat-2","name":"Aardbeienautomaat","img":["http://www.rechtvanbijdeboer.be/sites/default/files/styles/producer_teaser/public/10363332_776877332331409_4323796495604880457_n.jpg?itok=bPjtaTuA"],"type":["at:pointOfSale","at:vendingMachine"],"upstream":[{"@type":"ofd:ActorRelationship","ofd:relatedContext":"at:producer","ofd:relatedActor":"https://w3id.org/openfooddata/actors/aardbeien-aardappelen-de-cock"}]}}