{"type":"Feature","geometry":{"type":"Point","coordinates":[4.469936,50.503887]},"properties":{"foaf:account":[],"foaf:name":"www.sanguisorba.be","foaf:isPrimaryTopicOf":["http://www.rechtvanbijdeboer.be/wwwsanguisorbabe","http://www.rechtvanbijdeboer.be/node/3164"],"@type":"foaf:Agent","schema:image":[],"@context":"https://openfooddata.github.io/actors/_common/context.jsonld","schema:geo":{"schema:latitude":"50.503887","schema:longitude":"4.469936","@type":"schema:GeoCoordinates","schema:addressCountry":"Belgium","schema:address":{"@type":"schema:PostalAddress"}},"ofd:offersFoodType":["ft:fruits","ft:vegetables","ft:spices"],"foaf:depiction":[],"schema:description":"","ofd:upstreamRel":[{"@type":"ofd:ActorRelationship","ofd:relatedContext":"at:producer","ofd:relatedActor":"https://w3id.org/openfooddata/actors/sanguisorba"}],"@id":"https://w3id.org/openfooddata/actors/wwwsanguisorbabe","extraHeader":"<link rel=\"alternate\" href=\"wwwsanguisorbabe.rdf\" type=\"application/rdf+xml\"/>\n<link rel=\"alternate\" href=\"wwwsanguisorbabe.jsonld\" type=\"application/ld+json\"/>\n<link rel=\"alternate\" href=\"wwwsanguisorbabe.nq\" type=\"application/n-quads\"/>\n<link rel=\"alternate\" href=\"wwwsanguisorbabe.nt\" type=\"application/n-triples\"/>\n<link rel=\"alternate\" href=\"wwwsanguisorbabe.ttl\" type=\"text/turtle\"/>\n<link rel=\"alternate\" href=\"wwwsanguisorbabe.rj\" type=\"application/rdf+json\"/>\n<link rel=\"alternate\" href=\"wwwsanguisorbabe.trig\" type=\"text/trig\"/>\n<link rel=\"alternate\" href=\"wwwsanguisorbabe.trix\" type=\"application/trix\"/>\n","schema:name":"www.sanguisorba.be","ofd:actorType":["at:pointOfSale","at:webshop"]}}