{"type":"Feature","geometry":{"type":"Point","coordinates":[4.416667,50.8]},"properties":{"foaf:account":[],"foaf:name":"Watermaal-Bosvoorde","foaf:isPrimaryTopicOf":["http://www.rechtvanbijdeboer.be/watermaal-bosvoorde","http://www.rechtvanbijdeboer.be/node/2061"],"@type":"foaf:Agent","schema:image":[],"@context":"https://openfooddata.github.io/actors/_common/context.jsonld","schema:geo":{"schema:latitude":"50.800000","schema:longitude":"4.416667","@type":"schema:GeoCoordinates","schema:addressCountry":"Belgium","schema:address":{"@type":"schema:PostalAddress","schema:postalCode":"1170","schema:addressLocality":"Watermaal-Bosvoorde"}},"ofd:offersFoodType":["ft:milk_products"],"foaf:depiction":[],"schema:description":"","ofd:upstreamRel":[{"@type":"ofd:ActorRelationship","ofd:relatedContext":"at:producer","ofd:relatedActor":"https://w3id.org/openfooddata/actors/hof-ten-broeke"}],"@id":"https://w3id.org/openfooddata/actors/watermaal-bosvoorde","schema:name":"Watermaal-Bosvoorde","ofd:actorType":["at:pointOfSale","at:market"]}}