{"type":"Feature","geometry":{"type":"Point","coordinates":[3.857491,51.081538]},"properties":{"foaf:account":[],"foaf:name":"De Clercq","schema:url":[],"foaf:homepage":[],"foaf:isPrimaryTopicOf":["http://www.rechtvanbijdeboer.be/de-clercq-0","http://www.rechtvanbijdeboer.be/node/3062","https://www.rechtvanbijdeboer.be/de-clercq","https://www.rechtvanbijdeboer.be/node/1572"],"@type":"foaf:Agent","schema:image":[],"@context":"https://openfooddata.github.io/actors/_common/context.jsonld","schema:geo":{"schema:latitude":"51.081538","schema:longitude":"3.857491","@type":"schema:GeoCoordinates","schema:addressCountry":"Belgium","schema:address":{"@type":"schema:PostalAddress","schema:streetAddress":"Pensionaatstraat 3","schema:postalCode":"9080","schema:addressLocality":"Beervelde"}},"ofd:offersFoodType":["ft:milk_products","ft:icecream","ft:potatoes"],"foaf:depiction":[],"schema:description":"","ofd:upstreamRel":[],"ofd:downstreamRel":[],"@id":"https://w3id.org/openfooddata/actors/de-clercq","extraHeader":"<link rel=\"alternate\" href=\"de-clercq.rdf\" type=\"application/rdf+xml\"/>\n<link rel=\"alternate\" href=\"de-clercq.jsonld\" type=\"application/ld+json\"/>\n<link rel=\"alternate\" href=\"de-clercq.nq\" type=\"application/n-quads\"/>\n<link rel=\"alternate\" href=\"de-clercq.nt\" type=\"application/n-triples\"/>\n<link rel=\"alternate\" href=\"de-clercq.ttl\" type=\"text/turtle\"/>\n<link rel=\"alternate\" href=\"de-clercq.rj\" type=\"application/rdf+json\"/>\n<link rel=\"alternate\" href=\"de-clercq.trig\" type=\"text/trig\"/>\n<link rel=\"alternate\" href=\"de-clercq.trix\" type=\"application/trix\"/>\n","schema:name":"De Clercq","ofd:actorType":["at:pointOfSale","at:farmShop","at:producer"]}}