{"type":"Feature","geometry":{"type":"Point","coordinates":[3.090536,51.199097]},"properties":{"foaf:account":[{"@type":"foaf:OnlineAccount","@id":"https://www.facebook.com/pages/Hoevevlees-Maertens/418647361484324?fref=ts","skos:prefLabel":"Facebook","foaf:accountServiceHomepage":"https://www.facebook.com","foaf:accountName":"Hoevevlees-Maertens","dct:identifier":"418647361484324?fref=ts"}],"foaf:name":"Hoevevlees Maertens","schema:url":["http://www.hoevevleesmaertens.be"],"foaf:homepage":["http://www.hoevevleesmaertens.be"],"foaf:isPrimaryTopicOf":["http://www.rechtvanbijdeboer.be/hoevevlees-maertens-0","http://www.rechtvanbijdeboer.be/node/2635","http://www.rechtvanbijdeboer.be/hoevevlees-maertens","http://www.rechtvanbijdeboer.be/node/1229","http://www.rechtvanbijdeboer.be/hoevevlees-maertens-1","http://www.rechtvanbijdeboer.be/node/3441"],"@type":"foaf:Agent","schema:image":["http://www.rechtvanbijdeboer.be/sites/default/files/styles/producer_teaser/public/pate2.jpg?itok=P-lhKFUx","http://www.rechtvanbijdeboer.be/sites/default/files/styles/producer_teaser/public/dsc_0004bewfondu.jpg?itok=ri3ylX-O"],"@context":"https://openfooddata.github.io/actors/_common/context.jsonld","schema:geo":{"schema:latitude":"51.199097","schema:longitude":"3.090536","@type":"schema:GeoCoordinates","schema:addressCountry":"Belgium","schema:address":{"@type":"schema:PostalAddress","schema:streetAddress":"Stationsstraat 59","schema:postalCode":"8490","schema:addressLocality":"Jabbeke"}},"ofd:offersFoodType":["ft:poultry_meat","ft:eggs","ft:pork","ft:beef","ft:spices"],"foaf:depiction":["http://www.rechtvanbijdeboer.be/sites/default/files/styles/producer_teaser/public/pate2.jpg?itok=P-lhKFUx","http://www.rechtvanbijdeboer.be/sites/default/files/styles/producer_teaser/public/dsc_0004bewfondu.jpg?itok=ri3ylX-O"],"schema:description":["De Limousinrunderen grazen in ruime weilanden. Wanneer de grasvoorraden minderen worden ze bijgevoederd met een maïs en hooi. Tijdens de wintermaanden verblijven ze in open ruime loopstallen. Onze boerderij zorgt ervoor dat bijna alle eten van eigen bodem komt.Vandaar dat de hoeve een groot gedeelte landbouwgrond (90 ha) bewerkt. Naast de weilanden hebben we veel maïs, suikerbieten, gras (hooi, graszaad) en tarwe.",""],"ofd:upstreamRel":[],"schema:contactPoint":{"@type":"schema:ContactPoint","schema:telephone":["050/814495"],"schema:email":["hoevevlees.maertens@skynet.be"],"foaf:homepage":["http://www.hoevevleesmaertens.be"],"schema:url":["http://www.hoevevleesmaertens.be"]},"ofd:downstreamRel":[],"@id":"https://w3id.org/openfooddata/actors/hoevevlees-maertens","schema:name":"Hoevevlees Maertens","ofd:actorType":["at:pointOfSale","at:collectionPoint","at:producer","at:farmShop"]}}