{"type":"Feature","geometry":{"type":"Point","coordinates":[3.090536,51.199097]},"properties":{"id":"https://w3id.org/openfooddata/actors/hoevevlees-maertens","name":"Hoevevlees Maertens","img":["http://www.rechtvanbijdeboer.be/sites/default/files/styles/producer_teaser/public/pate2.jpg?itok=P-lhKFUx","http://www.rechtvanbijdeboer.be/sites/default/files/styles/producer_teaser/public/dsc_0004bewfondu.jpg?itok=ri3ylX-O"],"type":["at:pointOfSale","at:collectionPoint","at:producer","at:farmShop"],"upstream":[],"downstream":[]}}