{"type":"Feature","geometry":{"type":"Point","coordinates":[5.682845,51.110106]},"properties":{"id":"https://w3id.org/openfooddata/actors/voedselteam-neeroeteren","name":"Voedselteam Neeroeteren","img":["http://www.rechtvanbijdeboer.be/sites/default/files/styles/producer_teaser/public/familiefoto.jpg?itok=CBHVp8pB"],"type":["at:pointOfSale","at:foodTeams"],"upstream":[{"@type":"ofd:ActorRelationship","ofd:relatedContext":"at:producer","ofd:relatedActor":"https://w3id.org/openfooddata/actors/de-wroeter-maatwerkbedrijf-vzw"},{"@type":"ofd:ActorRelationship","ofd:relatedContext":"at:producer","ofd:relatedActor":"https://w3id.org/openfooddata/actors/catharinadal"},{"@type":"ofd:ActorRelationship","ofd:relatedContext":"at:producer","ofd:relatedActor":"https://w3id.org/openfooddata/actors/herkenrodeboer"},{"@type":"ofd:ActorRelationship","ofd:relatedContext":"at:producer","ofd:relatedActor":"https://w3id.org/openfooddata/actors/stichting-ommersteyn"},{"@type":"ofd:ActorRelationship","ofd:relatedContext":"at:producer","ofd:relatedActor":"https://w3id.org/openfooddata/actors/natlandhoeve"}]}}