{"type":"Feature","geometry":{"type":"Point","coordinates":[4.377298,50.867416]},"properties":{"id":"https://w3id.org/openfooddata/actors/vegetaria","name":"Vegetaria","img":["http://www.rechtvanbijdeboer.be/sites/default/files/styles/producer_teaser/public/biobellogroentenenfruitmaxi.jpg?itok=n2EToMw3"],"type":["at:pointOfSale","at:vegetableSubscription"],"upstream":[{"@type":"ofd:ActorRelationship","ofd:relatedContext":"at:producer","ofd:relatedActor":"https://w3id.org/openfooddata/actors/de-lochting-vzw"}]}}