{"type":"Feature","geometry":{"type":"Point","coordinates":[5.201256,50.964706]},"properties":{"foaf:account":[],"foaf:name":"t' Aardappelschuurtje","schema:url":[],"foaf:homepage":[],"foaf:isPrimaryTopicOf":["http://www.rechtvanbijdeboer.be/t-aardappelschuurtje-0","http://www.rechtvanbijdeboer.be/node/3215","https://www.rechtvanbijdeboer.be/t-aardappelschuurtje","https://www.rechtvanbijdeboer.be/node/1692"],"@type":"foaf:Agent","schema:image":[],"@context":"https://openfooddata.github.io/actors/_common/context.jsonld","schema:geo":{"schema:latitude":"50.964706","schema:longitude":"5.201256","@type":"schema:GeoCoordinates","schema:addressCountry":"Belgium","schema:address":{"@type":"schema:PostalAddress","schema:streetAddress":"Pannestraat 16","schema:postalCode":"3540","schema:addressLocality":"Herk-de-Stad"}},"ofd:offersFoodType":["ft:potatoes"],"foaf:depiction":[],"schema:description":"","ofd:upstreamRel":[],"ofd:downstreamRel":[],"@id":"https://w3id.org/openfooddata/actors/t-aardappelschuurtje","extraHeader":"<link rel=\"alternate\" href=\"t-aardappelschuurtje.rdf\" type=\"application/rdf+xml\"/>\n<link rel=\"alternate\" href=\"t-aardappelschuurtje.jsonld\" type=\"application/ld+json\"/>\n<link rel=\"alternate\" href=\"t-aardappelschuurtje.nq\" type=\"application/n-quads\"/>\n<link rel=\"alternate\" href=\"t-aardappelschuurtje.nt\" type=\"application/n-triples\"/>\n<link rel=\"alternate\" href=\"t-aardappelschuurtje.ttl\" type=\"text/turtle\"/>\n<link rel=\"alternate\" href=\"t-aardappelschuurtje.rj\" type=\"application/rdf+json\"/>\n<link rel=\"alternate\" href=\"t-aardappelschuurtje.trig\" type=\"text/trig\"/>\n<link rel=\"alternate\" href=\"t-aardappelschuurtje.trix\" type=\"application/trix\"/>\n","schema:name":"t' Aardappelschuurtje","ofd:actorType":["at:pointOfSale","at:farmShop","at:producer"]}}