{"type":"Feature","geometry":{"type":"Point","coordinates":[4.908375,50.847233]},"properties":{"id":"https://w3id.org/openfooddata/actors/hoeve-de-zon","name":"Hoeve In de Zon","img":["http://www.rechtvanbijdeboer.be/sites/default/files/styles/producer_teaser/public/p4131116.jpg?itok=4MSAU1Yu","http://www.rechtvanbijdeboer.be/sites/default/files/styles/producer_teaser/public/indezoncdreportage001.jpg?itok=531jAxcW"],"type":["at:pointOfSale","at:collectionPoint","at:producer","at:vendingMachine"],"upstream":[{"@type":"ofd:ActorRelationship","ofd:relatedContext":"at:producer","ofd:relatedActor":"https://w3id.org/openfooddata/actors/hhv"}],"downstream":[{"@type":"ofd:ActorRelationship","ofd:relatedContext":"at:pointOfSale","ofd:relatedActor":"https://w3id.org/openfooddata/actors/hoevewinkel-de-zon"}]}}