{"type":"Feature","geometry":{"type":"Point","coordinates":[4.160006,50.75815]},"properties":{"id":"https://w3id.org/openfooddata/actors/pajottenlander","name":"Pajottenlander","img":[],"type":["at:pointOfSale","at:farmShop","at:producer"],"upstream":[],"downstream":[]}}