{"type":"Feature","geometry":{"type":"Point","coordinates":[3.448833,50.932844]},"properties":{"foaf:account":[],"foaf:name":"Purfruit","schema:url":[],"foaf:homepage":[],"foaf:isPrimaryTopicOf":["http://www.rechtvanbijdeboer.be/purfruit-0","http://www.rechtvanbijdeboer.be/node/2740","https://www.rechtvanbijdeboer.be/purfruit","https://www.rechtvanbijdeboer.be/node/1302"],"@type":"foaf:Agent","schema:image":[],"@context":"https://openfooddata.github.io/actors/_common/context.jsonld","schema:geo":{"schema:latitude":"50.932844","schema:longitude":"3.448833","@type":"schema:GeoCoordinates","schema:addressCountry":"Belgium","schema:address":{"@type":"schema:PostalAddress","schema:streetAddress":"Neerhoek 7","schema:postalCode":"8720","schema:addressLocality":"Oeselgem"}},"ofd:offersFoodType":["ft:poultry_meat","ft:alcoholic_beverages","ft:fruits","ft:icecream"],"foaf:depiction":[],"schema:description":"","ofd:upstreamRel":[],"ofd:downstreamRel":[],"@id":"https://w3id.org/openfooddata/actors/purfruit","schema:name":"Purfruit","ofd:actorType":["at:pointOfSale","at:producer"]}}