{"type":"Feature","geometry":{"type":"Point","coordinates":[4.505556,51.061424]},"properties":{"foaf:account":[],"foaf:name":"De Doederij","foaf:isPrimaryTopicOf":["http://www.rechtvanbijdeboer.be/de-doederij-0","http://www.rechtvanbijdeboer.be/node/3152"],"@type":"foaf:Agent","schema:image":[],"@context":"https://openfooddata.github.io/actors/_common/context.jsonld","schema:geo":{"schema:latitude":"51.061424","schema:longitude":"4.505556","@type":"schema:GeoCoordinates","schema:addressCountry":"Belgium","schema:address":{"@type":"schema:PostalAddress","schema:streetAddress":"De Rooi 5","schema:postalCode":"2860","schema:addressLocality":"Sint-Katelijne-Waver"}},"ofd:offersFoodType":["ft:fruits","ft:spices","ft:vegetables"],"foaf:depiction":[],"schema:description":"","ofd:upstreamRel":[{"@type":"ofd:ActorRelationship","ofd:relatedContext":"at:producer","ofd:relatedActor":"https://w3id.org/openfooddata/actors/de-doederij"}],"@id":"https://w3id.org/openfooddata/actors/de-doederij-0","extraHeader":"<link rel=\"alternate\" href=\"de-doederij-0.rdf\" type=\"application/rdf+xml\"/>\n<link rel=\"alternate\" href=\"de-doederij-0.jsonld\" type=\"application/ld+json\"/>\n<link rel=\"alternate\" href=\"de-doederij-0.nq\" type=\"application/n-quads\"/>\n<link rel=\"alternate\" href=\"de-doederij-0.nt\" type=\"application/n-triples\"/>\n<link rel=\"alternate\" href=\"de-doederij-0.ttl\" type=\"text/turtle\"/>\n<link rel=\"alternate\" href=\"de-doederij-0.rj\" type=\"application/rdf+json\"/>\n<link rel=\"alternate\" href=\"de-doederij-0.trig\" type=\"text/trig\"/>\n<link rel=\"alternate\" href=\"de-doederij-0.trix\" type=\"application/trix\"/>\n","schema:name":"De Doederij","ofd:actorType":["at:pointOfSale","at:csaFarm"]}}