{"type":"Feature","geometry":{"type":"Point","coordinates":[4.433346,51.000812]},"properties":{"foaf:account":[],"foaf:name":"De Grenshoeve","foaf:isPrimaryTopicOf":["http://www.rechtvanbijdeboer.be/de-grenshoeve-0","http://www.rechtvanbijdeboer.be/node/2632"],"@type":"foaf:Agent","schema:image":[],"@context":"https://openfooddata.github.io/actors/_common/context.jsonld","schema:geo":{"schema:latitude":"51.000812","schema:longitude":"4.433346","@type":"schema:GeoCoordinates","schema:addressCountry":"Belgium","schema:address":{"@type":"schema:PostalAddress","schema:streetAddress":"Poreistraat 19","schema:postalCode":"2811","schema:addressLocality":"Hombeek (Mechelen)"}},"ofd:offersFoodType":["ft:potatoes","ft:fruits","ft:eggs","ft:vegetables"],"foaf:depiction":[],"schema:description":"","ofd:upstreamRel":[{"@type":"ofd:ActorRelationship","ofd:relatedContext":"at:producer","ofd:relatedActor":"https://w3id.org/openfooddata/actors/grenshoeve"}],"@id":"https://w3id.org/openfooddata/actors/de-grenshoeve-0","schema:name":"De Grenshoeve","ofd:actorType":["at:pointOfSale","at:farmShop"]}}