{"type":"Feature","geometry":{"type":"Point","coordinates":[4.489436,51.19572]},"properties":{"id":"https://w3id.org/openfooddata/actors/voedselteam-borsbeek","name":"Voedselteam Borsbeek","img":[],"type":["at:pointOfSale","at:foodTeams"],"upstream":[{"@type":"ofd:ActorRelationship","ofd:relatedContext":"at:producer","ofd:relatedActor":"https://w3id.org/openfooddata/actors/antwerpse-honing---de-stadsimker"},{"@type":"ofd:ActorRelationship","ofd:relatedContext":"at:producer","ofd:relatedActor":"https://w3id.org/openfooddata/actors/wijngaardhof"}]}}