{"type":"Feature","geometry":{"type":"Point","coordinates":[5.379016,50.783677]},"properties":{"foaf:account":[],"foaf:name":"'t Bommerhof","foaf:isPrimaryTopicOf":["http://www.rechtvanbijdeboer.be/node/2905","http://www.rechtvanbijdeboer.be/node/2905"],"@type":"foaf:Agent","schema:image":[],"@context":"https://openfooddata.github.io/actors/_common/context.jsonld","schema:geo":{"schema:latitude":"50.783677","schema:longitude":"5.379016","@type":"schema:GeoCoordinates","schema:addressCountry":"Belgium","schema:address":{"@type":"schema:PostalAddress","schema:streetAddress":"Alfonsstraat 66","schema:postalCode":"3840","schema:addressLocality":"Borgloon"}},"ofd:offersFoodType":["ft:fruits","ft:poultry_meat"],"foaf:depiction":[],"schema:description":"","ofd:upstreamRel":[{"@type":"ofd:ActorRelationship","ofd:relatedContext":"at:producer","ofd:relatedActor":"https://w3id.org/openfooddata/actors/t-bommerhof"}],"@id":"https://w3id.org/openfooddata/actors/2905","schema:name":"'t Bommerhof","ofd:actorType":["at:pointOfSale","at:vendingMachine"]}}