{"type":"Feature","geometry":{"type":"Point","coordinates":[4.469936,50.503887]},"properties":{"foaf:account":[],"foaf:name":"Hof de veldroute","foaf:isPrimaryTopicOf":["http://www.rechtvanbijdeboer.be/hof-de-veldroute-0","http://www.rechtvanbijdeboer.be/node/3281"],"@type":"foaf:Agent","schema:image":[],"@context":"https://openfooddata.github.io/actors/_common/context.jsonld","schema:geo":{"schema:latitude":"50.503887","schema:longitude":"4.469936","@type":"schema:GeoCoordinates","schema:addressCountry":"Belgium","schema:address":{"@type":"schema:PostalAddress"}},"ofd:offersFoodType":["ft:potatoes","ft:fruits","ft:vegetables"],"foaf:depiction":[],"schema:description":"","ofd:upstreamRel":[{"@type":"ofd:ActorRelationship","ofd:relatedContext":"at:producer","ofd:relatedActor":"https://w3id.org/openfooddata/actors/hof-de-veldroute"}],"@id":"https://w3id.org/openfooddata/actors/hof-de-veldroute-0","extraHeader":"<link rel=\"alternate\" href=\"hof-de-veldroute-0.rdf\" type=\"application/rdf+xml\"/>\n<link rel=\"alternate\" href=\"hof-de-veldroute-0.jsonld\" type=\"application/ld+json\"/>\n<link rel=\"alternate\" href=\"hof-de-veldroute-0.nq\" type=\"application/n-quads\"/>\n<link rel=\"alternate\" href=\"hof-de-veldroute-0.nt\" type=\"application/n-triples\"/>\n<link rel=\"alternate\" href=\"hof-de-veldroute-0.ttl\" type=\"text/turtle\"/>\n<link rel=\"alternate\" href=\"hof-de-veldroute-0.rj\" type=\"application/rdf+json\"/>\n<link rel=\"alternate\" href=\"hof-de-veldroute-0.trig\" type=\"text/trig\"/>\n<link rel=\"alternate\" href=\"hof-de-veldroute-0.trix\" type=\"application/trix\"/>\n","schema:name":"Hof de veldroute","ofd:actorType":["at:pointOfSale","at:farmShop"]}}