{"type":"Feature","geometry":{"type":"Point","coordinates":[4.407325,51.329204]},"properties":{"id":"https://w3id.org/openfooddata/actors/de-schutter-hoevezuivel","name":"De Schutter Hoevezuivel","img":[],"type":["at:pointOfSale","at:farmShop","at:producer"],"upstream":[],"downstream":[]}}