{"type":"Feature","geometry":{"type":"Point","coordinates":[4.098414,50.715988]},"properties":{"foaf:account":[],"foaf:name":"Herrebeekhof","schema:url":["http://www.herrebeekhof.be"],"foaf:homepage":["http://www.herrebeekhof.be"],"foaf:isPrimaryTopicOf":["http://www.rechtvanbijdeboer.be/herrebeekhof-0","http://www.rechtvanbijdeboer.be/node/2354","http://www.rechtvanbijdeboer.be/herrebeekhof","http://www.rechtvanbijdeboer.be/node/1084"],"@type":"foaf:Agent","schema:image":["http://www.rechtvanbijdeboer.be/sites/default/files/styles/producer_teaser/public/herrebeekhof_-marktkraam_lr.jpg?itok=BcACx0qC"],"@context":"https://openfooddata.github.io/actors/_common/context.jsonld","schema:geo":{"schema:latitude":"50.715988","schema:longitude":"4.098414","@type":"schema:GeoCoordinates","schema:addressCountry":"Belgium","schema:address":{"@type":"schema:PostalAddress","schema:streetAddress":"Nanovestraat 6","schema:postalCode":"1670","schema:addressLocality":"Heikruis (Pepingen)"}},"ofd:offersFoodType":["ft:pork","ft:beef"],"foaf:depiction":["http://www.rechtvanbijdeboer.be/sites/default/files/styles/producer_teaser/public/herrebeekhof_-marktkraam_lr.jpg?itok=BcACx0qC"],"schema:description":"Het vlees dat je in het Herrebeekhof vindt, is het resultaat van de eigen, 100 procent natuurlijke kweek. Hun dieren kunnen, doordat ze geen antibiotica of groeibevorderaars krijgen voorgeschoteld, in vergelijking met hun soortgenoten uit de agro-industrie, veel langer van de pure boslucht genieten. Daarenboven controleert de bedrijfsdierenarts middels bloed-en meststalen minstens elke twee maanden de gezondheidstoestand van de dieren. Het resultaat: pure gezondheid. Ook op uw bord! Bezoek ook hun website www.herrebeekhof.be waar je online kan bestellen! In de nieuwe degustatieruimte kan je elke zondag komen proeven van heerlijke boterhammen met eigen gemaakte charcuterie of een hoeve-ijsje. In de zomermaanden (juni tot september) kan je al dit lekkers ook nuttigen op het terras!","ofd:upstreamRel":[],"schema:contactPoint":{"@type":"schema:ContactPoint","schema:telephone":["02/3962428"],"schema:email":["info.herrebeekhof@telenet.be"],"foaf:homepage":["http://www.herrebeekhof.be"],"schema:url":["http://www.herrebeekhof.be"]},"ofd:downstreamRel":[{"@type":"ofd:ActorRelationship","ofd:relatedContext":"at:pointOfSale","ofd:relatedActor":"https://w3id.org/openfooddata/actors/boerenmarkt-kester"},{"@type":"ofd:ActorRelationship","ofd:relatedContext":"at:pointOfSale","ofd:relatedActor":"https://w3id.org/openfooddata/actors/boerenmarkt-teralfene"},{"@type":"ofd:ActorRelationship","ofd:relatedContext":"at:pointOfSale","ofd:relatedActor":"https://w3id.org/openfooddata/actors/boerenmarkt-gooik"},{"@type":"ofd:ActorRelationship","ofd:relatedContext":"at:pointOfSale","ofd:relatedActor":"https://w3id.org/openfooddata/actors/boerenmarkt-gaasbeek"}],"@id":"https://w3id.org/openfooddata/actors/herrebeekhof","extraHeader":"<link rel=\"alternate\" href=\"herrebeekhof.rdf\" type=\"application/rdf+xml\"/>\n<link rel=\"alternate\" href=\"herrebeekhof.jsonld\" type=\"application/ld+json\"/>\n<link rel=\"alternate\" href=\"herrebeekhof.nq\" type=\"application/n-quads\"/>\n<link rel=\"alternate\" href=\"herrebeekhof.nt\" type=\"application/n-triples\"/>\n<link rel=\"alternate\" href=\"herrebeekhof.ttl\" type=\"text/turtle\"/>\n<link rel=\"alternate\" href=\"herrebeekhof.rj\" type=\"application/rdf+json\"/>\n<link rel=\"alternate\" href=\"herrebeekhof.trig\" type=\"text/trig\"/>\n<link rel=\"alternate\" href=\"herrebeekhof.trix\" type=\"application/trix\"/>\n","schema:name":"Herrebeekhof","ofd:actorType":["at:pointOfSale","at:farmShop","at:producer"]}}