{"type":"Feature","geometry":{"type":"Point","coordinates":[3.539278,50.948212]},"properties":{"foaf:account":[{"@type":"foaf:OnlineAccount","@id":"https://www.facebook.com/pages/Azaleatuin/192484477449630?fref=ts","skos:prefLabel":"Facebook","foaf:accountServiceHomepage":"https://www.facebook.com","foaf:accountName":"Azaleatuin","dct:identifier":"192484477449630?fref=ts"}],"foaf:name":"Azaleatuin","schema:url":["http://www.azaleatuin.be"],"foaf:homepage":["http://www.azaleatuin.be"],"foaf:isPrimaryTopicOf":["http://www.rechtvanbijdeboer.be/azaleatuin-0","http://www.rechtvanbijdeboer.be/node/3099","http://www.rechtvanbijdeboer.be/azaleatuin","http://www.rechtvanbijdeboer.be/node/1611"],"@type":"foaf:Agent","schema:image":["http://www.rechtvanbijdeboer.be/sites/default/files/styles/producer_teaser/public/IMG_1355%20%281%29.JPG?itok=vZBu8VvP","http://www.rechtvanbijdeboer.be/sites/default/files/styles/producer_teaser/public/bedrijfkl2013.jpg?itok=EUDwnAWO","http://www.rechtvanbijdeboer.be/sites/default/files/styles/producer_teaser/public/tuin_a_200506.jpg?itok=6lEdSjbd","http://www.rechtvanbijdeboer.be/sites/default/files/styles/producer_teaser/public/dsc_3230.jpg?itok=E3od8Rav"],"@context":"https://openfooddata.github.io/actors/_common/context.jsonld","schema:geo":{"schema:latitude":"50.948212","schema:longitude":"3.539278","@type":"schema:GeoCoordinates","schema:addressCountry":"Belgium","schema:address":{"@type":"schema:PostalAddress","schema:streetAddress":"Lulstraat 3","schema:postalCode":"9770","schema:addressLocality":"Kruishoutem"}},"ofd:offersFoodType":[],"foaf:depiction":["http://www.rechtvanbijdeboer.be/sites/default/files/styles/producer_teaser/public/IMG_1355%20%281%29.JPG?itok=vZBu8VvP","http://www.rechtvanbijdeboer.be/sites/default/files/styles/producer_teaser/public/bedrijfkl2013.jpg?itok=EUDwnAWO","http://www.rechtvanbijdeboer.be/sites/default/files/styles/producer_teaser/public/tuin_a_200506.jpg?itok=6lEdSjbd","http://www.rechtvanbijdeboer.be/sites/default/files/styles/producer_teaser/public/dsc_3230.jpg?itok=E3od8Rav"],"schema:description":"De Azaleatuin biedt haar klanten een uniek assortiment van bijzondere azalea’s en rododendrons aan. Kwaliteitszorg staat centraal in onze bedrijfsvoering. We produceren sterke, mooie en exclusieve planten, we leveren advies en maatwerk voor onze klanten, we werken met kennis en vakmanschap en respect voor mens en milieu.","ofd:upstreamRel":[],"schema:contactPoint":{"@type":"schema:ContactPoint","schema:telephone":["093/860597"],"schema:email":["info@azaleatuin.be"],"foaf:homepage":["http://www.azaleatuin.be"],"schema:url":["http://www.azaleatuin.be"]},"ofd:downstreamRel":[],"@id":"https://w3id.org/openfooddata/actors/azaleatuin","schema:name":"Azaleatuin","ofd:actorType":["at:pointOfSale","at:farmShop","at:producer"]}}