{"type":"Feature","geometry":{"type":"Point","coordinates":[4.588443,51.190318]},"properties":{"foaf:account":[],"foaf:name":"Pomme d'aMoor -'t Stalleke","foaf:isPrimaryTopicOf":["http://www.rechtvanbijdeboer.be/pomme-damoor-t-stalleke","http://www.rechtvanbijdeboer.be/node/3138"],"@type":"foaf:Agent","schema:image":[],"@context":"https://openfooddata.github.io/actors/_common/context.jsonld","schema:geo":{"schema:latitude":"51.190318","schema:longitude":"4.588443","@type":"schema:GeoCoordinates","schema:addressCountry":"Belgium","schema:address":{"@type":"schema:PostalAddress","schema:streetAddress":"Moorstraat 9","schema:postalCode":"2520","schema:addressLocality":"Broechem"}},"ofd:offersFoodType":["ft:fruits","ft:poultry_meat","ft:vegetables"],"foaf:depiction":[],"schema:description":"","ofd:upstreamRel":[{"@type":"ofd:ActorRelationship","ofd:relatedContext":"at:producer","ofd:relatedActor":"https://w3id.org/openfooddata/actors/pomdamoor"}],"@id":"https://w3id.org/openfooddata/actors/pomme-damoor-t-stalleke","extraHeader":"<link rel=\"alternate\" href=\"pomme-damoor-t-stalleke.rdf\" type=\"application/rdf+xml\"/>\n<link rel=\"alternate\" href=\"pomme-damoor-t-stalleke.jsonld\" type=\"application/ld+json\"/>\n<link rel=\"alternate\" href=\"pomme-damoor-t-stalleke.nq\" type=\"application/n-quads\"/>\n<link rel=\"alternate\" href=\"pomme-damoor-t-stalleke.nt\" type=\"application/n-triples\"/>\n<link rel=\"alternate\" href=\"pomme-damoor-t-stalleke.ttl\" type=\"text/turtle\"/>\n<link rel=\"alternate\" href=\"pomme-damoor-t-stalleke.rj\" type=\"application/rdf+json\"/>\n<link rel=\"alternate\" href=\"pomme-damoor-t-stalleke.trig\" type=\"text/trig\"/>\n<link rel=\"alternate\" href=\"pomme-damoor-t-stalleke.trix\" type=\"application/trix\"/>\n","schema:name":"Pomme d'aMoor -'t Stalleke","ofd:actorType":["at:pointOfSale","at:farmShop"]}}