{"type":"Feature","geometry":{"type":"Point","coordinates":[4.588443,51.190318]},"properties":{"foaf:account":[],"foaf:name":"Pomme d'aMoor -'t Stalleke","foaf:isPrimaryTopicOf":["http://www.rechtvanbijdeboer.be/pomme-damoor-t-stalleke","http://www.rechtvanbijdeboer.be/node/3138"],"@type":"foaf:Agent","schema:image":[],"@context":"https://openfooddata.github.io/actors/_common/context.jsonld","schema:geo":{"schema:latitude":"51.190318","schema:longitude":"4.588443","@type":"schema:GeoCoordinates","schema:addressCountry":"Belgium","schema:address":{"@type":"schema:PostalAddress","schema:streetAddress":"Moorstraat 9","schema:postalCode":"2520","schema:addressLocality":"Broechem"}},"ofd:offersFoodType":["ft:fruits","ft:poultry_meat","ft:vegetables"],"foaf:depiction":[],"schema:description":"","ofd:upstreamRel":[{"@type":"ofd:ActorRelationship","ofd:relatedContext":"at:producer","ofd:relatedActor":"https://w3id.org/openfooddata/actors/pomdamoor"}],"@id":"https://w3id.org/openfooddata/actors/pomme-damoor-t-stalleke","schema:name":"Pomme d'aMoor -'t Stalleke","ofd:actorType":["at:pointOfSale","at:farmShop"]}}