{"type":"Feature","geometry":{"type":"Point","coordinates":[4.115321,51.154061]},"properties":{"foaf:account":[{"@type":"foaf:OnlineAccount","@id":"https://www.facebook.com/ThoevekeBelsele?ref=hl","skos:prefLabel":"Facebook","foaf:accountServiceHomepage":"https://www.facebook.com","foaf:accountName":"https:","dct:identifier":""}],"foaf:name":"'t Hoeveke","schema:url":["http://thoevekebelsele.be/"],"foaf:homepage":["http://thoevekebelsele.be/"],"foaf:isPrimaryTopicOf":["http://www.rechtvanbijdeboer.be/t-hoeveke-0","http://www.rechtvanbijdeboer.be/node/2495","http://www.rechtvanbijdeboer.be/t-hoeveke","http://www.rechtvanbijdeboer.be/node/1126"],"@type":"foaf:Agent","schema:image":["http://www.rechtvanbijdeboer.be/sites/default/files/styles/producer_teaser/public/t_Hoeveke_groenten_fruit.jpg?itok=FJ1mYBgo"],"@context":"https://openfooddata.github.io/actors/_common/context.jsonld","schema:geo":{"schema:latitude":"51.154061","schema:longitude":"4.115321","@type":"schema:GeoCoordinates","schema:addressCountry":"Belgium","schema:address":{"@type":"schema:PostalAddress","schema:streetAddress":"Arnhoutstraat 65","schema:postalCode":"9111","schema:addressLocality":"Belsele"}},"ofd:offersFoodType":["ft:poultry_meat","ft:milk_products","ft:fruits","ft:vegetables","ft:icecream","ft:potatoes"],"foaf:depiction":["http://www.rechtvanbijdeboer.be/sites/default/files/styles/producer_teaser/public/t_Hoeveke_groenten_fruit.jpg?itok=FJ1mYBgo"],"schema:description":"","ofd:upstreamRel":[],"schema:contactPoint":{"@type":"schema:ContactPoint","schema:telephone":["0473749755"],"schema:email":["info@thoevekebelsele.be"],"foaf:homepage":["http://thoevekebelsele.be/"],"schema:url":["http://thoevekebelsele.be/"]},"ofd:downstreamRel":[],"@id":"https://w3id.org/openfooddata/actors/t-hoeveke","schema:name":"'t Hoeveke","ofd:actorType":["at:pointOfSale","at:farmShop","at:producer"]}}