{"type":"Feature","geometry":{"type":"Point","coordinates":[4.469936,50.503887]},"properties":{"id":"https://w3id.org/openfooddata/actors/wwwmeelhovenseheidebe","name":"www.meelhovenseheide.be","img":[],"type":["at:pointOfSale","at:webshop"],"upstream":[{"@type":"ofd:ActorRelationship","ofd:relatedContext":"at:producer","ofd:relatedActor":"https://w3id.org/openfooddata/actors/van-den-heuvel-lv"}]}}