{"type":"Feature","geometry":{"type":"Point","coordinates":[5.309013,50.850132]},"properties":{"id":"https://w3id.org/openfooddata/actors/fruitbedrijf-neiss","name":"Fruitbedrijf Neiss","img":[],"type":["at:pointOfSale","at:farmShop","at:producer"],"upstream":[],"downstream":[]}}