{"type":"Feature","geometry":{"type":"Point","coordinates":[2.82748,50.853259]},"properties":{"foaf:account":[],"foaf:name":"'t Zonneroosje","foaf:isPrimaryTopicOf":["http://www.rechtvanbijdeboer.be/t-zonneroosje","http://www.rechtvanbijdeboer.be/node/2474"],"@type":"foaf:Agent","schema:image":["http://www.rechtvanbijdeboer.be/sites/default/files/styles/producer_teaser/public/biobellogroentenenfruitmaxi.jpg?itok=n2EToMw3"],"@context":"https://openfooddata.github.io/actors/_common/context.jsonld","schema:geo":{"schema:latitude":"50.853259","schema:longitude":"2.827480","@type":"schema:GeoCoordinates","schema:addressCountry":"Belgium","schema:address":{"@type":"schema:PostalAddress","schema:streetAddress":"Poperingseweg 166","schema:postalCode":"8908","schema:addressLocality":"Vlamertinge"}},"ofd:offersFoodType":["ft:potatoes","ft:fruits","ft:eggs","ft:vegetables"],"foaf:depiction":["http://www.rechtvanbijdeboer.be/sites/default/files/styles/producer_teaser/public/biobellogroentenenfruitmaxi.jpg?itok=n2EToMw3"],"schema:description":"","ofd:upstreamRel":[{"@type":"ofd:ActorRelationship","ofd:relatedContext":"at:producer","ofd:relatedActor":"https://w3id.org/openfooddata/actors/de-lochting-vzw"}],"@id":"https://w3id.org/openfooddata/actors/t-zonneroosje","schema:name":"'t Zonneroosje","ofd:actorType":["at:pointOfSale","at:vegetableSubscription"]}}