{"type":"Feature","geometry":{"type":"Point","coordinates":[5.123097,50.948412]},"properties":{"id":"https://w3id.org/openfooddata/actors/ijsafhaalpunt","name":"Ijsafhaalpunt","img":[],"type":["at:pointOfSale","at:collectionPoint"],"upstream":[{"@type":"ofd:ActorRelationship","ofd:relatedContext":"at:producer","ofd:relatedActor":"https://w3id.org/openfooddata/actors/ijskafee"}]}}