{"type":"Feature","geometry":{"type":"Point","coordinates":[5.123097,50.948412]},"properties":{"foaf:account":[],"foaf:name":"Ijsafhaalpunt","foaf:isPrimaryTopicOf":["http://www.rechtvanbijdeboer.be/ijsafhaalpunt","http://www.rechtvanbijdeboer.be/node/3262"],"@type":"foaf:Agent","schema:image":[],"@context":"https://openfooddata.github.io/actors/_common/context.jsonld","schema:geo":{"schema:latitude":"50.948412","schema:longitude":"5.123097","@type":"schema:GeoCoordinates","schema:addressCountry":"Belgium","schema:address":{"@type":"schema:PostalAddress","schema:streetAddress":"Grote Baan 78","schema:postalCode":"3540","schema:addressLocality":"Herk-de-Stad"}},"ofd:offersFoodType":["ft:icecream"],"foaf:depiction":[],"schema:description":"","ofd:upstreamRel":[{"@type":"ofd:ActorRelationship","ofd:relatedContext":"at:producer","ofd:relatedActor":"https://w3id.org/openfooddata/actors/ijskafee"}],"@id":"https://w3id.org/openfooddata/actors/ijsafhaalpunt","extraHeader":"<link rel=\"alternate\" href=\"ijsafhaalpunt.rdf\" type=\"application/rdf+xml\"/>\n<link rel=\"alternate\" href=\"ijsafhaalpunt.jsonld\" type=\"application/ld+json\"/>\n<link rel=\"alternate\" href=\"ijsafhaalpunt.nq\" type=\"application/n-quads\"/>\n<link rel=\"alternate\" href=\"ijsafhaalpunt.nt\" type=\"application/n-triples\"/>\n<link rel=\"alternate\" href=\"ijsafhaalpunt.ttl\" type=\"text/turtle\"/>\n<link rel=\"alternate\" href=\"ijsafhaalpunt.rj\" type=\"application/rdf+json\"/>\n<link rel=\"alternate\" href=\"ijsafhaalpunt.trig\" type=\"text/trig\"/>\n<link rel=\"alternate\" href=\"ijsafhaalpunt.trix\" type=\"application/trix\"/>\n","schema:name":"Ijsafhaalpunt","ofd:actorType":["at:pointOfSale","at:collectionPoint"]}}