{"type":"Feature","geometry":{"type":"Point","coordinates":[2.90514,51.209375]},"properties":{"id":"https://w3id.org/openfooddata/actors/bioshop-mordan-0","name":"Bioshop Mordan","img":[],"type":["at:pointOfSale","at:collectionPoint"],"upstream":[{"@type":"ofd:ActorRelationship","ofd:relatedContext":"at:producer","ofd:relatedActor":"https://w3id.org/openfooddata/actors/vesche-vis"}]}}