{"type":"Feature","geometry":{"type":"Point","coordinates":[3.612414,50.849027]},"properties":{"foaf:account":[],"foaf:name":"Slagerij Blockeel Oudenaarde","foaf:isPrimaryTopicOf":["http://www.rechtvanbijdeboer.be/slagerij-blockeel-oudenaarde","http://www.rechtvanbijdeboer.be/node/2696"],"@type":"foaf:Agent","schema:image":[],"@context":"https://openfooddata.github.io/actors/_common/context.jsonld","schema:geo":{"schema:latitude":"50.849027","schema:longitude":"3.612414","@type":"schema:GeoCoordinates","schema:addressCountry":"Belgium","schema:address":{"@type":"schema:PostalAddress","schema:streetAddress":"Prins Leopoldstraat 65","schema:postalCode":"9700","schema:addressLocality":"Oudenaarde"}},"ofd:offersFoodType":["ft:bakery_products","ft:fruit_juices","ft:lamb_meat","ft:beef","ft:pork","ft:milk_products"],"foaf:depiction":[],"schema:description":"","ofd:upstreamRel":[{"@type":"ofd:ActorRelationship","ofd:relatedContext":"at:producer","ofd:relatedActor":"https://w3id.org/openfooddata/actors/slagerij-en-stal-blockeel"}],"@id":"https://w3id.org/openfooddata/actors/slagerij-blockeel-oudenaarde","extraHeader":"<link rel=\"alternate\" href=\"slagerij-blockeel-oudenaarde.rdf\" type=\"application/rdf+xml\"/>\n<link rel=\"alternate\" href=\"slagerij-blockeel-oudenaarde.jsonld\" type=\"application/ld+json\"/>\n<link rel=\"alternate\" href=\"slagerij-blockeel-oudenaarde.nq\" type=\"application/n-quads\"/>\n<link rel=\"alternate\" href=\"slagerij-blockeel-oudenaarde.nt\" type=\"application/n-triples\"/>\n<link rel=\"alternate\" href=\"slagerij-blockeel-oudenaarde.ttl\" type=\"text/turtle\"/>\n<link rel=\"alternate\" href=\"slagerij-blockeel-oudenaarde.rj\" type=\"application/rdf+json\"/>\n<link rel=\"alternate\" href=\"slagerij-blockeel-oudenaarde.trig\" type=\"text/trig\"/>\n<link rel=\"alternate\" href=\"slagerij-blockeel-oudenaarde.trix\" type=\"application/trix\"/>\n","schema:name":"Slagerij Blockeel Oudenaarde","ofd:actorType":["at:pointOfSale","at:farmShop"]}}