{"type":"Feature","geometry":{"type":"Point","coordinates":[3.751364,51.063559]},"properties":{"id":"https://w3id.org/openfooddata/actors/bioshop-sint-amandsberg","name":"Bioshop Sint-Amandsberg","img":[],"type":["at:pointOfSale","at:vegetableSubscription"],"upstream":[{"@type":"ofd:ActorRelationship","ofd:relatedContext":"at:producer","ofd:relatedActor":"https://w3id.org/openfooddata/actors/de-wassende-maan"}]}}