{"type":"Feature","geometry":{"type":"Point","coordinates":[3.115058,51.210946]},"properties":{"foaf:account":[],"foaf:name":"De Nachtegaal","schema:url":[],"foaf:homepage":[],"foaf:isPrimaryTopicOf":["http://www.rechtvanbijdeboer.be/de-nachtegaal-0","http://www.rechtvanbijdeboer.be/node/2564","https://www.rechtvanbijdeboer.be/de-nachtegaal","https://www.rechtvanbijdeboer.be/node/1168"],"@type":"foaf:Agent","schema:image":[],"@context":"https://openfooddata.github.io/actors/_common/context.jsonld","schema:geo":{"schema:latitude":"51.210946","schema:longitude":"3.115058","@type":"schema:GeoCoordinates","schema:addressCountry":"Belgium","schema:address":{"@type":"schema:PostalAddress","schema:streetAddress":"Nachtegaalstraat 31","schema:postalCode":"8490","schema:addressLocality":"Varsenare (Jabbeke)"}},"ofd:offersFoodType":["ft:milk_products","ft:vegetables","ft:potatoes"],"foaf:depiction":[],"schema:description":"","ofd:upstreamRel":[],"ofd:downstreamRel":[],"@id":"https://w3id.org/openfooddata/actors/de-nachtegaal","schema:name":"De Nachtegaal","ofd:actorType":["at:pointOfSale","at:farmShop","at:producer"]}}