{"type":"Feature","geometry":{"type":"Point","coordinates":[4.742086,51.149613]},"properties":{"id":"https://w3id.org/openfooddata/actors/melktap-hoeve-de-kroon","name":"Melktap Hoeve de Kroon","img":["http://www.rechtvanbijdeboer.be/sites/default/files/styles/producer_teaser/public/logo_1.jpg?itok=EDsu3mwI"],"type":["at:pointOfSale","at:vendingMachine","at:producer"],"upstream":[],"downstream":[]}}