{"type":"Feature","geometry":{"type":"Point","coordinates":[3.393332,50.867219]},"properties":{"foaf:account":[],"foaf:name":"Hoeveproducten Haerinck","schema:url":[],"foaf:homepage":[],"foaf:isPrimaryTopicOf":["http://www.rechtvanbijdeboer.be/hoeveproducten-haerinck-0","http://www.rechtvanbijdeboer.be/node/3376","https://www.rechtvanbijdeboer.be/hoeveproducten-haerinck","https://www.rechtvanbijdeboer.be/node/1808"],"@type":"foaf:Agent","schema:image":[],"@context":"https://openfooddata.github.io/actors/_common/context.jsonld","schema:geo":{"schema:latitude":"50.867219","schema:longitude":"3.393332","@type":"schema:GeoCoordinates","schema:addressCountry":"Belgium","schema:address":{"@type":"schema:PostalAddress","schema:streetAddress":"Harelbekestraat 13","schema:postalCode":"8790","schema:addressLocality":"Waregem"}},"ofd:offersFoodType":["ft:milk_products","ft:eggs","ft:vegetables","ft:potatoes"],"foaf:depiction":[],"schema:description":"","ofd:upstreamRel":[],"ofd:downstreamRel":[],"@id":"https://w3id.org/openfooddata/actors/hoeveproducten-haerinck","schema:name":"Hoeveproducten Haerinck","ofd:actorType":["at:pointOfSale","at:farmShop","at:producer"]}}