{"type":"Feature","geometry":{"type":"Point","coordinates":[2.908586,51.204178]},"properties":{"id":"https://w3id.org/openfooddata/actors/buurderij-stene-oostende","name":"Buurderij Stene (Oostende)","img":[],"type":["at:pointOfSale","at:foodAssembly"],"upstream":[{"@type":"ofd:ActorRelationship","ofd:relatedContext":"at:producer","ofd:relatedActor":"https://w3id.org/openfooddata/actors/milki"},{"@type":"ofd:ActorRelationship","ofd:relatedContext":"at:producer","ofd:relatedActor":"https://w3id.org/openfooddata/actors/vesche-vis"},{"@type":"ofd:ActorRelationship","ofd:relatedContext":"at:producer","ofd:relatedActor":"https://w3id.org/openfooddata/actors/hoeve-t-lijsternest"}]}}