{"type":"Feature","geometry":{"type":"Point","coordinates":[4.588438,50.909063]},"properties":{"id":"https://w3id.org/openfooddata/actors/silsomhof","name":"Silsomhof","img":["http://www.rechtvanbijdeboer.be/sites/default/files/styles/producer_teaser/public/Logo%20ballonnen.png?itok=H-cF2d_m"],"type":["at:pointOfSale","at:farmShop"],"upstream":[{"@type":"ofd:ActorRelationship","ofd:relatedContext":"at:producer","ofd:relatedActor":"https://w3id.org/openfooddata/actors/t-silsomhof"}]}}