{"type":"Feature","geometry":{"type":"Point","coordinates":[3.262604,51.126872]},"properties":{"foaf:account":[],"foaf:name":"Scharreleierenautomaat","foaf:isPrimaryTopicOf":["http://www.rechtvanbijdeboer.be/scharreleierenautomaat","http://www.rechtvanbijdeboer.be/node/3301"],"@type":"foaf:Agent","schema:image":[],"@context":"https://openfooddata.github.io/actors/_common/context.jsonld","schema:geo":{"schema:latitude":"51.126872","schema:longitude":"3.262604","@type":"schema:GeoCoordinates","schema:addressCountry":"Belgium","schema:address":{"@type":"schema:PostalAddress","schema:streetAddress":"Hertsbergsestraat 106","schema:postalCode":"8020","schema:addressLocality":"Oostkamp"}},"ofd:offersFoodType":["ft:eggs"],"foaf:depiction":[],"schema:description":"","ofd:upstreamRel":[{"@type":"ofd:ActorRelationship","ofd:relatedContext":"at:producer","ofd:relatedActor":"https://w3id.org/openfooddata/actors/strubbe-de-pestel"}],"@id":"https://w3id.org/openfooddata/actors/scharreleierenautomaat","extraHeader":"<link rel=\"alternate\" href=\"scharreleierenautomaat.rdf\" type=\"application/rdf+xml\"/>\n<link rel=\"alternate\" href=\"scharreleierenautomaat.jsonld\" type=\"application/ld+json\"/>\n<link rel=\"alternate\" href=\"scharreleierenautomaat.nq\" type=\"application/n-quads\"/>\n<link rel=\"alternate\" href=\"scharreleierenautomaat.nt\" type=\"application/n-triples\"/>\n<link rel=\"alternate\" href=\"scharreleierenautomaat.ttl\" type=\"text/turtle\"/>\n<link rel=\"alternate\" href=\"scharreleierenautomaat.rj\" type=\"application/rdf+json\"/>\n<link rel=\"alternate\" href=\"scharreleierenautomaat.trig\" type=\"text/trig\"/>\n<link rel=\"alternate\" href=\"scharreleierenautomaat.trix\" type=\"application/trix\"/>\n","schema:name":"Scharreleierenautomaat","ofd:actorType":["at:pointOfSale","at:vendingMachine"]}}