{"type":"Feature","geometry":{"type":"Point","coordinates":[2.89023,50.852632]},"properties":{"foaf:account":[],"foaf:name":"Het Steengoed idee","foaf:isPrimaryTopicOf":["http://www.rechtvanbijdeboer.be/het-steengoed-idee","http://www.rechtvanbijdeboer.be/node/3337"],"@type":"foaf:Agent","schema:image":[],"@context":"https://openfooddata.github.io/actors/_common/context.jsonld","schema:geo":{"schema:latitude":"50.852632","schema:longitude":"2.890230","@type":"schema:GeoCoordinates","schema:addressCountry":"Belgium","schema:address":{"@type":"schema:PostalAddress","schema:streetAddress":"Kauwekijnstraat 11","schema:postalCode":"8900","schema:addressLocality":"Ieper"}},"ofd:offersFoodType":["ft:potatoes","ft:vegetables"],"foaf:depiction":[],"schema:description":"","ofd:upstreamRel":[{"@type":"ofd:ActorRelationship","ofd:relatedContext":"at:producer","ofd:relatedActor":"https://w3id.org/openfooddata/actors/de-lovie"}],"@id":"https://w3id.org/openfooddata/actors/het-steengoed-idee","extraHeader":"<link rel=\"alternate\" href=\"het-steengoed-idee.rdf\" type=\"application/rdf+xml\"/>\n<link rel=\"alternate\" href=\"het-steengoed-idee.jsonld\" type=\"application/ld+json\"/>\n<link rel=\"alternate\" href=\"het-steengoed-idee.nq\" type=\"application/n-quads\"/>\n<link rel=\"alternate\" href=\"het-steengoed-idee.nt\" type=\"application/n-triples\"/>\n<link rel=\"alternate\" href=\"het-steengoed-idee.ttl\" type=\"text/turtle\"/>\n<link rel=\"alternate\" href=\"het-steengoed-idee.rj\" type=\"application/rdf+json\"/>\n<link rel=\"alternate\" href=\"het-steengoed-idee.trig\" type=\"text/trig\"/>\n<link rel=\"alternate\" href=\"het-steengoed-idee.trix\" type=\"application/trix\"/>\n","schema:name":"Het Steengoed idee","ofd:actorType":["at:pointOfSale","at:collectionPoint"]}}