{"type":"Feature","geometry":{"type":"Point","coordinates":[2.89023,50.852632]},"properties":{"foaf:account":[],"foaf:name":"Het Steengoed idee","foaf:isPrimaryTopicOf":["http://www.rechtvanbijdeboer.be/het-steengoed-idee","http://www.rechtvanbijdeboer.be/node/3337"],"@type":"foaf:Agent","schema:image":[],"@context":"https://openfooddata.github.io/actors/_common/context.jsonld","schema:geo":{"schema:latitude":"50.852632","schema:longitude":"2.890230","@type":"schema:GeoCoordinates","schema:addressCountry":"Belgium","schema:address":{"@type":"schema:PostalAddress","schema:streetAddress":"Kauwekijnstraat 11","schema:postalCode":"8900","schema:addressLocality":"Ieper"}},"ofd:offersFoodType":["ft:potatoes","ft:vegetables"],"foaf:depiction":[],"schema:description":"","ofd:upstreamRel":[{"@type":"ofd:ActorRelationship","ofd:relatedContext":"at:producer","ofd:relatedActor":"https://w3id.org/openfooddata/actors/de-lovie"}],"@id":"https://w3id.org/openfooddata/actors/het-steengoed-idee","schema:name":"Het Steengoed idee","ofd:actorType":["at:pointOfSale","at:collectionPoint"]}}