{"type":"Feature","geometry":{"type":"Point","coordinates":[3.350458,51.215853]},"properties":{"id":"https://w3id.org/openfooddata/actors/ter-doorn-aardbeien-asperges","name":"Ter Doorn - Aardbeien & Asperges","img":[],"type":["at:pointOfSale","at:farmShop"],"upstream":[{"@type":"ofd:ActorRelationship","ofd:relatedContext":"at:producer","ofd:relatedActor":"https://w3id.org/openfooddata/actors/ter-doorn"}]}}