{"type":"Feature","geometry":{"type":"Point","coordinates":[5.05328,50.98521]},"properties":{"id":"https://w3id.org/openfooddata/actors/ijssalon-ijsafhaalpunt","name":"IJssalon-IJsafhaalpunt","img":[],"type":["at:pointOfSale","at:collectionPoint"],"upstream":[{"@type":"ofd:ActorRelationship","ofd:relatedContext":"at:producer","ofd:relatedActor":"https://w3id.org/openfooddata/actors/ijskafee"}]}}